Workbook

Sheet Notes
A1: =C4&" "&C3&" RIAPA CGE Model" -> 2019 Rwanda RIAPA CGE Model
A3: * | B3: Country | C3: Rwanda
A4: * | B4: Base year | C4: 2019
A5: * | B5: Units | C5: Billions of Rwandan Francs
A10: Activities (a) and commodities (c) | E10: Factors (f) | I10: Households (hhd) | M10: Other accounts
A11: cere | B11: Cereals | E11: lab-n | F11: Labor - uneducated | I11: f1 | J11: Rural farm - quintile 1 | M11: trc | N11: Transaction costs
A12: puls | B12: Pulses | E12: lab-p | F12: Labor - primary | I12: f2 | J12: Rural farm - quintile 2 | M12: ent | N12: Enterprises
A13: oils | B13: Oilseeds | E13: lab-s | F13: Labor - secondary | I13: f3 | J13: Rural farm - quintile 3 | M13: gov | N13: Government
A14: root | B14: Roots and Tubers | E14: lab-t | F14: Labor - tertiary | I14: f4 | J14: Rural farm - quintile 4 | M14: atax | N14: Taxes - activity
A15: vege | B15: Vegetables | E15: lnd | F15: Land - agricultural crops | I15: f5 | J15: Rural farm - quintile 5 | M15: dtax | N15: Taxes - direct
A16: frui | B16: Fruits | E16: cap-c | F16: Capital - crops | I16: n1 | J16: Rural nonfarm - quintile 1 | M16: etax | N16: Taxes - export
A17: becr | B17: Beverage crops | E17: cap-l | F17: Capital - livestock | I17: n2 | J17: Rural nonfarm - quintile 2 | M17: ftax | N17: Taxes - factor
A18: ocrp | B18: Other non-food crops | E18: cap-m | F18: Capital - mining | I18: n3 | J18: Rural nonfarm - quintile 3 | M18: mtax | N18: Taxes - import
A19: live | B19: Livestock | E19: cap-o | F19: Capital - other | I19: n4 | J19: Rural nonfarm - quintile 4 | M19: stax | N19: Taxes - sales
A20: milk | B20: Raw milk | I20: n5 | J20: Rural nonfarm - quintile 5 | M20: s-i | N20: Savings-investment
A21: fore | B21: Forestry | I21: u1 | J21: Urban - quintile 1 | M21: dstk | N21: Change in stocks
A22: fish | B22: Fishery | I22: u2 | J22: Urban - quintile 2 | M22: row | N22: Rest of world
A23: mine | B23: Mining - energy | I23: u3 | J23: Urban - quintile 3 | M23: total | N23: Total
A24: mino | B24: Mining - other | I24: u4 | J24: Urban - quintile 4
A25: gmll | B25: Grain milling | I25: u5 | J25: Urban - quintile 5
A26: foil | B26: Fats and oils
A27: fveg | B27: Fruit and vegetable processing
A28: meat | B28: Meat processing
A29: fsea | B29: Fish and seafood processing
A30: dair | B30: Dairy
A31: fobe | B31: Other food and beverages
A32: oapr | B32: Other processing of ag products
A33: text | B33: Textiles
A34: wood | B34: Wood products
A35: petr | B35: Petroleum products
A36: fert | B36: Fertilizers and herbicides
A37: chem | B37: Chemicals
... A56: osrv | B56: Other services

Sheet Index
A1: GAMS GDX Index
A2: Instruction | B2: Do not alter this sheet.
D7: rdim | E7: cdim
A8: par | B8: nsam | C8: sam!a7 | D8: 1 | E8: 1
D15: rdim | E15: cdim
A16: dset | B16: ac | C16: sets!a7 | D16: 1
A17: dset | B17: rg | C17: sets!b7 | D17: 1
A18: dset | B18: a | C18: sets!c7 | D18: 1
A19: dset | B19: arg | C19: sets!d7 | D19: 1
A20: dset | B20: c | C20: sets!e7 | D20: 1
A21: dset | B21: f | C21: sets!f7 | D21: 1
A22: dset | B22: flab | C22: sets!g7 | D22: 1
A23: dset | B23: flnd | C23: sets!h7 | D23: 1
A24: dset | B24: fliv | C24: sets!i7 | D24: 1
A25: dset | B25: fcap | C25: sets!j7 | D25: 1
A26: dset | B26: ins | C26: sets!k7 | D26: 1
A27: dset | B27: insd | C27: sets!l7 | D27: 1
... A33: dset | B33: ctm | C33: sets!r7 | D33: 1
A34: set | B34: mac | C34: sets!t7 | D34: 2 | F34: values=nodata
A35: set | B35: marg | C35: sets!w7 | D35: 3 | F35: values=nodata
A36: dset | B36: eagr | C36: sets!aa7 | D36: 1
A37: dset | B37: emin | C37: sets!ab7 | D37: 1
A38: dset | B38: eman | C38: sets!ac7 | D38: 1
A39: dset | B39: eutl | C39: sets!ad7 | D39: 1
A40: dset | B40: econ | C40: sets!ae7 | D40: 1
A41: dset | B41: etrd | C41: sets!af7 | D41: 1
A42: dset | B42: etrc | C42: sets!ag7 | D42: 1
A43: dset | B43: ehfs | C43: sets!ah7 | D43: 1
A44: dset | B44: efbs | C44: sets!ai7 | D44: 1
A45: dset | B45: eres | C45: sets!aj7 | D45: 1
A46: dset | B46: egsv | C46: sets!ak7 | D46: 1
A47: dset | B47: eosv | C47: sets!al7 | D47: 1
... A53: dset | B53: cer | C53: adjust!f7 | D53: 1
A54: par | B54: sam | C54: sam!a7 | D54: 1 | E54: 1
A55: par | B55: leselas1 | C55: LES!b131 | D55: 1 | E55: 1
A56: par | B56: leselas2 | C56: LES!s131 | D56: 1 | E56: 1
A57: par | B57: FRISCH | C57: LES!C206 | E57: 1
A58: par | B58: tradelas | C58: elasticities!a7 | D58: 1 | E58: 1
A59: par | B59: prodelastab | C59: elasticities!e7 | D59: 1 | E59: 1
A60: par | B60: proddata | C60: production!a7 | D60: 1 | E60: 2
A61: dset | B61: al | C61: employment!a7 | D61: 1
A62: set | B62: mala | C62: employment!c7 | D62: 2 | F62: values=nodata
A63: par | B63: wfinput | C63: employment!g6 | D63: 1 | E63: 1
A64: par | B64: qfinput | C64: employment!g50 | D64: 1 | E64: 1
A65: par | B65: poptab | C65: population!a7 | D65: 1

Sheet Sets
A1: Set Definitions
A2: Instruction | B2: Do not alter this sheet, unless you are adding new regions.
A4: Global set | B4: Regions | C4: Activities | E4: Commodities | F4: Factors | K4: Institutions | P4: Transaction costs | T4: Mapping activities to commodities | W4: Mapping activities to regions | AA4: Sectoral groups for employment calculations
C5: All | F5: All | G5: Labor | H5: Land | I5: Livestock | J5: Capital | K5: All | L5: Domestic | M5: Non-government | N5: Enterprises | O5: Households | P5: Domestic | Q5: Export | R5: Import | T5: MAC | W5: MARG | AA5: Agriculture | AB5: Industry
A6: AC | B6: RG | C6: A | D6: ARG | E6: C | F6: F | G6: FLAB | H6: FLND | I6: FLIV | J6: FCAP | K6: INS | L6: INSD | M6: INSDNG | N6: EN | O6: H | P6: CTD | Q6: CTE | R6: CTM | T6: A | U6: C | W6: ARG | X6: A | Y6: RG | AA6: EAGR | AB6: EMIN | AC6: EMAN | AD6: EUTL | AE6: ECON | AF6: ETRD | AG6: ETRC | AH6: EHFS | AI6: EFBS | AJ6: ERES | AK6: EGSV | AL6: EOSV
A7: acere | B7: x | C7: acere | D7: acere | E7: ccere | F7: flab-n | G7: flab-n | H7: flnd | I7: fcap-l | J7: fcap-c | K7: ent | L7: ent | M7: ent | N7: ent | O7: hhd-f1 | P7: trd | Q7: tre | R7: trm | T7: =C7 -> acere | U7: =E7 -> ccere | W7: =D7 -> acere | X7: =C7 -> acere | Y7: x | AA7: =W7 -> acere | AB7: =W19 -> amine | AC7: =W21 -> agmll | AD7: aelec | AE7: acons | AF7: atrad | AG7: atran | AH7: ahotl | AI7: afsrv | AJ7: areal | AK7: apadm | AL7: aosrv
A8: apuls | C8: apuls | D8: apuls | E8: cpuls | F8: flab-p | G8: flab-p | J8: fcap-m | K8: hhd-f1 | L8: hhd-f1 | M8: hhd-f1 | O8: hhd-f2 | T8: =C8 -> apuls | U8: =E8 -> cpuls | W8: =D8 -> apuls | X8: =C8 -> apuls | Y8: x | AA8: =W8 -> apuls | AB8: =W20 -> amino | AC8: =W22 -> afoil | AD8: awatr | AG8: acomm | AH8: arest | AJ8: absrv | AK8: aeduc
A9: aoils | C9: aoils | D9: aoils | E9: coils | F9: flab-s | G9: flab-s | J9: fcap-o | K9: hhd-f2 | L9: hhd-f2 | M9: hhd-f2 | O9: hhd-f3 | T9: =C9 -> aoils | U9: =E9 -> coils | W9: =D9 -> aoils | X9: =C9 -> aoils | Y9: x | AA9: =W9 -> aoils | AC9: =W23 -> afveg | AK9: aheal
A10: aroot | C10: aroot | D10: aroot | E10: croot | F10: flab-t | G10: flab-t | K10: hhd-f3 | L10: hhd-f3 | M10: hhd-f3 | O10: hhd-f4 | T10: =C10 -> aroot | U10: =E10 -> croot | W10: =D10 -> aroot | X10: =C10 -> aroot | Y10: x | AA10: =W10 -> aroot | AC10: =W24 -> ameat
A11: avege | C11: avege | D11: avege | E11: cvege | F11: flnd | K11: hhd-f4 | L11: hhd-f4 | M11: hhd-f4 | O11: hhd-f5 | T11: =C11 -> avege | U11: =E11 -> cvege | W11: =D11 -> avege | X11: =C11 -> avege | Y11: x | AA11: =W11 -> avege | AC11: =W25 -> afsea
A12: afrui | C12: afrui | D12: afrui | E12: cfrui | F12: fcap-c | K12: hhd-f5 | L12: hhd-f5 | M12: hhd-f5 | O12: hhd-n1 | T12: =C12 -> afrui | U12: =E12 -> cfrui | W12: =D12 -> afrui | X12: =C12 -> afrui | Y12: x | AA12: =W12 -> afrui | AC12: =W26 -> adair
A13: abecr | C13: abecr | D13: abecr | E13: cbecr | F13: fcap-l | K13: hhd-n1 | L13: hhd-n1 | M13: hhd-n1 | O13: hhd-n2 | T13: abecr | U13: cbecr | W13: abecr | X13: abecr | Y13: x | AA13: abecr | AC13: =W27 -> afobe
A14: aocrp | C14: aocrp | D14: aocrp | E14: cocrp | F14: fcap-m | K14: hhd-n2 | L14: hhd-n2 | M14: hhd-n2 | O14: hhd-n3 | T14: =C14 -> aocrp | U14: =E14 -> cocrp | W14: =D14 -> aocrp | X14: =C14 -> aocrp | Y14: x | AA14: =W14 -> aocrp | AC14: =W28 -> aoapr
A15: alive | C15: alive | D15: alive | E15: clive | F15: fcap-o | K15: hhd-n3 | L15: hhd-n3 | M15: hhd-n3 | O15: hhd-n4 | T15: =C15 -> alive | U15: =E15 -> clive | W15: =D15 -> alive | X15: =C15 -> alive | Y15: x | AA15: =W15 -> alive | AC15: =W29 -> atext
A16: amilk | C16: amilk | D16: amilk | E16: cmilk | K16: hhd-n4 | L16: hhd-n4 | M16: hhd-n4 | O16: hhd-n5 | T16: =C16 -> amilk | U16: =E16 -> cmilk | W16: =D16 -> amilk | X16: =C16 -> amilk | Y16: x | AA16: =W16 -> amilk | AC16: =W30 -> awood
A17: afore | C17: afore | D17: afore | E17: cfore | K17: hhd-n5 | L17: hhd-n5 | M17: hhd-n5 | O17: hhd-u1 | T17: =C17 -> afore | U17: =E17 -> cfore | W17: =D17 -> afore | X17: =C17 -> afore | Y17: x | AA17: =W17 -> afore | AC17: =W31 -> apetr
A18: afish | C18: afish | D18: afish | E18: cfish | K18: hhd-u1 | L18: hhd-u1 | M18: hhd-u1 | O18: hhd-u2 | T18: =C18 -> afish | U18: =E18 -> cfish | W18: =D18 -> afish | X18: =C18 -> afish | Y18: x | AA18: =W18 -> afish | AC18: =W32 -> afert
A19: amine | C19: amine | D19: amine | E19: cmine | K19: hhd-u2 | L19: hhd-u2 | M19: hhd-u2 | O19: hhd-u3 | T19: =C19 -> amine | U19: =E19 -> cmine | W19: =D19 -> amine | X19: =C19 -> amine | Y19: x | AC19: =W33 -> achem
A20: amino | C20: amino | D20: amino | E20: cmino | K20: hhd-u3 | L20: hhd-u3 | M20: hhd-u3 | O20: hhd-u4 | T20: =C20 -> amino | U20: =E20 -> cmino | W20: =D20 -> amino | X20: =C20 -> amino | Y20: x | AC20: =W34 -> anmet
A21: agmll | C21: agmll | D21: agmll | E21: cgmll | K21: hhd-u4 | L21: hhd-u4 | M21: hhd-u4 | O21: hhd-u5 | T21: =C21 -> agmll | U21: =E21 -> cgmll | W21: =D21 -> agmll | X21: =C21 -> agmll | Y21: x | AC21: =W35 -> ametl
A22: afoil | C22: afoil | D22: afoil | E22: cfoil | K22: hhd-u5 | L22: hhd-u5 | M22: hhd-u5 | T22: =C22 -> afoil | U22: =E22 -> cfoil | W22: =D22 -> afoil | X22: =C22 -> afoil | Y22: x | AC22: =W36 -> amach
A23: afveg | C23: afveg | D23: afveg | E23: cfveg | K23: gov | L23: gov | T23: =C23 -> afveg | U23: =E23 -> cfveg | W23: =D23 -> afveg | X23: =C23 -> afveg | Y23: x | AC23: =W37 -> aoman
A24: ameat | C24: ameat | D24: ameat | E24: cmeat | K24: row | T24: =C24 -> ameat | U24: =E24 -> cmeat | W24: =D24 -> ameat | X24: =C24 -> ameat | Y24: x
A25: afsea | C25: afsea | D25: afsea | E25: cfsea | T25: =C25 -> afsea | U25: =E25 -> cfsea | W25: =D25 -> afsea | X25: =C25 -> afsea | Y25: x
A26: adair | C26: adair | D26: adair | E26: cdair | T26: =C26 -> adair | U26: =E26 -> cdair | W26: =D26 -> adair | X26: =C26 -> adair | Y26: x
A27: afobe | C27: afobe | D27: afobe | E27: cfobe | T27: =C27 -> afobe | U27: =E27 -> cfobe | W27: =D27 -> afobe | X27: =C27 -> afobe | Y27: x
A28: aoapr | C28: aoapr | D28: aoapr | E28: coapr | T28: =C28 -> aoapr | U28: =E28 -> coapr | W28: =D28 -> aoapr | X28: =C28 -> aoapr | Y28: x
A29: atext | C29: atext | D29: atext | E29: ctext | T29: =C29 -> atext | U29: =E29 -> ctext | W29: =D29 -> atext | X29: =C29 -> atext | Y29: x
A30: awood | C30: awood | D30: awood | E30: cwood | T30: =C30 -> awood | U30: =E30 -> cwood | W30: =D30 -> awood | X30: =C30 -> awood | Y30: x
A31: apetr | C31: apetr | D31: apetr | E31: cpetr | T31: =C31 -> apetr | U31: =E31 -> cpetr | W31: =D31 -> apetr | X31: =C31 -> apetr | Y31: x
A32: afert | C32: afert | D32: afert | E32: cfert | T32: =C32 -> afert | U32: =E32 -> cfert | W32: =D32 -> afert | X32: =C32 -> afert | Y32: x
A33: achem | C33: achem | D33: achem | E33: cchem | T33: =C33 -> achem | U33: =E33 -> cchem | W33: =D33 -> achem | X33: =C33 -> achem | Y33: x
A34: anmet | C34: anmet | D34: anmet | E34: cnmet | T34: =C34 -> anmet | U34: =E34 -> cnmet | W34: =D34 -> anmet | X34: =C34 -> anmet | Y34: x
A35: ametl | C35: ametl | D35: ametl | E35: cmetl | T35: =C35 -> ametl | U35: =E35 -> cmetl | W35: =D35 -> ametl | X35: =C35 -> ametl | Y35: x
A36: amach | C36: amach | D36: amach | E36: cmach | T36: =C36 -> amach | U36: =E36 -> cmach | W36: =D36 -> amach | X36: =C36 -> amach | Y36: x
... A52: aosrv | C52: aosrv | D52: aosrv | E52: cosrv | T52: =C52 -> aosrv | U52: =E52 -> cosrv | W52: =D52 -> aosrv | X52: =C52 -> aosrv | Y52: x
A53: ccere
A54: cpuls
A55: coils
A56: croot
A57: cvege
A58: cfrui
A59: cbecr
A60: cocrp
A61: clive
A62: cmilk
A63: cfore
A64: cfish
... A151: total

Sheet Adjust
A1: Adjustments to SAM Trade Flows
A3: * | B3: * | C3: * | D3: * | E3: * | F3: *
A4: Remove small trade shares | C4: Re-exports | D4: Net out trade | F4: Perfect substitutes
A5: Exports | B5: Imports | D5: Exports | E5: Imports | F5: Exports
A6: REMEXP | B6: REMIMP | C6: REEXPORT | D6: NETEXPS | E6: NETIMPS | F6: CER | K6: VAshr | L6: PRDshr | M6: EMPshr | N6: EXPshr | O6: EXP-OUTshr | P6: IMPshr | Q6: IMP-DEMshr
B7: clive | D7: cfsrv | E7: cpuls | J7: ccere | K7: 1.7859389 | L7: 1.1397621 | M7: 3.4352083 | P7: 0.64118867 | Q7: 12.7526
B8: cmine | D8: cheal | E8: cvege | J8: cpuls | K8: 1.4410933 | L8: 0.90124884 | M8: 3.3298736 | N8: 1.85945 | O8: 32.301065
B9: cheal | D9: cosrv | E9: cfrui | J9: coils | K9: 0.57823985 | L9: 0.45952805 | M9: 1.2140011 | P9: 0.21887973 | Q9: 10.647417
B10: cosrv | J10: croot | K10: 6.0068381 | L10: 3.8276188 | M10: 11.883446
J11: cvege | K11: 0.98224881 | L11: 0.60294225 | M11: 2.1754799 | N11: 1.5644154 | O11: 32.113531
J12: cfrui | K12: 3.6539123 | L12: 2.2272571 | M12: 8.0290801 | N12: 2.4975494 | O12: 17.572612
J13: cbecr | K13: 1.599627 | L13: 1.4584081 | M13: 4.601759 | N13: 10.029369 | O13: 79.829316
J14: cocrp | K14: 0.069902725 | L14: 0.045074561 | M14: 0.15435798 | N14: 0.162142 | O14: 44.299758
J15: clive | K15: 1.7191152 | L15: 1.2291168 | M15: 3.3736601
J16: cmilk | K16: 1.0958969 | L16: 0.81059328 | M16: 1.6903128
J17: cfore | K17: 6.3964122 | L17: 4.1953 | M17: 22.436112
J18: cfish | K18: 0.39768199 | L18: 0.24726316 | M18: 1.561841
J19: cmine | K19: 0.048513412 | L19: 0.035239379 | M19: 0.0073630343
J20: cmino | K20: 1.5362705 | L20: 1.3206146 | M20: 1.1344224 | N20: 14.499061 | O20: 77.7582 | P20: 0.43852641 | Q20: 29.212594
J21: cgmll | K21: 0.54262426 | L21: 1.0316 | M21: 0.35258413 | P21: 0.69580552 | Q21: 13.920561
J22: cfoil | K22: 0.31590893 | L22: 0.39656911 | M22: 0.21954933 | P22: 1.1120045 | Q22: 40.879359
J23: cfveg | K23: 0.1392824 | L23: 0.25458225 | M23: 0.079739733 | P23: 0.08598798 | Q23: 7.4842282
J24: cmeat | K24: 0.25724115 | L24: 0.74586553 | M24: 0.14846489
J25: cfsea | K25: 0.0027541765 | L25: 0.0074333964 | M25: 0.0017476103 | P25: 0.47985947 | Q25: 94.008746
J26: cdair | K26: 0.19137364 | L26: 0.20478729 | M26: 0.12866561 | P26: 0.19111259 | Q26: 38.45558
J27: cfobe | K27: 3.5544526 | L27: 4.8755869 | M27: 1.1986042 | N27: 2.9745679 | O27: 8.8152801 | P27: 2.8519078 | Q27: 15.210634
J28: coapr | K28: 0.24268468 | L28: 0.26241306 | M28: 0.078950296 | P28: 0.10298444 | Q28: 8.2937748
J29: ctext | K29: 0.83019902 | L29: 1.0218093 | M29: 0.42845425 | P29: 4.1965053 | Q29: 51.859839
J30: cwood | K30: 0.39985639 | L30: 0.50896392 | M30: 0.15198191 | P30: 2.499274 | Q30: 54.266281
J31: cpetr | K31: 0.0069941474 | L31: 0.0048947301 | M31: 0.00041044037 | P31: 16.462606 | Q31: 99.871464
J32: cfert | P32: 3.151409 | Q32: 100
J33: cchem | K33: 0.65497188 | L33: 0.78113772 | M33: 0.045533145 | N33: 4.6202424 | O33: 64.276993 | P33: 9.9891939 | Q33: 89.505921
J34: cnmet | K34: 0.53529082 | L34: 0.69050836 | M34: 0.16142002 | N34: 2.5220564 | O34: 39.658391 | P34: 2.1742647 | Q34: 55.892731
J35: cmetl | K35: 0.15913926 | L35: 0.53093956 | M35: 0.065098562 | P35: 9.0039449 | Q35: 80.308813
J36: cmach | K36: 1.081371 | L36: 0.95111132 | M36: 0.47244052 | P36: 24.314897 | Q36: 86.19234
J37: coman | K37: 0.22979396 | L37: 0.22306967 | M37: 0.079111167 | P37: 0.74900002 | Q37: 44.130362
J38: celec | K38: 1.1948186 | L38: 1.5433985 | M38: 0.2451767
J39: cwatr | K39: 0.5099012 | L39: 0.530125 | M39: 0.11845646
J40: ccons | K40: 8.1952173 | L40: 13.043909 | M40: 6.1549163
J41: ctrad | K41: 9.8505778 | L41: 9.8618079 | M41: 10.60763
J42: ctran | K42: 6.7137651 | L42: 7.343906 | M42: 2.7094937 | N42: 23.846899 | O42: 43.991704 | P42: 12.109855 | Q42: 40.404604
J43: chotl | K43: 0.44183216 | L43: 0.95600576 | M43: 0.11087193 | N43: 1.8683175 | O43: 26.476231 | P43: 1.7052666 | Q43: 35.843126
J44: crest | K44: 1.5770664 | L44: 3.3886404 | M44: 0.37580239
J45: ccomm | K45: 2.1243043 | L45: 2.4369259 | M45: 0.16948197 | N45: 16.332169 | O45: 89.088905 | P45: 5.909052 | Q45: 83.653704
J46: cfsrv | K46: 2.640969 | L46: 2.5304883 | M46: 0.22288281 | P46: 0.9164742 | Q46: 7.6981272
J47: creal | K47: 7.5624535 | L47: 4.6532349 | M47: 0.23023793
J48: cbsrv | K48: 6.1122353 | L48: 4.1297674 | M48: 0.89086321
J49: cpadm | K49: 6.1395981 | L49: 9.3955679 | M49: 3.1674728 | N49: 17.223761 | O49: 24.835387
J50: ceduc | K50: 3.0284193 | L50: 2.7894767 | M50: 0.82173611
J51: cheal | K51: 1.8429429 | L51: 2.1199405 | M51: 0.43286207
J52: cosrv | K52: 5.6102694 | L52: 4.2855668 | M52: 5.102442
J53: TOTAL-1 | K53: 100 | L53: 100 | M53: 100 | N53: 100 | O53: 12.943172 | P53: 100 | Q53: 24.721843

Sheet SAM
A1: Nexus Social Accounting Matrix
A2: Instruction | B2: Do not alter this sheet. This data is exported from x1aggregate.gms and x1aggregate.xlsx files, which aggregates the original SAM into the standard Nexus SAM structure.
B5: =B104/SUM(B100:B108) -> 0.47094117 | C5: =C104/SUM(C100:C108) -> 0.34589964 | D5: =D104/SUM(D100:D108) -> 0.44280743 | E5: =E104/SUM(E100:E108) -> 0.47171801 | F5: =F104/SUM(F100:F108) -> 0.39275717 | G5: =G104/SUM(G100:G108) -> 0.20980197 | H5: =H104/SUM(H100:H108) -> 0.34010801 | I5: =I104/SUM(I100:I108) -> 0.39526124 | J5: {=SUM(B104:I104/SUM(B100:I106))} -> 0.41063561
B7: acere | C7: apuls | D7: aoils | E7: aroot | F7: avege | G7: abecr | H7: aocrp | I7: afrui | J7: alive | K7: amilk | L7: afore | M7: afish | N7: amine | O7: amino | P7: ameat | Q7: afsea | R7: afveg | S7: afoil | T7: adair | U7: agmll | V7: afobe | W7: aoapr | X7: atext | Y7: awood | Z7: apetr | AA7: achem | AB7: anmet | AC7: ametl | AD7: amach | AE7: aoman | AF7: aelec | AG7: awatr | AH7: acons | AI7: atrad | AJ7: atran | AK7: ahotl | AL7: arest | AM7: acomm | AN7: afsrv | AO7: areal | AP7: absrv | AQ7: apadm | AR7: aeduc | AS7: aheal | AT7: aosrv | AU7: ccere | AV7: cpuls | AW7: coils | AX7: croot | AY7: cvege | AZ7: cbecr | BA7: cocrp | BB7: cfrui | BC7: clive | BD7: cmilk | BE7: cfore | BF7: cfish | BG7: cmine | BH7: cmino | BI7: cmeat | BJ7: cfsea | BK7: cfveg | BL7: cfoil | BM7: cdair | BN7: cgmll | BO7: cfobe | BP7: coapr | BQ7: ctext | BR7: cwood | BS7: cpetr | BT7: cfert | BU7: cchem | BV7: cnmet | BW7: cmetl | BX7: cmach | BY7: coman | BZ7: celec | CA7: cwatr | CB7: ccons | CC7: ctrad | CD7: ctran | CE7: chotl | CF7: crest | CG7: ccomm | CH7: cfsrv | CI7: creal | CJ7: cbsrv | CK7: cpadm | CL7: ceduc | CM7: cheal | CN7: cosrv | CO7: trc | CP7: flab-n | CQ7: flab-p | CR7: flab-s | CS7: flab-t | CT7: flnd | CU7: fcap-c | CV7: fcap-l | CW7: fcap-m | CX7: fcap-o | CY7: ent | CZ7: hhd-f1 | DA7: hhd-f2 | DB7: hhd-f3 | DC7: hhd-f4 | DD7: hhd-f5 | DE7: hhd-n1 | DF7: hhd-n2 | DG7: hhd-n3 | DH7: hhd-n4 | DI7: hhd-n5 | DJ7: hhd-u1 | DK7: hhd-u2 | DL7: hhd-u3 | DM7: hhd-u4 | DN7: hhd-u5 | DO7: gov | DP7: dtax | DQ7: mtax | DR7: stax | DS7: s-i | DT7: row | DU7: total
A8: acere | AU8: 145.09821 | CZ8: 1.7820724 | DA8: 3.1392521 | DB8: 3.4494678 | DC8: 4.2713719 | DD8: 1.8633422 | DE8: 0.29108973 | DF8: 0.72137474 | DG8: 0.60155906 | DH8: 0.7359538 | DI8: 0.41571703 | DJ8: 0.024624876 | DK8: 0.086573363 | DL8: 0.075457568 | DM8: 0.14457011 | DN8: 0.2121983 | DU8: 162.91284
A9: apuls | AV9: 99.520762 | CZ9: 2.4893385 | DA9: 4.2393935 | DB9: 5.6110611 | DC9: 7.0294043 | DD9: 3.928866 | DE9: 0.56070403 | DF9: 0.93306068 | DG9: 1.0558421 | DH9: 1.0823772 | DI9: 0.60731415 | DJ9: 0.071234165 | DK9: 0.13987332 | DL9: 0.24626211 | DM9: 0.40529715 | DN9: 0.89996177 | DU9: 128.82075
A10: aoils | AW10: 60.304902 | CZ10: 0.066754537 | DA10: 0.47476601 | DB10: 0.51146258 | DC10: 2.050175 | DD10: 1.2453566 | DE10: 0.11179547 | DF10: 0.19114966 | DH10: 0.34784657 | DI10: 0.03358021 | DM10: 0.020303787 | DN10: 0.32493121 | DU10: 65.683023
A11: aroot | AX11: 325.84099 | CZ11: 17.039033 | DA11: 33.437974 | DB11: 46.567662 | DC11: 54.837768 | DD11: 26.865786 | DE11: 3.798836 | DF11: 6.6830325 | DG11: 9.3374122 | DH11: 9.1941426 | DI11: 4.3758533 | DJ11: 0.37170609 | DK11: 1.4679745 | DL11: 1.6377807 | DM11: 2.0660144 | DN11: 3.5819084 | DU11: 547.10388
A12: avege | AY12: 78.999376 | CZ12: 0.98642824 | DA12: 1.129752 | DB12: 1.3454564 | DC12: 1.3456928 | DD12: 0.69813728 | DE12: 0.21015605 | DF12: 0.22810182 | DG12: 0.23602143 | DH12: 0.19301601 | DI12: 0.15412739 | DJ12: 0.068304876 | DK12: 0.086814327 | DL12: 0.11652082 | DM12: 0.13546358 | DN12: 0.24868201 | DU12: 86.182051
A13: abecr | AZ13: 207.09947 | CZ13: 0.020909498 | DA13: 0.14862248 | DB13: 0.160102 | DC13: 0.64028896 | DD13: 0.3893766 | DU13: 208.45877
A14: aocrp | BA14: 6.2139681 | CZ14: 0.0031915993 | DA14: 0.0075054861 | DB14: 6.7278264e-05 | DC14: 0.0322881 | DD14: 0.085926117 | DH14: 0.07796561 | DN14: 0.021857578 | DU14: 6.4427698
A15: afrui | BB15: 238.8893 | CZ15: 3.9033868 | DA15: 7.4907735 | DB15: 12.816528 | DC15: 21.126911 | DD15: 16.380037 | DE15: 0.57414547 | DF15: 1.97384 | DG15: 2.1171639 | DH15: 2.9894256 | DI15: 2.2074637 | DJ15: 0.095860698 | DK15: 0.33230953 | DL15: 1.1139412 | DM15: 1.4695902 | DN15: 4.8741653 | DU15: 318.35484
A16: alive | BC16: 159.5966 | CZ16: 0.46639921 | DA16: 0.95987788 | DB16: 1.5816904 | DC16: 2.6660497 | DD16: 4.3651155 | DE16: 0.090104946 | DF16: 0.1667572 | DG16: 0.26375588 | DH16: 0.55935128 | DI16: 0.69822616 | DJ16: 0.015205968 | DK16: 0.053003564 | DL16: 0.038825463 | DM16: 0.072125097 | DN16: 4.0917431 | DU16: 175.68484
A17: amilk | BD17: 82.94532 | CZ17: 0.29871704 | DA17: 1.8652035 | DB17: 3.4592336 | DC17: 9.0587726 | DD17: 10.36788 | DE17: 0.036381651 | DF17: 0.26036541 | DG17: 0.5942017 | DH17: 1.2106905 | DI17: 0.63797885 | DJ17: 0.015797378 | DK17: 0.1772489 | DL17: 0.32283471 | DM17: 0.92540094 | DN17: 3.6867976 | DU17: 115.86282
A18: afore | BE18: 69.964671 | CZ18: 79.115102 | DA18: 90.832292 | DB18: 98.451839 | DC18: 97.144046 | DD18: 52.975167 | DE18: 12.233701 | DF18: 14.676812 | DG18: 13.341029 | DH18: 14.344895 | DI18: 8.2614425 | DJ18: 5.7746827 | DK18: 7.9225168 | DL18: 11.369502 | DM18: 14.319446 | DN18: 8.9315511 | DU18: 599.6587
A19: afish | BF19: 33.642323 | CZ19: 0.11437143 | DA19: 0.28374004 | DB19: 0.47849884 | DC19: 0.32159525 | DD19: 0.43390641 | DE19: 0.0019076325 | DF19: 0.010221411 | DG19: 0.039596287 | DH19: 0.016605131 | DU19: 35.342765
A20: amine | BG20: 5.0369699 | DU20: 5.0369699
A21: amino | BH21: 188.76315 | DU21: 188.76315
A22: ameat | BI22: 106.61091 | DU22: 106.61091
A23: afsea | BJ23: 1.0624987 | DU23: 1.0624987
A24: afveg | BK24: 36.388926 | DU24: 36.388926
A25: afoil | BL25: 56.683936 | DU25: 56.683936
A26: adair | BM26: 9.5578741 | CZ26: 0.40362686 | DA26: 1.6233443 | DB26: 2.8280152 | DC26: 6.0225056 | DD26: 5.2531041 | DE26: 0.10996782 | DF26: 0.47454756 | DG26: 0.46336986 | DH26: 0.9219724 | DI26: 0.36630071 | DJ26: 0.068747358 | DL26: 0.32053678 | DM26: 0.48395548 | DN26: 0.37357415 | DU26: 29.271442
A27: agmll | BN27: 141.31635 | CZ27: 0.32198242 | DA27: 0.78378158 | DB27: 1.1874143 | DC27: 1.5925571 | DD27: 1.2480283 | DE27: 0.046170185 | DF27: 0.13559999 | DG27: 0.18283369 | DH27: 0.19339316 | DI27: 0.13896518 | DJ27: 0.013071076 | DK27: 0.016059855 | DL27: 0.045165062 | DM27: 0.10577161 | DN27: 0.12545317 | DU27: 147.4526
A28: afobe | BO28: 580.15588 | CZ28: 2.9228081 | DA28: 5.3369042 | DB28: 13.591556 | DC28: 34.682694 | DD28: 32.962728 | DE28: 0.50394281 | DF28: 2.1598576 | DG28: 4.3488146 | DH28: 4.0375209 | DI28: 4.6875275 | DJ28: 1.1359115e-05 | DK28: 0.88532665 | DL28: 0.68465487 | DM28: 1.0224212 | DN28: 8.9134268 | DU28: 696.89607
A29: aoapr | BP29: 37.508228 | DU29: 37.508228
A30: atext | BQ30: 146.05317 | DU30: 146.05317
A31: awood | BR31: 72.749181 | DU31: 72.749181
A32: apetr | BS32: 0.69963232 | DU32: 0.69963232
A33: achem | BU33: 111.65257 | DU33: 111.65257
A34: anmet | BV34: 98.698386 | DU34: 98.698386
A35: ametl | BW35: 75.890287 | DU35: 75.890287
A36: amach | BX36: 135.94789 | DU36: 135.94789
A37: aoman | BY37: 31.884649 | DU37: 31.884649
A38: aelec | BZ38: 220.60694 | DU38: 220.60694
A39: awatr | CA39: 75.773857 | DU39: 75.773857
A40: acons | CB40: 1864.4419 | DU40: 1864.4419
A41: atrad | CC41: 1409.6057 | DU41: 1409.6057
A42: atran | CD42: 1049.7073 | DU42: 1049.7073
A43: ahotl | CE43: 136.64748 | DU43: 136.64748
A44: arest | CF44: 484.35813 | DU44: 484.35813
A45: acomm | CG45: 348.32403 | DU45: 348.32403
A46: afsrv | CH46: 361.69745 | DU46: 361.69745
A47: areal | CI47: 665.114 | DU47: 665.114
A48: absrv | CJ48: 590.29173 | DU48: 590.29173
A49: apadm | CK49: 1342.9633 | DU49: 1342.9633
A50: aeduc | CL50: 398.71618 | DU50: 398.71618
A51: aheal | CM51: 303.01546 | DU51: 303.01546
A52: aosrv | CN52: 612.56106 | DU52: 612.56106
A53: ccere | B53: 1.990673 | J53: 7.4487626 | U53: 82.051765 | V53: 8.1652637 | CZ53: 8.3784421 | DA53: 12.279522 | DB53: 13.873731 | DC53: 13.893501 | DD53: 9.2052915 | DE53: 1.6815114 | DF53: 1.3080258 | DG53: 2.8195568 | DH53: 2.4491433 | DI53: 1.4579352 | DJ53: 0.3551569 | DK53: 0.76700151 | DL53: 0.75515549 | DM53: 1.617054 | DN53: 4.6805725 | DU53: 175.17807
A54: cpuls | C54: 1.0093277 | AK54: 2.2417399 | AL54: 8.1961383 | CZ54: 5.4119486 | DA54: 7.4494451 | DB54: 9.0359364 | DC54: 9.2688042 | DD54: 6.7083537 | DE54: 1.1916042 | DF54: 1.2926038 | DG54: 1.5274885 | DH54: 1.2582 | DI54: 1.3624336 | DJ54: 0.60777679 | DK54: 1.1692168 | DL54: 1.6930729 | DM54: 2.8298049 | DN54: 11.444245 | DT54: 36.897745 | DU54: 110.59588
A55: coils | D55: 7.5988349 | S55: 24.734089 | U55: 0.39027334 | V55: 7.0817224 | W55: 13.380256 | AK55: 0.0035991548 | AL55: 0.013303105 | CZ55: 0.082848644 | DA55: 0.15732568 | DB55: 0.35745288 | DC55: 0.84763119 | DD55: 1.9707705 | DF55: 0.076334912 | DG55: 0.068371713 | DH55: 0.14775492 | DI55: 0.43170522 | DJ55: 0.062514218 | DK55: 0.17910417 | DL55: 0.41529811 | DM55: 0.86348344 | DN55: 13.065844 | DU55: 71.928517
A56: croot | E56: 7.7105442 | U56: 0.38980858 | V56: 44.451336 | AK56: 10.565579 | AL56: 38.451812 | CZ56: 28.031863 | DA56: 33.687296 | DB56: 37.351416 | DC56: 40.154543 | DD56: 23.834845 | DE56: 5.6427771 | DF56: 6.3829731 | DG56: 5.1005826 | DH56: 6.1397041 | DI56: 4.7273714 | DJ56: 4.3842555 | DK56: 7.0414223 | DL56: 8.5175708 | DM56: 11.369426 | DN56: 30.743448 | DU56: 354.67857
A57: cvege | F57: 0.4167789 | R57: 5.3849376 | AK57: 1.5929321 | AL57: 5.7982456 | CZ57: 4.6736776 | DA57: 5.8167717 | DB57: 6.3007514 | DC57: 6.5593797 | DD57: 5.2100441 | DE57: 1.0060443 | DF57: 0.98575393 | DG57: 1.0683735 | DH57: 1.0065173 | DI57: 1.0666564 | DJ57: 0.43037335 | DK57: 0.96724918 | DL57: 1.2419949 | DM57: 2.3264072 | DN57: 11.529799 | DT57: 31.674154 | DU57: 95.056842
A58: cbecr | G58: 19.646192 | V58: 28.263987 | CZ58: 0.015927414 | DA58: 0.10231367 | DB58: 0.11094024 | DC58: 0.43401545 | DD58: 0.26580538 | DE58: 0.023872448 | DF58: 0.040610678 | DG58: 0.00075382299 | DH58: 0.073546878 | DI58: 0.0080927017 | DJ58: 0.00026243474 | DK58: 0.00050163675 | DL58: 0.00073806035 | DM58: 0.0056640571 | DN58: 0.079356604 | DT58: 194.21407 | DU58: 243.28665
A59: cocrp | W59: 1.0158152 | CZ59: 0.077551063 | DA59: 0.098551584 | DB59: 0.11838894 | DC59: 0.12033955 | DD59: 0.1301297 | DE59: 0.020921082 | DF59: 0.030824594 | DG59: 0.020800858 | DH59: 0.021934081 | DI59: 0.012335056 | DJ59: 0.003416932 | DK59: 0.0044949778 | DL59: 0.019483924 | DM59: 0.057230074 | DN59: 2.1737538 | DT59: 3.1398045 | DU59: 7.065776
A60: cfrui | I60: 1.3162401 | R60: 5.2964831 | S60: 0.70066465 | V60: 32.48456 | AK60: 5.1676869 | AL60: 19.19237 | CZ60: 6.5214655 | DA60: 11.412929 | DB60: 15.459818 | DC60: 22.270047 | DD60: 21.416681 | DE60: 1.2379764 | DF60: 1.8347025 | DG60: 2.6906369 | DH60: 3.235964 | DI60: 4.030414 | DJ60: 0.95805085 | DK60: 1.7233062 | DL60: 2.7630629 | DM60: 7.1741737 | DN60: 51.49186 | DT60: 51.284225 | DU60: 269.66332
A61: clive | J61: 3.3707994 | P61: 77.30627 | Q61: 0.74966068 | V61: 0.10053313 | AK61: 3.5314239 | AL61: 13.321687 | CZ61: 1.9960695 | DA61: 3.4673569 | DB61: 5.582501 | DC61: 9.3557918 | DD61: 12.959505 | DE61: 0.83700206 | DF61: 0.57468905 | DG61: 1.3252964 | DH61: 1.5138392 | DI61: 3.1937491 | DJ61: 0.18297818 | DK61: 0.40042752 | DL61: 1.0635107 | DM61: 1.6674503 | DN61: 20.021666 | DS61: 8.1051688 | DU61: 170.62738
A62: cmilk | K62: 9.8494374 | R62: 1.4741718 | T62: 8.0694824 | V62: 9.2765791 | AK62: 0.060156848 | AL62: 0.22250046 | CZ62: 0.46355098 | DA62: 1.4035607 | DB62: 2.2376939 | DC62: 5.3211501 | DD62: 9.1199547 | DE62: 0.12610133 | DF62: 0.13592275 | DG62: 0.36508629 | DH62: 0.79980613 | DI62: 2.2730095 | DJ62: 0.080579277 | DK62: 0.31242839 | DL62: 0.77466561 | DM62: 2.2120168 | DN62: 37.241075 | DU62: 91.818929
A63: cfore | L63: 20.981762 | N63: 0.014979307 | O63: 0.45725808 | R63: 0.2948724 | V63: 1.3009023 | Y63: 14.807927 | AB63: 0.02373539 | AF63: 1.2192273 | AH63: 41.393199 | AK63: 4.1745375 | AL63: 15.386634 | CZ63: 0.0078059219 | DA63: 0.023117667 | DB63: 0.056233424 | DC63: 0.1120336 | DD63: 0.17897657 | DE63: 0.0030860813 | DF63: 0.0055738233 | DG63: 0.0066159201 | DH63: 0.015742561 | DI63: 0.036959735 | DJ63: 0.0080516903 | DK63: 0.04006068 | DL63: 0.063310901 | DM63: 0.20943162 | DN63: 1.2289077 | DU63: 102.05094
A64: cfish | M64: 0.11504801 | AK64: 0.27915762 | AL64: 1.0415887 | CZ64: 1.3576106 | DA64: 1.5253723 | DB64: 2.5341819 | DC64: 4.6264038 | DD64: 5.4175748 | DE64: 0.15535856 | DF64: 0.29583384 | DG64: 0.34684633 | DH64: 0.62496686 | DI64: 0.75592625 | DJ64: 0.04996617 | DK64: 0.23483029 | DL64: 0.39886361 | DM64: 1.5635654 | DN64: 15.229718 | DU64: 36.552813
A65: cmine | N65: 0.0051844858 | O65: 0.15969141 | V65: 0.36405973 | Z65: 0.10352232 | AC65: 0.085299334 | AK65: 0.82048283 | AL65: 3.7596333 | DU65: 5.2978734
A66: cmino | N66: 0.023298471 | O66: 0.75119765 | AB66: 6.1670173 | AC66: 5.5143036 | AD66: 0.042128393 | AH66: 100.1769 | AJ66: 0.25368206 | AK66: 0.13361999 | AL66: 0.49343643 | DT66: 280.76759 | DU66: 394.32317
A67: cmeat | P67: 0.056209481 | Q67: 0.00059252082 | V67: 13.432203 | AK67: 3.2408345 | AL67: 12.031711 | CZ67: 0.71219578 | DA67: 2.4493541 | DB67: 4.3388518 | DC67: 10.278342 | DD67: 18.25776 | DE67: 0.10773925 | DF67: 0.45469334 | DG67: 0.60264061 | DH67: 1.4374906 | DI67: 2.6859359 | DJ67: 0.15198395 | DK67: 0.5835696 | DL67: 1.3309473 | DM67: 3.2902213 | DN67: 43.720711 | DU67: 119.16399
A68: cfsea | V68: 1.8480429 | CZ68: 1.0668239 | DA68: 1.6631789 | DB68: 2.3133819 | DC68: 3.1127847 | DD68: 2.9077932 | DE68: 0.2972593 | DF68: 0.36729993 | DG68: 0.41790209 | DH68: 0.51906638 | DI68: 0.47825172 | DJ68: 0.18219507 | DK68: 0.32946651 | DL68: 0.50912251 | DM68: 1.0982475 | DN68: 4.117161 | DU68: 21.227978
A69: cfveg | AK69: 0.037450694 | AL69: 0.13847036 | CZ69: 0.025741911 | DA69: 0.15625205 | DB69: 0.39243118 | DC69: 1.2658461 | DD69: 2.8951632 | DF69: 0.021054123 | DG69: 0.0279124 | DH69: 0.094961976 | DI69: 1.0646285 | DJ69: 0.016968154 | DK69: 0.031286404 | DL69: 0.20849521 | DM69: 0.75100001 | DN69: 37.111016 | DU69: 44.238678
A70: cfoil | V70: 5.0164909 | AK70: 1.9928938 | AL70: 7.3291351 | CZ70: 3.9799703 | DA70: 6.9682787 | DB70: 10.225512 | DC70: 15.28241 | DD70: 14.96495 | DE70: 0.83784389 | DF70: 1.4129162 | DG70: 1.7550301 | DH70: 2.2508181 | DI70: 3.02437 | DJ70: 0.5701748 | DK70: 1.2915372 | DL70: 2.2281864 | DM70: 4.1441268 | DN70: 26.289547 | DU70: 109.56419
A71: cdair | AK71: 0.67875776 | AL71: 2.5449546 | CZ71: 0.18501356 | DA71: 0.44252413 | DB71: 0.8286076 | DC71: 1.8097729 | DD71: 2.8274095 | DE71: 0.055618926 | DF71: 0.11571258 | DG71: 0.1944016 | DH71: 0.23524753 | DI71: 0.72242376 | DJ71: 0.0066980269 | DK71: 0.069148774 | DL71: 0.11769391 | DM71: 0.26339893 | DN71: 9.2745341 | DU71: 20.371918
A72: cgmll | V72: 53.286805 | AK72: 0.39105641 | AL72: 1.4137392 | CZ72: 6.7101614 | DA72: 9.11645 | DB72: 12.122152 | DC72: 18.26951 | DD72: 18.313719 | DE72: 1.6341303 | DF72: 2.1342829 | DG72: 2.2616671 | DH72: 2.8003278 | DI72: 3.3990167 | DJ72: 0.95087392 | DK72: 1.9416743 | DL72: 2.9933354 | DM72: 6.1289788 | DN72: 33.463332 | DU72: 177.33121
A73: cfobe | R73: 0.68435963 | T73: 0.23598559 | V73: 89.814412 | AE73: 0.010899574 | AH73: 0.22607678 | AK73: 42.54872 | AL73: 151.81663 | AT73: 0.60740249 | CZ73: 16.056955 | DA73: 26.878493 | DB73: 40.727031 | DC73: 63.190047 | DD73: 86.411488 | DE73: 3.5671099 | DF73: 5.6256407 | DG73: 7.4791135 | DH73: 10.751018 | DI73: 15.164868 | DJ73: 1.6616657 | DK73: 3.8003877 | DL73: 7.663775 | DM73: 16.064735 | DN73: 222.997 | DT73: 57.601126 | DU73: 871.58494
A74: coapr | J74: 17.648922 | K74: 8.2332198 | M74: 1.0264108 | AK74: 0.4182854 | AL74: 1.5369231 | CZ74: 0.95090288 | DA74: 1.6011533 | DB74: 2.3500117 | DC74: 3.1670134 | DD74: 2.0097711 | DE74: 0.15452341 | DF74: 0.34357123 | DG74: 0.36590324 | DH74: 0.38730184 | DI74: 0.32319006 | DJ74: 0.33377583 | DK74: 0.40020777 | DL74: 1.0581356 | DM74: 1.2907555 | DN74: 7.2885293 | DU74: 50.888508
A75: ctext | N75: 0.0033609127 | O75: 0.19852275 | X75: 28.627956 | AD75: 2.8203503 | AF75: 0.101839 | AH75: 5.3255096 | AJ75: 2.7273065 | AK75: 2.2902586 | AL75: 8.452315 | AM75: 6.2229115 | AN75: 8.0080454 | AP75: 10.328618 | AQ75: 9.0461956 | AR75: 3.1075683 | AS75: 0.022338983 | CZ75: 13.152642 | DA75: 22.164772 | DB75: 32.3457 | DC75: 46.243384 | DD75: 52.622715 | DE75: 3.0360187 | DF75: 4.5041249 | DG75: 5.5424246 | DH75: 7.3506884 | DI75: 9.0329601 | DJ75: 1.2272682 | DK75: 2.6945781 | DL75: 5.2739213 | DM75: 11.615767 | DN75: 142.80203 | DU75: 446.89209
A76: cwood | N76: 0.013564005 | O76: 0.45428766 | P76: 0.56183588 | Q76: 0.0059299515 | R76: 3.6890379 | S76: 0.0080770439 | T76: 1.337799 | U76: 1.2826429 | V76: 13.187785 | X76: 0.66640372 | Y76: 14.062871 | Z76: 2.7583198e-06 | AA76: 2.5797941 | AB76: 0.25246376 | AC76: 0.10006958 | AD76: 9.8671822 | AE76: 0.051637602 | AF76: 0.22309559 | AG76: 0.11208234 | AH76: 50.648008 | AI76: 1.2031685 | AJ76: 3.9637416 | AK76: 0.37574664 | AL76: 1.3875223 | AM76: 0.087075059 | AN76: 0.002287225 | AO76: 0.22588606 | AP76: 1.9482301 | AQ76: 14.3343 | AR76: 13.324331 | AS76: 3.2263364 | AT76: 9.5750042 | CZ76: 0.45978841 | DA76: 0.77380942 | DB76: 2.7834335 | DC76: 3.4207354 | DD76: 5.2584011 | DE76: 0.050050955 | DF76: 0.22319253 | DG76: 0.29253178 | DH76: 0.43835986 | DI76: 1.0601161 | DJ76: 0.082427249 | DK76: 0.15247152 | DL76: 0.37101678 | DM76: 1.3362903 | DN76: 22.697336 | DS76: 0.28980168 | DU76: 188.44796
A77: cpetr | B77: 0.24234109 | C77: 0.0067082951 | D77: 0.21025716 | E77: 0.094344148 | F77: 0.0027694826 | G77: 3.6291478 | H77: 0.016656805 | I77: 0.074480763 | J77: 0.54514668 | K77: 2.9171733 | L77: 20.686125 | M77: 0.21398859 | N77: 0.24292138 | O77: 11.520402 | P77: 1.4759349 | Q77: 0.015602683 | R77: 0.81081101 | S77: 2.5405062 | T77: 1.2035335 | U77: 0.94288503 | V77: 16.991928 | X77: 1.0979674 | Y77: 0.35775246 | Z77: 2.2746733e-05 | AA77: 3.4138896 | AB77: 14.593297 | AC77: 1.4496411 | AD77: 3.8790233 | AF77: 84.722281 | AG77: 3.621959 | AH77: 49.221063 | AI77: 9.1529913 | AJ77: 219.02263 | AK77: 1.3160053 | AL77: 4.8482585 | AM77: 13.278608 | AN77: 1.1909681 | AO77: 0.48750048 | AP77: 4.0416423 | AQ77: 80.087567 | AR77: 7.7256429 | AS77: 3.7784331 | AT77: 14.95897 | CZ77: 0.34341211 | DA77: 0.47429725 | DB77: 0.75450406 | DC77: 1.9943355 | DD77: 8.2405276 | DE77: 0.058536622 | DF77: 0.052557356 | DG77: 0.092985022 | DH77: 0.25585851 | DI77: 1.4144913 | DJ77: 0.085636539 | DK77: 0.09156938 | DL77: 0.16222536 | DM77: 0.14501447 | DN77: 72.198179 | DU77: 672.9939
A78: cfert | B78: 7.7807634 | C78: 4.6454324 | D78: 3.1222586 | E78: 2.3504586 | F78: 1.9205132 | G78: 9.8585791 | H78: 0.078216858 | I78: 1.1264915 | AQ78: 0.0026346071 | AS78: 87.445032 | AT78: 0.00044022878 | DU78: 118.33082
A79: cchem | B79: 0.74512631 | C79: 0.38463878 | D79: 5.4882466 | E79: 25.193028 | F79: 0.15882313 | G79: 35.889598 | H79: 0.37728491 | I79: 4.5407872 | J79: 0.074880922 | K79: 0.40199583 | M79: 0.019881313 | N79: 0.39295028 | O79: 12.291036 | P79: 0.12059554 | Q79: 0.0012716013 | R79: 1.0037016 | S79: 0.89754896 | T79: 0.63039075 | U79: 0.1090926 | V79: 22.71763 | W79: 0.8844485 | X79: 14.528508 | Y79: 4.9501637 | AA79: 3.2288274 | AB79: 5.8307447 | AC79: 0.0052880703 | AD79: 5.8163454 | AE79: 4.4285225 | AG79: 2.1231439 | AH79: 129.77964 | AI79: 16.902271 | AJ79: 61.830901 | AK79: 0.38655523 | AL79: 1.4263122 | AQ79: 3.3225417 | AR79: 0.023027189 | AS79: 2.5858492 | CZ79: 6.7813853 | DA79: 10.547825 | DB79: 15.086034 | DC79: 18.177265 | DD79: 16.540064 | DE79: 1.3409173 | DF79: 2.1681749 | DG79: 2.5295989 | DH79: 2.7790332 | DI79: 3.203396 | DJ79: 0.84983886 | DK79: 1.7103983 | DL79: 2.7923395 | DM79: 5.0977824 | DN79: 44.071377 | DT79: 89.468848 | DU79: 592.63587
A80: cnmet | R80: 1.7828497 | AF80: 8.0766946 | AH80: 139.96952 | CZ80: 0.65432465 | DA80: 0.99576985 | DB80: 1.5981411 | DC80: 2.4447193 | DD80: 3.2281566 | DE80: 0.12832105 | DF80: 0.20114912 | DG80: 0.27830251 | DH80: 0.40855337 | DI80: 0.64506846 | DJ80: 0.059371122 | DK80: 0.12436287 | DL80: 0.26380036 | DM80: 0.60263604 | DN80: 8.1987305 | DT80: 48.838451 | DU80: 218.49892
A81: cmetl | N81: 0.0060832321 | O81: 0.18548167 | AB81: 12.783129 | AC81: 31.753556 | AD81: 2.2870476 | AE81: 0.50234888 | AF81: 8.4697875 | AH81: 377.18589 | CZ81: 0.2165661 | DA81: 0.37087861 | DB81: 0.51803141 | DC81: 0.73128068 | DD81: 0.80877195 | DE81: 0.046113534 | DF81: 0.07088971 | DG81: 0.095743153 | DH81: 0.13476244 | DI81: 0.17838242 | DJ81: 0.016860149 | DK81: 0.031591256 | DL81: 0.062688549 | DM81: 0.2202795 | DN81: 1.9903854 | DU81: 438.66655
A82: cmach | N82: 0.0044476142 | O82: 0.16123411 | P82: 0.17683865 | Q82: 0.0018647254 | R82: 0.59182714 | U82: 0.26069774 | V82: 8.211489 | W82: 0.9345383 | X82: 3.2603205 | Y82: 0.34225327 | Z82: 2.2009216e-05 | AA82: 2.3205215 | AB82: 0.23142027 | AC82: 0.96775926 | AD82: 11.396363 | AE82: 0.30861967 | AF82: 0.9087776 | AG82: 7.3011831 | AH82: 99.828901 | AI82: 315.91852 | AJ82: 4.0188109 | AK82: 0.64422841 | AL82: 2.3790689 | AM82: 0.18101997 | AO82: 0.27030524 | AP82: 6.2900758 | AQ82: 10.862922 | AR82: 2.1243635 | AS82: 1.216442 | AT82: 5.5657616 | CZ82: 5.4341529 | DA82: 9.4153003 | DB82: 15.727916 | DC82: 28.065899 | DD82: 42.684112 | DE82: 1.2525449 | DF82: 2.3494596 | DG82: 2.4216256 | DH82: 4.408832 | DI82: 7.61539 | DJ82: 0.55598211 | DK82: 0.8720533 | DL82: 2.9298603 | DM82: 5.8118511 | DN82: 126.16127 | DS82: 540.36044 | DU82: 1282.7473
A83: coman | AQ83: 12.194146 | AR83: 2.4168123 | AS83: 13.572953 | AT83: 0.00043439938 | CZ83: 0.58884902 | DA83: 0.94354841 | DB83: 1.4082016 | DC83: 2.2448506 | DD83: 3.2649887 | DE83: 0.13977542 | DF83: 0.21348849 | DG83: 0.25402497 | DH83: 0.35686259 | DI83: 0.62814463 | DJ83: 0.060427865 | DK83: 0.13357083 | DL83: 0.25505953 | DM83: 0.61525529 | DN83: 12.181538 | DS83: 16.69271 | DU83: 68.165641
A84: celec | N84: 0.078226468 | O84: 2.8612158 | P84: 0.60682082 | Q84: 0.006481057 | R84: 2.5130108 | S84: 0.026034038 | T84: 0.60878701 | U84: 11.709763 | V84: 17.031442 | W84: 0.2073225 | X84: 4.1515421 | Y84: 0.76415627 | Z84: 2.7889892e-05 | AA84: 14.546006 | AB84: 8.5104081 | AC84: 12.560366 | AD84: 3.0633413 | AE84: 3.0597659 | AF84: 8.2466028 | AG84: 14.388594 | AH84: 39.645839 | AI84: 6.7303091 | AJ84: 1.0542818 | AK84: 5.2411263 | AL84: 9.2968404 | AM84: 6.8447145 | AN84: 1.8206534 | AO84: 3.88389 | AP84: 3.958937 | AQ84: 7.42991 | AR84: 7.7538847 | AS84: 3.9670228 | AT84: 6.8192732 | CZ84: 0.076637194 | DA84: 0.16275087 | DB84: 0.40617712 | DC84: 0.67899017 | DD84: 1.1769034 | DE84: 0.010933863 | DF84: 0.042374549 | DG84: 0.067199469 | DH84: 0.093303486 | DI84: 0.1782765 | DJ84: 0.02813734 | DK84: 0.083753538 | DL84: 0.23302974 | DM84: 0.67330447 | DN84: 7.4017182 | DU84: 220.70009
A85: cwatr | N85: 0.0014254958 | O85: 0.10647285 | P85: 0.89898103 | Q85: 0.009575753 | S85: 8.256324e-05 | T85: 0.14973029 | U85: 0.24688187 | V85: 4.3141097 | W85: 0.0059854202 | X85: 0.52785868 | Y85: 0.08610417 | Z85: 6.6510072e-06 | AA85: 5.024862 | AB85: 3.7656732 | AC85: 6.6100712 | AD85: 0.37669085 | AG85: 0.80987995 | AH85: 2.6488456 | AI85: 2.8491901 | AJ85: 0.63560528 | AK85: 2.042506 | AL85: 7.0167872 | AM85: 0.64369119 | AN85: 1.5638508e-05 | AO85: 2.4505966 | AP85: 1.1533987 | AR85: 11.133078 | AS85: 1.0970081 | AT85: 3.1698992 | CZ85: 0.25471635 | DA85: 0.49334694 | DB85: 0.72983992 | DC85: 1.3076826 | DD85: 2.3592161 | DE85: 0.045372274 | DF85: 0.099834689 | DG85: 0.13316252 | DH85: 0.21009872 | DI85: 0.43661859 | DJ85: 0.067996613 | DK85: 0.34203239 | DL85: 0.52041813 | DM85: 1.1127151 | DN85: 11.214533 | DU85: 77.102598
A86: ccons | N86: 0.023120048 | O86: 22.791724 | R86: 0.33766883 | T86: 0.22984626 | U86: 0.32029528 | V86: 2.6088961 | X86: 0.0032172396 | Y86: 0.37634348 | AA86: 4.1253318 | AC86: 0.18905852 | AD86: 0.11470355 | AE86: 1.3125763 | AF86: 0.42172848 | AG86: 0.0668722 | AH86: 25.014677 | AI86: 3.2990553 | AJ86: 3.0257204 | AK86: 1.1221301 | AL86: 4.1318593 | AO86: 5.3916999 | AP86: 1.3123028 | AQ86: 94.467489 | AR86: 10.968046 | AS86: 2.2004102 | AT86: 11.575944 | CZ86: 1.4962895 | DA86: 2.9976292 | DB86: 5.1637531 | DC86: 10.708254 | DD86: 18.559486 | DE86: 0.27987387 | DF86: 0.64946888 | DG86: 1.1286191 | DH86: 1.911545 | DI86: 2.3844117 | DJ86: 0.12491128 | DK86: 0.23398814 | DL86: 0.8251408 | DM86: 1.2149916 | DN86: 27.597149 | DS86: 1609.2127 | DU86: 1879.919
A87: ctrad | L87: 3.3492565 | M87: 0.033268986 | N87: 0.002608705 | O87: 1.9319099 | P87: 0.021228778 | Q87: 0.00022378258 | R87: 0.14274514 | T87: 0.20809849 | U87: 0.44293871 | V87: 2.0461349 | W87: 0.14889211 | X87: 0.34119638 | Y87: 0.093491375 | AA87: 1.665245 | AB87: 0.0067495216 | AC87: 0.28920729 | AD87: 0.8868051 | AF87: 1.1521205 | AG87: 0.060194091 | AH87: 2.7501886 | AI87: 93.718195 | AJ87: 39.161223 | AK87: 0.43595895 | AL87: 1.609146 | AM87: 2.7007853 | AO87: 0.061090431 | AP87: 3.4445521 | AQ87: 2.2045852 | AR87: 1.7411837 | AS87: 1.5686641 | AT87: 10.136261 | CO87: 1141.0154 | CZ87: 0.68412402 | DA87: 1.6521636 | DB87: 3.8562522 | DC87: 8.0745807 | DD87: 18.395544 | DE87: 0.049758062 | DF87: 0.17859489 | DG87: 0.34771245 | DH87: 0.70517513 | DI87: 1.4419879 | DJ87: 0.064936188 | DK87: 0.21279527 | DL87: 0.75985246 | DM87: 0.60996314 | DN87: 59.202731 | DU87: 1409.6057
A88: ctran | N88: 0.014183624 | O88: 0.62356055 | P88: 1.0534038 | Q88: 0.011122167 | R88: 0.3269335 | T88: 0.13920085 | U88: 1.8198544 | V88: 2.8802117 | W88: 0.012591423 | X88: 4.2415816 | Y88: 0.92181807 | Z88: 2.7072708e-05 | AA88: 2.5660284 | AB88: 0.015803081 | AC88: 0.68337138 | AD88: 0.89951371 | AF88: 0.58968079 | AG88: 0.49605673 | AH88: 21.812357 | AI88: 47.151325 | AJ88: 70.397132 | AK88: 0.82020373 | AL88: 3.0280082 | AM88: 4.185112 | AN88: 0.0004933174 | AO88: 0.82761596 | AP88: 5.7208166 | AQ88: 21.897671 | AR88: 10.96556 | AS88: 4.1996543 | AT88: 10.153249 | CZ88: 4.0152788 | DA88: 8.5352836 | DB88: 17.971151 | DC88: 44.493359 | DD88: 104.80842 | DE88: 0.48846281 | DF88: 1.4014005 | DG88: 2.9514904 | DH88: 4.981485 | DI88: 16.451995 | DJ88: 1.341929 | DK88: 4.2824182 | DL88: 8.4734592 | DM88: 35.702108 | DN88: 639.2609 | DT88: 461.78413 | DU88: 1575.3974
A89: chotl | N89: 0.011201989 | O89: 0.68849829 | P89: 0.1962666 | Q89: 0.0020701958 | R89: 0.0040614437 | S89: 0.14979704 | U89: 0.31654168 | V89: 1.5525424 | X89: 1.9555752 | Y89: 0.16885573 | Z89: 4.1044045e-06 | AA89: 2.6121578 | AB89: 0.13762271 | AC89: 0.66700984 | AD89: 0.55741387 | AE89: 2.085194 | AF89: 1.5849861 | AG89: 0.36814043 | AH89: 17.006115 | AI89: 3.4940168 | AJ89: 10.16751 | AK89: 0.73160519 | AL89: 2.6916976 | AM89: 1.8076487 | AN89: 0.050548125 | AO89: 1.1416954 | AP89: 6.3351062 | AQ89: 53.646045 | AR89: 15.599551 | AS89: 5.1713001 | AT89: 5.5365484 | CZ89: 0.5575475 | DA89: 1.2119794 | DB89: 2.2304577 | DC89: 3.5478848 | DD89: 4.6607259 | DE89: 0.13650066 | DF89: 0.27536849 | DG89: 0.41244578 | DH89: 0.5868995 | DI89: 1.1150421 | DJ89: 0.040362633 | DK89: 0.16556567 | DL89: 0.2216249 | DM89: 0.77315108 | DN89: 11.59638 | DT89: 36.179102 | DU89: 200.14836
A90: crest | AQ90: 60.394425 | AR90: 16.057887 | AS90: 5.2192232 | AT90: 5.5922147 | CZ90: 8.0325197 | DA90: 17.435491 | DB90: 32.009658 | DC90: 50.751492 | DD90: 66.918958 | DE90: 1.9682317 | DF90: 3.9691545 | DG90: 5.9419539 | DH90: 8.4531136 | DI90: 16.071046 | DJ90: 0.58213256 | DK90: 2.3877948 | DL90: 3.1963463 | DM90: 11.153043 | DN90: 168.22345 | DU90: 484.35813
A91: ccomm | G91: 3.1542483 | H91: 0.015214509 | J91: 0.13546508 | K91: 1.0955263 | L91: 9.6960924 | M91: 0.053456059 | N91: 0.001047189 | O91: 0.099879913 | P91: 0.12639087 | Q91: 0.0013325059 | R91: 0.075512785 | S91: 0.007636204 | T91: 0.0034337315 | U91: 0.03868981 | V91: 1.0783378 | W91: 0.006259028 | X91: 0.50551526 | Y91: 0.076970396 | Z91: 4.4827427e-06 | AA91: 0.70432507 | AB91: 0.036219931 | AC91: 0.028272551 | AD91: 0.32110898 | AE91: 0.13658428 | AF91: 0.024162381 | AG91: 0.49327946 | AH91: 1.2092838 | AI91: 2.9693676 | AJ91: 0.60918163 | AK91: 0.37424472 | AL91: 1.3828368 | AM91: 48.054846 | AN91: 0.62625817 | AO91: 0.22177279 | AP91: 2.7795294 | AQ91: 18.924681 | AR91: 8.2546369 | AS91: 2.3556229 | AT91: 2.5512614 | CZ91: 2.418384 | DA91: 5.9029364 | DB91: 10.854397 | DC91: 18.247579 | DD91: 22.113195 | DE91: 0.43386075 | DF91: 1.1978231 | DG91: 1.8916187 | DH91: 2.5975905 | DI91: 3.6363315 | DJ91: 0.4256692 | DK91: 1.1645508 | DL91: 2.4427853 | DM91: 6.9593059 | DN91: 80.532812 | DT91: 316.26488 | DU91: 585.31221
A92: cfsrv | N92: 0.019441252 | O92: 0.61315143 | P92: 0.43951083 | Q92: 0.0046361964 | R92: 0.063800011 | S92: 0.36897915 | T92: 0.039652806 | U92: 0.58440417 | V92: 1.5833148 | W92: 0.23648 | X92: 7.0460176 | Y92: 0.34956483 | Z92: 9.1184042e-05 | AA92: 5.38335 | AB92: 0.11909408 | AC92: 0.9831819 | AD92: 0.56818473 | AE92: 0.19257061 | AF92: 0.92837761 | AG92: 0.49395573 | AH92: 10.066964 | AI92: 20.514588 | AJ92: 6.42917 | AK92: 0.70660719 | AL92: 2.6086901 | AM92: 3.5048224 | AN92: 124.82766 | AO92: 1.6573252 | AP92: 5.4291374 | AQ92: 0.001231506 | AR92: 5.8605292 | AS92: 0.45500502 | AT92: 5.5497139 | CZ92: 14.966023 | DA92: 18.909959 | DB92: 22.662181 | DC92: 24.743495 | DD92: 18.951267 | DE92: 2.6712816 | DF92: 3.7296907 | DG92: 3.8781815 | DH92: 3.5710983 | DI92: 2.6158839 | DJ92: 1.0947598 | DK92: 2.0661286 | DL92: 3.3125613 | DM92: 5.0354991 | DN92: 52.165312 | DO92: 22.897405 | DT92: 15.274308 | DU92: 426.17424
A93: creal | N93: 0.020381947 | O93: 1.1895497 | P93: 1.6423012 | Q93: 0.017359305 | S93: 0.27129817 | T93: 0.020690573 | U93: 0.083889259 | V93: 3.1253423 | X93: 6.859774 | Y93: 1.145343 | AA93: 0.27842413 | AB93: 0.082465355 | AC93: 0.32670744 | AD93: 0.40181259 | AE93: 0.14051067 | AF93: 0.98407651 | AG93: 1.4212449 | AH93: 9.7974295 | AI93: 42.366087 | AJ93: 10.590489 | AK93: 3.7999136 | AL93: 13.952948 | AM93: 26.335619 | AN93: 0.0083238826 | AO93: 2.2126607 | AP93: 7.5086838 | AQ93: 19.274499 | AR93: 0.28158268 | AS93: 1.1828894 | AT93: 25.201551 | CZ93: 12.261993 | DA93: 15.939678 | DB93: 20.85319 | DC93: 31.017429 | DD93: 37.797221 | DE93: 2.5205458 | DF93: 3.3643012 | DG93: 3.9820193 | DH93: 4.8696771 | DI93: 7.5866688 | DJ93: 2.1072246 | DK93: 5.1891071 | DL93: 9.3933723 | DM93: 21.120229 | DN93: 306.5875 | DU93: 665.114
A94: cbsrv | N94: 0.02479055 | O94: 0.7755863 | P94: 0.012536735 | Q94: 0.00013215241 | S94: 0.065207231 | T94: 0.082804698 | U94: 0.23290613 | V94: 1.8028585 | X94: 0.96314075 | Y94: 0.12013702 | Z94: 3.0208477e-05 | AA94: 4.9280549 | AB94: 0.51195625 | AC94: 0.11605085 | AD94: 0.51368274 | AE94: 0.028872432 | AF94: 0.98204982 | AG94: 0.44348544 | AH94: 17.554263 | AI94: 4.0460147 | AJ94: 10.676881 | AK94: 0.78751377 | AL94: 2.9063532 | AM94: 6.5452413 | AN94: 0.082734201 | AO94: 1.9944906 | AP94: 8.7797923 | AQ94: 401.45468 | AR94: 12.056253 | AS94: 4.3565912 | AT94: 14.962785 | CZ94: 3.07259 | DA94: 5.1607675 | DB94: 6.3521159 | DC94: 9.9711535 | DD94: 11.120374 | DE94: 0.57127169 | DF94: 1.0685256 | DG94: 1.1121224 | DH94: 1.5255336 | DI94: 1.7368372 | DJ94: 0.62239293 | DK94: 1.4760247 | DL94: 3.550977 | DM94: 5.7382331 | DN94: 45.373554 | DO94: 69.539243 | DU94: 665.79959
A95: cpadm | AH95: 24.609902 | AJ95: 33.112167 | AM95: 46.950797 | CZ95: 1.2938372 | DA95: 1.535852 | DB95: 3.115822 | DC95: 4.2407319 | DD95: 6.6092265 | DE95: 0.23712065 | DF95: 0.44637634 | DG95: 0.5637536 | DH95: 0.90106068 | DI95: 1.5539372 | DJ95: 0.11789698 | DK95: 0.22393239 | DL95: 0.41958796 | DM95: 1.0040941 | DN95: 30.634602 | DO95: 851.86247 | DT95: 333.53013 | DU95: 1342.9633
A96: ceduc | N96: 0.00062914123 | O96: 0.019176212 | R96: 0.045909021 | T96: 0.0078353814 | U96: 0.0001314312 | V96: 0.05382527 | X96: 0.54738009 | Y96: 0.059468808 | Z96: 1.0890624e-06 | AA96: 2.4751038 | AB96: 0.026224183 | AC96: 0.0031255399 | AD96: 0.0082573688 | AE96: 0.049137704 | AF96: 0.17829949 | AG96: 0.13250439 | AH96: 0.37583653 | AI96: 0.065826279 | AJ96: 0.048394167 | AK96: 0.051853973 | AL96: 0.19163528 | AN96: 0.080822575 | AO96: 0.00056043684 | AP96: 0.52604388 | AR96: 8.3118206 | AS96: 2.2736724 | AT96: 2.6347069 | CZ96: 2.5088952 | DA96: 4.454806 | DB96: 7.8041372 | DC96: 14.999366 | DD96: 24.388391 | DE96: 0.42062913 | DF96: 0.72749006 | DG96: 1.0391532 | DH96: 2.2689416 | DI96: 3.2604064 | DJ96: 0.34956396 | DK96: 0.98177954 | DL96: 1.8625686 | DM96: 5.1668026 | DN96: 101.56259 | DO96: 208.75248 | DU96: 398.71618
A97: cheal | AQ97: 0.28170747 | CZ97: 5.9101048 | DA97: 7.0143657 | DB97: 7.8152701 | DC97: 9.0398419 | DD97: 12.977856 | DE97: 1.053393 | DF97: 1.3103666 | DG97: 1.5020694 | DH97: 2.9606187 | DI97: 1.6671473 | DJ97: 0.62668871 | DK97: 1.3105815 | DL97: 1.4164212 | DM97: 2.8146166 | DN97: 34.551928 | DO97: 211.16813 | DT97: 0.090589672 | DU97: 303.51169
A98: cosrv | AQ98: 10.070018 | AR98: 3.0027596 | AS98: 0.11059542 | CZ98: 12.200374 | DA98: 19.992951 | DB98: 27.159668 | DC98: 52.032565 | DD98: 63.879826 | DE98: 2.5267483 | DF98: 4.1214178 | DG98: 4.7949373 | DH98: 7.3322226 | DI98: 14.424989 | DJ98: 1.1622556 | DK98: 2.5320097 | DL98: 5.5677057 | DM98: 10.655592 | DN98: 337.37357 | DO98: 89.100599 | DT98: 5.1015758 | DU98: 673.14238
A99: trc | AU99: 8.7920022 | AV99: 10.181833 | AW99: 4.3964349 | AX99: 28.837581 | AY99: 14.676557 | AZ99: 36.187175 | BA99: 0.85180792 | BB99: 27.726993 | BC99: 10.497063 | BD99: 8.8736092 | BE99: 32.086271 | BF99: 2.9104908 | BG99: 0.10219318 | BH99: 188.13099 | BI99: 7.6199393 | BJ99: 1.7119136 | BK99: 2.9691517 | BL99: 5.5383047 | BM99: 2.7553898 | BN99: 12.828387 | BO99: 71.864913 | BP99: 3.2649339 | BQ99: 107.74658 | BR99: 21.986952 | BS99: 75.828062 | BT99: 14.600778 | BU99: 111.45141 | BV99: 43.144698 | BW99: 49.728779 | BX99: 216.97677 | BY99: 6.3449646 | CG99: 10.402449 | DU99: 1141.0154
A100: flab-n | B100: 13.48259 | C100: 13.476554 | D100: 5.0710019 | E100: 49.705573 | F100: 8.7877183 | G100: 15.305789 | H100: 0.5459166 | I100: 31.472301 | J100: 13.582914 | K100: 6.3174432 | L100: 142.11218 | M100: 11.118809 | N100: 0.094563737 | O100: 18.321921 | P100: 2.9054722 | Q100: 0.032046882 | R100: 1.570265 | S100: 3.9225401 | T100: 2.2757825 | U100: 6.6257583 | V100: 24.083325 | W100: 1.6289054 | X100: 8.5876983 | Y100: 3.3538419 | Z100: 0.0044475698 | AA100: 0.60815108 | AB100: 3.4829539 | AC100: 1.5199543 | AD100: 7.8261039 | AE100: 1.0819165 | AF100: 7.310637 | AG100: 3.7140572 | AH100: 109.93843 | AI100: 102.51847 | AJ100: 62.406988 | AK100: 2.4813277 | AL100: 10.393955 | AM100: 0.83093056 | AN100: 0.67765375 | AO100: 1.1414798 | AP100: 17.956654 | AQ100: 27.917875 | AR100: 2.4052214 | AS100: 3.4502111 | AT100: 63.016029 | DT100: 1.3621038 | DU100: 816.42646
A101: flab-p | B101: 44.802435 | C101: 42.729905 | D101: 15.319773 | E101: 148.184 | F101: 27.926062 | G101: 67.814268 | H101: 2.1384972 | I101: 105.65056 | J101: 42.608374 | K101: 18.830911 | L101: 176.26928 | M101: 9.2437897 | N101: 0.06371865 | O101: 30.231109 | P101: 4.0027249 | Q101: 0.052087305 | R101: 2.1265341 | S101: 6.7796573 | T101: 4.0295961 | U101: 10.137947 | V101: 26.169425 | W101: 1.7286966 | X101: 11.531989 | Y101: 2.9417051 | Z101: 0.0050269524 | AA101: 0.68446052 | AB101: 4.2898022 | AC101: 1.4597946 | AD101: 15.571351 | AE101: 2.8585508 | AF101: 5.0364329 | AG101: 3.1074667 | AH101: 205.39224 | AI101: 107.68198 | AJ101: 74.335806 | AK101: 6.5361578 | AL101: 22.236166 | AM101: 0.90057571 | AN101: 2.7061102 | AO101: 5.8216655 | AP101: 25.048022 | AQ101: 38.643706 | AR101: 3.2651589 | AS101: 1.3628966 | AT101: 84.68757 | DT101: 2.361257 | DU101: 1415.3053
A102: flab-s | B102: 8.8017917 | C102: 7.5507027 | D102: 2.3321118 | E102: 28.356191 | F102: 5.0391834 | G102: 7.9030717 | H102: 0.46243441 | I102: 17.706427 | J102: 10.578478 | K102: 17.968106 | L102: 8.2608251 | M102: 0.78809253 | N102: 0.52694536 | O102: 4.6591776 | P102: 1.8303805 | Q102: 0.015886972 | R102: 1.0167992 | S102: 1.7511403 | T102: 0.93235561 | U102: 3.6366173 | V102: 21.734293 | W102: 1.4477248 | X102: 4.4720745 | Y102: 4.6646255 | Z102: 0.025902877 | AA102: 2.3036804 | AB102: 0.76379812 | AC102: 0.74276794 | AD102: 3.8883938 | AE102: 0.36136487 | AF102: 8.6638181 | AG102: 3.8831543 | AH102: 47.168353 | AI102: 83.24555 | AJ102: 70.003448 | AK102: 4.4239193 | AL102: 5.2168174 | AM102: 6.4716684 | AN102: 4.7825518 | AP102: 37.873373 | AQ102: 44.436787 | AR102: 35.11969 | AS102: 9.267771 | AT102: 33.082561 | DT102: 0.94280357 | DU102: 565.10361
A103: flab-t | N103: 1.3257927 | O103: 9.7962287 | P103: 1.6468248 | Q103: 0.011074214 | R103: 0.91125026 | S103: 0.95571076 | T103: 0.5162988 | U103: 2.838441 | V103: 56.660987 | W103: 2.945296 | X103: 3.7146397 | Y103: 1.9025331 | Z103: 0.080231667 | AA103: 7.0025682 | AB103: 0.32211312 | AC103: 0.29339368 | AD103: 0.38167434 | AE103: 1.5934689 | AF103: 37.356667 | AG103: 12.755097 | AH103: 31.039467 | AI103: 139.88253 | AJ103: 135.16672 | AK103: 5.4741396 | AL103: 17.375103 | AM103: 66.496966 | AN103: 128.43382 | AO103: 114.91084 | AP103: 205.14064 | AQ103: 412.06769 | AR103: 158.33665 | AS103: 97.706213 | AT103: 238.22662 | DT103: 3.1639553 | DU103: 1896.4317
...

Sheet LES
A1: Households LES parametrization | R1: abecr | S1: cbecr
A2: DO NOT CHANGE ANYTHING UNLESS INSTRUCTED (BLACK cells should NOT be changed; color cells CAN be changed). Follow steps. | R2: aocrp | S2: cocrp
A4: STEP 0: classification
A6: SAM 4 letters | B6: cere | C6: gmll | D6: root | E6: puls | F6: vege | G6: frui | H6: fveg | I6: live | J6: fish | K6: meat | L6: fsea | M6: milk | N6: dair | O6: oils | P6: foil | Q6: fobe | R6: text | S6: elec | T6: watr | U6: real | V6: educ | W6: heal | X6: padm | Y6: becr | Z6: ocrp | AA6: fore | AB6: oapr | AC6: mine | AD6: mino | AE6: wood | AF6: petr | AG6: fert | AH6: chem | AI6: nmet | AJ6: metl | AK6: mach | AL6: oman | AM6: cons | AN6: hotl | AO6: rest | AP6: trad | AQ6: tran | AR6: comm | AS6: fsrv | AT6: bsrv | AU6: osrv
A7: SAM commodities | B7: ="c"&B6 -> ccere | C7: ="c"&C6 -> cgmll | D7: ="c"&D6 -> croot | E7: ="c"&E6 -> cpuls | F7: ="c"&F6 -> cvege | G7: ="c"&G6 -> cfrui | H7: ="c"&H6 -> cfveg | I7: ="c"&I6 -> clive | ... X7: ="c"&X6 -> cpadm | Y7: cbecr | Z7: ="c"&Z6 -> cocrp | AA7: ="c"&AA6 -> cfore | AB7: ="c"&AB6 -> coapr | AC7: ="c"&AC6 -> cmine | AD7: ="c"&AD6 -> cmino | AE7: ="c"&AE6 -> cwood | AF7: ="c"&AF6 -> cpetr | AG7: ="c"&AG6 -> cfert | ... AU7: ="c"&AU6 -> cosrv
A8: SAM activities | B8: ="a"&B6 -> acere | C8: ="a"&C6 -> agmll | D8: ="a"&D6 -> aroot | E8: ="a"&E6 -> apuls | F8: ="a"&F6 -> avege | G8: ="a"&G6 -> afrui | H8: ="a"&H6 -> afveg | I8: ="a"&I6 -> alive | ... X8: ="a"&X6 -> apadm | Y8: abecr | Z8: ="a"&Z6 -> aocrp | AA8: ="a"&AA6 -> afore | AB8: ="a"&AB6 -> aoapr | AC8: ="a"&AC6 -> amine | AD8: ="a"&AD6 -> amino | AE8: ="a"&AE6 -> awood | AF8: ="a"&AF6 -> apetr | AG8: ="a"&AG6 -> afert | ... AU8: ="a"&AU6 -> aosrv
A9: broad categories | B9: cereals | C9: cereals | D9: roots | E9: pulses | F9: vegetables | G9: fruits | H9: fruits | I9: fish-meat-egg | J9: fish-meat-egg | K9: fish-meat-egg | L9: fish-meat-egg | M9: diary | N9: diary | O9: fats & oils | P9: fats & oils | Q9: other food | R9: clothing and textile | S9: utilities | T9: utilities | U9: housing | V9: education, health and public | W9: education, health and public | X9: education, health and public | Y9: other ag | Z9: other ag | AA9: other ag | AB9: other ag | AC9: mining | AD9: mining | AE9: manufacturing | AF9: manufacturing | AG9: manufacturing | AH9: manufacturing | AI9: manufacturing | AJ9: manufacturing | AK9: manufacturing | AL9: manufacturing | AM9: contruction | AN9: hotels and restaurants | AO9: hotels and restaurants | AP9: trade, transport and comm | AQ9: trade, transport and comm | AR9: other services | AS9: other services | AT9: other services | AU9: other services
A10: given - residual categories | B10: =VLOOKUP(B9,$R$102:$S$122,2,FALSE) -> given | C10: =VLOOKUP(C9,$R$102:$S$122,2,FALSE) -> given | D10: =VLOOKUP(D9,$R$102:$S$122,2,FALSE) -> given | E10: =VLOOKUP(E9,$R$102:$S$122,2,FALSE) -> given | F10: =VLOOKUP(F9,$R$102:$S$122,2,FALSE) -> given | G10: =VLOOKUP(G9,$R$102:$S$122,2,FALSE) -> given | H10: =VLOOKUP(H9,$R$102:$S$122,2,FALSE) -> given | I10: =VLOOKUP(I9,$R$102:$S$122,2,FALSE) -> given | ... AU10: =VLOOKUP(AU9,$R$102:$S$122,2,FALSE) -> residual
A12: given=income elasticity WILL bew given
A13: residual = income elasticity WILL be calculated/calibrated as a residual
A15: STEP 1: calculate ABS - average budget shares (based on SAM).
A16: 20 groups - ABS | U16: SAM values
A17: given - residual categories | B17: caregory | C17: Rural farm | H17: Rural nonfarm | M17: Urban | R17: Total national | U17: Rural farm | Z17: Rural nonfarm | AE17: Urban | AJ17: total
C18: hhd-f1 | D18: hhd-f2 | E18: hhd-f3 | F18: hhd-f4 | G18: hhd-f5 | H18: hhd-n1 | I18: hhd-n2 | J18: hhd-n3 | K18: hhd-n4 | L18: hhd-n5 | M18: hhd-u1 | N18: hhd-u2 | O18: hhd-u3 | P18: hhd-u4 | Q18: hhd-u5 | U18: hhd-f1 | V18: hhd-f2 | W18: hhd-f3 | X18: hhd-f4 | Y18: hhd-f5 | Z18: hhd-n1 | AA18: hhd-n2 | AB18: hhd-n3 | AC18: hhd-n4 | AD18: hhd-n5 | AE18: hhd-u1 | AF18: hhd-u2 | AG18: hhd-u3 | AH18: hhd-u4 | AI18: hhd-u5
A19: =S102 -> given | B19: cereals | C19: =SUM(C49:C50) -> 5.8474237 | D19: =SUM(D49:D50) -> 5.8132634 | E19: =SUM(E49:E50) -> 5.1262812 | F19: =SUM(F49:F50) -> 4.4251416 | G19: =SUM(G49:G50) -> 3.2193942 | H19: =SUM(H49:H50) -> 6.4521064 | I19: =SUM(I49:I50) -> 5.0927933 | J19: =SUM(J49:J50) -> 5.7348475 | ... R19: =SUM(R49:R50) -> 3.1414299 | T19: cereals | U19: =SUM(U49:U50) -> 17.192658 | V19: =SUM(V49:V50) -> 25.319005 | W19: =SUM(W49:W50) -> 30.632765 | X19: =SUM(X49:X50) -> 38.02694 | Y19: =SUM(Y49:Y50) -> 30.630381 | Z19: =SUM(Z49:Z50) -> 3.6529017 | AA19: =SUM(AA49:AA50) -> 4.2992834 | AB19: =SUM(AB49:AB50) -> 5.8656167 | ... AJ19: =SUM(AJ49:AJ50) -> 221.71208
A20: =S103 -> given | B20: roots | C20: =SUM(C51:C51) -> 15.329137 | D20: =SUM(D51:D51) -> 15.412014 | E20: =SUM(E51:E51) -> 14.043551 | F20: =SUM(F51:F51) -> 11.054122 | G20: =SUM(G51:G51) -> 5.3288698 | H20: =SUM(H51:H51) -> 16.676685 | I20: =SUM(I51:I51) -> 15.477571 | J20: =SUM(J51:J51) -> 14.116111 | ... R20: =SUM(R51:R51) -> 6.7213637 | T20: roots | U20: =SUM(U51:U51) -> 45.070896 | V20: =SUM(V51:V51) -> 67.12527 | W20: =SUM(W51:W51) -> 83.919078 | X20: =SUM(X51:X51) -> 94.992311 | Y20: =SUM(Y51:Y51) -> 50.700631 | Z20: =SUM(Z51:Z51) -> 9.4416131 | AA20: =SUM(AA51:AA51) -> 13.066006 | AB20: =SUM(AB51:AB51) -> 14.437995 | ... AJ20: =SUM(AJ51:AJ51) -> 474.37238
A21: =S104 -> given | B21: pulses | C21: =C52 -> 2.6873199 | D21: =D52 -> 2.6837665 | E21: =E52 -> 2.4511214 | F21: =F52 -> 1.8965997 | G21: =G52 -> 1.1180208 | H21: =H52 -> 3.0950954 | I21: =I52 -> 2.6364508 | J21: =J52 -> 2.5257373 | ... R21: =R52 -> 1.2971815 | T21: pulses | U21: =U52 -> 7.9012871 | V21: =V52 -> 11.688839 | W21: =W52 -> 14.646997 | X21: =X52 -> 16.298208 | Y21: =Y52 -> 10.63722 | Z21: =Z52 -> 1.7523083 | AA21: =AA52 -> 2.2256645 | AB21: =AB52 -> 2.5833306 | ... AJ21: =AJ52 -> 91.550925
A22: =S105 -> given | B22: vegetables | C22: =SUM(C53:C53) -> 1.925068 | D22: =SUM(D53:D53) -> 1.5949273 | E22: =SUM(E53:E53) -> 1.2795649 | F22: =SUM(F53:F53) -> 0.91990221 | G22: =SUM(G53:G53) -> 0.62097707 | H22: =SUM(H53:H53) -> 2.1481701 | I22: =SUM(I53:I53) -> 1.4378946 | J22: =SUM(J53:J53) -> 1.2753145 | ... R22: =SUM(R53:R53) -> 0.81290826 | T22: vegetables | U22: =SUM(U53:U53) -> 5.6601058 | V22: =SUM(V53:V53) -> 6.9465237 | W22: =SUM(W53:W53) -> 7.6462077 | X22: =SUM(X53:X53) -> 7.9050725 | Y22: =SUM(Y53:Y53) -> 5.9081814 | Z22: =SUM(Z53:Z53) -> 1.2162004 | AA22: =SUM(AA53:AA53) -> 1.2138557 | AB22: =SUM(AB53:AB53) -> 1.304395 | ... AJ22: =SUM(AJ53:AJ53) -> 57.372468
A23: =S106 -> given | B23: fruits | C23: =SUM(C54:C55) -> 3.554369 | D23: =SUM(D54:D55) -> 4.3761805 | E23: =SUM(E54:E55) -> 4.7976149 | F23: =SUM(F54:F55) -> 5.197348 | G23: =SUM(G54:G55) -> 4.2769042 | H23: =SUM(H54:H55) -> 3.200744 | I23: =SUM(I54:I55) -> 4.5364174 | J23: =SUM(J54:J55) -> 4.7279048 | ... R23: =SUM(R54:R55) -> 3.9354202 | T23: fruits | U23: =SUM(U54:U55) -> 10.450594 | V23: =SUM(V54:V55) -> 19.059955 | W23: =SUM(W54:W55) -> 28.668777 | X23: =SUM(X54:X55) -> 44.662805 | Y23: =SUM(Y54:Y55) -> 40.691882 | Z23: =SUM(Z54:Z55) -> 1.8121219 | AA23: =SUM(AA54:AA55) -> 3.8295966 | AB23: =SUM(AB54:AB55) -> 4.8357131 | ... AJ23: =SUM(AJ54:AJ55) -> 277.74939
A24: =S107 -> given | B24: fish-meat-egg | C24: =SUM(C56:C59) -> 1.9432179 | D24: =SUM(D56:D59) -> 2.3761109 | E24: =SUM(E56:E59) -> 2.8162893 | F24: =SUM(F56:F59) -> 3.5330632 | G24: =SUM(G56:G59) -> 4.6605122 | H24: =SUM(H56:H59) -> 2.6306717 | I24: =SUM(I56:I59) -> 2.2145436 | J24: =SUM(J56:J59) -> 2.9292434 | ... R24: =SUM(R56:R59) -> 3.2139439 | T24: fish-meat-egg | U24: =SUM(U56:U59) -> 5.7134703 | V24: =SUM(V56:V59) -> 10.34888 | W24: =SUM(W56:W59) -> 16.829106 | X24: =SUM(X56:X59) -> 30.360967 | Y24: =SUM(Y56:Y59) -> 44.341655 | Z24: =SUM(Z56:Z59) -> 1.4893717 | AA24: =SUM(AA56:AA59) -> 1.8694948 | AB24: =SUM(AB56:AB59) -> 2.9960376 | ... AJ24: =SUM(AJ56:AJ59) -> 226.8299
A25: =S108 -> given | B25: diary | C25: =SUM(C60:C61) -> 0.45945972 | D25: =SUM(D60:D61) -> 1.2248358 | E25: =SUM(E60:E61) -> 1.5652824 | F25: =SUM(F60:F61) -> 2.5848027 | G25: =SUM(G60:G61) -> 2.8975604 | H25: =SUM(H60:H61) -> 0.57946833 | I25: =SUM(I60:I61) -> 1.1686335 | J25: =SUM(J60:J61) -> 1.5810084 | ... R25: =SUM(R60:R61) -> 1.8794543 | T25: diary | U25: =SUM(U60:U61) -> 1.3509084 | V25: =SUM(V60:V61) -> 5.3346325 | W25: =SUM(W60:W61) -> 9.3535502 | X25: =SUM(X60:X61) -> 22.212201 | Y25: =SUM(Y60:Y61) -> 27.568348 | Z25: =SUM(Z60:Z61) -> 0.32806973 | AA25: =SUM(AA60:AA61) -> 0.9865483 | AB25: =SUM(AB60:AB61) -> 1.6170595 | ... AJ25: =SUM(AJ60:AJ61) -> 132.64588
A26: =S109 -> given | B26: fats & oils | C26: =SUM(C62:C63) -> 1.4045161 | D26: =SUM(D62:D63) -> 1.745051 | E26: =SUM(E62:E63) -> 1.8566119 | F26: =SUM(F62:F63) -> 2.1156062 | G26: =SUM(G62:G63) -> 1.910915 | H26: =SUM(H62:H63) -> 1.6773444 | I26: =SUM(I62:I63) -> 1.9905489 | J26: =SUM(J62:J63) -> 1.7827506 | ... R26: =SUM(R62:R63) -> 1.6907854 | T26: fats & oils | U26: =SUM(U62:U63) -> 4.1295735 | V26: =SUM(V62:V63) -> 7.6003704 | W26: =SUM(W62:W63) -> 11.094428 | X26: =SUM(X62:X63) -> 18.180216 | Y26: =SUM(Y62:Y63) -> 18.181077 | Z26: =SUM(Z62:Z63) -> 0.94963936 | AA26: =SUM(AA62:AA63) -> 1.6804008 | AB26: =SUM(AB62:AB63) -> 1.8234018 | ... AJ26: =SUM(AJ62:AJ63) -> 119.33023
A27: =S110 -> given | B27: other food | C27: =SUM(C64:C64) -> 6.4552387 | D27: =SUM(D64:D64) -> 7.3966803 | E27: =SUM(E64:E64) -> 9.0900167 | F27: =SUM(F64:F64) -> 11.389314 | G27: =SUM(G64:G64) -> 12.54678 | H27: =SUM(H64:H64) -> 7.1906849 | I27: =SUM(I64:I64) -> 9.2224516 | J27: =SUM(J64:J64) -> 11.564234 | ... R27: =SUM(R64:R64) -> 9.1358558 | T27: other food | U27: =SUM(U64:U64) -> 18.979763 | V27: =SUM(V64:V64) -> 32.215397 | W27: =SUM(W64:W64) -> 54.318586 | X27: =SUM(X64:X64) -> 97.872741 | Y27: =SUM(Y64:Y64) -> 119.37422 | Z27: =SUM(Z64:Z64) -> 4.0710527 | AA27: =SUM(AA64:AA64) -> 7.7854982 | AB27: =SUM(AB64:AB64) -> 11.827928 | ... AJ27: =SUM(AJ64:AJ64) -> 644.77952
A28: =S111 -> given | B28: clothing and textile | C28: =SUM(C65:C65) -> 4.473367 | D28: =SUM(D65:D65) -> 5.089049 | E28: =SUM(E65:E65) -> 5.4129345 | F28: =SUM(F65:F65) -> 5.3812777 | G28: =SUM(G65:G65) -> 5.5308897 | H28: =SUM(H65:H65) -> 5.3625083 | I28: =SUM(I65:I65) -> 5.335442 | J28: =SUM(J65:J65) -> 5.4188607 | ... R28: =SUM(R65:R65) -> 5.0952858 | T28: clothing and textile | U28: =SUM(U65:U65) -> 13.152642 | V28: =SUM(V65:V65) -> 22.164772 | W28: =SUM(W65:W65) -> 32.3457 | X28: =SUM(X65:X65) -> 46.243384 | Y28: =SUM(Y65:Y65) -> 52.622715 | Z28: =SUM(Z65:Z65) -> 3.0360187 | AA28: =SUM(AA65:AA65) -> 4.5041249 | AB28: =SUM(AB65:AB65) -> 5.5424246 | ... AJ28: =SUM(AJ65:AJ65) -> 359.60899
A29: =S112 -> given | B29: utilities | C29: =SUM(C66:C67) -> 0.11269721 | D29: =SUM(D66:D67) -> 0.15064057 | E29: =SUM(E66:E67) -> 0.19010829 | F29: =SUM(F66:F67) -> 0.23118633 | G29: =SUM(G66:G67) -> 0.37166245 | H29: =SUM(H66:H67) -> 0.099453317 | I29: =SUM(I66:I67) -> 0.1684565 | J29: =SUM(J66:J67) -> 0.19589508 | ... R29: =SUM(R66:R67) -> 0.43415218 | T29: utilities | U29: =SUM(U66:U67) -> 0.33135355 | V29: =SUM(V66:V67) -> 0.6560978 | W29: =SUM(W66:W67) -> 1.136017 | X29: =SUM(X66:X67) -> 1.9866728 | Y29: =SUM(Y66:Y67) -> 3.5361196 | Z29: =SUM(Z66:Z67) -> 0.056306137 | AA29: =SUM(AA66:AA67) -> 0.14220924 | AB29: =SUM(AB66:AB67) -> 0.20036199 | ... AJ29: =SUM(AJ66:AJ67) -> 30.641074
A30: =S113 -> given | B30: housing | C30: =C68 -> 4.170447 | D30: =D68 -> 3.6597626 | E30: =E68 -> 3.489705 | F30: =F68 -> 3.6094547 | G30: =G68 -> 3.972662 | H30: =H68 -> 4.4520305 | I30: =I68 -> 3.9852434 | J30: =J68 -> 3.8932434 | ... R30: =R68 -> 6.866139 | T30: housing | U30: =U68 -> 12.261993 | V30: =V68 -> 15.939678 | W30: =W68 -> 20.85319 | X30: =X68 -> 31.017429 | Y30: =Y68 -> 37.797221 | Z30: =Z68 -> 2.5205458 | AA30: =AA68 -> 3.3643012 | AB30: =AB68 -> 3.9820193 | ... AJ30: =AJ68 -> 484.59015
A31: =S114 -> given | B31: education, health and public | C31: =SUM(C69:C71) -> 3.3034492 | D31: =SUM(D69:D71) -> 2.9859636 | E31: =SUM(E69:E71) -> 3.1352721 | F31: =SUM(F69:F71) -> 3.2908969 | G31: =SUM(G69:G71) -> 4.6220248 | H31: =SUM(H69:H71) -> 3.0223849 | I31: =SUM(I69:I71) -> 2.9427428 | J31: =SUM(J69:J71) -> 3.0357533 | ... R31: =SUM(R69:R71) -> 4.4868086 | T31: education, health and public | U31: =SUM(U69:U71) -> 9.7128372 | V31: =SUM(V69:V71) -> 13.005024 | W31: =SUM(W69:W71) -> 18.735229 | X31: =SUM(X69:X71) -> 28.27994 | Y31: =SUM(Y69:Y71) -> 43.975474 | Z31: =SUM(Z69:Z71) -> 1.7111427 | AA31: =SUM(AA69:AA71) -> 2.484233 | AB31: =SUM(AB69:AB71) -> 3.1049762 | ... AJ31: =SUM(AJ69:AJ71) -> 316.66462
A32: =S116 -> residual | B32: other ag | C32: =SUM(C72:C75) -> 27.274027 | D32: =SUM(D72:D75) -> 21.310065 | E32: =SUM(E72:E75) -> 16.943412 | F32: =SUM(F72:F75) -> 11.828871 | G32: =SUM(G72:G75) -> 5.8895526 | H32: =SUM(H72:H75) -> 21.965844 | I32: =SUM(I72:I75) -> 17.883887 | J32: =SUM(J72:J75) -> 13.42889 | ... R32: =SUM(R72:R75) -> 7.9257673 | T32: other ag | U32: =SUM(U72:U75) -> 80.191391 | V32: =SUM(V72:V75) -> 92.813556 | W32: =SUM(W72:W75) -> 101.24758 | X32: =SUM(X72:X75) -> 101.65003 | Y32: =SUM(Y72:Y75) -> 56.035152 | Z32: =SUM(Z72:Z75) -> 12.436104 | AA32: =SUM(AA72:AA75) -> 15.097393 | AB32: =SUM(AB72:AB75) -> 13.735103 | ... AJ32: =SUM(AJ72:AJ75) -> 559.37534
A33: =S117 -> residual | B33: mining | C33: =SUM(C76:C77) -> 0 | D33: =SUM(D76:D77) -> 0 | E33: =SUM(E76:E77) -> 0 | F33: =SUM(F76:F77) -> 0 | G33: =SUM(G76:G77) -> 0 | H33: =SUM(H76:H77) -> 0 | I33: =SUM(I76:I77) -> 0 | J33: =SUM(J76:J77) -> 0 | ... R33: =SUM(R76:R77) -> 0 | T33: mining | U33: =SUM(U76:U77) -> 0 | V33: =SUM(V76:V77) -> 0 | W33: =SUM(W76:W77) -> 0 | X33: =SUM(X76:X77) -> 0 | Y33: =SUM(Y76:Y77) -> 0 | Z33: =SUM(Z76:Z77) -> 0 | AA33: =SUM(AA76:AA77) -> 0 | AB33: =SUM(AB76:AB77) -> 0 | ... AJ33: =SUM(AJ76:AJ77) -> 0
A34: =S118 -> residual | B34: manufacturing | C34: =SUM(C78:C85) -> 4.9242994 | D34: =SUM(D78:D85) -> 5.4005383 | E34: =SUM(E78:E85) -> 6.3384538 | F34: =SUM(F78:F85) -> 6.6422132 | G34: =SUM(G78:G85) -> 8.4109984 | H34: =SUM(H78:H85) -> 5.3276082 | I34: =SUM(I78:I85) -> 6.2532297 | J34: =SUM(J78:J85) -> 5.8318313 | ... R34: =SUM(R78:R85) -> 7.9878791 | T34: manufacturing | U34: =SUM(U78:U85) -> 14.478478 | V34: =SUM(V78:V85) -> 23.521428 | W34: =SUM(W78:W85) -> 37.876262 | X34: =SUM(X78:X85) -> 57.079086 | Y34: =SUM(Y78:Y85) -> 80.025022 | Z34: =SUM(Z78:Z85) -> 3.0162598 | AA34: =SUM(AA78:AA85) -> 5.2789118 | AB34: =SUM(AB78:AB85) -> 5.9648119 | ... AJ34: =SUM(AJ78:AJ85) -> 563.75899
A35: =S119 -> residual | B35: contruction | C35: =C86 -> 0.50890552 | D35: =D86 -> 0.688258 | E35: =E86 -> 0.86413519 | F35: =F86 -> 1.2461045 | G35: =G86 -> 1.9506874 | H35: =H86 -> 0.49434015 | I35: =I86 -> 0.76934001 | J35: =J86 -> 1.1034575 | ... R35: =R86 -> 1.0665758 | T35: contruction | U35: =U86 -> 1.4962895 | V35: =V86 -> 2.9976292 | W35: =W86 -> 5.1637531 | X35: =X86 -> 10.708254 | Y35: =Y86 -> 18.559486 | Z35: =Z86 -> 0.27987387 | AA35: =AA86 -> 0.64946888 | AB35: =AB86 -> 1.1286191 | ... AJ35: =AJ86 -> 75.275511
A36: =S120 -> residual | B36: hotels and restaurants | C36: =SUM(C87,C88) -> 2.9215821 | D36: =SUM(D87,D88) -> 4.2814738 | E36: =SUM(E87,E88) -> 5.729958 | F36: =SUM(F87,F88) -> 6.3187424 | G36: =SUM(G87,G88) -> 7.5233544 | H36: =SUM(H87,H88) -> 3.7175808 | I36: =SUM(I87,I88) -> 5.0279259 | J36: =SUM(J87,J88) -> 6.2127334 | ... R36: =SUM(R87,R88) -> 6.0165137 | T36: hotels and restaurants | U36: =SUM(U87,U88) -> 8.5900672 | V36: =SUM(V87,V88) -> 18.647471 | W36: =SUM(W87,W88) -> 34.240115 | X36: =SUM(X87,X88) -> 54.299377 | Y36: =SUM(Y87,Y88) -> 71.579684 | Z36: =SUM(Z87,Z88) -> 2.1047324 | AA36: =SUM(AA87,AA88) -> 4.244523 | AB36: =SUM(AB87,AB88) -> 6.3543996 | ... AJ36: =SUM(AJ87,AJ88) -> 424.62632
A37: =S121 -> residual | B37: trade, transport and comm | C37: =SUM(C89:C91) -> 2.4208423 | D37: =SUM(D89:D91) -> 3.6943646 | E37: =SUM(E89:E91) -> 5.4691798 | F37: =SUM(F89:F91) -> 8.2407026 | G37: =SUM(G89:G91) -> 15.273503 | H37: =SUM(H89:H91) -> 1.7169841 | I37: =SUM(I89:I91) -> 3.2905148 | J37: =SUM(J89:J91) -> 5.0750963 | ... R37: =SUM(R89:R91) -> 16.325677 | T37: trade, transport and comm | U37: =SUM(U89:U91) -> 7.1177869 | V37: =SUM(V89:V91) -> 16.090384 | W37: =SUM(W89:W91) -> 32.681801 | X37: =SUM(X89:X91) -> 70.815518 | Y37: =SUM(Y89:Y91) -> 145.31716 | Z37: =SUM(Z89:Z91) -> 0.97208162 | AA37: =SUM(AA89:AA91) -> 2.7778186 | AB37: =SUM(AB89:AB91) -> 5.1908215 | ... AJ37: =SUM(AJ89:AJ91) -> 1152.2142
A38: =S122 -> residual | B38: other services | C38: =SUM(C92:C94) -> 10.284632 | D38: =SUM(D92:D94) -> 10.117055 | E38: =SUM(E92:E94) -> 9.4005074 | F38: =SUM(F92:F94) -> 10.094652 | G38: =SUM(G92:G94) -> 9.874732 | H38: =SUM(H92:H94) -> 10.190295 | I38: =SUM(I92:I94) -> 10.565913 | J38: =SUM(J92:J94) -> 9.5670872 | ... R38: =SUM(R92:R94) -> 11.966858 | T38: other services | U38: =SUM(U92:U94) -> 30.238987 | V38: =SUM(V92:V94) -> 44.063677 | W38: =SUM(W92:W94) -> 56.173964 | X38: =SUM(X92:X94) -> 86.747214 | Y38: =SUM(Y92:Y94) -> 93.951467 | Z38: =SUM(Z92:Z94) -> 5.7693016 | AA38: =SUM(AA92:AA94) -> 8.9196341 | AB38: =SUM(AB92:AB94) -> 9.7852413 | ... AJ38: =SUM(AJ92:AJ94) -> 844.58263
A39: Total food | C39: =SUM(C19:C27) -> 39.60575 | D39: =SUM(D19:D27) -> 42.62283 | E39: =SUM(E19:E27) -> 43.026333 | F39: =SUM(F19:F27) -> 43.115899 | G39: =SUM(G19:G27) -> 36.579933 | H39: =SUM(H19:H27) -> 43.650971 | I39: =SUM(I19:I27) -> 43.777305 | J39: =SUM(J19:J27) -> 46.237152 | ... R39: =SUM(R19:R27) -> 31.828343 | T39: Total food | U39: =SUM(U19:U27) -> 116.44926 | V39: =SUM(V19:V27) -> 185.63887 | W39: =SUM(W19:W27) -> 257.1095 | X39: =SUM(X19:X27) -> 370.51146 | Y39: =SUM(Y19:Y27) -> 348.03359 | Z39: =SUM(Z19:Z27) -> 24.713279 | AA39: =SUM(AA19:AA27) -> 36.956348 | AB39: =SUM(AB19:AB27) -> 47.291477 | ... AJ39: =SUM(AJ19:AJ27) -> 2246.3428
A40: Total nonfood | C40: =SUM(C28:C38) -> 60.39425 | D40: =SUM(D28:D38) -> 57.37717 | E40: =SUM(E28:E38) -> 56.973667 | F40: =SUM(F28:F38) -> 56.884101 | G40: =SUM(G28:G38) -> 63.420067 | H40: =SUM(H28:H38) -> 56.349029 | I40: =SUM(I28:I38) -> 56.222695 | J40: =SUM(J28:J38) -> 53.762848 | ... R40: =SUM(R28:R38) -> 68.171657 | T40: Total nonfood | U40: =SUM(U29:U38) -> 164.41918 | V40: =SUM(V29:V38) -> 227.73494 | W40: =SUM(W29:W38) -> 308.10791 | X40: =SUM(X29:X38) -> 442.58352 | Y40: =SUM(Y29:Y38) -> 550.77678 | Z40: =SUM(Z29:Z38) -> 28.866348 | AA40: =SUM(AA29:AA38) -> 42.958492 | AB40: =SUM(AB29:AB38) -> 49.446354 | ... AJ40: =SUM(AJ29:AJ38) -> 4451.7288
A41: Total given | C41: =SUM(C19:C31) -> 51.665711 | D41: =SUM(D19:D31) -> 54.508246 | E41: =SUM(E19:E31) -> 55.254353 | F41: =SUM(F19:F31) -> 55.628715 | G41: =SUM(G19:G31) -> 51.077172 | H41: =SUM(H19:H31) -> 56.587348 | I41: =SUM(I19:I31) -> 56.20919 | J41: =SUM(J19:J31) -> 58.780904 | ... R41: =SUM(R19:R31) -> 48.710729
A42: Total residual | C42: =SUM(C32:C38) -> 48.334289 | D42: =SUM(D32:D38) -> 45.491754 | E42: =SUM(E32:E38) -> 44.745647 | F42: =SUM(F32:F38) -> 44.371285 | G42: =SUM(G32:G38) -> 48.922828 | H42: =SUM(H32:H38) -> 43.412652 | I42: =SUM(I32:I38) -> 43.79081 | J42: =SUM(J32:J38) -> 41.219096 | ... R42: =SUM(R32:R38) -> 51.289271
A43: Total | C43: =C39+C40 -> 100 | D43: =D39+D40 -> 100 | E43: =E39+E40 -> 100 | F43: =F39+F40 -> 100 | G43: =G39+G40 -> 100 | H43: =H39+H40 -> 100 | I43: =I39+I40 -> 100 | J43: =J39+J40 -> 100 | ... R43: =R39+R40 -> 100 | T43: Total | U43: =U39+U40 -> 280.86844 | V43: =V39+V40 -> 413.37382 | W43: =W39+W40 -> 565.21741 | X43: =X39+X40 -> 813.09498 | Y43: =Y39+Y40 -> 898.81038 | Z43: =Z39+Z40 -> 53.579627 | AA43: =AA39+AA40 -> 79.91484 | AB43: =AB39+AB40 -> 96.737831 | ... AJ43: =AJ39+AJ40 -> 6698.0716
A46: ABS - disagg
U47: Extract SAM values - total | AL47: Extract SAM values - marketed | BC47: Extract SAM values - home
A48: category | B48: sam | C48: hhd-f1 | D48: hhd-f2 | E48: hhd-f3 | F48: hhd-f4 | G48: hhd-f5 | H48: hhd-n1 | I48: hhd-n2 | J48: hhd-n3 | K48: hhd-n4 | L48: hhd-n5 | M48: hhd-u1 | N48: hhd-u2 | O48: hhd-u3 | P48: hhd-u4 | Q48: hhd-u5 | R48: total | U48: hhd-f1 | V48: hhd-f2 | W48: hhd-f3 | X48: hhd-f4 | Y48: hhd-f5 | Z48: hhd-n1 | AA48: hhd-n2 | AB48: hhd-n3 | AC48: hhd-n4 | AD48: hhd-n5 | AE48: hhd-u1 | AF48: hhd-u2 | AG48: hhd-u3 | AH48: hhd-u4 | AI48: hhd-u5 | AJ48: total | AM48: hhd-f1 | AN48: hhd-f2 | AO48: hhd-f3 | AP48: hhd-f4 | AQ48: hhd-f5 | AR48: hhd-n1 | AS48: hhd-n2 | AT48: hhd-n3 | AU48: hhd-n4 | AV48: hhd-n5 | AW48: hhd-u1 | AX48: hhd-u2 | AY48: hhd-u3 | AZ48: hhd-u4 | BA48: hhd-u5 | BD48: hhd-f1 | BE48: hhd-f2 | BF48: hhd-f3 | BG48: hhd-f4 | BH48: hhd-f5 | BI48: hhd-n1 | BJ48: hhd-n2 | BK48: hhd-n3 | BL48: hhd-n4 | BM48: hhd-n5 | BN48: hhd-u1 | BO48: hhd-u2 | BP48: hhd-u3 | BQ48: hhd-u4 | BR48: hhd-u5 | BW48: shares rearranged
A49: =HLOOKUP(B49,$B$6:$BR$9,4,FALSE) -> cereals | B49: cere | C49: =IFERROR(100*U49/U$95,"") -> 3.4557095 | D49: =IFERROR(100*V49/V$95,"") -> 3.5401625 | E49: =IFERROR(100*W49/W$95,"") -> 2.898974 | F49: =IFERROR(100*X49/X$95,"") -> 2.1138208 | G49: =IFERROR(100*Y49/Y$95,"") -> 1.1633644 | H49: =IFERROR(100*Z49/Z$95,"") -> 3.484198 | I49: =IFERROR(100*AA49/AA$95,"") -> 2.4039628 | J49: =IFERROR(100*AB49/AB$95,"") -> 3.3448449 | ... R49: =IFERROR(100*AJ49/AJ$95,"") -> 1.3224773 | T49: =B49 -> cere | U49: =IFERROR(AM49+BD49,"") -> 10.160515 | V49: =IFERROR(AN49+BE49,"") -> 15.418774 | W49: =IFERROR(AO49+BF49,"") -> 17.323199 | X49: =IFERROR(AP49+BG49,"") -> 18.164873 | Y49: =IFERROR(AQ49+BH49,"") -> 11.068634 | Z49: =IFERROR(AR49+BI49,"") -> 1.9726012 | AA49: =IFERROR(AS49+BJ49,"") -> 2.0294005 | AB49: =IFERROR(AT49+BK49,"") -> 3.4211159 | ... AI49: =IFERROR(BA49+BR49,"") -> 4.8927708 | AJ49: =SUM(U49:AI49) -> 93.336226 | AL49: ="c"&T49 -> ccere | AM49: =_xlfn.IFNA(INDEX(SAM!$B$8:$HC$215,MATCH($AL49,SAM!$A$8:$A$215,0),MATCH(AM$48,SAM!$B$7:$HC$7,0)),0) -> 8.3784421 | AN49: =_xlfn.IFNA(INDEX(SAM!$B$8:$HC$215,MATCH($AL49,SAM!$A$8:$A$215,0),MATCH(AN$48,SAM!$B$7:$HC$7,0)),0) -> 12.279522 | AO49: =_xlfn.IFNA(INDEX(SAM!$B$8:$HC$215,MATCH($AL49,SAM!$A$8:$A$215,0),MATCH(AO$48,SAM!$B$7:$HC$7,0)),0) -> 13.873731 | AP49: =_xlfn.IFNA(INDEX(SAM!$B$8:$HC$215,MATCH($AL49,SAM!$A$8:$A$215,0),MATCH(AP$48,SAM!$B$7:$HC$7,0)),0) -> 13.893501 | AQ49: =_xlfn.IFNA(INDEX(SAM!$B$8:$HC$215,MATCH($AL49,SAM!$A$8:$A$215,0),MATCH(AQ$48,SAM!$B$7:$HC$7,0)),0) -> 9.2052915 | AR49: =_xlfn.IFNA(INDEX(SAM!$B$8:$HC$215,MATCH($AL49,SAM!$A$8:$A$215,0),MATCH(AR$48,SAM!$B$7:$HC$7,0)),0) -> 1.6815114 | AS49: =_xlfn.IFNA(INDEX(SAM!$B$8:$HC$215,MATCH($AL49,SAM!$A$8:$A$215,0),MATCH(AS$48,SAM!$B$7:$HC$7,0)),0) -> 1.3080258 | AT49: =_xlfn.IFNA(INDEX(SAM!$B$8:$HC$215,MATCH($AL49,SAM!$A$8:$A$215,0),MATCH(AT$48,SAM!$B$7:$HC$7,0)),0) -> 2.8195568 | ... BA49: =_xlfn.IFNA(INDEX(SAM!$B$8:$HC$215,MATCH($AL49,SAM!$A$8:$A$215,0),MATCH(BA$48,SAM!$B$7:$HC$7,0)),0) -> 4.6805725 | BC49: ="a"&T49 -> acere | BD49: =_xlfn.IFNA(INDEX(SAM!$B$8:$HC$215,MATCH($BC49,SAM!$A$8:$A$215,0),MATCH(BD$48,SAM!$B$7:$HC$7,0)),0) -> 1.7820724 | BE49: =_xlfn.IFNA(INDEX(SAM!$B$8:$HC$215,MATCH($BC49,SAM!$A$8:$A$215,0),MATCH(BE$48,SAM!$B$7:$HC$7,0)),0) -> 3.1392521 | BF49: =_xlfn.IFNA(INDEX(SAM!$B$8:$HC$215,MATCH($BC49,SAM!$A$8:$A$215,0),MATCH(BF$48,SAM!$B$7:$HC$7,0)),0) -> 3.4494678 | BG49: =_xlfn.IFNA(INDEX(SAM!$B$8:$HC$215,MATCH($BC49,SAM!$A$8:$A$215,0),MATCH(BG$48,SAM!$B$7:$HC$7,0)),0) -> 4.2713719 | BH49: =_xlfn.IFNA(INDEX(SAM!$B$8:$HC$215,MATCH($BC49,SAM!$A$8:$A$215,0),MATCH(BH$48,SAM!$B$7:$HC$7,0)),0) -> 1.8633422 | BI49: =_xlfn.IFNA(INDEX(SAM!$B$8:$HC$215,MATCH($BC49,SAM!$A$8:$A$215,0),MATCH(BI$48,SAM!$B$7:$HC$7,0)),0) -> 0.29108973 | BJ49: =_xlfn.IFNA(INDEX(SAM!$B$8:$HC$215,MATCH($BC49,SAM!$A$8:$A$215,0),MATCH(BJ$48,SAM!$B$7:$HC$7,0)),0) -> 0.72137474 | BK49: =_xlfn.IFNA(INDEX(SAM!$B$8:$HC$215,MATCH($BC49,SAM!$A$8:$A$215,0),MATCH(BK$48,SAM!$B$7:$HC$7,0)),0) -> 0.60155906 | ... BR49: =_xlfn.IFNA(INDEX(SAM!$B$8:$HC$215,MATCH($BC49,SAM!$A$8:$A$215,0),MATCH(BR$48,SAM!$B$7:$HC$7,0)),0) -> 0.2121983 | BT49: =AL49 -> ccere | BU49: =SUM(BD49:BR49,AM49:BA49) -> 93.336226 | BW49: ccere | BX49: =100*VLOOKUP(BW49,$BT$49:$BU$94,2,FALSE)/$BU$95 -> 1.3224773
A50: =HLOOKUP(B50,$B$6:$BR$9,4,FALSE) -> cereals | B50: gmll | C50: =IFERROR(100*U50/U$95,"") -> 2.3917142 | D50: =IFERROR(100*V50/V$95,"") -> 2.2731009 | E50: =IFERROR(100*W50/W$95,"") -> 2.2273072 | F50: =IFERROR(100*X50/X$95,"") -> 2.3113208 | G50: =IFERROR(100*Y50/Y$95,"") -> 2.0560298 | H50: =IFERROR(100*Z50/Z$95,"") -> 2.9679084 | I50: =IFERROR(100*AA50/AA$95,"") -> 2.6888305 | J50: =IFERROR(100*AB50/AB$95,"") -> 2.3900027 | ... R50: =IFERROR(100*AJ50/AJ$95,"") -> 1.8189525 | T50: =B50 -> gmll | U50: =IFERROR(AM50+BD50,"") -> 7.0321439 | V50: =IFERROR(AN50+BE50,"") -> 9.9002315 | W50: =IFERROR(AO50+BF50,"") -> 13.309566 | X50: =IFERROR(AP50+BG50,"") -> 19.862067 | Y50: =IFERROR(AQ50+BH50,"") -> 19.561748 | Z50: =IFERROR(AR50+BI50,"") -> 1.6803005 | AA50: =IFERROR(AS50+BJ50,"") -> 2.2698829 | AB50: =IFERROR(AT50+BK50,"") -> 2.4445008 | ... AI50: =IFERROR(BA50+BR50,"") -> 33.588786 | AJ50: =SUM(U50:AI50) -> 128.37586 | AL50: ="c"&T50 -> cgmll | AM50: =_xlfn.IFNA(INDEX(SAM!$B$8:$HC$215,MATCH($AL50,SAM!$A$8:$A$215,0),MATCH(AM$48,SAM!$B$7:$HC$7,0)),0) -> 6.7101614 | AN50: =_xlfn.IFNA(INDEX(SAM!$B$8:$HC$215,MATCH($AL50,SAM!$A$8:$A$215,0),MATCH(AN$48,SAM!$B$7:$HC$7,0)),0) -> 9.11645 | AO50: =_xlfn.IFNA(INDEX(SAM!$B$8:$HC$215,MATCH($AL50,SAM!$A$8:$A$215,0),MATCH(AO$48,SAM!$B$7:$HC$7,0)),0) -> 12.122152 | AP50: =_xlfn.IFNA(INDEX(SAM!$B$8:$HC$215,MATCH($AL50,SAM!$A$8:$A$215,0),MATCH(AP$48,SAM!$B$7:$HC$7,0)),0) -> 18.26951 | AQ50: =_xlfn.IFNA(INDEX(SAM!$B$8:$HC$215,MATCH($AL50,SAM!$A$8:$A$215,0),MATCH(AQ$48,SAM!$B$7:$HC$7,0)),0) -> 18.313719 | AR50: =_xlfn.IFNA(INDEX(SAM!$B$8:$HC$215,MATCH($AL50,SAM!$A$8:$A$215,0),MATCH(AR$48,SAM!$B$7:$HC$7,0)),0) -> 1.6341303 | AS50: =_xlfn.IFNA(INDEX(SAM!$B$8:$HC$215,MATCH($AL50,SAM!$A$8:$A$215,0),MATCH(AS$48,SAM!$B$7:$HC$7,0)),0) -> 2.1342829 | AT50: =_xlfn.IFNA(INDEX(SAM!$B$8:$HC$215,MATCH($AL50,SAM!$A$8:$A$215,0),MATCH(AT$48,SAM!$B$7:$HC$7,0)),0) -> 2.2616671 | ... BA50: =_xlfn.IFNA(INDEX(SAM!$B$8:$HC$215,MATCH($AL50,SAM!$A$8:$A$215,0),MATCH(BA$48,SAM!$B$7:$HC$7,0)),0) -> 33.463332 | BC50: ="a"&T50 -> agmll | BD50: =_xlfn.IFNA(INDEX(SAM!$B$8:$HC$215,MATCH($BC50,SAM!$A$8:$A$215,0),MATCH(BD$48,SAM!$B$7:$HC$7,0)),0) -> 0.32198242 | BE50: =_xlfn.IFNA(INDEX(SAM!$B$8:$HC$215,MATCH($BC50,SAM!$A$8:$A$215,0),MATCH(BE$48,SAM!$B$7:$HC$7,0)),0) -> 0.78378158 | BF50: =_xlfn.IFNA(INDEX(SAM!$B$8:$HC$215,MATCH($BC50,SAM!$A$8:$A$215,0),MATCH(BF$48,SAM!$B$7:$HC$7,0)),0) -> 1.1874143 | BG50: =_xlfn.IFNA(INDEX(SAM!$B$8:$HC$215,MATCH($BC50,SAM!$A$8:$A$215,0),MATCH(BG$48,SAM!$B$7:$HC$7,0)),0) -> 1.5925571 | BH50: =_xlfn.IFNA(INDEX(SAM!$B$8:$HC$215,MATCH($BC50,SAM!$A$8:$A$215,0),MATCH(BH$48,SAM!$B$7:$HC$7,0)),0) -> 1.2480283 | BI50: =_xlfn.IFNA(INDEX(SAM!$B$8:$HC$215,MATCH($BC50,SAM!$A$8:$A$215,0),MATCH(BI$48,SAM!$B$7:$HC$7,0)),0) -> 0.046170185 | BJ50: =_xlfn.IFNA(INDEX(SAM!$B$8:$HC$215,MATCH($BC50,SAM!$A$8:$A$215,0),MATCH(BJ$48,SAM!$B$7:$HC$7,0)),0) -> 0.13559999 | BK50: =_xlfn.IFNA(INDEX(SAM!$B$8:$HC$215,MATCH($BC50,SAM!$A$8:$A$215,0),MATCH(BK$48,SAM!$B$7:$HC$7,0)),0) -> 0.18283369 | ... BR50: =_xlfn.IFNA(INDEX(SAM!$B$8:$HC$215,MATCH($BC50,SAM!$A$8:$A$215,0),MATCH(BR$48,SAM!$B$7:$HC$7,0)),0) -> 0.12545317 | BT50: =AL50 -> cgmll | BU50: =SUM(BD50:BR50,AM50:BA50) -> 128.37586 | BW50: cpuls | BX50: =100*VLOOKUP(BW50,$BT$49:$BU$94,2,FALSE)/$BU$95 -> 1.2971815
A51: =HLOOKUP(B51,$B$6:$BR$9,4,FALSE) -> roots | B51: root | C51: =IFERROR(100*U51/U$95,"") -> 15.329137 | D51: =IFERROR(100*V51/V$95,"") -> 15.412014 | E51: =IFERROR(100*W51/W$95,"") -> 14.043551 | F51: =IFERROR(100*X51/X$95,"") -> 11.054122 | G51: =IFERROR(100*Y51/Y$95,"") -> 5.3288698 | H51: =IFERROR(100*Z51/Z$95,"") -> 16.676685 | I51: =IFERROR(100*AA51/AA$95,"") -> 15.477571 | J51: =IFERROR(100*AB51/AB$95,"") -> 14.116111 | ... R51: =IFERROR(100*AJ51/AJ$95,"") -> 6.7213637 | T51: =B51 -> root | U51: =IFERROR(AM51+BD51,"") -> 45.070896 | V51: =IFERROR(AN51+BE51,"") -> 67.12527 | W51: =IFERROR(AO51+BF51,"") -> 83.919078 | X51: =IFERROR(AP51+BG51,"") -> 94.992311 | Y51: =IFERROR(AQ51+BH51,"") -> 50.700631 | Z51: =IFERROR(AR51+BI51,"") -> 9.4416131 | AA51: =IFERROR(AS51+BJ51,"") -> 13.066006 | AB51: =IFERROR(AT51+BK51,"") -> 14.437995 | ... AI51: =IFERROR(BA51+BR51,"") -> 34.325356 | AJ51: =SUM(U51:AI51) -> 474.37238 | AL51: ="c"&T51 -> croot | AM51: =_xlfn.IFNA(INDEX(SAM!$B$8:$HC$215,MATCH($AL51,SAM!$A$8:$A$215,0),MATCH(AM$48,SAM!$B$7:$HC$7,0)),0) -> 28.031863 | AN51: =_xlfn.IFNA(INDEX(SAM!$B$8:$HC$215,MATCH($AL51,SAM!$A$8:$A$215,0),MATCH(AN$48,SAM!$B$7:$HC$7,0)),0) -> 33.687296 | AO51: =_xlfn.IFNA(INDEX(SAM!$B$8:$HC$215,MATCH($AL51,SAM!$A$8:$A$215,0),MATCH(AO$48,SAM!$B$7:$HC$7,0)),0) -> 37.351416 | AP51: =_xlfn.IFNA(INDEX(SAM!$B$8:$HC$215,MATCH($AL51,SAM!$A$8:$A$215,0),MATCH(AP$48,SAM!$B$7:$HC$7,0)),0) -> 40.154543 | AQ51: =_xlfn.IFNA(INDEX(SAM!$B$8:$HC$215,MATCH($AL51,SAM!$A$8:$A$215,0),MATCH(AQ$48,SAM!$B$7:$HC$7,0)),0) -> 23.834845 | AR51: =_xlfn.IFNA(INDEX(SAM!$B$8:$HC$215,MATCH($AL51,SAM!$A$8:$A$215,0),MATCH(AR$48,SAM!$B$7:$HC$7,0)),0) -> 5.6427771 | AS51: =_xlfn.IFNA(INDEX(SAM!$B$8:$HC$215,MATCH($AL51,SAM!$A$8:$A$215,0),MATCH(AS$48,SAM!$B$7:$HC$7,0)),0) -> 6.3829731 | AT51: =_xlfn.IFNA(INDEX(SAM!$B$8:$HC$215,MATCH($AL51,SAM!$A$8:$A$215,0),MATCH(AT$48,SAM!$B$7:$HC$7,0)),0) -> 5.1005826 | ... BA51: =_xlfn.IFNA(INDEX(SAM!$B$8:$HC$215,MATCH($AL51,SAM!$A$8:$A$215,0),MATCH(BA$48,SAM!$B$7:$HC$7,0)),0) -> 30.743448 | BC51: ="a"&T51 -> aroot | BD51: =_xlfn.IFNA(INDEX(SAM!$B$8:$HC$215,MATCH($BC51,SAM!$A$8:$A$215,0),MATCH(BD$48,SAM!$B$7:$HC$7,0)),0) -> 17.039033 | BE51: =_xlfn.IFNA(INDEX(SAM!$B$8:$HC$215,MATCH($BC51,SAM!$A$8:$A$215,0),MATCH(BE$48,SAM!$B$7:$HC$7,0)),0) -> 33.437974 | BF51: =_xlfn.IFNA(INDEX(SAM!$B$8:$HC$215,MATCH($BC51,SAM!$A$8:$A$215,0),MATCH(BF$48,SAM!$B$7:$HC$7,0)),0) -> 46.567662 | BG51: =_xlfn.IFNA(INDEX(SAM!$B$8:$HC$215,MATCH($BC51,SAM!$A$8:$A$215,0),MATCH(BG$48,SAM!$B$7:$HC$7,0)),0) -> 54.837768 | BH51: =_xlfn.IFNA(INDEX(SAM!$B$8:$HC$215,MATCH($BC51,SAM!$A$8:$A$215,0),MATCH(BH$48,SAM!$B$7:$HC$7,0)),0) -> 26.865786 | BI51: =_xlfn.IFNA(INDEX(SAM!$B$8:$HC$215,MATCH($BC51,SAM!$A$8:$A$215,0),MATCH(BI$48,SAM!$B$7:$HC$7,0)),0) -> 3.798836 | BJ51: =_xlfn.IFNA(INDEX(SAM!$B$8:$HC$215,MATCH($BC51,SAM!$A$8:$A$215,0),MATCH(BJ$48,SAM!$B$7:$HC$7,0)),0) -> 6.6830325 | BK51: =_xlfn.IFNA(INDEX(SAM!$B$8:$HC$215,MATCH($BC51,SAM!$A$8:$A$215,0),MATCH(BK$48,SAM!$B$7:$HC$7,0)),0) -> 9.3374122 | ... BR51: =_xlfn.IFNA(INDEX(SAM!$B$8:$HC$215,MATCH($BC51,SAM!$A$8:$A$215,0),MATCH(BR$48,SAM!$B$7:$HC$7,0)),0) -> 3.5819084 | BT51: =AL51 -> croot | BU51: =SUM(BD51:BR51,AM51:BA51) -> 474.37238 | BW51: coils | BX51: =100*VLOOKUP(BW51,$BT$49:$BU$94,2,FALSE)/$BU$95 -> 0.34153659
A52: =HLOOKUP(B52,$B$6:$BR$9,4,FALSE) -> pulses | B52: puls | C52: =IFERROR(100*U52/U$95,"") -> 2.6873199 | D52: =IFERROR(100*V52/V$95,"") -> 2.6837665 | E52: =IFERROR(100*W52/W$95,"") -> 2.4511214 | F52: =IFERROR(100*X52/X$95,"") -> 1.8965997 | G52: =IFERROR(100*Y52/Y$95,"") -> 1.1180208 | H52: =IFERROR(100*Z52/Z$95,"") -> 3.0950954 | I52: =IFERROR(100*AA52/AA$95,"") -> 2.6364508 | J52: =IFERROR(100*AB52/AB$95,"") -> 2.5257373 | ... R52: =IFERROR(100*AJ52/AJ$95,"") -> 1.2971815 | T52: =B52 -> puls | U52: =IFERROR(AM52+BD52,"") -> 7.9012871 | V52: =IFERROR(AN52+BE52,"") -> 11.688839 | W52: =IFERROR(AO52+BF52,"") -> 14.646997 | X52: =IFERROR(AP52+BG52,"") -> 16.298208 | Y52: =IFERROR(AQ52+BH52,"") -> 10.63722 | Z52: =IFERROR(AR52+BI52,"") -> 1.7523083 | AA52: =IFERROR(AS52+BJ52,"") -> 2.2256645 | AB52: =IFERROR(AT52+BK52,"") -> 2.5833306 | ... AI52: =IFERROR(BA52+BR52,"") -> 12.344207 | AJ52: =SUM(U52:AI52) -> 91.550925 | AL52: ="c"&T52 -> cpuls | AM52: =_xlfn.IFNA(INDEX(SAM!$B$8:$HC$215,MATCH($AL52,SAM!$A$8:$A$215,0),MATCH(AM$48,SAM!$B$7:$HC$7,0)),0) -> 5.4119486 | AN52: =_xlfn.IFNA(INDEX(SAM!$B$8:$HC$215,MATCH($AL52,SAM!$A$8:$A$215,0),MATCH(AN$48,SAM!$B$7:$HC$7,0)),0) -> 7.4494451 | AO52: =_xlfn.IFNA(INDEX(SAM!$B$8:$HC$215,MATCH($AL52,SAM!$A$8:$A$215,0),MATCH(AO$48,SAM!$B$7:$HC$7,0)),0) -> 9.0359364 | AP52: =_xlfn.IFNA(INDEX(SAM!$B$8:$HC$215,MATCH($AL52,SAM!$A$8:$A$215,0),MATCH(AP$48,SAM!$B$7:$HC$7,0)),0) -> 9.2688042 | AQ52: =_xlfn.IFNA(INDEX(SAM!$B$8:$HC$215,MATCH($AL52,SAM!$A$8:$A$215,0),MATCH(AQ$48,SAM!$B$7:$HC$7,0)),0) -> 6.7083537 | AR52: =_xlfn.IFNA(INDEX(SAM!$B$8:$HC$215,MATCH($AL52,SAM!$A$8:$A$215,0),MATCH(AR$48,SAM!$B$7:$HC$7,0)),0) -> 1.1916042 | AS52: =_xlfn.IFNA(INDEX(SAM!$B$8:$HC$215,MATCH($AL52,SAM!$A$8:$A$215,0),MATCH(AS$48,SAM!$B$7:$HC$7,0)),0) -> 1.2926038 | AT52: =_xlfn.IFNA(INDEX(SAM!$B$8:$HC$215,MATCH($AL52,SAM!$A$8:$A$215,0),MATCH(AT$48,SAM!$B$7:$HC$7,0)),0) -> 1.5274885 | ... BA52: =_xlfn.IFNA(INDEX(SAM!$B$8:$HC$215,MATCH($AL52,SAM!$A$8:$A$215,0),MATCH(BA$48,SAM!$B$7:$HC$7,0)),0) -> 11.444245 | BC52: ="a"&T52 -> apuls | BD52: =_xlfn.IFNA(INDEX(SAM!$B$8:$HC$215,MATCH($BC52,SAM!$A$8:$A$215,0),MATCH(BD$48,SAM!$B$7:$HC$7,0)),0) -> 2.4893385 | BE52: =_xlfn.IFNA(INDEX(SAM!$B$8:$HC$215,MATCH($BC52,SAM!$A$8:$A$215,0),MATCH(BE$48,SAM!$B$7:$HC$7,0)),0) -> 4.2393935 | BF52: =_xlfn.IFNA(INDEX(SAM!$B$8:$HC$215,MATCH($BC52,SAM!$A$8:$A$215,0),MATCH(BF$48,SAM!$B$7:$HC$7,0)),0) -> 5.6110611 | BG52: =_xlfn.IFNA(INDEX(SAM!$B$8:$HC$215,MATCH($BC52,SAM!$A$8:$A$215,0),MATCH(BG$48,SAM!$B$7:$HC$7,0)),0) -> 7.0294043 | BH52: =_xlfn.IFNA(INDEX(SAM!$B$8:$HC$215,MATCH($BC52,SAM!$A$8:$A$215,0),MATCH(BH$48,SAM!$B$7:$HC$7,0)),0) -> 3.928866 | BI52: =_xlfn.IFNA(INDEX(SAM!$B$8:$HC$215,MATCH($BC52,SAM!$A$8:$A$215,0),MATCH(BI$48,SAM!$B$7:$HC$7,0)),0) -> 0.56070403 | BJ52: =_xlfn.IFNA(INDEX(SAM!$B$8:$HC$215,MATCH($BC52,SAM!$A$8:$A$215,0),MATCH(BJ$48,SAM!$B$7:$HC$7,0)),0) -> 0.93306068 | BK52: =_xlfn.IFNA(INDEX(SAM!$B$8:$HC$215,MATCH($BC52,SAM!$A$8:$A$215,0),MATCH(BK$48,SAM!$B$7:$HC$7,0)),0) -> 1.0558421 | ... BR52: =_xlfn.IFNA(INDEX(SAM!$B$8:$HC$215,MATCH($BC52,SAM!$A$8:$A$215,0),MATCH(BR$48,SAM!$B$7:$HC$7,0)),0) -> 0.89996177 | BT52: =AL52 -> cpuls | BU52: =SUM(BD52:BR52,AM52:BA52) -> 91.550925 | BW52: croot | BX52: =100*VLOOKUP(BW52,$BT$49:$BU$94,2,FALSE)/$BU$95 -> 6.7213637
A53: =HLOOKUP(B53,$B$6:$BR$9,4,FALSE) -> vegetables | B53: vege | C53: =IFERROR(100*U53/U$95,"") -> 1.925068 | D53: =IFERROR(100*V53/V$95,"") -> 1.5949273 | E53: =IFERROR(100*W53/W$95,"") -> 1.2795649 | F53: =IFERROR(100*X53/X$95,"") -> 0.91990221 | G53: =IFERROR(100*Y53/Y$95,"") -> 0.62097707 | H53: =IFERROR(100*Z53/Z$95,"") -> 2.1481701 | I53: =IFERROR(100*AA53/AA$95,"") -> 1.4378946 | J53: =IFERROR(100*AB53/AB$95,"") -> 1.2753145 | ... R53: =IFERROR(100*AJ53/AJ$95,"") -> 0.81290826 | T53: =B53 -> vege | U53: =IFERROR(AM53+BD53,"") -> 5.6601058 | V53: =IFERROR(AN53+BE53,"") -> 6.9465237 | W53: =IFERROR(AO53+BF53,"") -> 7.6462077 | X53: =IFERROR(AP53+BG53,"") -> 7.9050725 | Y53: =IFERROR(AQ53+BH53,"") -> 5.9081814 | Z53: =IFERROR(AR53+BI53,"") -> 1.2162004 | AA53: =IFERROR(AS53+BJ53,"") -> 1.2138557 | AB53: =IFERROR(AT53+BK53,"") -> 1.304395 | ... AI53: =IFERROR(BA53+BR53,"") -> 11.778481 | AJ53: =SUM(U53:AI53) -> 57.372468 | AL53: ="c"&T53 -> cvege | AM53: =_xlfn.IFNA(INDEX(SAM!$B$8:$HC$215,MATCH($AL53,SAM!$A$8:$A$215,0),MATCH(AM$48,SAM!$B$7:$HC$7,0)),0) -> 4.6736776 | AN53: =_xlfn.IFNA(INDEX(SAM!$B$8:$HC$215,MATCH($AL53,SAM!$A$8:$A$215,0),MATCH(AN$48,SAM!$B$7:$HC$7,0)),0) -> 5.8167717 | AO53: =_xlfn.IFNA(INDEX(SAM!$B$8:$HC$215,MATCH($AL53,SAM!$A$8:$A$215,0),MATCH(AO$48,SAM!$B$7:$HC$7,0)),0) -> 6.3007514 | AP53: =_xlfn.IFNA(INDEX(SAM!$B$8:$HC$215,MATCH($AL53,SAM!$A$8:$A$215,0),MATCH(AP$48,SAM!$B$7:$HC$7,0)),0) -> 6.5593797 | AQ53: =_xlfn.IFNA(INDEX(SAM!$B$8:$HC$215,MATCH($AL53,SAM!$A$8:$A$215,0),MATCH(AQ$48,SAM!$B$7:$HC$7,0)),0) -> 5.2100441 | AR53: =_xlfn.IFNA(INDEX(SAM!$B$8:$HC$215,MATCH($AL53,SAM!$A$8:$A$215,0),MATCH(AR$48,SAM!$B$7:$HC$7,0)),0) -> 1.0060443 | AS53: =_xlfn.IFNA(INDEX(SAM!$B$8:$HC$215,MATCH($AL53,SAM!$A$8:$A$215,0),MATCH(AS$48,SAM!$B$7:$HC$7,0)),0) -> 0.98575393 | AT53: =_xlfn.IFNA(INDEX(SAM!$B$8:$HC$215,MATCH($AL53,SAM!$A$8:$A$215,0),MATCH(AT$48,SAM!$B$7:$HC$7,0)),0) -> 1.0683735 | ... BA53: =_xlfn.IFNA(INDEX(SAM!$B$8:$HC$215,MATCH($AL53,SAM!$A$8:$A$215,0),MATCH(BA$48,SAM!$B$7:$HC$7,0)),0) -> 11.529799 | BC53: ="a"&T53 -> avege | BD53: =_xlfn.IFNA(INDEX(SAM!$B$8:$HC$215,MATCH($BC53,SAM!$A$8:$A$215,0),MATCH(BD$48,SAM!$B$7:$HC$7,0)),0) -> 0.98642824 | BE53: =_xlfn.IFNA(INDEX(SAM!$B$8:$HC$215,MATCH($BC53,SAM!$A$8:$A$215,0),MATCH(BE$48,SAM!$B$7:$HC$7,0)),0) -> 1.129752 | BF53: =_xlfn.IFNA(INDEX(SAM!$B$8:$HC$215,MATCH($BC53,SAM!$A$8:$A$215,0),MATCH(BF$48,SAM!$B$7:$HC$7,0)),0) -> 1.3454564 | BG53: =_xlfn.IFNA(INDEX(SAM!$B$8:$HC$215,MATCH($BC53,SAM!$A$8:$A$215,0),MATCH(BG$48,SAM!$B$7:$HC$7,0)),0) -> 1.3456928 | BH53: =_xlfn.IFNA(INDEX(SAM!$B$8:$HC$215,MATCH($BC53,SAM!$A$8:$A$215,0),MATCH(BH$48,SAM!$B$7:$HC$7,0)),0) -> 0.69813728 | BI53: =_xlfn.IFNA(INDEX(SAM!$B$8:$HC$215,MATCH($BC53,SAM!$A$8:$A$215,0),MATCH(BI$48,SAM!$B$7:$HC$7,0)),0) -> 0.21015605 | BJ53: =_xlfn.IFNA(INDEX(SAM!$B$8:$HC$215,MATCH($BC53,SAM!$A$8:$A$215,0),MATCH(BJ$48,SAM!$B$7:$HC$7,0)),0) -> 0.22810182 | BK53: =_xlfn.IFNA(INDEX(SAM!$B$8:$HC$215,MATCH($BC53,SAM!$A$8:$A$215,0),MATCH(BK$48,SAM!$B$7:$HC$7,0)),0) -> 0.23602143 | ... BR53: =_xlfn.IFNA(INDEX(SAM!$B$8:$HC$215,MATCH($BC53,SAM!$A$8:$A$215,0),MATCH(BR$48,SAM!$B$7:$HC$7,0)),0) -> 0.24868201 | BT53: =AL53 -> cvege | BU53: =SUM(BD53:BR53,AM53:BA53) -> 57.372468 | BW53: cvege | BX53: =100*VLOOKUP(BW53,$BT$49:$BU$94,2,FALSE)/$BU$95 -> 0.81290826
A54: =HLOOKUP(B54,$B$6:$BR$9,4,FALSE) -> fruits | B54: frui | C54: =IFERROR(100*U54/U$95,"") -> 3.5456139 | D54: =IFERROR(100*V54/V$95,"") -> 4.3403049 | E54: =IFERROR(100*W54/W$95,"") -> 4.731943 | F54: =IFERROR(100*X54/X$95,"") -> 5.0500432 | G54: =IFERROR(100*Y54/Y$95,"") -> 3.9726092 | H54: =IFERROR(100*Z54/Z$95,"") -> 3.200744 | I54: =IFERROR(100*AA54/AA$95,"") -> 4.5114773 | J54: =IFERROR(100*AB54/AB$95,"") -> 4.7006147 | ... R54: =IFERROR(100*AJ54/AJ$95,"") -> 3.3110967 | T54: =B54 -> frui | U54: =IFERROR(AM54+BD54,"") -> 10.424852 | V54: =IFERROR(AN54+BE54,"") -> 18.903703 | W54: =IFERROR(AO54+BF54,"") -> 28.276346 | X54: =IFERROR(AP54+BG54,"") -> 43.396959 | Y54: =IFERROR(AQ54+BH54,"") -> 37.796719 | Z54: =IFERROR(AR54+BI54,"") -> 1.8121219 | AA54: =IFERROR(AS54+BJ54,"") -> 3.8085425 | AB54: =IFERROR(AT54+BK54,"") -> 4.8078007 | ... AI54: =IFERROR(BA54+BR54,"") -> 56.366025 | AJ54: =SUM(U54:AI54) -> 233.68663 | AL54: ="c"&T54 -> cfrui | AM54: =_xlfn.IFNA(INDEX(SAM!$B$8:$HC$215,MATCH($AL54,SAM!$A$8:$A$215,0),MATCH(AM$48,SAM!$B$7:$HC$7,0)),0) -> 6.5214655 | AN54: =_xlfn.IFNA(INDEX(SAM!$B$8:$HC$215,MATCH($AL54,SAM!$A$8:$A$215,0),MATCH(AN$48,SAM!$B$7:$HC$7,0)),0) -> 11.412929 | AO54: =_xlfn.IFNA(INDEX(SAM!$B$8:$HC$215,MATCH($AL54,SAM!$A$8:$A$215,0),MATCH(AO$48,SAM!$B$7:$HC$7,0)),0) -> 15.459818 | AP54: =_xlfn.IFNA(INDEX(SAM!$B$8:$HC$215,MATCH($AL54,SAM!$A$8:$A$215,0),MATCH(AP$48,SAM!$B$7:$HC$7,0)),0) -> 22.270047 | AQ54: =_xlfn.IFNA(INDEX(SAM!$B$8:$HC$215,MATCH($AL54,SAM!$A$8:$A$215,0),MATCH(AQ$48,SAM!$B$7:$HC$7,0)),0) -> 21.416681 | AR54: =_xlfn.IFNA(INDEX(SAM!$B$8:$HC$215,MATCH($AL54,SAM!$A$8:$A$215,0),MATCH(AR$48,SAM!$B$7:$HC$7,0)),0) -> 1.2379764 | AS54: =_xlfn.IFNA(INDEX(SAM!$B$8:$HC$215,MATCH($AL54,SAM!$A$8:$A$215,0),MATCH(AS$48,SAM!$B$7:$HC$7,0)),0) -> 1.8347025 | AT54: =_xlfn.IFNA(INDEX(SAM!$B$8:$HC$215,MATCH($AL54,SAM!$A$8:$A$215,0),MATCH(AT$48,SAM!$B$7:$HC$7,0)),0) -> 2.6906369 | ... BA54: =_xlfn.IFNA(INDEX(SAM!$B$8:$HC$215,MATCH($AL54,SAM!$A$8:$A$215,0),MATCH(BA$48,SAM!$B$7:$HC$7,0)),0) -> 51.49186 | BC54: ="a"&T54 -> afrui | BD54: =_xlfn.IFNA(INDEX(SAM!$B$8:$HC$215,MATCH($BC54,SAM!$A$8:$A$215,0),MATCH(BD$48,SAM!$B$7:$HC$7,0)),0) -> 3.9033868 | BE54: =_xlfn.IFNA(INDEX(SAM!$B$8:$HC$215,MATCH($BC54,SAM!$A$8:$A$215,0),MATCH(BE$48,SAM!$B$7:$HC$7,0)),0) -> 7.4907735 | BF54: =_xlfn.IFNA(INDEX(SAM!$B$8:$HC$215,MATCH($BC54,SAM!$A$8:$A$215,0),MATCH(BF$48,SAM!$B$7:$HC$7,0)),0) -> 12.816528 | BG54: =_xlfn.IFNA(INDEX(SAM!$B$8:$HC$215,MATCH($BC54,SAM!$A$8:$A$215,0),MATCH(BG$48,SAM!$B$7:$HC$7,0)),0) -> 21.126911 | BH54: =_xlfn.IFNA(INDEX(SAM!$B$8:$HC$215,MATCH($BC54,SAM!$A$8:$A$215,0),MATCH(BH$48,SAM!$B$7:$HC$7,0)),0) -> 16.380037 | BI54: =_xlfn.IFNA(INDEX(SAM!$B$8:$HC$215,MATCH($BC54,SAM!$A$8:$A$215,0),MATCH(BI$48,SAM!$B$7:$HC$7,0)),0) -> 0.57414547 | BJ54: =_xlfn.IFNA(INDEX(SAM!$B$8:$HC$215,MATCH($BC54,SAM!$A$8:$A$215,0),MATCH(BJ$48,SAM!$B$7:$HC$7,0)),0) -> 1.97384 | BK54: =_xlfn.IFNA(INDEX(SAM!$B$8:$HC$215,MATCH($BC54,SAM!$A$8:$A$215,0),MATCH(BK$48,SAM!$B$7:$HC$7,0)),0) -> 2.1171639 | ... BR54: =_xlfn.IFNA(INDEX(SAM!$B$8:$HC$215,MATCH($BC54,SAM!$A$8:$A$215,0),MATCH(BR$48,SAM!$B$7:$HC$7,0)),0) -> 4.8741653 | BT54: =AL54 -> cfrui | BU54: =SUM(BD54:BR54,AM54:BA54) -> 233.68663 | BW54: cfrui | BX54: =100*VLOOKUP(BW54,$BT$49:$BU$94,2,FALSE)/$BU$95 -> 3.3110967
A55: =HLOOKUP(B55,$B$6:$BR$9,4,FALSE) -> fruits | B55: fveg | C55: =IFERROR(100*U55/U$95,"") -> 0.0087551241 | D55: =IFERROR(100*V55/V$95,"") -> 0.035875594 | E55: =IFERROR(100*W55/W$95,"") -> 0.065671923 | F55: =IFERROR(100*X55/X$95,"") -> 0.14730474 | G55: =IFERROR(100*Y55/Y$95,"") -> 0.30429499 | H55: =IFERROR(100*Z55/Z$95,"") -> 0 | I55: =IFERROR(100*AA55/AA$95,"") -> 0.02494004 | J55: =IFERROR(100*AB55/AB$95,"") -> 0.027290116 | ... R55: =IFERROR(100*AJ55/AJ$95,"") -> 0.62432349 | T55: =B55 -> fveg | U55: =IFERROR(AM55+BD55,"") -> 0.025741911 | V55: =IFERROR(AN55+BE55,"") -> 0.15625205 | W55: =IFERROR(AO55+BF55,"") -> 0.39243118 | X55: =IFERROR(AP55+BG55,"") -> 1.2658461 | Y55: =IFERROR(AQ55+BH55,"") -> 2.8951632 | Z55: =IFERROR(AR55+BI55,"") -> 0 | AA55: =IFERROR(AS55+BJ55,"") -> 0.021054123 | AB55: =IFERROR(AT55+BK55,"") -> 0.0279124 | ... AI55: =IFERROR(BA55+BR55,"") -> 37.111016 | AJ55: =SUM(U55:AI55) -> 44.062757 | AL55: ="c"&T55 -> cfveg | AM55: =_xlfn.IFNA(INDEX(SAM!$B$8:$HC$215,MATCH($AL55,SAM!$A$8:$A$215,0),MATCH(AM$48,SAM!$B$7:$HC$7,0)),0) -> 0.025741911 | AN55: =_xlfn.IFNA(INDEX(SAM!$B$8:$HC$215,MATCH($AL55,SAM!$A$8:$A$215,0),MATCH(AN$48,SAM!$B$7:$HC$7,0)),0) -> 0.15625205 | AO55: =_xlfn.IFNA(INDEX(SAM!$B$8:$HC$215,MATCH($AL55,SAM!$A$8:$A$215,0),MATCH(AO$48,SAM!$B$7:$HC$7,0)),0) -> 0.39243118 | AP55: =_xlfn.IFNA(INDEX(SAM!$B$8:$HC$215,MATCH($AL55,SAM!$A$8:$A$215,0),MATCH(AP$48,SAM!$B$7:$HC$7,0)),0) -> 1.2658461 | AQ55: =_xlfn.IFNA(INDEX(SAM!$B$8:$HC$215,MATCH($AL55,SAM!$A$8:$A$215,0),MATCH(AQ$48,SAM!$B$7:$HC$7,0)),0) -> 2.8951632 | AR55: =_xlfn.IFNA(INDEX(SAM!$B$8:$HC$215,MATCH($AL55,SAM!$A$8:$A$215,0),MATCH(AR$48,SAM!$B$7:$HC$7,0)),0) -> 0 | AS55: =_xlfn.IFNA(INDEX(SAM!$B$8:$HC$215,MATCH($AL55,SAM!$A$8:$A$215,0),MATCH(AS$48,SAM!$B$7:$HC$7,0)),0) -> 0.021054123 | AT55: =_xlfn.IFNA(INDEX(SAM!$B$8:$HC$215,MATCH($AL55,SAM!$A$8:$A$215,0),MATCH(AT$48,SAM!$B$7:$HC$7,0)),0) -> 0.0279124 | ... BA55: =_xlfn.IFNA(INDEX(SAM!$B$8:$HC$215,MATCH($AL55,SAM!$A$8:$A$215,0),MATCH(BA$48,SAM!$B$7:$HC$7,0)),0) -> 37.111016 | BC55: ="a"&T55 -> afveg | BD55: =_xlfn.IFNA(INDEX(SAM!$B$8:$HC$215,MATCH($BC55,SAM!$A$8:$A$215,0),MATCH(BD$48,SAM!$B$7:$HC$7,0)),0) -> 0 | BE55: =_xlfn.IFNA(INDEX(SAM!$B$8:$HC$215,MATCH($BC55,SAM!$A$8:$A$215,0),MATCH(BE$48,SAM!$B$7:$HC$7,0)),0) -> 0 | BF55: =_xlfn.IFNA(INDEX(SAM!$B$8:$HC$215,MATCH($BC55,SAM!$A$8:$A$215,0),MATCH(BF$48,SAM!$B$7:$HC$7,0)),0) -> 0 | BG55: =_xlfn.IFNA(INDEX(SAM!$B$8:$HC$215,MATCH($BC55,SAM!$A$8:$A$215,0),MATCH(BG$48,SAM!$B$7:$HC$7,0)),0) -> 0 | BH55: =_xlfn.IFNA(INDEX(SAM!$B$8:$HC$215,MATCH($BC55,SAM!$A$8:$A$215,0),MATCH(BH$48,SAM!$B$7:$HC$7,0)),0) -> 0 | BI55: =_xlfn.IFNA(INDEX(SAM!$B$8:$HC$215,MATCH($BC55,SAM!$A$8:$A$215,0),MATCH(BI$48,SAM!$B$7:$HC$7,0)),0) -> 0 | BJ55: =_xlfn.IFNA(INDEX(SAM!$B$8:$HC$215,MATCH($BC55,SAM!$A$8:$A$215,0),MATCH(BJ$48,SAM!$B$7:$HC$7,0)),0) -> 0 | BK55: =_xlfn.IFNA(INDEX(SAM!$B$8:$HC$215,MATCH($BC55,SAM!$A$8:$A$215,0),MATCH(BK$48,SAM!$B$7:$HC$7,0)),0) -> 0 | ... BR55: =_xlfn.IFNA(INDEX(SAM!$B$8:$HC$215,MATCH($BC55,SAM!$A$8:$A$215,0),MATCH(BR$48,SAM!$B$7:$HC$7,0)),0) -> 0 | BT55: =AL55 -> cfveg | BU55: =SUM(BD55:BR55,AM55:BA55) -> 44.062757 | BW55: cbecr | BX55: =100*VLOOKUP(BW55,$BT$49:$BU$94,2,FALSE)/$BU$95 -> 0.035729883
A56: fish-meat-egg | B56: live | C56: =IFERROR(100*U56/U$95,"") -> 0.83751432 | D56: =IFERROR(100*V56/V$95,"") -> 1.0164966 | E56: =IFERROR(100*W56/W$95,"") -> 1.1989012 | F56: =IFERROR(100*X56/X$95,"") -> 1.3989648 | G56: =IFERROR(100*Y56/Y$95,"") -> 1.8208974 | H56: =IFERROR(100*Z56/Z$95,"") -> 1.6375456 | I56: =IFERROR(100*AA56/AA$95,"") -> 0.87829346 | J56: =IFERROR(100*AB56/AB$95,"") -> 1.5536256 | ... R56: =IFERROR(100*AJ56/AJ$95,"") -> 1.1367766 | T56: =B56 -> live | U56: =IFERROR(AM56+BD56,"") -> 2.4624687 | V56: =IFERROR(AN56+BE56,"") -> 4.4272347 | W56: =IFERROR(AO56+BF56,"") -> 7.1641914 | X56: =IFERROR(AP56+BG56,"") -> 12.021841 | Y56: =IFERROR(AQ56+BH56,"") -> 17.32462 | Z56: =IFERROR(AR56+BI56,"") -> 0.92710701 | AA56: =IFERROR(AS56+BJ56,"") -> 0.74144625 | AB56: =IFERROR(AT56+BK56,"") -> 1.5890523 | ... AI56: =IFERROR(BA56+BR56,"") -> 24.113409 | AJ56: =SUM(U56:AI56) -> 80.230064 | AL56: ="c"&T56 -> clive | AM56: =_xlfn.IFNA(INDEX(SAM!$B$8:$HC$215,MATCH($AL56,SAM!$A$8:$A$215,0),MATCH(AM$48,SAM!$B$7:$HC$7,0)),0) -> 1.9960695 | AN56: =_xlfn.IFNA(INDEX(SAM!$B$8:$HC$215,MATCH($AL56,SAM!$A$8:$A$215,0),MATCH(AN$48,SAM!$B$7:$HC$7,0)),0) -> 3.4673569 | AO56: =_xlfn.IFNA(INDEX(SAM!$B$8:$HC$215,MATCH($AL56,SAM!$A$8:$A$215,0),MATCH(AO$48,SAM!$B$7:$HC$7,0)),0) -> 5.582501 | AP56: =_xlfn.IFNA(INDEX(SAM!$B$8:$HC$215,MATCH($AL56,SAM!$A$8:$A$215,0),MATCH(AP$48,SAM!$B$7:$HC$7,0)),0) -> 9.3557918 | AQ56: =_xlfn.IFNA(INDEX(SAM!$B$8:$HC$215,MATCH($AL56,SAM!$A$8:$A$215,0),MATCH(AQ$48,SAM!$B$7:$HC$7,0)),0) -> 12.959505 | AR56: =_xlfn.IFNA(INDEX(SAM!$B$8:$HC$215,MATCH($AL56,SAM!$A$8:$A$215,0),MATCH(AR$48,SAM!$B$7:$HC$7,0)),0) -> 0.83700206 | AS56: =_xlfn.IFNA(INDEX(SAM!$B$8:$HC$215,MATCH($AL56,SAM!$A$8:$A$215,0),MATCH(AS$48,SAM!$B$7:$HC$7,0)),0) -> 0.57468905 | AT56: =_xlfn.IFNA(INDEX(SAM!$B$8:$HC$215,MATCH($AL56,SAM!$A$8:$A$215,0),MATCH(AT$48,SAM!$B$7:$HC$7,0)),0) -> 1.3252964 | ... BA56: =_xlfn.IFNA(INDEX(SAM!$B$8:$HC$215,MATCH($AL56,SAM!$A$8:$A$215,0),MATCH(BA$48,SAM!$B$7:$HC$7,0)),0) -> 20.021666 | BC56: ="a"&T56 -> alive | BD56: =_xlfn.IFNA(INDEX(SAM!$B$8:$HC$215,MATCH($BC56,SAM!$A$8:$A$215,0),MATCH(BD$48,SAM!$B$7:$HC$7,0)),0) -> 0.46639921 | BE56: =_xlfn.IFNA(INDEX(SAM!$B$8:$HC$215,MATCH($BC56,SAM!$A$8:$A$215,0),MATCH(BE$48,SAM!$B$7:$HC$7,0)),0) -> 0.95987788 | BF56: =_xlfn.IFNA(INDEX(SAM!$B$8:$HC$215,MATCH($BC56,SAM!$A$8:$A$215,0),MATCH(BF$48,SAM!$B$7:$HC$7,0)),0) -> 1.5816904 | BG56: =_xlfn.IFNA(INDEX(SAM!$B$8:$HC$215,MATCH($BC56,SAM!$A$8:$A$215,0),MATCH(BG$48,SAM!$B$7:$HC$7,0)),0) -> 2.6660497 | BH56: =_xlfn.IFNA(INDEX(SAM!$B$8:$HC$215,MATCH($BC56,SAM!$A$8:$A$215,0),MATCH(BH$48,SAM!$B$7:$HC$7,0)),0) -> 4.3651155 | BI56: =_xlfn.IFNA(INDEX(SAM!$B$8:$HC$215,MATCH($BC56,SAM!$A$8:$A$215,0),MATCH(BI$48,SAM!$B$7:$HC$7,0)),0) -> 0.090104946 | BJ56: =_xlfn.IFNA(INDEX(SAM!$B$8:$HC$215,MATCH($BC56,SAM!$A$8:$A$215,0),MATCH(BJ$48,SAM!$B$7:$HC$7,0)),0) -> 0.1667572 | BK56: =_xlfn.IFNA(INDEX(SAM!$B$8:$HC$215,MATCH($BC56,SAM!$A$8:$A$215,0),MATCH(BK$48,SAM!$B$7:$HC$7,0)),0) -> 0.26375588 | ... BR56: =_xlfn.IFNA(INDEX(SAM!$B$8:$HC$215,MATCH($BC56,SAM!$A$8:$A$215,0),MATCH(BR$48,SAM!$B$7:$HC$7,0)),0) -> 4.0917431 | BT56: =AL56 -> clive | BU56: =SUM(BD56:BR56,AM56:BA56) -> 80.230064 | BW56: cocrp | BX56: =100*VLOOKUP(BW56,$BT$49:$BU$94,2,FALSE)/$BU$95 -> 0.044475774
A57: =HLOOKUP(B57,$B$6:$BR$9,4,FALSE) -> fish-meat-egg | B57: fish | C57: =IFERROR(100*U57/U$95,"") -> 0.50063824 | D57: =IFERROR(100*V57/V$95,"") -> 0.41537361 | E57: =IFERROR(100*W57/W$95,"") -> 0.50416109 | F57: =IFERROR(100*X57/X$95,"") -> 0.57579171 | G57: =IFERROR(100*Y57/Y$95,"") -> 0.61501763 | H57: =IFERROR(100*Z57/Z$95,"") -> 0.27777867 | I57: =IFERROR(100*AA57/AA$95,"") -> 0.36254324 | J57: =IFERROR(100*AB57/AB$95,"") -> 0.37782719 | ... R57: =IFERROR(100*AJ57/AJ$95,"") -> 0.52166517 | T57: =B57 -> fish | U57: =IFERROR(AM57+BD57,"") -> 1.471982 | V57: =IFERROR(AN57+BE57,"") -> 1.8091124 | W57: =IFERROR(AO57+BF57,"") -> 3.0126807 | X57: =IFERROR(AP57+BG57,"") -> 4.9479991 | Y57: =IFERROR(AQ57+BH57,"") -> 5.8514812 | Z57: =IFERROR(AR57+BI57,"") -> 0.15726619 | AA57: =IFERROR(AS57+BJ57,"") -> 0.30605526 | AB57: =IFERROR(AT57+BK57,"") -> 0.38644262 | ... AI57: =IFERROR(BA57+BR57,"") -> 15.229718 | AJ57: =SUM(U57:AI57) -> 36.817462 | AL57: ="c"&T57 -> cfish | AM57: =_xlfn.IFNA(INDEX(SAM!$B$8:$HC$215,MATCH($AL57,SAM!$A$8:$A$215,0),MATCH(AM$48,SAM!$B$7:$HC$7,0)),0) -> 1.3576106 | AN57: =_xlfn.IFNA(INDEX(SAM!$B$8:$HC$215,MATCH($AL57,SAM!$A$8:$A$215,0),MATCH(AN$48,SAM!$B$7:$HC$7,0)),0) -> 1.5253723 | AO57: =_xlfn.IFNA(INDEX(SAM!$B$8:$HC$215,MATCH($AL57,SAM!$A$8:$A$215,0),MATCH(AO$48,SAM!$B$7:$HC$7,0)),0) -> 2.5341819 | AP57: =_xlfn.IFNA(INDEX(SAM!$B$8:$HC$215,MATCH($AL57,SAM!$A$8:$A$215,0),MATCH(AP$48,SAM!$B$7:$HC$7,0)),0) -> 4.6264038 | AQ57: =_xlfn.IFNA(INDEX(SAM!$B$8:$HC$215,MATCH($AL57,SAM!$A$8:$A$215,0),MATCH(AQ$48,SAM!$B$7:$HC$7,0)),0) -> 5.4175748 | AR57: =_xlfn.IFNA(INDEX(SAM!$B$8:$HC$215,MATCH($AL57,SAM!$A$8:$A$215,0),MATCH(AR$48,SAM!$B$7:$HC$7,0)),0) -> 0.15535856 | AS57: =_xlfn.IFNA(INDEX(SAM!$B$8:$HC$215,MATCH($AL57,SAM!$A$8:$A$215,0),MATCH(AS$48,SAM!$B$7:$HC$7,0)),0) -> 0.29583384 | AT57: =_xlfn.IFNA(INDEX(SAM!$B$8:$HC$215,MATCH($AL57,SAM!$A$8:$A$215,0),MATCH(AT$48,SAM!$B$7:$HC$7,0)),0) -> 0.34684633 | ... BA57: =_xlfn.IFNA(INDEX(SAM!$B$8:$HC$215,MATCH($AL57,SAM!$A$8:$A$215,0),MATCH(BA$48,SAM!$B$7:$HC$7,0)),0) -> 15.229718 | BC57: ="a"&T57 -> afish | BD57: =_xlfn.IFNA(INDEX(SAM!$B$8:$HC$215,MATCH($BC57,SAM!$A$8:$A$215,0),MATCH(BD$48,SAM!$B$7:$HC$7,0)),0) -> 0.11437143 | BE57: =_xlfn.IFNA(INDEX(SAM!$B$8:$HC$215,MATCH($BC57,SAM!$A$8:$A$215,0),MATCH(BE$48,SAM!$B$7:$HC$7,0)),0) -> 0.28374004 | BF57: =_xlfn.IFNA(INDEX(SAM!$B$8:$HC$215,MATCH($BC57,SAM!$A$8:$A$215,0),MATCH(BF$48,SAM!$B$7:$HC$7,0)),0) -> 0.47849884 | BG57: =_xlfn.IFNA(INDEX(SAM!$B$8:$HC$215,MATCH($BC57,SAM!$A$8:$A$215,0),MATCH(BG$48,SAM!$B$7:$HC$7,0)),0) -> 0.32159525 | BH57: =_xlfn.IFNA(INDEX(SAM!$B$8:$HC$215,MATCH($BC57,SAM!$A$8:$A$215,0),MATCH(BH$48,SAM!$B$7:$HC$7,0)),0) -> 0.43390641 | BI57: =_xlfn.IFNA(INDEX(SAM!$B$8:$HC$215,MATCH($BC57,SAM!$A$8:$A$215,0),MATCH(BI$48,SAM!$B$7:$HC$7,0)),0) -> 0.0019076325 | BJ57: =_xlfn.IFNA(INDEX(SAM!$B$8:$HC$215,MATCH($BC57,SAM!$A$8:$A$215,0),MATCH(BJ$48,SAM!$B$7:$HC$7,0)),0) -> 0.010221411 | BK57: =_xlfn.IFNA(INDEX(SAM!$B$8:$HC$215,MATCH($BC57,SAM!$A$8:$A$215,0),MATCH(BK$48,SAM!$B$7:$HC$7,0)),0) -> 0.039596287 | ... BR57: =_xlfn.IFNA(INDEX(SAM!$B$8:$HC$215,MATCH($BC57,SAM!$A$8:$A$215,0),MATCH(BR$48,SAM!$B$7:$HC$7,0)),0) -> 0 | BT57: =AL57 -> cfish | BU57: =SUM(BD57:BR57,AM57:BA57) -> 36.817462 | BW57: clive | BX57: =100*VLOOKUP(BW57,$BT$49:$BU$94,2,FALSE)/$BU$95 -> 1.1367766
A58: =HLOOKUP(B58,$B$6:$BR$9,4,FALSE) -> fish-meat-egg | B58: meat | C58: =IFERROR(100*U58/U$95,"") -> 0.24222609 | D58: =IFERROR(100*V58/V$95,"") -> 0.56237361 | E58: =IFERROR(100*W58/W$95,"") -> 0.72609098 | F58: =IFERROR(100*X58/X$95,"") -> 1.1960762 | G58: =IFERROR(100*Y58/Y$95,"") -> 1.9189747 | H58: =IFERROR(100*Z58/Z$95,"") -> 0.19029943 | I58: =IFERROR(100*AA58/AA$95,"") -> 0.53861516 | J58: =IFERROR(100*AB58/AB$95,"") -> 0.58920523 | ... R58: =IFERROR(100*AJ58/AJ$95,"") -> 1.2809086 | T58: =B58 -> meat | U58: =IFERROR(AM58+BD58,"") -> 0.71219578 | V58: =IFERROR(AN58+BE58,"") -> 2.4493541 | W58: =IFERROR(AO58+BF58,"") -> 4.3388518 | X58: =IFERROR(AP58+BG58,"") -> 10.278342 | Y58: =IFERROR(AQ58+BH58,"") -> 18.25776 | Z58: =IFERROR(AR58+BI58,"") -> 0.10773925 | AA58: =IFERROR(AS58+BJ58,"") -> 0.45469334 | AB58: =IFERROR(AT58+BK58,"") -> 0.60264061 | ... AI58: =IFERROR(BA58+BR58,"") -> 43.720711 | AJ58: =SUM(U58:AI58) -> 90.402437 | AL58: ="c"&T58 -> cmeat | AM58: =_xlfn.IFNA(INDEX(SAM!$B$8:$HC$215,MATCH($AL58,SAM!$A$8:$A$215,0),MATCH(AM$48,SAM!$B$7:$HC$7,0)),0) -> 0.71219578 | AN58: =_xlfn.IFNA(INDEX(SAM!$B$8:$HC$215,MATCH($AL58,SAM!$A$8:$A$215,0),MATCH(AN$48,SAM!$B$7:$HC$7,0)),0) -> 2.4493541 | AO58: =_xlfn.IFNA(INDEX(SAM!$B$8:$HC$215,MATCH($AL58,SAM!$A$8:$A$215,0),MATCH(AO$48,SAM!$B$7:$HC$7,0)),0) -> 4.3388518 | AP58: =_xlfn.IFNA(INDEX(SAM!$B$8:$HC$215,MATCH($AL58,SAM!$A$8:$A$215,0),MATCH(AP$48,SAM!$B$7:$HC$7,0)),0) -> 10.278342 | AQ58: =_xlfn.IFNA(INDEX(SAM!$B$8:$HC$215,MATCH($AL58,SAM!$A$8:$A$215,0),MATCH(AQ$48,SAM!$B$7:$HC$7,0)),0) -> 18.25776 | AR58: =_xlfn.IFNA(INDEX(SAM!$B$8:$HC$215,MATCH($AL58,SAM!$A$8:$A$215,0),MATCH(AR$48,SAM!$B$7:$HC$7,0)),0) -> 0.10773925 | AS58: =_xlfn.IFNA(INDEX(SAM!$B$8:$HC$215,MATCH($AL58,SAM!$A$8:$A$215,0),MATCH(AS$48,SAM!$B$7:$HC$7,0)),0) -> 0.45469334 | AT58: =_xlfn.IFNA(INDEX(SAM!$B$8:$HC$215,MATCH($AL58,SAM!$A$8:$A$215,0),MATCH(AT$48,SAM!$B$7:$HC$7,0)),0) -> 0.60264061 | ... BA58: =_xlfn.IFNA(INDEX(SAM!$B$8:$HC$215,MATCH($AL58,SAM!$A$8:$A$215,0),MATCH(BA$48,SAM!$B$7:$HC$7,0)),0) -> 43.720711 | BC58: ="a"&T58 -> ameat | BD58: =_xlfn.IFNA(INDEX(SAM!$B$8:$HC$215,MATCH($BC58,SAM!$A$8:$A$215,0),MATCH(BD$48,SAM!$B$7:$HC$7,0)),0) -> 0 | BE58: =_xlfn.IFNA(INDEX(SAM!$B$8:$HC$215,MATCH($BC58,SAM!$A$8:$A$215,0),MATCH(BE$48,SAM!$B$7:$HC$7,0)),0) -> 0 | BF58: =_xlfn.IFNA(INDEX(SAM!$B$8:$HC$215,MATCH($BC58,SAM!$A$8:$A$215,0),MATCH(BF$48,SAM!$B$7:$HC$7,0)),0) -> 0 | BG58: =_xlfn.IFNA(INDEX(SAM!$B$8:$HC$215,MATCH($BC58,SAM!$A$8:$A$215,0),MATCH(BG$48,SAM!$B$7:$HC$7,0)),0) -> 0 | BH58: =_xlfn.IFNA(INDEX(SAM!$B$8:$HC$215,MATCH($BC58,SAM!$A$8:$A$215,0),MATCH(BH$48,SAM!$B$7:$HC$7,0)),0) -> 0 | BI58: =_xlfn.IFNA(INDEX(SAM!$B$8:$HC$215,MATCH($BC58,SAM!$A$8:$A$215,0),MATCH(BI$48,SAM!$B$7:$HC$7,0)),0) -> 0 | BJ58: =_xlfn.IFNA(INDEX(SAM!$B$8:$HC$215,MATCH($BC58,SAM!$A$8:$A$215,0),MATCH(BJ$48,SAM!$B$7:$HC$7,0)),0) -> 0 | BK58: =_xlfn.IFNA(INDEX(SAM!$B$8:$HC$215,MATCH($BC58,SAM!$A$8:$A$215,0),MATCH(BK$48,SAM!$B$7:$HC$7,0)),0) -> 0 | ... BR58: =_xlfn.IFNA(INDEX(SAM!$B$8:$HC$215,MATCH($BC58,SAM!$A$8:$A$215,0),MATCH(BR$48,SAM!$B$7:$HC$7,0)),0) -> 0 | BT58: =AL58 -> cmeat | BU58: =SUM(BD58:BR58,AM58:BA58) -> 90.402437 | BW58: cmilk | BX58: =100*VLOOKUP(BW58,$BT$49:$BU$94,2,FALSE)/$BU$95 -> 1.3571612
A59: =HLOOKUP(B59,$B$6:$BR$9,4,FALSE) -> fish-meat-egg | B59: fsea | C59: =IFERROR(100*U59/U$95,"") -> 0.36283924 | D59: =IFERROR(100*V59/V$95,"") -> 0.38186716 | E59: =IFERROR(100*W59/W$95,"") -> 0.387136 | F59: =IFERROR(100*X59/X$95,"") -> 0.36223039 | G59: =IFERROR(100*Y59/Y$95,"") -> 0.30562246 | H59: =IFERROR(100*Z59/Z$95,"") -> 0.52504797 | I59: =IFERROR(100*AA59/AA$95,"") -> 0.43509173 | J59: =IFERROR(100*AB59/AB$95,"") -> 0.4085853 | ... R59: =IFERROR(100*AJ59/AJ$95,"") -> 0.27459354 | T59: =B59 -> fsea | U59: =IFERROR(AM59+BD59,"") -> 1.0668239 | V59: =IFERROR(AN59+BE59,"") -> 1.6631789 | W59: =IFERROR(AO59+BF59,"") -> 2.3133819 | X59: =IFERROR(AP59+BG59,"") -> 3.1127847 | Y59: =IFERROR(AQ59+BH59,"") -> 2.9077932 | Z59: =IFERROR(AR59+BI59,"") -> 0.2972593 | AA59: =IFERROR(AS59+BJ59,"") -> 0.36729993 | AB59: =IFERROR(AT59+BK59,"") -> 0.41790209 | ... AI59: =IFERROR(BA59+BR59,"") -> 4.117161 | AJ59: =SUM(U59:AI59) -> 19.379935 | AL59: ="c"&T59 -> cfsea | AM59: =_xlfn.IFNA(INDEX(SAM!$B$8:$HC$215,MATCH($AL59,SAM!$A$8:$A$215,0),MATCH(AM$48,SAM!$B$7:$HC$7,0)),0) -> 1.0668239 | AN59: =_xlfn.IFNA(INDEX(SAM!$B$8:$HC$215,MATCH($AL59,SAM!$A$8:$A$215,0),MATCH(AN$48,SAM!$B$7:$HC$7,0)),0) -> 1.6631789 | AO59: =_xlfn.IFNA(INDEX(SAM!$B$8:$HC$215,MATCH($AL59,SAM!$A$8:$A$215,0),MATCH(AO$48,SAM!$B$7:$HC$7,0)),0) -> 2.3133819 | AP59: =_xlfn.IFNA(INDEX(SAM!$B$8:$HC$215,MATCH($AL59,SAM!$A$8:$A$215,0),MATCH(AP$48,SAM!$B$7:$HC$7,0)),0) -> 3.1127847 | AQ59: =_xlfn.IFNA(INDEX(SAM!$B$8:$HC$215,MATCH($AL59,SAM!$A$8:$A$215,0),MATCH(AQ$48,SAM!$B$7:$HC$7,0)),0) -> 2.9077932 | AR59: =_xlfn.IFNA(INDEX(SAM!$B$8:$HC$215,MATCH($AL59,SAM!$A$8:$A$215,0),MATCH(AR$48,SAM!$B$7:$HC$7,0)),0) -> 0.2972593 | AS59: =_xlfn.IFNA(INDEX(SAM!$B$8:$HC$215,MATCH($AL59,SAM!$A$8:$A$215,0),MATCH(AS$48,SAM!$B$7:$HC$7,0)),0) -> 0.36729993 | AT59: =_xlfn.IFNA(INDEX(SAM!$B$8:$HC$215,MATCH($AL59,SAM!$A$8:$A$215,0),MATCH(AT$48,SAM!$B$7:$HC$7,0)),0) -> 0.41790209 | ... BA59: =_xlfn.IFNA(INDEX(SAM!$B$8:$HC$215,MATCH($AL59,SAM!$A$8:$A$215,0),MATCH(BA$48,SAM!$B$7:$HC$7,0)),0) -> 4.117161 | BC59: ="a"&T59 -> afsea | BD59: =_xlfn.IFNA(INDEX(SAM!$B$8:$HC$215,MATCH($BC59,SAM!$A$8:$A$215,0),MATCH(BD$48,SAM!$B$7:$HC$7,0)),0) -> 0 | BE59: =_xlfn.IFNA(INDEX(SAM!$B$8:$HC$215,MATCH($BC59,SAM!$A$8:$A$215,0),MATCH(BE$48,SAM!$B$7:$HC$7,0)),0) -> 0 | BF59: =_xlfn.IFNA(INDEX(SAM!$B$8:$HC$215,MATCH($BC59,SAM!$A$8:$A$215,0),MATCH(BF$48,SAM!$B$7:$HC$7,0)),0) -> 0 | BG59: =_xlfn.IFNA(INDEX(SAM!$B$8:$HC$215,MATCH($BC59,SAM!$A$8:$A$215,0),MATCH(BG$48,SAM!$B$7:$HC$7,0)),0) -> 0 | BH59: =_xlfn.IFNA(INDEX(SAM!$B$8:$HC$215,MATCH($BC59,SAM!$A$8:$A$215,0),MATCH(BH$48,SAM!$B$7:$HC$7,0)),0) -> 0 | BI59: =_xlfn.IFNA(INDEX(SAM!$B$8:$HC$215,MATCH($BC59,SAM!$A$8:$A$215,0),MATCH(BI$48,SAM!$B$7:$HC$7,0)),0) -> 0 | BJ59: =_xlfn.IFNA(INDEX(SAM!$B$8:$HC$215,MATCH($BC59,SAM!$A$8:$A$215,0),MATCH(BJ$48,SAM!$B$7:$HC$7,0)),0) -> 0 | BK59: =_xlfn.IFNA(INDEX(SAM!$B$8:$HC$215,MATCH($BC59,SAM!$A$8:$A$215,0),MATCH(BK$48,SAM!$B$7:$HC$7,0)),0) -> 0 | ... BR59: =_xlfn.IFNA(INDEX(SAM!$B$8:$HC$215,MATCH($BC59,SAM!$A$8:$A$215,0),MATCH(BR$48,SAM!$B$7:$HC$7,0)),0) -> 0 | BT59: =AL59 -> cfsea | BU59: =SUM(BD59:BR59,AM59:BA59) -> 19.379935 | BW59: cfore | BX59: =100*VLOOKUP(BW59,$BT$49:$BU$94,2,FALSE)/$BU$95 -> 7.5334939
A60: =HLOOKUP(B60,$B$6:$BR$9,4,FALSE) -> diary | B60: milk | C60: =IFERROR(100*U60/U$95,"") -> 0.25925625 | D60: =IFERROR(100*V60/V$95,"") -> 0.7505108 | E60: =IFERROR(100*W60/W$95,"") -> 0.95335997 | F60: =IFERROR(100*X60/X$95,"") -> 1.6733714 | G60: =IFERROR(100*Y60/Y$95,"") -> 2.0482612 | H60: =IFERROR(100*Z60/Z$95,"") -> 0.28699308 | I60: =IFERROR(100*AA60/AA$95,"") -> 0.46943025 | J60: =IFERROR(100*AB60/AB$95,"") -> 0.93790144 | ... R60: =IFERROR(100*AJ60/AJ$95,"") -> 1.3571612 | T60: =B60 -> milk | U60: =IFERROR(AM60+BD60,"") -> 0.76226802 | V60: =IFERROR(AN60+BE60,"") -> 3.2687642 | W60: =IFERROR(AO60+BF60,"") -> 5.6969275 | X60: =IFERROR(AP60+BG60,"") -> 14.379923 | Y60: =IFERROR(AQ60+BH60,"") -> 19.487835 | Z60: =IFERROR(AR60+BI60,"") -> 0.16248298 | AA60: =IFERROR(AS60+BJ60,"") -> 0.39628816 | AB60: =IFERROR(AT60+BK60,"") -> 0.959288 | ... AI60: =IFERROR(BA60+BR60,"") -> 40.927872 | AJ60: =SUM(U60:AI60) -> 95.784105 | AL60: ="c"&T60 -> cmilk | AM60: =_xlfn.IFNA(INDEX(SAM!$B$8:$HC$215,MATCH($AL60,SAM!$A$8:$A$215,0),MATCH(AM$48,SAM!$B$7:$HC$7,0)),0) -> 0.46355098 | AN60: =_xlfn.IFNA(INDEX(SAM!$B$8:$HC$215,MATCH($AL60,SAM!$A$8:$A$215,0),MATCH(AN$48,SAM!$B$7:$HC$7,0)),0) -> 1.4035607 | AO60: =_xlfn.IFNA(INDEX(SAM!$B$8:$HC$215,MATCH($AL60,SAM!$A$8:$A$215,0),MATCH(AO$48,SAM!$B$7:$HC$7,0)),0) -> 2.2376939 | AP60: =_xlfn.IFNA(INDEX(SAM!$B$8:$HC$215,MATCH($AL60,SAM!$A$8:$A$215,0),MATCH(AP$48,SAM!$B$7:$HC$7,0)),0) -> 5.3211501 | AQ60: =_xlfn.IFNA(INDEX(SAM!$B$8:$HC$215,MATCH($AL60,SAM!$A$8:$A$215,0),MATCH(AQ$48,SAM!$B$7:$HC$7,0)),0) -> 9.1199547 | AR60: =_xlfn.IFNA(INDEX(SAM!$B$8:$HC$215,MATCH($AL60,SAM!$A$8:$A$215,0),MATCH(AR$48,SAM!$B$7:$HC$7,0)),0) -> 0.12610133 | AS60: =_xlfn.IFNA(INDEX(SAM!$B$8:$HC$215,MATCH($AL60,SAM!$A$8:$A$215,0),MATCH(AS$48,SAM!$B$7:$HC$7,0)),0) -> 0.13592275 | AT60: =_xlfn.IFNA(INDEX(SAM!$B$8:$HC$215,MATCH($AL60,SAM!$A$8:$A$215,0),MATCH(AT$48,SAM!$B$7:$HC$7,0)),0) -> 0.36508629 | ... BA60: =_xlfn.IFNA(INDEX(SAM!$B$8:$HC$215,MATCH($AL60,SAM!$A$8:$A$215,0),MATCH(BA$48,SAM!$B$7:$HC$7,0)),0) -> 37.241075 | BC60: ="a"&T60 -> amilk | BD60: =_xlfn.IFNA(INDEX(SAM!$B$8:$HC$215,MATCH($BC60,SAM!$A$8:$A$215,0),MATCH(BD$48,SAM!$B$7:$HC$7,0)),0) -> 0.29871704 | BE60: =_xlfn.IFNA(INDEX(SAM!$B$8:$HC$215,MATCH($BC60,SAM!$A$8:$A$215,0),MATCH(BE$48,SAM!$B$7:$HC$7,0)),0) -> 1.8652035 | BF60: =_xlfn.IFNA(INDEX(SAM!$B$8:$HC$215,MATCH($BC60,SAM!$A$8:$A$215,0),MATCH(BF$48,SAM!$B$7:$HC$7,0)),0) -> 3.4592336 | BG60: =_xlfn.IFNA(INDEX(SAM!$B$8:$HC$215,MATCH($BC60,SAM!$A$8:$A$215,0),MATCH(BG$48,SAM!$B$7:$HC$7,0)),0) -> 9.0587726 | BH60: =_xlfn.IFNA(INDEX(SAM!$B$8:$HC$215,MATCH($BC60,SAM!$A$8:$A$215,0),MATCH(BH$48,SAM!$B$7:$HC$7,0)),0) -> 10.36788 | BI60: =_xlfn.IFNA(INDEX(SAM!$B$8:$HC$215,MATCH($BC60,SAM!$A$8:$A$215,0),MATCH(BI$48,SAM!$B$7:$HC$7,0)),0) -> 0.036381651 | BJ60: =_xlfn.IFNA(INDEX(SAM!$B$8:$HC$215,MATCH($BC60,SAM!$A$8:$A$215,0),MATCH(BJ$48,SAM!$B$7:$HC$7,0)),0) -> 0.26036541 | BK60: =_xlfn.IFNA(INDEX(SAM!$B$8:$HC$215,MATCH($BC60,SAM!$A$8:$A$215,0),MATCH(BK$48,SAM!$B$7:$HC$7,0)),0) -> 0.5942017 | ... BR60: =_xlfn.IFNA(INDEX(SAM!$B$8:$HC$215,MATCH($BC60,SAM!$A$8:$A$215,0),MATCH(BR$48,SAM!$B$7:$HC$7,0)),0) -> 3.6867976 | BT60: =AL60 -> cmilk | BU60: =SUM(BD60:BR60,AM60:BA60) -> 95.784105 | BW60: cfish | BX60: =100*VLOOKUP(BW60,$BT$49:$BU$94,2,FALSE)/$BU$95 -> 0.52166517
A61: =HLOOKUP(B61,$B$6:$BR$9,4,FALSE) -> diary | B61: dair | C61: =IFERROR(100*U61/U$95,"") -> 0.20020347 | D61: =IFERROR(100*V61/V$95,"") -> 0.47432499 | E61: =IFERROR(100*W61/W$95,"") -> 0.61192244 | F61: =IFERROR(100*X61/X$95,"") -> 0.91143127 | G61: =IFERROR(100*Y61/Y$95,"") -> 0.8492992 | H61: =IFERROR(100*Z61/Z$95,"") -> 0.29247525 | I61: =IFERROR(100*AA61/AA$95,"") -> 0.69920325 | J61: =IFERROR(100*AB61/AB$95,"") -> 0.64310698 | ... R61: =IFERROR(100*AJ61/AJ$95,"") -> 0.52229303 | T61: =B61 -> dair | U61: =IFERROR(AM61+BD61,"") -> 0.58864042 | V61: =IFERROR(AN61+BE61,"") -> 2.0658684 | W61: =IFERROR(AO61+BF61,"") -> 3.6566228 | X61: =IFERROR(AP61+BG61,"") -> 7.8322785 | Y61: =IFERROR(AQ61+BH61,"") -> 8.0805136 | Z61: =IFERROR(AR61+BI61,"") -> 0.16558675 | AA61: =IFERROR(AS61+BJ61,"") -> 0.59026015 | AB61: =IFERROR(AT61+BK61,"") -> 0.65777146 | ... AI61: =IFERROR(BA61+BR61,"") -> 9.6481082 | AJ61: =SUM(U61:AI61) -> 36.861774 | AL61: ="c"&T61 -> cdair | AM61: =_xlfn.IFNA(INDEX(SAM!$B$8:$HC$215,MATCH($AL61,SAM!$A$8:$A$215,0),MATCH(AM$48,SAM!$B$7:$HC$7,0)),0) -> 0.18501356 | AN61: =_xlfn.IFNA(INDEX(SAM!$B$8:$HC$215,MATCH($AL61,SAM!$A$8:$A$215,0),MATCH(AN$48,SAM!$B$7:$HC$7,0)),0) -> 0.44252413 | AO61: =_xlfn.IFNA(INDEX(SAM!$B$8:$HC$215,MATCH($AL61,SAM!$A$8:$A$215,0),MATCH(AO$48,SAM!$B$7:$HC$7,0)),0) -> 0.8286076 | AP61: =_xlfn.IFNA(INDEX(SAM!$B$8:$HC$215,MATCH($AL61,SAM!$A$8:$A$215,0),MATCH(AP$48,SAM!$B$7:$HC$7,0)),0) -> 1.8097729 | AQ61: =_xlfn.IFNA(INDEX(SAM!$B$8:$HC$215,MATCH($AL61,SAM!$A$8:$A$215,0),MATCH(AQ$48,SAM!$B$7:$HC$7,0)),0) -> 2.8274095 | AR61: =_xlfn.IFNA(INDEX(SAM!$B$8:$HC$215,MATCH($AL61,SAM!$A$8:$A$215,0),MATCH(AR$48,SAM!$B$7:$HC$7,0)),0) -> 0.055618926 | AS61: =_xlfn.IFNA(INDEX(SAM!$B$8:$HC$215,MATCH($AL61,SAM!$A$8:$A$215,0),MATCH(AS$48,SAM!$B$7:$HC$7,0)),0) -> 0.11571258 | AT61: =_xlfn.IFNA(INDEX(SAM!$B$8:$HC$215,MATCH($AL61,SAM!$A$8:$A$215,0),MATCH(AT$48,SAM!$B$7:$HC$7,0)),0) -> 0.1944016 | ... BA61: =_xlfn.IFNA(INDEX(SAM!$B$8:$HC$215,MATCH($AL61,SAM!$A$8:$A$215,0),MATCH(BA$48,SAM!$B$7:$HC$7,0)),0) -> 9.2745341 | BC61: ="a"&T61 -> adair | BD61: =_xlfn.IFNA(INDEX(SAM!$B$8:$HC$215,MATCH($BC61,SAM!$A$8:$A$215,0),MATCH(BD$48,SAM!$B$7:$HC$7,0)),0) -> 0.40362686 | BE61: =_xlfn.IFNA(INDEX(SAM!$B$8:$HC$215,MATCH($BC61,SAM!$A$8:$A$215,0),MATCH(BE$48,SAM!$B$7:$HC$7,0)),0) -> 1.6233443 | BF61: =_xlfn.IFNA(INDEX(SAM!$B$8:$HC$215,MATCH($BC61,SAM!$A$8:$A$215,0),MATCH(BF$48,SAM!$B$7:$HC$7,0)),0) -> 2.8280152 | BG61: =_xlfn.IFNA(INDEX(SAM!$B$8:$HC$215,MATCH($BC61,SAM!$A$8:$A$215,0),MATCH(BG$48,SAM!$B$7:$HC$7,0)),0) -> 6.0225056 | BH61: =_xlfn.IFNA(INDEX(SAM!$B$8:$HC$215,MATCH($BC61,SAM!$A$8:$A$215,0),MATCH(BH$48,SAM!$B$7:$HC$7,0)),0) -> 5.2531041 | BI61: =_xlfn.IFNA(INDEX(SAM!$B$8:$HC$215,MATCH($BC61,SAM!$A$8:$A$215,0),MATCH(BI$48,SAM!$B$7:$HC$7,0)),0) -> 0.10996782 | BJ61: =_xlfn.IFNA(INDEX(SAM!$B$8:$HC$215,MATCH($BC61,SAM!$A$8:$A$215,0),MATCH(BJ$48,SAM!$B$7:$HC$7,0)),0) -> 0.47454756 | BK61: =_xlfn.IFNA(INDEX(SAM!$B$8:$HC$215,MATCH($BC61,SAM!$A$8:$A$215,0),MATCH(BK$48,SAM!$B$7:$HC$7,0)),0) -> 0.46336986 | ... BR61: =_xlfn.IFNA(INDEX(SAM!$B$8:$HC$215,MATCH($BC61,SAM!$A$8:$A$215,0),MATCH(BR$48,SAM!$B$7:$HC$7,0)),0) -> 0.37357415 | BT61: =AL61 -> cdair | BU61: =SUM(BD61:BR61,AM61:BA61) -> 36.861774 | BW61: cmine | BX61: =100*VLOOKUP(BW61,$BT$49:$BU$94,2,FALSE)/$BU$95 -> 0
A62: =HLOOKUP(B62,$B$6:$BR$9,4,FALSE) -> fats & oils | B62: oils | C62: =IFERROR(100*U62/U$95,"") -> 0.050881787 | D62: =IFERROR(100*V62/V$95,"") -> 0.14512875 | E62: =IFERROR(100*W62/W$95,"") -> 0.14540982 | F62: =IFERROR(100*X62/X$95,"") -> 0.33721365 | G62: =IFERROR(100*Y62/Y$95,"") -> 0.33802977 | H62: =IFERROR(100*Z62/Z$95,"") -> 0.19746392 | I62: =IFERROR(100*AA62/AA$95,"") -> 0.31685365 | J62: =IFERROR(100*AB62/AB$95,"") -> 0.066847421 | ... R62: =IFERROR(100*AJ62/AJ$95,"") -> 0.34153659 | T62: =B62 -> oils | U62: =IFERROR(AM62+BD62,"") -> 0.14960318 | V62: =IFERROR(AN62+BE62,"") -> 0.63209169 | W62: =IFERROR(AO62+BF62,"") -> 0.86891546 | X62: =IFERROR(AP62+BG62,"") -> 2.8978062 | Y62: =IFERROR(AQ62+BH62,"") -> 3.2161271 | Z62: =IFERROR(AR62+BI62,"") -> 0.11179547 | AA62: =IFERROR(AS62+BJ62,"") -> 0.26748457 | AB62: =IFERROR(AT62+BK62,"") -> 0.068371713 | ... AI62: =IFERROR(BA62+BR62,"") -> 13.390775 | AJ62: =SUM(U62:AI62) -> 24.104561 | AL62: ="c"&T62 -> coils | AM62: =_xlfn.IFNA(INDEX(SAM!$B$8:$HC$215,MATCH($AL62,SAM!$A$8:$A$215,0),MATCH(AM$48,SAM!$B$7:$HC$7,0)),0) -> 0.082848644 | AN62: =_xlfn.IFNA(INDEX(SAM!$B$8:$HC$215,MATCH($AL62,SAM!$A$8:$A$215,0),MATCH(AN$48,SAM!$B$7:$HC$7,0)),0) -> 0.15732568 | AO62: =_xlfn.IFNA(INDEX(SAM!$B$8:$HC$215,MATCH($AL62,SAM!$A$8:$A$215,0),MATCH(AO$48,SAM!$B$7:$HC$7,0)),0) -> 0.35745288 | AP62: =_xlfn.IFNA(INDEX(SAM!$B$8:$HC$215,MATCH($AL62,SAM!$A$8:$A$215,0),MATCH(AP$48,SAM!$B$7:$HC$7,0)),0) -> 0.84763119 | AQ62: =_xlfn.IFNA(INDEX(SAM!$B$8:$HC$215,MATCH($AL62,SAM!$A$8:$A$215,0),MATCH(AQ$48,SAM!$B$7:$HC$7,0)),0) -> 1.9707705 | AR62: =_xlfn.IFNA(INDEX(SAM!$B$8:$HC$215,MATCH($AL62,SAM!$A$8:$A$215,0),MATCH(AR$48,SAM!$B$7:$HC$7,0)),0) -> 0 | AS62: =_xlfn.IFNA(INDEX(SAM!$B$8:$HC$215,MATCH($AL62,SAM!$A$8:$A$215,0),MATCH(AS$48,SAM!$B$7:$HC$7,0)),0) -> 0.076334912 | AT62: =_xlfn.IFNA(INDEX(SAM!$B$8:$HC$215,MATCH($AL62,SAM!$A$8:$A$215,0),MATCH(AT$48,SAM!$B$7:$HC$7,0)),0) -> 0.068371713 | ... BA62: =_xlfn.IFNA(INDEX(SAM!$B$8:$HC$215,MATCH($AL62,SAM!$A$8:$A$215,0),MATCH(BA$48,SAM!$B$7:$HC$7,0)),0) -> 13.065844 | BC62: ="a"&T62 -> aoils | BD62: =_xlfn.IFNA(INDEX(SAM!$B$8:$HC$215,MATCH($BC62,SAM!$A$8:$A$215,0),MATCH(BD$48,SAM!$B$7:$HC$7,0)),0) -> 0.066754537 | BE62: =_xlfn.IFNA(INDEX(SAM!$B$8:$HC$215,MATCH($BC62,SAM!$A$8:$A$215,0),MATCH(BE$48,SAM!$B$7:$HC$7,0)),0) -> 0.47476601 | BF62: =_xlfn.IFNA(INDEX(SAM!$B$8:$HC$215,MATCH($BC62,SAM!$A$8:$A$215,0),MATCH(BF$48,SAM!$B$7:$HC$7,0)),0) -> 0.51146258 | BG62: =_xlfn.IFNA(INDEX(SAM!$B$8:$HC$215,MATCH($BC62,SAM!$A$8:$A$215,0),MATCH(BG$48,SAM!$B$7:$HC$7,0)),0) -> 2.050175 | BH62: =_xlfn.IFNA(INDEX(SAM!$B$8:$HC$215,MATCH($BC62,SAM!$A$8:$A$215,0),MATCH(BH$48,SAM!$B$7:$HC$7,0)),0) -> 1.2453566 | BI62: =_xlfn.IFNA(INDEX(SAM!$B$8:$HC$215,MATCH($BC62,SAM!$A$8:$A$215,0),MATCH(BI$48,SAM!$B$7:$HC$7,0)),0) -> 0.11179547 | BJ62: =_xlfn.IFNA(INDEX(SAM!$B$8:$HC$215,MATCH($BC62,SAM!$A$8:$A$215,0),MATCH(BJ$48,SAM!$B$7:$HC$7,0)),0) -> 0.19114966 | BK62: =_xlfn.IFNA(INDEX(SAM!$B$8:$HC$215,MATCH($BC62,SAM!$A$8:$A$215,0),MATCH(BK$48,SAM!$B$7:$HC$7,0)),0) -> 0 | ... BR62: =_xlfn.IFNA(INDEX(SAM!$B$8:$HC$215,MATCH($BC62,SAM!$A$8:$A$215,0),MATCH(BR$48,SAM!$B$7:$HC$7,0)),0) -> 0.32493121 | BT62: =AL62 -> coils | BU62: =SUM(BD62:BR62,AM62:BA62) -> 24.104561 | BW62: cmino | BX62: =100*VLOOKUP(BW62,$BT$49:$BU$94,2,FALSE)/$BU$95 -> 0
A63: =HLOOKUP(B63,$B$6:$BR$9,4,FALSE) -> fats & oils | B63: foil | C63: =IFERROR(100*U63/U$95,"") -> 1.3536343 | D63: =IFERROR(100*V63/V$95,"") -> 1.5999222 | E63: =IFERROR(100*W63/W$95,"") -> 1.711202 | F63: =IFERROR(100*X63/X$95,"") -> 1.7783926 | G63: =IFERROR(100*Y63/Y$95,"") -> 1.5728852 | H63: =IFERROR(100*Z63/Z$95,"") -> 1.4798805 | I63: =IFERROR(100*AA63/AA$95,"") -> 1.6736953 | J63: =IFERROR(100*AB63/AB$95,"") -> 1.7159031 | ... R63: =IFERROR(100*AJ63/AJ$95,"") -> 1.3492488 | T63: =B63 -> foil | U63: =IFERROR(AM63+BD63,"") -> 3.9799703 | V63: =IFERROR(AN63+BE63,"") -> 6.9682787 | W63: =IFERROR(AO63+BF63,"") -> 10.225512 | X63: =IFERROR(AP63+BG63,"") -> 15.28241 | Y63: =IFERROR(AQ63+BH63,"") -> 14.96495 | Z63: =IFERROR(AR63+BI63,"") -> 0.83784389 | AA63: =IFERROR(AS63+BJ63,"") -> 1.4129162 | AB63: =IFERROR(AT63+BK63,"") -> 1.7550301 | ... AI63: =IFERROR(BA63+BR63,"") -> 26.289547 | AJ63: =SUM(U63:AI63) -> 95.225671 | AL63: ="c"&T63 -> cfoil | AM63: =_xlfn.IFNA(INDEX(SAM!$B$8:$HC$215,MATCH($AL63,SAM!$A$8:$A$215,0),MATCH(AM$48,SAM!$B$7:$HC$7,0)),0) -> 3.9799703 | AN63: =_xlfn.IFNA(INDEX(SAM!$B$8:$HC$215,MATCH($AL63,SAM!$A$8:$A$215,0),MATCH(AN$48,SAM!$B$7:$HC$7,0)),0) -> 6.9682787 | AO63: =_xlfn.IFNA(INDEX(SAM!$B$8:$HC$215,MATCH($AL63,SAM!$A$8:$A$215,0),MATCH(AO$48,SAM!$B$7:$HC$7,0)),0) -> 10.225512 | AP63: =_xlfn.IFNA(INDEX(SAM!$B$8:$HC$215,MATCH($AL63,SAM!$A$8:$A$215,0),MATCH(AP$48,SAM!$B$7:$HC$7,0)),0) -> 15.28241 | AQ63: =_xlfn.IFNA(INDEX(SAM!$B$8:$HC$215,MATCH($AL63,SAM!$A$8:$A$215,0),MATCH(AQ$48,SAM!$B$7:$HC$7,0)),0) -> 14.96495 | AR63: =_xlfn.IFNA(INDEX(SAM!$B$8:$HC$215,MATCH($AL63,SAM!$A$8:$A$215,0),MATCH(AR$48,SAM!$B$7:$HC$7,0)),0) -> 0.83784389 | AS63: =_xlfn.IFNA(INDEX(SAM!$B$8:$HC$215,MATCH($AL63,SAM!$A$8:$A$215,0),MATCH(AS$48,SAM!$B$7:$HC$7,0)),0) -> 1.4129162 | AT63: =_xlfn.IFNA(INDEX(SAM!$B$8:$HC$215,MATCH($AL63,SAM!$A$8:$A$215,0),MATCH(AT$48,SAM!$B$7:$HC$7,0)),0) -> 1.7550301 | ... BA63: =_xlfn.IFNA(INDEX(SAM!$B$8:$HC$215,MATCH($AL63,SAM!$A$8:$A$215,0),MATCH(BA$48,SAM!$B$7:$HC$7,0)),0) -> 26.289547 | BC63: ="a"&T63 -> afoil | BD63: =_xlfn.IFNA(INDEX(SAM!$B$8:$HC$215,MATCH($BC63,SAM!$A$8:$A$215,0),MATCH(BD$48,SAM!$B$7:$HC$7,0)),0) -> 0 | BE63: =_xlfn.IFNA(INDEX(SAM!$B$8:$HC$215,MATCH($BC63,SAM!$A$8:$A$215,0),MATCH(BE$48,SAM!$B$7:$HC$7,0)),0) -> 0 | BF63: =_xlfn.IFNA(INDEX(SAM!$B$8:$HC$215,MATCH($BC63,SAM!$A$8:$A$215,0),MATCH(BF$48,SAM!$B$7:$HC$7,0)),0) -> 0 | BG63: =_xlfn.IFNA(INDEX(SAM!$B$8:$HC$215,MATCH($BC63,SAM!$A$8:$A$215,0),MATCH(BG$48,SAM!$B$7:$HC$7,0)),0) -> 0 | BH63: =_xlfn.IFNA(INDEX(SAM!$B$8:$HC$215,MATCH($BC63,SAM!$A$8:$A$215,0),MATCH(BH$48,SAM!$B$7:$HC$7,0)),0) -> 0 | BI63: =_xlfn.IFNA(INDEX(SAM!$B$8:$HC$215,MATCH($BC63,SAM!$A$8:$A$215,0),MATCH(BI$48,SAM!$B$7:$HC$7,0)),0) -> 0 | BJ63: =_xlfn.IFNA(INDEX(SAM!$B$8:$HC$215,MATCH($BC63,SAM!$A$8:$A$215,0),MATCH(BJ$48,SAM!$B$7:$HC$7,0)),0) -> 0 | BK63: =_xlfn.IFNA(INDEX(SAM!$B$8:$HC$215,MATCH($BC63,SAM!$A$8:$A$215,0),MATCH(BK$48,SAM!$B$7:$HC$7,0)),0) -> 0 | ... BR63: =_xlfn.IFNA(INDEX(SAM!$B$8:$HC$215,MATCH($BC63,SAM!$A$8:$A$215,0),MATCH(BR$48,SAM!$B$7:$HC$7,0)),0) -> 0 | BT63: =AL63 -> cfoil | BU63: =SUM(BD63:BR63,AM63:BA63) -> 95.225671 | BW63: cgmll | BX63: =100*VLOOKUP(BW63,$BT$49:$BU$94,2,FALSE)/$BU$95 -> 1.8189525
A64: other food | B64: fobe | C64: =IFERROR(100*U64/U$95,"") -> 6.4552387 | D64: =IFERROR(100*V64/V$95,"") -> 7.3966803 | E64: =IFERROR(100*W64/W$95,"") -> 9.0900167 | F64: =IFERROR(100*X64/X$95,"") -> 11.389314 | G64: =IFERROR(100*Y64/Y$95,"") -> 12.54678 | H64: =IFERROR(100*Z64/Z$95,"") -> 7.1906849 | I64: =IFERROR(100*AA64/AA$95,"") -> 9.2224516 | J64: =IFERROR(100*AB64/AB$95,"") -> 11.564234 | ... R64: =IFERROR(100*AJ64/AJ$95,"") -> 9.1358558 | T64: =B64 -> fobe | U64: =IFERROR(AM64+BD64,"") -> 18.979763 | V64: =IFERROR(AN64+BE64,"") -> 32.215397 | W64: =IFERROR(AO64+BF64,"") -> 54.318586 | X64: =IFERROR(AP64+BG64,"") -> 97.872741 | Y64: =IFERROR(AQ64+BH64,"") -> 119.37422 | Z64: =IFERROR(AR64+BI64,"") -> 4.0710527 | AA64: =IFERROR(AS64+BJ64,"") -> 7.7854982 | AB64: =IFERROR(AT64+BK64,"") -> 11.827928 | ... AI64: =IFERROR(BA64+BR64,"") -> 231.91043 | AJ64: =SUM(U64:AI64) -> 644.77952 | AL64: ="c"&T64 -> cfobe | AM64: =_xlfn.IFNA(INDEX(SAM!$B$8:$HC$215,MATCH($AL64,SAM!$A$8:$A$215,0),MATCH(AM$48,SAM!$B$7:$HC$7,0)),0) -> 16.056955 | AN64: =_xlfn.IFNA(INDEX(SAM!$B$8:$HC$215,MATCH($AL64,SAM!$A$8:$A$215,0),MATCH(AN$48,SAM!$B$7:$HC$7,0)),0) -> 26.878493 | AO64: =_xlfn.IFNA(INDEX(SAM!$B$8:$HC$215,MATCH($AL64,SAM!$A$8:$A$215,0),MATCH(AO$48,SAM!$B$7:$HC$7,0)),0) -> 40.727031 | AP64: =_xlfn.IFNA(INDEX(SAM!$B$8:$HC$215,MATCH($AL64,SAM!$A$8:$A$215,0),MATCH(AP$48,SAM!$B$7:$HC$7,0)),0) -> 63.190047 | AQ64: =_xlfn.IFNA(INDEX(SAM!$B$8:$HC$215,MATCH($AL64,SAM!$A$8:$A$215,0),MATCH(AQ$48,SAM!$B$7:$HC$7,0)),0) -> 86.411488 | AR64: =_xlfn.IFNA(INDEX(SAM!$B$8:$HC$215,MATCH($AL64,SAM!$A$8:$A$215,0),MATCH(AR$48,SAM!$B$7:$HC$7,0)),0) -> 3.5671099 | AS64: =_xlfn.IFNA(INDEX(SAM!$B$8:$HC$215,MATCH($AL64,SAM!$A$8:$A$215,0),MATCH(AS$48,SAM!$B$7:$HC$7,0)),0) -> 5.6256407 | AT64: =_xlfn.IFNA(INDEX(SAM!$B$8:$HC$215,MATCH($AL64,SAM!$A$8:$A$215,0),MATCH(AT$48,SAM!$B$7:$HC$7,0)),0) -> 7.4791135 | ... BA64: =_xlfn.IFNA(INDEX(SAM!$B$8:$HC$215,MATCH($AL64,SAM!$A$8:$A$215,0),MATCH(BA$48,SAM!$B$7:$HC$7,0)),0) -> 222.997 | BC64: ="a"&T64 -> afobe | BD64: =_xlfn.IFNA(INDEX(SAM!$B$8:$HC$215,MATCH($BC64,SAM!$A$8:$A$215,0),MATCH(BD$48,SAM!$B$7:$HC$7,0)),0) -> 2.9228081 | BE64: =_xlfn.IFNA(INDEX(SAM!$B$8:$HC$215,MATCH($BC64,SAM!$A$8:$A$215,0),MATCH(BE$48,SAM!$B$7:$HC$7,0)),0) -> 5.3369042 | BF64: =_xlfn.IFNA(INDEX(SAM!$B$8:$HC$215,MATCH($BC64,SAM!$A$8:$A$215,0),MATCH(BF$48,SAM!$B$7:$HC$7,0)),0) -> 13.591556 | BG64: =_xlfn.IFNA(INDEX(SAM!$B$8:$HC$215,MATCH($BC64,SAM!$A$8:$A$215,0),MATCH(BG$48,SAM!$B$7:$HC$7,0)),0) -> 34.682694 | BH64: =_xlfn.IFNA(INDEX(SAM!$B$8:$HC$215,MATCH($BC64,SAM!$A$8:$A$215,0),MATCH(BH$48,SAM!$B$7:$HC$7,0)),0) -> 32.962728 | BI64: =_xlfn.IFNA(INDEX(SAM!$B$8:$HC$215,MATCH($BC64,SAM!$A$8:$A$215,0),MATCH(BI$48,SAM!$B$7:$HC$7,0)),0) -> 0.50394281 | BJ64: =_xlfn.IFNA(INDEX(SAM!$B$8:$HC$215,MATCH($BC64,SAM!$A$8:$A$215,0),MATCH(BJ$48,SAM!$B$7:$HC$7,0)),0) -> 2.1598576 | BK64: =_xlfn.IFNA(INDEX(SAM!$B$8:$HC$215,MATCH($BC64,SAM!$A$8:$A$215,0),MATCH(BK$48,SAM!$B$7:$HC$7,0)),0) -> 4.3488146 | ... BR64: =_xlfn.IFNA(INDEX(SAM!$B$8:$HC$215,MATCH($BC64,SAM!$A$8:$A$215,0),MATCH(BR$48,SAM!$B$7:$HC$7,0)),0) -> 8.9134268 | BT64: =AL64 -> cfobe | BU64: =SUM(BD64:BR64,AM64:BA64) -> 644.77952 | BW64: cfoil | BX64: =100*VLOOKUP(BW64,$BT$49:$BU$94,2,FALSE)/$BU$95 -> 1.3492488
A65: =HLOOKUP(B65,$B$6:$BR$9,4,FALSE) -> clothing and textile | B65: text | C65: =IFERROR(100*U65/U$95,"") -> 4.473367 | D65: =IFERROR(100*V65/V$95,"") -> 5.089049 | E65: =IFERROR(100*W65/W$95,"") -> 5.4129345 | F65: =IFERROR(100*X65/X$95,"") -> 5.3812777 | G65: =IFERROR(100*Y65/Y$95,"") -> 5.5308897 | H65: =IFERROR(100*Z65/Z$95,"") -> 5.3625083 | I65: =IFERROR(100*AA65/AA$95,"") -> 5.335442 | J65: =IFERROR(100*AB65/AB$95,"") -> 5.4188607 | ... R65: =IFERROR(100*AJ65/AJ$95,"") -> 5.0952858 | T65: =B65 -> text | U65: =IFERROR(AM65+BD65,"") -> 13.152642 | V65: =IFERROR(AN65+BE65,"") -> 22.164772 | W65: =IFERROR(AO65+BF65,"") -> 32.3457 | X65: =IFERROR(AP65+BG65,"") -> 46.243384 | Y65: =IFERROR(AQ65+BH65,"") -> 52.622715 | Z65: =IFERROR(AR65+BI65,"") -> 3.0360187 | AA65: =IFERROR(AS65+BJ65,"") -> 4.5041249 | AB65: =IFERROR(AT65+BK65,"") -> 5.5424246 | ... AI65: =IFERROR(BA65+BR65,"") -> 142.80203 | AJ65: =SUM(U65:AI65) -> 359.60899 | AL65: ="c"&T65 -> ctext | AM65: =_xlfn.IFNA(INDEX(SAM!$B$8:$HC$215,MATCH($AL65,SAM!$A$8:$A$215,0),MATCH(AM$48,SAM!$B$7:$HC$7,0)),0) -> 13.152642 | AN65: =_xlfn.IFNA(INDEX(SAM!$B$8:$HC$215,MATCH($AL65,SAM!$A$8:$A$215,0),MATCH(AN$48,SAM!$B$7:$HC$7,0)),0) -> 22.164772 | AO65: =_xlfn.IFNA(INDEX(SAM!$B$8:$HC$215,MATCH($AL65,SAM!$A$8:$A$215,0),MATCH(AO$48,SAM!$B$7:$HC$7,0)),0) -> 32.3457 | AP65: =_xlfn.IFNA(INDEX(SAM!$B$8:$HC$215,MATCH($AL65,SAM!$A$8:$A$215,0),MATCH(AP$48,SAM!$B$7:$HC$7,0)),0) -> 46.243384 | AQ65: =_xlfn.IFNA(INDEX(SAM!$B$8:$HC$215,MATCH($AL65,SAM!$A$8:$A$215,0),MATCH(AQ$48,SAM!$B$7:$HC$7,0)),0) -> 52.622715 | AR65: =_xlfn.IFNA(INDEX(SAM!$B$8:$HC$215,MATCH($AL65,SAM!$A$8:$A$215,0),MATCH(AR$48,SAM!$B$7:$HC$7,0)),0) -> 3.0360187 | AS65: =_xlfn.IFNA(INDEX(SAM!$B$8:$HC$215,MATCH($AL65,SAM!$A$8:$A$215,0),MATCH(AS$48,SAM!$B$7:$HC$7,0)),0) -> 4.5041249 | AT65: =_xlfn.IFNA(INDEX(SAM!$B$8:$HC$215,MATCH($AL65,SAM!$A$8:$A$215,0),MATCH(AT$48,SAM!$B$7:$HC$7,0)),0) -> 5.5424246 | ... BA65: =_xlfn.IFNA(INDEX(SAM!$B$8:$HC$215,MATCH($AL65,SAM!$A$8:$A$215,0),MATCH(BA$48,SAM!$B$7:$HC$7,0)),0) -> 142.80203 | BC65: ="a"&T65 -> atext | BD65: =_xlfn.IFNA(INDEX(SAM!$B$8:$HC$215,MATCH($BC65,SAM!$A$8:$A$215,0),MATCH(BD$48,SAM!$B$7:$HC$7,0)),0) -> 0 | BE65: =_xlfn.IFNA(INDEX(SAM!$B$8:$HC$215,MATCH($BC65,SAM!$A$8:$A$215,0),MATCH(BE$48,SAM!$B$7:$HC$7,0)),0) -> 0 | BF65: =_xlfn.IFNA(INDEX(SAM!$B$8:$HC$215,MATCH($BC65,SAM!$A$8:$A$215,0),MATCH(BF$48,SAM!$B$7:$HC$7,0)),0) -> 0 | BG65: =_xlfn.IFNA(INDEX(SAM!$B$8:$HC$215,MATCH($BC65,SAM!$A$8:$A$215,0),MATCH(BG$48,SAM!$B$7:$HC$7,0)),0) -> 0 | BH65: =_xlfn.IFNA(INDEX(SAM!$B$8:$HC$215,MATCH($BC65,SAM!$A$8:$A$215,0),MATCH(BH$48,SAM!$B$7:$HC$7,0)),0) -> 0 | BI65: =_xlfn.IFNA(INDEX(SAM!$B$8:$HC$215,MATCH($BC65,SAM!$A$8:$A$215,0),MATCH(BI$48,SAM!$B$7:$HC$7,0)),0) -> 0 | BJ65: =_xlfn.IFNA(INDEX(SAM!$B$8:$HC$215,MATCH($BC65,SAM!$A$8:$A$215,0),MATCH(BJ$48,SAM!$B$7:$HC$7,0)),0) -> 0 | BK65: =_xlfn.IFNA(INDEX(SAM!$B$8:$HC$215,MATCH($BC65,SAM!$A$8:$A$215,0),MATCH(BK$48,SAM!$B$7:$HC$7,0)),0) -> 0 | ... BR65: =_xlfn.IFNA(INDEX(SAM!$B$8:$HC$215,MATCH($BC65,SAM!$A$8:$A$215,0),MATCH(BR$48,SAM!$B$7:$HC$7,0)),0) -> 0 | BT65: =AL65 -> ctext | BU65: =SUM(BD65:BR65,AM65:BA65) -> 359.60899 | BW65: cfveg | BX65: =100*VLOOKUP(BW65,$BT$49:$BU$94,2,FALSE)/$BU$95 -> 0.62432349
A66: =HLOOKUP(B66,$B$6:$BR$9,4,FALSE) -> utilities | B66: elec | C66: =IFERROR(100*U66/U$95,"") -> 0.026065204 | D66: =IFERROR(100*V66/V$95,"") -> 0.037367726 | E66: =IFERROR(100*W66/W$95,"") -> 0.067972254 | F66: =IFERROR(100*X66/X$95,"") -> 0.079013134 | G66: =IFERROR(100*Y66/Y$95,"") -> 0.12369797 | H66: =IFERROR(100*Z66/Z$95,"") -> 0.019312442 | I66: =IFERROR(100*AA66/AA$95,"") -> 0.050195532 | J66: =IFERROR(100*AB66/AB$95,"") -> 0.065701311 | ... R66: =IFERROR(100*AJ66/AJ$95,"") -> 0.1603004 | T66: =B66 -> elec | U66: =IFERROR(AM66+BD66,"") -> 0.076637194 | V66: =IFERROR(AN66+BE66,"") -> 0.16275087 | W66: =IFERROR(AO66+BF66,"") -> 0.40617712 | X66: =IFERROR(AP66+BG66,"") -> 0.67899017 | Y66: =IFERROR(AQ66+BH66,"") -> 1.1769034 | Z66: =IFERROR(AR66+BI66,"") -> 0.010933863 | AA66: =IFERROR(AS66+BJ66,"") -> 0.042374549 | AB66: =IFERROR(AT66+BK66,"") -> 0.067199469 | ... AI66: =IFERROR(BA66+BR66,"") -> 7.4017182 | AJ66: =SUM(U66:AI66) -> 11.31349 | AL66: ="c"&T66 -> celec | AM66: =_xlfn.IFNA(INDEX(SAM!$B$8:$HC$215,MATCH($AL66,SAM!$A$8:$A$215,0),MATCH(AM$48,SAM!$B$7:$HC$7,0)),0) -> 0.076637194 | AN66: =_xlfn.IFNA(INDEX(SAM!$B$8:$HC$215,MATCH($AL66,SAM!$A$8:$A$215,0),MATCH(AN$48,SAM!$B$7:$HC$7,0)),0) -> 0.16275087 | AO66: =_xlfn.IFNA(INDEX(SAM!$B$8:$HC$215,MATCH($AL66,SAM!$A$8:$A$215,0),MATCH(AO$48,SAM!$B$7:$HC$7,0)),0) -> 0.40617712 | AP66: =_xlfn.IFNA(INDEX(SAM!$B$8:$HC$215,MATCH($AL66,SAM!$A$8:$A$215,0),MATCH(AP$48,SAM!$B$7:$HC$7,0)),0) -> 0.67899017 | AQ66: =_xlfn.IFNA(INDEX(SAM!$B$8:$HC$215,MATCH($AL66,SAM!$A$8:$A$215,0),MATCH(AQ$48,SAM!$B$7:$HC$7,0)),0) -> 1.1769034 | AR66: =_xlfn.IFNA(INDEX(SAM!$B$8:$HC$215,MATCH($AL66,SAM!$A$8:$A$215,0),MATCH(AR$48,SAM!$B$7:$HC$7,0)),0) -> 0.010933863 | AS66: =_xlfn.IFNA(INDEX(SAM!$B$8:$HC$215,MATCH($AL66,SAM!$A$8:$A$215,0),MATCH(AS$48,SAM!$B$7:$HC$7,0)),0) -> 0.042374549 | AT66: =_xlfn.IFNA(INDEX(SAM!$B$8:$HC$215,MATCH($AL66,SAM!$A$8:$A$215,0),MATCH(AT$48,SAM!$B$7:$HC$7,0)),0) -> 0.067199469 | ... BA66: =_xlfn.IFNA(INDEX(SAM!$B$8:$HC$215,MATCH($AL66,SAM!$A$8:$A$215,0),MATCH(BA$48,SAM!$B$7:$HC$7,0)),0) -> 7.4017182 | BC66: ="a"&T66 -> aelec | BD66: =_xlfn.IFNA(INDEX(SAM!$B$8:$HC$215,MATCH($BC66,SAM!$A$8:$A$215,0),MATCH(BD$48,SAM!$B$7:$HC$7,0)),0) -> 0 | BE66: =_xlfn.IFNA(INDEX(SAM!$B$8:$HC$215,MATCH($BC66,SAM!$A$8:$A$215,0),MATCH(BE$48,SAM!$B$7:$HC$7,0)),0) -> 0 | BF66: =_xlfn.IFNA(INDEX(SAM!$B$8:$HC$215,MATCH($BC66,SAM!$A$8:$A$215,0),MATCH(BF$48,SAM!$B$7:$HC$7,0)),0) -> 0 | BG66: =_xlfn.IFNA(INDEX(SAM!$B$8:$HC$215,MATCH($BC66,SAM!$A$8:$A$215,0),MATCH(BG$48,SAM!$B$7:$HC$7,0)),0) -> 0 | BH66: =_xlfn.IFNA(INDEX(SAM!$B$8:$HC$215,MATCH($BC66,SAM!$A$8:$A$215,0),MATCH(BH$48,SAM!$B$7:$HC$7,0)),0) -> 0 | BI66: =_xlfn.IFNA(INDEX(SAM!$B$8:$HC$215,MATCH($BC66,SAM!$A$8:$A$215,0),MATCH(BI$48,SAM!$B$7:$HC$7,0)),0) -> 0 | BJ66: =_xlfn.IFNA(INDEX(SAM!$B$8:$HC$215,MATCH($BC66,SAM!$A$8:$A$215,0),MATCH(BJ$48,SAM!$B$7:$HC$7,0)),0) -> 0 | BK66: =_xlfn.IFNA(INDEX(SAM!$B$8:$HC$215,MATCH($BC66,SAM!$A$8:$A$215,0),MATCH(BK$48,SAM!$B$7:$HC$7,0)),0) -> 0 | ... BR66: =_xlfn.IFNA(INDEX(SAM!$B$8:$HC$215,MATCH($BC66,SAM!$A$8:$A$215,0),MATCH(BR$48,SAM!$B$7:$HC$7,0)),0) -> 0 | BT66: =AL66 -> celec | BU66: =SUM(BD66:BR66,AM66:BA66) -> 11.31349 | BW66: cmeat | BX66: =100*VLOOKUP(BW66,$BT$49:$BU$94,2,FALSE)/$BU$95 -> 1.2809086
A67: =HLOOKUP(B67,$B$6:$BR$9,4,FALSE) -> utilities | B67: watr | C67: =IFERROR(100*U67/U$95,"") -> 0.086632003 | D67: =IFERROR(100*V67/V$95,"") -> 0.11327284 | E67: =IFERROR(100*W67/W$95,"") -> 0.12213604 | F67: =IFERROR(100*X67/X$95,"") -> 0.15217319 | G67: =IFERROR(100*Y67/Y$95,"") -> 0.24796448 | H67: =IFERROR(100*Z67/Z$95,"") -> 0.080140875 | I67: =IFERROR(100*AA67/AA$95,"") -> 0.11826097 | J67: =IFERROR(100*AB67/AB$95,"") -> 0.13019377 | ... R67: =IFERROR(100*AJ67/AJ$95,"") -> 0.27385178 | T67: =B67 -> watr | U67: =IFERROR(AM67+BD67,"") -> 0.25471635 | V67: =IFERROR(AN67+BE67,"") -> 0.49334694 | W67: =IFERROR(AO67+BF67,"") -> 0.72983992 | X67: =IFERROR(AP67+BG67,"") -> 1.3076826 | Y67: =IFERROR(AQ67+BH67,"") -> 2.3592161 | Z67: =IFERROR(AR67+BI67,"") -> 0.045372274 | AA67: =IFERROR(AS67+BJ67,"") -> 0.099834689 | AB67: =IFERROR(AT67+BK67,"") -> 0.13316252 | ... AI67: =IFERROR(BA67+BR67,"") -> 11.214533 | AJ67: =SUM(U67:AI67) -> 19.327584 | AL67: ="c"&T67 -> cwatr | AM67: =_xlfn.IFNA(INDEX(SAM!$B$8:$HC$215,MATCH($AL67,SAM!$A$8:$A$215,0),MATCH(AM$48,SAM!$B$7:$HC$7,0)),0) -> 0.25471635 | AN67: =_xlfn.IFNA(INDEX(SAM!$B$8:$HC$215,MATCH($AL67,SAM!$A$8:$A$215,0),MATCH(AN$48,SAM!$B$7:$HC$7,0)),0) -> 0.49334694 | AO67: =_xlfn.IFNA(INDEX(SAM!$B$8:$HC$215,MATCH($AL67,SAM!$A$8:$A$215,0),MATCH(AO$48,SAM!$B$7:$HC$7,0)),0) -> 0.72983992 | AP67: =_xlfn.IFNA(INDEX(SAM!$B$8:$HC$215,MATCH($AL67,SAM!$A$8:$A$215,0),MATCH(AP$48,SAM!$B$7:$HC$7,0)),0) -> 1.3076826 | AQ67: =_xlfn.IFNA(INDEX(SAM!$B$8:$HC$215,MATCH($AL67,SAM!$A$8:$A$215,0),MATCH(AQ$48,SAM!$B$7:$HC$7,0)),0) -> 2.3592161 | AR67: =_xlfn.IFNA(INDEX(SAM!$B$8:$HC$215,MATCH($AL67,SAM!$A$8:$A$215,0),MATCH(AR$48,SAM!$B$7:$HC$7,0)),0) -> 0.045372274 | AS67: =_xlfn.IFNA(INDEX(SAM!$B$8:$HC$215,MATCH($AL67,SAM!$A$8:$A$215,0),MATCH(AS$48,SAM!$B$7:$HC$7,0)),0) -> 0.099834689 | AT67: =_xlfn.IFNA(INDEX(SAM!$B$8:$HC$215,MATCH($AL67,SAM!$A$8:$A$215,0),MATCH(AT$48,SAM!$B$7:$HC$7,0)),0) -> 0.13316252 | ... BA67: =_xlfn.IFNA(INDEX(SAM!$B$8:$HC$215,MATCH($AL67,SAM!$A$8:$A$215,0),MATCH(BA$48,SAM!$B$7:$HC$7,0)),0) -> 11.214533 | BC67: ="a"&T67 -> awatr | BD67: =_xlfn.IFNA(INDEX(SAM!$B$8:$HC$215,MATCH($BC67,SAM!$A$8:$A$215,0),MATCH(BD$48,SAM!$B$7:$HC$7,0)),0) -> 0 | BE67: =_xlfn.IFNA(INDEX(SAM!$B$8:$HC$215,MATCH($BC67,SAM!$A$8:$A$215,0),MATCH(BE$48,SAM!$B$7:$HC$7,0)),0) -> 0 | BF67: =_xlfn.IFNA(INDEX(SAM!$B$8:$HC$215,MATCH($BC67,SAM!$A$8:$A$215,0),MATCH(BF$48,SAM!$B$7:$HC$7,0)),0) -> 0 | BG67: =_xlfn.IFNA(INDEX(SAM!$B$8:$HC$215,MATCH($BC67,SAM!$A$8:$A$215,0),MATCH(BG$48,SAM!$B$7:$HC$7,0)),0) -> 0 | BH67: =_xlfn.IFNA(INDEX(SAM!$B$8:$HC$215,MATCH($BC67,SAM!$A$8:$A$215,0),MATCH(BH$48,SAM!$B$7:$HC$7,0)),0) -> 0 | BI67: =_xlfn.IFNA(INDEX(SAM!$B$8:$HC$215,MATCH($BC67,SAM!$A$8:$A$215,0),MATCH(BI$48,SAM!$B$7:$HC$7,0)),0) -> 0 | BJ67: =_xlfn.IFNA(INDEX(SAM!$B$8:$HC$215,MATCH($BC67,SAM!$A$8:$A$215,0),MATCH(BJ$48,SAM!$B$7:$HC$7,0)),0) -> 0 | BK67: =_xlfn.IFNA(INDEX(SAM!$B$8:$HC$215,MATCH($BC67,SAM!$A$8:$A$215,0),MATCH(BK$48,SAM!$B$7:$HC$7,0)),0) -> 0 | ... BR67: =_xlfn.IFNA(INDEX(SAM!$B$8:$HC$215,MATCH($BC67,SAM!$A$8:$A$215,0),MATCH(BR$48,SAM!$B$7:$HC$7,0)),0) -> 0 | BT67: =AL67 -> cwatr | BU67: =SUM(BD67:BR67,AM67:BA67) -> 19.327584 | BW67: cfsea | BX67: =100*VLOOKUP(BW67,$BT$49:$BU$94,2,FALSE)/$BU$95 -> 0.27459354
A68: =HLOOKUP(B68,$B$6:$BR$9,4,FALSE) -> housing | B68: real | C68: =IFERROR(100*U68/U$95,"") -> 4.170447 | D68: =IFERROR(100*V68/V$95,"") -> 3.6597626 | E68: =IFERROR(100*W68/W$95,"") -> 3.489705 | F68: =IFERROR(100*X68/X$95,"") -> 3.6094547 | G68: =IFERROR(100*Y68/Y$95,"") -> 3.972662 | H68: =IFERROR(100*Z68/Z$95,"") -> 4.4520305 | I68: =IFERROR(100*AA68/AA$95,"") -> 3.9852434 | J68: =IFERROR(100*AB68/AB$95,"") -> 3.8932434 | ... R68: =IFERROR(100*AJ68/AJ$95,"") -> 6.866139 | T68: =B68 -> real | U68: =IFERROR(AM68+BD68,"") -> 12.261993 | V68: =IFERROR(AN68+BE68,"") -> 15.939678 | W68: =IFERROR(AO68+BF68,"") -> 20.85319 | X68: =IFERROR(AP68+BG68,"") -> 31.017429 | Y68: =IFERROR(AQ68+BH68,"") -> 37.797221 | Z68: =IFERROR(AR68+BI68,"") -> 2.5205458 | AA68: =IFERROR(AS68+BJ68,"") -> 3.3643012 | AB68: =IFERROR(AT68+BK68,"") -> 3.9820193 | ... AI68: =IFERROR(BA68+BR68,"") -> 306.5875 | AJ68: =SUM(U68:AI68) -> 484.59015 | AL68: ="c"&T68 -> creal | AM68: =_xlfn.IFNA(INDEX(SAM!$B$8:$HC$215,MATCH($AL68,SAM!$A$8:$A$215,0),MATCH(AM$48,SAM!$B$7:$HC$7,0)),0) -> 12.261993 | AN68: =_xlfn.IFNA(INDEX(SAM!$B$8:$HC$215,MATCH($AL68,SAM!$A$8:$A$215,0),MATCH(AN$48,SAM!$B$7:$HC$7,0)),0) -> 15.939678 | AO68: =_xlfn.IFNA(INDEX(SAM!$B$8:$HC$215,MATCH($AL68,SAM!$A$8:$A$215,0),MATCH(AO$48,SAM!$B$7:$HC$7,0)),0) -> 20.85319 | AP68: =_xlfn.IFNA(INDEX(SAM!$B$8:$HC$215,MATCH($AL68,SAM!$A$8:$A$215,0),MATCH(AP$48,SAM!$B$7:$HC$7,0)),0) -> 31.017429 | AQ68: =_xlfn.IFNA(INDEX(SAM!$B$8:$HC$215,MATCH($AL68,SAM!$A$8:$A$215,0),MATCH(AQ$48,SAM!$B$7:$HC$7,0)),0) -> 37.797221 | AR68: =_xlfn.IFNA(INDEX(SAM!$B$8:$HC$215,MATCH($AL68,SAM!$A$8:$A$215,0),MATCH(AR$48,SAM!$B$7:$HC$7,0)),0) -> 2.5205458 | AS68: =_xlfn.IFNA(INDEX(SAM!$B$8:$HC$215,MATCH($AL68,SAM!$A$8:$A$215,0),MATCH(AS$48,SAM!$B$7:$HC$7,0)),0) -> 3.3643012 | AT68: =_xlfn.IFNA(INDEX(SAM!$B$8:$HC$215,MATCH($AL68,SAM!$A$8:$A$215,0),MATCH(AT$48,SAM!$B$7:$HC$7,0)),0) -> 3.9820193 | ... BA68: =_xlfn.IFNA(INDEX(SAM!$B$8:$HC$215,MATCH($AL68,SAM!$A$8:$A$215,0),MATCH(BA$48,SAM!$B$7:$HC$7,0)),0) -> 306.5875 | BC68: ="a"&T68 -> areal | BD68: =_xlfn.IFNA(INDEX(SAM!$B$8:$HC$215,MATCH($BC68,SAM!$A$8:$A$215,0),MATCH(BD$48,SAM!$B$7:$HC$7,0)),0) -> 0 | BE68: =_xlfn.IFNA(INDEX(SAM!$B$8:$HC$215,MATCH($BC68,SAM!$A$8:$A$215,0),MATCH(BE$48,SAM!$B$7:$HC$7,0)),0) -> 0 | BF68: =_xlfn.IFNA(INDEX(SAM!$B$8:$HC$215,MATCH($BC68,SAM!$A$8:$A$215,0),MATCH(BF$48,SAM!$B$7:$HC$7,0)),0) -> 0 | BG68: =_xlfn.IFNA(INDEX(SAM!$B$8:$HC$215,MATCH($BC68,SAM!$A$8:$A$215,0),MATCH(BG$48,SAM!$B$7:$HC$7,0)),0) -> 0 | BH68: =_xlfn.IFNA(INDEX(SAM!$B$8:$HC$215,MATCH($BC68,SAM!$A$8:$A$215,0),MATCH(BH$48,SAM!$B$7:$HC$7,0)),0) -> 0 | BI68: =_xlfn.IFNA(INDEX(SAM!$B$8:$HC$215,MATCH($BC68,SAM!$A$8:$A$215,0),MATCH(BI$48,SAM!$B$7:$HC$7,0)),0) -> 0 | BJ68: =_xlfn.IFNA(INDEX(SAM!$B$8:$HC$215,MATCH($BC68,SAM!$A$8:$A$215,0),MATCH(BJ$48,SAM!$B$7:$HC$7,0)),0) -> 0 | BK68: =_xlfn.IFNA(INDEX(SAM!$B$8:$HC$215,MATCH($BC68,SAM!$A$8:$A$215,0),MATCH(BK$48,SAM!$B$7:$HC$7,0)),0) -> 0 | ... BR68: =_xlfn.IFNA(INDEX(SAM!$B$8:$HC$215,MATCH($BC68,SAM!$A$8:$A$215,0),MATCH(BR$48,SAM!$B$7:$HC$7,0)),0) -> 0 | BT68: =AL68 -> creal | BU68: =SUM(BD68:BR68,AM68:BA68) -> 484.59015 | BW68: cdair | BX68: =100*VLOOKUP(BW68,$BT$49:$BU$94,2,FALSE)/$BU$95 -> 0.52229303
A69: =HLOOKUP(B69,$B$6:$BR$9,4,FALSE) -> education, health and public | B69: educ | C69: =IFERROR(100*U69/U$95,"") -> 0.85330453 | D69: =IFERROR(100*V69/V$95,"") -> 1.0228269 | E69: =IFERROR(100*W69/W$95,"") -> 1.3059938 | F69: =IFERROR(100*X69/X$95,"") -> 1.7454552 | G69: =IFERROR(100*Y69/Y$95,"") -> 2.5633322 | H69: =IFERROR(100*Z69/Z$95,"") -> 0.74295563 | I69: =IFERROR(100*AA69/AA$95,"") -> 0.8617614 | J69: =IFERROR(100*AB69/AB$95,"") -> 1.0159861 | ... R69: =IFERROR(100*AJ69/AJ$95,"") -> 2.434164 | T69: =B69 -> educ | U69: =IFERROR(AM69+BD69,"") -> 2.5088952 | V69: =IFERROR(AN69+BE69,"") -> 4.454806 | W69: =IFERROR(AO69+BF69,"") -> 7.8041372 | X69: =IFERROR(AP69+BG69,"") -> 14.999366 | Y69: =IFERROR(AQ69+BH69,"") -> 24.388391 | Z69: =IFERROR(AR69+BI69,"") -> 0.42062913 | AA69: =IFERROR(AS69+BJ69,"") -> 0.72749006 | AB69: =IFERROR(AT69+BK69,"") -> 1.0391532 | ... AI69: =IFERROR(BA69+BR69,"") -> 101.56259 | AJ69: =SUM(U69:AI69) -> 171.79552 | AL69: ="c"&T69 -> ceduc | AM69: =_xlfn.IFNA(INDEX(SAM!$B$8:$HC$215,MATCH($AL69,SAM!$A$8:$A$215,0),MATCH(AM$48,SAM!$B$7:$HC$7,0)),0) -> 2.5088952 | AN69: =_xlfn.IFNA(INDEX(SAM!$B$8:$HC$215,MATCH($AL69,SAM!$A$8:$A$215,0),MATCH(AN$48,SAM!$B$7:$HC$7,0)),0) -> 4.454806 | AO69: =_xlfn.IFNA(INDEX(SAM!$B$8:$HC$215,MATCH($AL69,SAM!$A$8:$A$215,0),MATCH(AO$48,SAM!$B$7:$HC$7,0)),0) -> 7.8041372 | AP69: =_xlfn.IFNA(INDEX(SAM!$B$8:$HC$215,MATCH($AL69,SAM!$A$8:$A$215,0),MATCH(AP$48,SAM!$B$7:$HC$7,0)),0) -> 14.999366 | AQ69: =_xlfn.IFNA(INDEX(SAM!$B$8:$HC$215,MATCH($AL69,SAM!$A$8:$A$215,0),MATCH(AQ$48,SAM!$B$7:$HC$7,0)),0) -> 24.388391 | AR69: =_xlfn.IFNA(INDEX(SAM!$B$8:$HC$215,MATCH($AL69,SAM!$A$8:$A$215,0),MATCH(AR$48,SAM!$B$7:$HC$7,0)),0) -> 0.42062913 | AS69: =_xlfn.IFNA(INDEX(SAM!$B$8:$HC$215,MATCH($AL69,SAM!$A$8:$A$215,0),MATCH(AS$48,SAM!$B$7:$HC$7,0)),0) -> 0.72749006 | AT69: =_xlfn.IFNA(INDEX(SAM!$B$8:$HC$215,MATCH($AL69,SAM!$A$8:$A$215,0),MATCH(AT$48,SAM!$B$7:$HC$7,0)),0) -> 1.0391532 | ... BA69: =_xlfn.IFNA(INDEX(SAM!$B$8:$HC$215,MATCH($AL69,SAM!$A$8:$A$215,0),MATCH(BA$48,SAM!$B$7:$HC$7,0)),0) -> 101.56259 | BC69: ="a"&T69 -> aeduc | BD69: =_xlfn.IFNA(INDEX(SAM!$B$8:$HC$215,MATCH($BC69,SAM!$A$8:$A$215,0),MATCH(BD$48,SAM!$B$7:$HC$7,0)),0) -> 0 | BE69: =_xlfn.IFNA(INDEX(SAM!$B$8:$HC$215,MATCH($BC69,SAM!$A$8:$A$215,0),MATCH(BE$48,SAM!$B$7:$HC$7,0)),0) -> 0 | BF69: =_xlfn.IFNA(INDEX(SAM!$B$8:$HC$215,MATCH($BC69,SAM!$A$8:$A$215,0),MATCH(BF$48,SAM!$B$7:$HC$7,0)),0) -> 0 | BG69: =_xlfn.IFNA(INDEX(SAM!$B$8:$HC$215,MATCH($BC69,SAM!$A$8:$A$215,0),MATCH(BG$48,SAM!$B$7:$HC$7,0)),0) -> 0 | BH69: =_xlfn.IFNA(INDEX(SAM!$B$8:$HC$215,MATCH($BC69,SAM!$A$8:$A$215,0),MATCH(BH$48,SAM!$B$7:$HC$7,0)),0) -> 0 | BI69: =_xlfn.IFNA(INDEX(SAM!$B$8:$HC$215,MATCH($BC69,SAM!$A$8:$A$215,0),MATCH(BI$48,SAM!$B$7:$HC$7,0)),0) -> 0 | BJ69: =_xlfn.IFNA(INDEX(SAM!$B$8:$HC$215,MATCH($BC69,SAM!$A$8:$A$215,0),MATCH(BJ$48,SAM!$B$7:$HC$7,0)),0) -> 0 | BK69: =_xlfn.IFNA(INDEX(SAM!$B$8:$HC$215,MATCH($BC69,SAM!$A$8:$A$215,0),MATCH(BK$48,SAM!$B$7:$HC$7,0)),0) -> 0 | ... BR69: =_xlfn.IFNA(INDEX(SAM!$B$8:$HC$215,MATCH($BC69,SAM!$A$8:$A$215,0),MATCH(BR$48,SAM!$B$7:$HC$7,0)),0) -> 0 | BT69: =AL69 -> ceduc | BU69: =SUM(BD69:BR69,AM69:BA69) -> 171.79552 | BW69: cfobe | BX69: =100*VLOOKUP(BW69,$BT$49:$BU$94,2,FALSE)/$BU$95 -> 9.1358558
A70: =HLOOKUP(B70,$B$6:$BR$9,4,FALSE) -> education, health and public | B70: heal | C70: =IFERROR(100*U70/U$95,"") -> 2.0100956 | D70: =IFERROR(100*V70/V$95,"") -> 1.6105038 | E70: =IFERROR(100*W70/W$95,"") -> 1.3078569 | F70: =IFERROR(100*X70/X$95,"") -> 1.0519537 | G70: =IFERROR(100*Y70/Y$95,"") -> 1.3640325 | H70: =IFERROR(100*Z70/Z$95,"") -> 1.860604 | I70: =IFERROR(100*AA70/AA$95,"") -> 1.5522183 | J70: =IFERROR(100*AB70/AB$95,"") -> 1.468582 | ... R70: =IFERROR(100*AJ70/AJ$95,"") -> 1.3031373 | T70: =B70 -> heal | U70: =IFERROR(AM70+BD70,"") -> 5.9101048 | V70: =IFERROR(AN70+BE70,"") -> 7.0143657 | W70: =IFERROR(AO70+BF70,"") -> 7.8152701 | X70: =IFERROR(AP70+BG70,"") -> 9.0398419 | Y70: =IFERROR(AQ70+BH70,"") -> 12.977856 | Z70: =IFERROR(AR70+BI70,"") -> 1.053393 | AA70: =IFERROR(AS70+BJ70,"") -> 1.3103666 | AB70: =IFERROR(AT70+BK70,"") -> 1.5020694 | ... AI70: =IFERROR(BA70+BR70,"") -> 34.551928 | AJ70: =SUM(U70:AI70) -> 91.97127 | AL70: ="c"&T70 -> cheal | AM70: =_xlfn.IFNA(INDEX(SAM!$B$8:$HC$215,MATCH($AL70,SAM!$A$8:$A$215,0),MATCH(AM$48,SAM!$B$7:$HC$7,0)),0) -> 5.9101048 | AN70: =_xlfn.IFNA(INDEX(SAM!$B$8:$HC$215,MATCH($AL70,SAM!$A$8:$A$215,0),MATCH(AN$48,SAM!$B$7:$HC$7,0)),0) -> 7.0143657 | AO70: =_xlfn.IFNA(INDEX(SAM!$B$8:$HC$215,MATCH($AL70,SAM!$A$8:$A$215,0),MATCH(AO$48,SAM!$B$7:$HC$7,0)),0) -> 7.8152701 | AP70: =_xlfn.IFNA(INDEX(SAM!$B$8:$HC$215,MATCH($AL70,SAM!$A$8:$A$215,0),MATCH(AP$48,SAM!$B$7:$HC$7,0)),0) -> 9.0398419 | AQ70: =_xlfn.IFNA(INDEX(SAM!$B$8:$HC$215,MATCH($AL70,SAM!$A$8:$A$215,0),MATCH(AQ$48,SAM!$B$7:$HC$7,0)),0) -> 12.977856 | AR70: =_xlfn.IFNA(INDEX(SAM!$B$8:$HC$215,MATCH($AL70,SAM!$A$8:$A$215,0),MATCH(AR$48,SAM!$B$7:$HC$7,0)),0) -> 1.053393 | AS70: =_xlfn.IFNA(INDEX(SAM!$B$8:$HC$215,MATCH($AL70,SAM!$A$8:$A$215,0),MATCH(AS$48,SAM!$B$7:$HC$7,0)),0) -> 1.3103666 | AT70: =_xlfn.IFNA(INDEX(SAM!$B$8:$HC$215,MATCH($AL70,SAM!$A$8:$A$215,0),MATCH(AT$48,SAM!$B$7:$HC$7,0)),0) -> 1.5020694 | ... BA70: =_xlfn.IFNA(INDEX(SAM!$B$8:$HC$215,MATCH($AL70,SAM!$A$8:$A$215,0),MATCH(BA$48,SAM!$B$7:$HC$7,0)),0) -> 34.551928 | BC70: ="a"&T70 -> aheal | BD70: =_xlfn.IFNA(INDEX(SAM!$B$8:$HC$215,MATCH($BC70,SAM!$A$8:$A$215,0),MATCH(BD$48,SAM!$B$7:$HC$7,0)),0) -> 0 | BE70: =_xlfn.IFNA(INDEX(SAM!$B$8:$HC$215,MATCH($BC70,SAM!$A$8:$A$215,0),MATCH(BE$48,SAM!$B$7:$HC$7,0)),0) -> 0 | BF70: =_xlfn.IFNA(INDEX(SAM!$B$8:$HC$215,MATCH($BC70,SAM!$A$8:$A$215,0),MATCH(BF$48,SAM!$B$7:$HC$7,0)),0) -> 0 | BG70: =_xlfn.IFNA(INDEX(SAM!$B$8:$HC$215,MATCH($BC70,SAM!$A$8:$A$215,0),MATCH(BG$48,SAM!$B$7:$HC$7,0)),0) -> 0 | BH70: =_xlfn.IFNA(INDEX(SAM!$B$8:$HC$215,MATCH($BC70,SAM!$A$8:$A$215,0),MATCH(BH$48,SAM!$B$7:$HC$7,0)),0) -> 0 | BI70: =_xlfn.IFNA(INDEX(SAM!$B$8:$HC$215,MATCH($BC70,SAM!$A$8:$A$215,0),MATCH(BI$48,SAM!$B$7:$HC$7,0)),0) -> 0 | BJ70: =_xlfn.IFNA(INDEX(SAM!$B$8:$HC$215,MATCH($BC70,SAM!$A$8:$A$215,0),MATCH(BJ$48,SAM!$B$7:$HC$7,0)),0) -> 0 | BK70: =_xlfn.IFNA(INDEX(SAM!$B$8:$HC$215,MATCH($BC70,SAM!$A$8:$A$215,0),MATCH(BK$48,SAM!$B$7:$HC$7,0)),0) -> 0 | ... BR70: =_xlfn.IFNA(INDEX(SAM!$B$8:$HC$215,MATCH($BC70,SAM!$A$8:$A$215,0),MATCH(BR$48,SAM!$B$7:$HC$7,0)),0) -> 0 | BT70: =AL70 -> cheal | BU70: =SUM(BD70:BR70,AM70:BA70) -> 91.97127 | BW70: coapr | BX70: =100*VLOOKUP(BW70,$BT$49:$BU$94,2,FALSE)/$BU$95 -> 0.31206777
A71: =HLOOKUP(B71,$B$6:$BR$9,4,FALSE) -> education, health and public | B71: padm | C71: =IFERROR(100*U71/U$95,"") -> 0.44004912 | D71: =IFERROR(100*V71/V$95,"") -> 0.35263282 | E71: =IFERROR(100*W71/W$95,"") -> 0.52142142 | F71: =IFERROR(100*X71/X$95,"") -> 0.49348803 | G71: =IFERROR(100*Y71/Y$95,"") -> 0.69466015 | H71: =IFERROR(100*Z71/Z$95,"") -> 0.4188253 | I71: =IFERROR(100*AA71/AA$95,"") -> 0.5287631 | J71: =IFERROR(100*AB71/AB$95,"") -> 0.55118517 | ... R71: =IFERROR(100*AJ71/AJ$95,"") -> 0.74950731 | T71: =B71 -> padm | U71: =IFERROR(AM71+BD71,"") -> 1.2938372 | V71: =IFERROR(AN71+BE71,"") -> 1.535852 | W71: =IFERROR(AO71+BF71,"") -> 3.115822 | X71: =IFERROR(AP71+BG71,"") -> 4.2407319 | Y71: =IFERROR(AQ71+BH71,"") -> 6.6092265 | Z71: =IFERROR(AR71+BI71,"") -> 0.23712065 | AA71: =IFERROR(AS71+BJ71,"") -> 0.44637634 | AB71: =IFERROR(AT71+BK71,"") -> 0.5637536 | ... AI71: =IFERROR(BA71+BR71,"") -> 30.634602 | AJ71: =SUM(U71:AI71) -> 52.897832 | AL71: ="c"&T71 -> cpadm | AM71: =_xlfn.IFNA(INDEX(SAM!$B$8:$HC$215,MATCH($AL71,SAM!$A$8:$A$215,0),MATCH(AM$48,SAM!$B$7:$HC$7,0)),0) -> 1.2938372 | AN71: =_xlfn.IFNA(INDEX(SAM!$B$8:$HC$215,MATCH($AL71,SAM!$A$8:$A$215,0),MATCH(AN$48,SAM!$B$7:$HC$7,0)),0) -> 1.535852 | AO71: =_xlfn.IFNA(INDEX(SAM!$B$8:$HC$215,MATCH($AL71,SAM!$A$8:$A$215,0),MATCH(AO$48,SAM!$B$7:$HC$7,0)),0) -> 3.115822 | AP71: =_xlfn.IFNA(INDEX(SAM!$B$8:$HC$215,MATCH($AL71,SAM!$A$8:$A$215,0),MATCH(AP$48,SAM!$B$7:$HC$7,0)),0) -> 4.2407319 | AQ71: =_xlfn.IFNA(INDEX(SAM!$B$8:$HC$215,MATCH($AL71,SAM!$A$8:$A$215,0),MATCH(AQ$48,SAM!$B$7:$HC$7,0)),0) -> 6.6092265 | AR71: =_xlfn.IFNA(INDEX(SAM!$B$8:$HC$215,MATCH($AL71,SAM!$A$8:$A$215,0),MATCH(AR$48,SAM!$B$7:$HC$7,0)),0) -> 0.23712065 | AS71: =_xlfn.IFNA(INDEX(SAM!$B$8:$HC$215,MATCH($AL71,SAM!$A$8:$A$215,0),MATCH(AS$48,SAM!$B$7:$HC$7,0)),0) -> 0.44637634 | AT71: =_xlfn.IFNA(INDEX(SAM!$B$8:$HC$215,MATCH($AL71,SAM!$A$8:$A$215,0),MATCH(AT$48,SAM!$B$7:$HC$7,0)),0) -> 0.5637536 | ... BA71: =_xlfn.IFNA(INDEX(SAM!$B$8:$HC$215,MATCH($AL71,SAM!$A$8:$A$215,0),MATCH(BA$48,SAM!$B$7:$HC$7,0)),0) -> 30.634602 | BC71: ="a"&T71 -> apadm | BD71: =_xlfn.IFNA(INDEX(SAM!$B$8:$HC$215,MATCH($BC71,SAM!$A$8:$A$215,0),MATCH(BD$48,SAM!$B$7:$HC$7,0)),0) -> 0 | BE71: =_xlfn.IFNA(INDEX(SAM!$B$8:$HC$215,MATCH($BC71,SAM!$A$8:$A$215,0),MATCH(BE$48,SAM!$B$7:$HC$7,0)),0) -> 0 | BF71: =_xlfn.IFNA(INDEX(SAM!$B$8:$HC$215,MATCH($BC71,SAM!$A$8:$A$215,0),MATCH(BF$48,SAM!$B$7:$HC$7,0)),0) -> 0 | BG71: =_xlfn.IFNA(INDEX(SAM!$B$8:$HC$215,MATCH($BC71,SAM!$A$8:$A$215,0),MATCH(BG$48,SAM!$B$7:$HC$7,0)),0) -> 0 | BH71: =_xlfn.IFNA(INDEX(SAM!$B$8:$HC$215,MATCH($BC71,SAM!$A$8:$A$215,0),MATCH(BH$48,SAM!$B$7:$HC$7,0)),0) -> 0 | BI71: =_xlfn.IFNA(INDEX(SAM!$B$8:$HC$215,MATCH($BC71,SAM!$A$8:$A$215,0),MATCH(BI$48,SAM!$B$7:$HC$7,0)),0) -> 0 | BJ71: =_xlfn.IFNA(INDEX(SAM!$B$8:$HC$215,MATCH($BC71,SAM!$A$8:$A$215,0),MATCH(BJ$48,SAM!$B$7:$HC$7,0)),0) -> 0 | BK71: =_xlfn.IFNA(INDEX(SAM!$B$8:$HC$215,MATCH($BC71,SAM!$A$8:$A$215,0),MATCH(BK$48,SAM!$B$7:$HC$7,0)),0) -> 0 | ... BR71: =_xlfn.IFNA(INDEX(SAM!$B$8:$HC$215,MATCH($BC71,SAM!$A$8:$A$215,0),MATCH(BR$48,SAM!$B$7:$HC$7,0)),0) -> 0 | BT71: =AL71 -> cpadm | BU71: =SUM(BD71:BR71,AM71:BA71) -> 52.897832 | BW71: ctext | BX71: =100*VLOOKUP(BW71,$BT$49:$BU$94,2,FALSE)/$BU$95 -> 5.0952858
A72: =HLOOKUP(B72,$B$6:$BR$9,4,FALSE) -> other ag | B72: ocrp | C72: =IFERROR(100*U72/U$95,"") -> 0.027461521 | D72: =IFERROR(100*V72/V$95,"") -> 0.024350786 | E72: =IFERROR(100*W72/W$95,"") -> 0.019823215 | F72: =IFERROR(100*X72/X$95,"") -> 0.017761066 | G72: =IFERROR(100*Y72/Y$95,"") -> 0.022708461 | H72: =IFERROR(100*Z72/Z$95,"") -> 0.036952829 | I72: =IFERROR(100*AA72/AA$95,"") -> 0.036513826 | J72: =IFERROR(100*AB72/AB$95,"") -> 0.02033712 | ... R72: =IFERROR(100*AJ72/AJ$95,"") -> 0.044475774 | T72: =B72 -> ocrp | U72: =IFERROR(AM72+BD72,"") -> 0.080742663 | V72: =IFERROR(AN72+BE72,"") -> 0.10605707 | W72: =IFERROR(AO72+BF72,"") -> 0.11845622 | X72: =IFERROR(AP72+BG72,"") -> 0.15262765 | Y72: =IFERROR(AQ72+BH72,"") -> 0.21605582 | Z72: =IFERROR(AR72+BI72,"") -> 0.020921082 | AA72: =IFERROR(AS72+BJ72,"") -> 0.030824594 | AB72: =IFERROR(AT72+BK72,"") -> 0.020800858 | ... AI72: =IFERROR(BA72+BR72,"") -> 2.1956114 | AJ72: =SUM(U72:AI72) -> 3.138958 | AL72: ="c"&T72 -> cocrp | AM72: =_xlfn.IFNA(INDEX(SAM!$B$8:$HC$215,MATCH($AL72,SAM!$A$8:$A$215,0),MATCH(AM$48,SAM!$B$7:$HC$7,0)),0) -> 0.077551063 | AN72: =_xlfn.IFNA(INDEX(SAM!$B$8:$HC$215,MATCH($AL72,SAM!$A$8:$A$215,0),MATCH(AN$48,SAM!$B$7:$HC$7,0)),0) -> 0.098551584 | AO72: =_xlfn.IFNA(INDEX(SAM!$B$8:$HC$215,MATCH($AL72,SAM!$A$8:$A$215,0),MATCH(AO$48,SAM!$B$7:$HC$7,0)),0) -> 0.11838894 | AP72: =_xlfn.IFNA(INDEX(SAM!$B$8:$HC$215,MATCH($AL72,SAM!$A$8:$A$215,0),MATCH(AP$48,SAM!$B$7:$HC$7,0)),0) -> 0.12033955 | AQ72: =_xlfn.IFNA(INDEX(SAM!$B$8:$HC$215,MATCH($AL72,SAM!$A$8:$A$215,0),MATCH(AQ$48,SAM!$B$7:$HC$7,0)),0) -> 0.1301297 | AR72: =_xlfn.IFNA(INDEX(SAM!$B$8:$HC$215,MATCH($AL72,SAM!$A$8:$A$215,0),MATCH(AR$48,SAM!$B$7:$HC$7,0)),0) -> 0.020921082 | AS72: =_xlfn.IFNA(INDEX(SAM!$B$8:$HC$215,MATCH($AL72,SAM!$A$8:$A$215,0),MATCH(AS$48,SAM!$B$7:$HC$7,0)),0) -> 0.030824594 | AT72: =_xlfn.IFNA(INDEX(SAM!$B$8:$HC$215,MATCH($AL72,SAM!$A$8:$A$215,0),MATCH(AT$48,SAM!$B$7:$HC$7,0)),0) -> 0.020800858 | ... BA72: =_xlfn.IFNA(INDEX(SAM!$B$8:$HC$215,MATCH($AL72,SAM!$A$8:$A$215,0),MATCH(BA$48,SAM!$B$7:$HC$7,0)),0) -> 2.1737538 | BC72: ="a"&T72 -> aocrp | BD72: =_xlfn.IFNA(INDEX(SAM!$B$8:$HC$215,MATCH($BC72,SAM!$A$8:$A$215,0),MATCH(BD$48,SAM!$B$7:$HC$7,0)),0) -> 0.0031915993 | BE72: =_xlfn.IFNA(INDEX(SAM!$B$8:$HC$215,MATCH($BC72,SAM!$A$8:$A$215,0),MATCH(BE$48,SAM!$B$7:$HC$7,0)),0) -> 0.0075054861 | BF72: =_xlfn.IFNA(INDEX(SAM!$B$8:$HC$215,MATCH($BC72,SAM!$A$8:$A$215,0),MATCH(BF$48,SAM!$B$7:$HC$7,0)),0) -> 6.7278264e-05 | BG72: =_xlfn.IFNA(INDEX(SAM!$B$8:$HC$215,MATCH($BC72,SAM!$A$8:$A$215,0),MATCH(BG$48,SAM!$B$7:$HC$7,0)),0) -> 0.0322881 | BH72: =_xlfn.IFNA(INDEX(SAM!$B$8:$HC$215,MATCH($BC72,SAM!$A$8:$A$215,0),MATCH(BH$48,SAM!$B$7:$HC$7,0)),0) -> 0.085926117 | BI72: =_xlfn.IFNA(INDEX(SAM!$B$8:$HC$215,MATCH($BC72,SAM!$A$8:$A$215,0),MATCH(BI$48,SAM!$B$7:$HC$7,0)),0) -> 0 | BJ72: =_xlfn.IFNA(INDEX(SAM!$B$8:$HC$215,MATCH($BC72,SAM!$A$8:$A$215,0),MATCH(BJ$48,SAM!$B$7:$HC$7,0)),0) -> 0 | BK72: =_xlfn.IFNA(INDEX(SAM!$B$8:$HC$215,MATCH($BC72,SAM!$A$8:$A$215,0),MATCH(BK$48,SAM!$B$7:$HC$7,0)),0) -> 0 | ... BR72: =_xlfn.IFNA(INDEX(SAM!$B$8:$HC$215,MATCH($BC72,SAM!$A$8:$A$215,0),MATCH(BR$48,SAM!$B$7:$HC$7,0)),0) -> 0.021857578 | BT72: =AL72 -> cocrp | BU72: =SUM(BD72:BR72,AM72:BA72) -> 3.138958 | BW72: cwood | BX72: =100*VLOOKUP(BW72,$BT$49:$BU$94,2,FALSE)/$BU$95 -> 0.55825651
A73: other ag | B73: becr | C73: =IFERROR(100*U73/U$95,"") -> 0.012528663 | D73: =IFERROR(100*V73/V$95,"") -> 0.057615135 | E73: =IFERROR(100*W73/W$95,"") -> 0.045357928 | F73: =IFERROR(100*X73/X$95,"") -> 0.1250153 | G73: =IFERROR(100*Y73/Y$95,"") -> 0.068862644 | H73: =IFERROR(100*Z73/Z$95,"") -> 0.042165814 | I73: =IFERROR(100*AA73/AA$95,"") -> 0.048106107 | J73: =IFERROR(100*AB73/AB$95,"") -> 0.00073701712 | ... R73: =IFERROR(100*AJ73/AJ$95,"") -> 0.035729883 | T73: =B73 -> becr | U73: =IFERROR(AM73+BD73,"") -> 0.036836911 | V73: =IFERROR(AN73+BE73,"") -> 0.25093615 | W73: =IFERROR(AO73+BF73,"") -> 0.27104225 | X73: =IFERROR(AP73+BG73,"") -> 1.0743044 | Y73: =IFERROR(AQ73+BH73,"") -> 0.65518198 | Z73: =IFERROR(AR73+BI73,"") -> 0.023872448 | AA73: =IFERROR(AS73+BJ73,"") -> 0.040610678 | AB73: =IFERROR(AT73+BK73,"") -> 0.00075382299 | ... AI73: =IFERROR(BA73+BR73,"") -> 0.079356604 | AJ73: =SUM(U73:AI73) -> 2.521701 | AL73: ="c"&T73 -> cbecr | AM73: =_xlfn.IFNA(INDEX(SAM!$B$8:$HC$215,MATCH($AL73,SAM!$A$8:$A$215,0),MATCH(AM$48,SAM!$B$7:$HC$7,0)),0) -> 0.015927414 | AN73: =_xlfn.IFNA(INDEX(SAM!$B$8:$HC$215,MATCH($AL73,SAM!$A$8:$A$215,0),MATCH(AN$48,SAM!$B$7:$HC$7,0)),0) -> 0.10231367 | AO73: =_xlfn.IFNA(INDEX(SAM!$B$8:$HC$215,MATCH($AL73,SAM!$A$8:$A$215,0),MATCH(AO$48,SAM!$B$7:$HC$7,0)),0) -> 0.11094024 | AP73: =_xlfn.IFNA(INDEX(SAM!$B$8:$HC$215,MATCH($AL73,SAM!$A$8:$A$215,0),MATCH(AP$48,SAM!$B$7:$HC$7,0)),0) -> 0.43401545 | AQ73: =_xlfn.IFNA(INDEX(SAM!$B$8:$HC$215,MATCH($AL73,SAM!$A$8:$A$215,0),MATCH(AQ$48,SAM!$B$7:$HC$7,0)),0) -> 0.26580538 | AR73: =_xlfn.IFNA(INDEX(SAM!$B$8:$HC$215,MATCH($AL73,SAM!$A$8:$A$215,0),MATCH(AR$48,SAM!$B$7:$HC$7,0)),0) -> 0.023872448 | AS73: =_xlfn.IFNA(INDEX(SAM!$B$8:$HC$215,MATCH($AL73,SAM!$A$8:$A$215,0),MATCH(AS$48,SAM!$B$7:$HC$7,0)),0) -> 0.040610678 | AT73: =_xlfn.IFNA(INDEX(SAM!$B$8:$HC$215,MATCH($AL73,SAM!$A$8:$A$215,0),MATCH(AT$48,SAM!$B$7:$HC$7,0)),0) -> 0.00075382299 | ... BA73: =_xlfn.IFNA(INDEX(SAM!$B$8:$HC$215,MATCH($AL73,SAM!$A$8:$A$215,0),MATCH(BA$48,SAM!$B$7:$HC$7,0)),0) -> 0.079356604 | BC73: ="a"&T73 -> abecr | BD73: =_xlfn.IFNA(INDEX(SAM!$B$8:$HC$215,MATCH($BC73,SAM!$A$8:$A$215,0),MATCH(BD$48,SAM!$B$7:$HC$7,0)),0) -> 0.020909498 | BE73: =_xlfn.IFNA(INDEX(SAM!$B$8:$HC$215,MATCH($BC73,SAM!$A$8:$A$215,0),MATCH(BE$48,SAM!$B$7:$HC$7,0)),0) -> 0.14862248 | BF73: =_xlfn.IFNA(INDEX(SAM!$B$8:$HC$215,MATCH($BC73,SAM!$A$8:$A$215,0),MATCH(BF$48,SAM!$B$7:$HC$7,0)),0) -> 0.160102 | BG73: =_xlfn.IFNA(INDEX(SAM!$B$8:$HC$215,MATCH($BC73,SAM!$A$8:$A$215,0),MATCH(BG$48,SAM!$B$7:$HC$7,0)),0) -> 0.64028896 | BH73: =_xlfn.IFNA(INDEX(SAM!$B$8:$HC$215,MATCH($BC73,SAM!$A$8:$A$215,0),MATCH(BH$48,SAM!$B$7:$HC$7,0)),0) -> 0.3893766 | BI73: =_xlfn.IFNA(INDEX(SAM!$B$8:$HC$215,MATCH($BC73,SAM!$A$8:$A$215,0),MATCH(BI$48,SAM!$B$7:$HC$7,0)),0) -> 0 | BJ73: =_xlfn.IFNA(INDEX(SAM!$B$8:$HC$215,MATCH($BC73,SAM!$A$8:$A$215,0),MATCH(BJ$48,SAM!$B$7:$HC$7,0)),0) -> 0 | BK73: =_xlfn.IFNA(INDEX(SAM!$B$8:$HC$215,MATCH($BC73,SAM!$A$8:$A$215,0),MATCH(BK$48,SAM!$B$7:$HC$7,0)),0) -> 0 | ... BR73: =_xlfn.IFNA(INDEX(SAM!$B$8:$HC$215,MATCH($BC73,SAM!$A$8:$A$215,0),MATCH(BR$48,SAM!$B$7:$HC$7,0)),0) -> 0 | BT73: =AL73 -> cbecr | BU73: =SUM(BD73:BR73,AM73:BA73) -> 2.521701 | BW73: cpetr | BX73: =100*VLOOKUP(BW73,$BT$49:$BU$94,2,FALSE)/$BU$95 -> 1.22369
A74: other ag | B74: fore | C74: =IFERROR(100*U74/U$95,"") -> 26.910624 | D74: =IFERROR(100*V74/V$95,"") -> 20.860473 | E74: =IFERROR(100*W74/W$95,"") -> 16.484965 | F74: =IFERROR(100*X74/X$95,"") -> 11.317554 | G74: =IFERROR(100*Y74/Y$95,"") -> 5.5867453 | H74: =IFERROR(100*Z74/Z$95,"") -> 21.613791 | I74: =IFERROR(100*AA74/AA$95,"") -> 17.392284 | J74: =IFERROR(100*AB74/AB$95,"") -> 13.05007 | ... R74: =IFERROR(100*AJ74/AJ$95,"") -> 7.5334939 | T74: =B74 -> fore | U74: =IFERROR(AM74+BD74,"") -> 79.122908 | V74: =IFERROR(AN74+BE74,"") -> 90.855409 | W74: =IFERROR(AO74+BF74,"") -> 98.508072 | X74: =IFERROR(AP74+BG74,"") -> 97.25608 | Y74: =IFERROR(AQ74+BH74,"") -> 53.154143 | Z74: =IFERROR(AR74+BI74,"") -> 12.236787 | AA74: =IFERROR(AS74+BJ74,"") -> 14.682386 | AB74: =IFERROR(AT74+BK74,"") -> 13.347645 | ... AI74: =IFERROR(BA74+BR74,"") -> 10.160459 | AJ74: =SUM(U74:AI74) -> 531.68993 | AL74: ="c"&T74 -> cfore | AM74: =_xlfn.IFNA(INDEX(SAM!$B$8:$HC$215,MATCH($AL74,SAM!$A$8:$A$215,0),MATCH(AM$48,SAM!$B$7:$HC$7,0)),0) -> 0.0078059219 | AN74: =_xlfn.IFNA(INDEX(SAM!$B$8:$HC$215,MATCH($AL74,SAM!$A$8:$A$215,0),MATCH(AN$48,SAM!$B$7:$HC$7,0)),0) -> 0.023117667 | AO74: =_xlfn.IFNA(INDEX(SAM!$B$8:$HC$215,MATCH($AL74,SAM!$A$8:$A$215,0),MATCH(AO$48,SAM!$B$7:$HC$7,0)),0) -> 0.056233424 | AP74: =_xlfn.IFNA(INDEX(SAM!$B$8:$HC$215,MATCH($AL74,SAM!$A$8:$A$215,0),MATCH(AP$48,SAM!$B$7:$HC$7,0)),0) -> 0.1120336 | AQ74: =_xlfn.IFNA(INDEX(SAM!$B$8:$HC$215,MATCH($AL74,SAM!$A$8:$A$215,0),MATCH(AQ$48,SAM!$B$7:$HC$7,0)),0) -> 0.17897657 | AR74: =_xlfn.IFNA(INDEX(SAM!$B$8:$HC$215,MATCH($AL74,SAM!$A$8:$A$215,0),MATCH(AR$48,SAM!$B$7:$HC$7,0)),0) -> 0.0030860813 | AS74: =_xlfn.IFNA(INDEX(SAM!$B$8:$HC$215,MATCH($AL74,SAM!$A$8:$A$215,0),MATCH(AS$48,SAM!$B$7:$HC$7,0)),0) -> 0.0055738233 | AT74: =_xlfn.IFNA(INDEX(SAM!$B$8:$HC$215,MATCH($AL74,SAM!$A$8:$A$215,0),MATCH(AT$48,SAM!$B$7:$HC$7,0)),0) -> 0.0066159201 | ... BA74: =_xlfn.IFNA(INDEX(SAM!$B$8:$HC$215,MATCH($AL74,SAM!$A$8:$A$215,0),MATCH(BA$48,SAM!$B$7:$HC$7,0)),0) -> 1.2289077 | BC74: ="a"&T74 -> afore | BD74: =_xlfn.IFNA(INDEX(SAM!$B$8:$HC$215,MATCH($BC74,SAM!$A$8:$A$215,0),MATCH(BD$48,SAM!$B$7:$HC$7,0)),0) -> 79.115102 | BE74: =_xlfn.IFNA(INDEX(SAM!$B$8:$HC$215,MATCH($BC74,SAM!$A$8:$A$215,0),MATCH(BE$48,SAM!$B$7:$HC$7,0)),0) -> 90.832292 | BF74: =_xlfn.IFNA(INDEX(SAM!$B$8:$HC$215,MATCH($BC74,SAM!$A$8:$A$215,0),MATCH(BF$48,SAM!$B$7:$HC$7,0)),0) -> 98.451839 | BG74: =_xlfn.IFNA(INDEX(SAM!$B$8:$HC$215,MATCH($BC74,SAM!$A$8:$A$215,0),MATCH(BG$48,SAM!$B$7:$HC$7,0)),0) -> 97.144046 | BH74: =_xlfn.IFNA(INDEX(SAM!$B$8:$HC$215,MATCH($BC74,SAM!$A$8:$A$215,0),MATCH(BH$48,SAM!$B$7:$HC$7,0)),0) -> 52.975167 | BI74: =_xlfn.IFNA(INDEX(SAM!$B$8:$HC$215,MATCH($BC74,SAM!$A$8:$A$215,0),MATCH(BI$48,SAM!$B$7:$HC$7,0)),0) -> 12.233701 | BJ74: =_xlfn.IFNA(INDEX(SAM!$B$8:$HC$215,MATCH($BC74,SAM!$A$8:$A$215,0),MATCH(BJ$48,SAM!$B$7:$HC$7,0)),0) -> 14.676812 | BK74: =_xlfn.IFNA(INDEX(SAM!$B$8:$HC$215,MATCH($BC74,SAM!$A$8:$A$215,0),MATCH(BK$48,SAM!$B$7:$HC$7,0)),0) -> 13.341029 | ... BR74: =_xlfn.IFNA(INDEX(SAM!$B$8:$HC$215,MATCH($BC74,SAM!$A$8:$A$215,0),MATCH(BR$48,SAM!$B$7:$HC$7,0)),0) -> 8.9315511 | BT74: =AL74 -> cfore | BU74: =SUM(BD74:BR74,AM74:BA74) -> 531.68993 | BW74: cfert | BX74: =100*VLOOKUP(BW74,$BT$49:$BU$94,2,FALSE)/$BU$95 -> 0
A75: other ag | B75: oapr | C75: =IFERROR(100*U75/U$95,"") -> 0.32341316 | D75: =IFERROR(100*V75/V$95,"") -> 0.36762605 | E75: =IFERROR(100*W75/W$95,"") -> 0.39326586 | F75: =IFERROR(100*X75/X$95,"") -> 0.36854091 | G75: =IFERROR(100*Y75/Y$95,"") -> 0.2112362 | H75: =IFERROR(100*Z75/Z$95,"") -> 0.2729341 | I75: =IFERROR(100*AA75/AA$95,"") -> 0.40698347 | J75: =IFERROR(100*AB75/AB$95,"") -> 0.35774572 | ... R75: =IFERROR(100*AJ75/AJ$95,"") -> 0.31206777 | T75: =B75 -> oapr | U75: =IFERROR(AM75+BD75,"") -> 0.95090288 | V75: =IFERROR(AN75+BE75,"") -> 1.6011533 | W75: =IFERROR(AO75+BF75,"") -> 2.3500117 | X75: =IFERROR(AP75+BG75,"") -> 3.1670134 | Y75: =IFERROR(AQ75+BH75,"") -> 2.0097711 | Z75: =IFERROR(AR75+BI75,"") -> 0.15452341 | AA75: =IFERROR(AS75+BJ75,"") -> 0.34357123 | AB75: =IFERROR(AT75+BK75,"") -> 0.36590324 | ... AI75: =IFERROR(BA75+BR75,"") -> 7.2885293 | AJ75: =SUM(U75:AI75) -> 22.024746 | AL75: ="c"&T75 -> coapr | AM75: =_xlfn.IFNA(INDEX(SAM!$B$8:$HC$215,MATCH($AL75,SAM!$A$8:$A$215,0),MATCH(AM$48,SAM!$B$7:$HC$7,0)),0) -> 0.95090288 | AN75: =_xlfn.IFNA(INDEX(SAM!$B$8:$HC$215,MATCH($AL75,SAM!$A$8:$A$215,0),MATCH(AN$48,SAM!$B$7:$HC$7,0)),0) -> 1.6011533 | AO75: =_xlfn.IFNA(INDEX(SAM!$B$8:$HC$215,MATCH($AL75,SAM!$A$8:$A$215,0),MATCH(AO$48,SAM!$B$7:$HC$7,0)),0) -> 2.3500117 | AP75: =_xlfn.IFNA(INDEX(SAM!$B$8:$HC$215,MATCH($AL75,SAM!$A$8:$A$215,0),MATCH(AP$48,SAM!$B$7:$HC$7,0)),0) -> 3.1670134 | AQ75: =_xlfn.IFNA(INDEX(SAM!$B$8:$HC$215,MATCH($AL75,SAM!$A$8:$A$215,0),MATCH(AQ$48,SAM!$B$7:$HC$7,0)),0) -> 2.0097711 | AR75: =_xlfn.IFNA(INDEX(SAM!$B$8:$HC$215,MATCH($AL75,SAM!$A$8:$A$215,0),MATCH(AR$48,SAM!$B$7:$HC$7,0)),0) -> 0.15452341 | AS75: =_xlfn.IFNA(INDEX(SAM!$B$8:$HC$215,MATCH($AL75,SAM!$A$8:$A$215,0),MATCH(AS$48,SAM!$B$7:$HC$7,0)),0) -> 0.34357123 | AT75: =_xlfn.IFNA(INDEX(SAM!$B$8:$HC$215,MATCH($AL75,SAM!$A$8:$A$215,0),MATCH(AT$48,SAM!$B$7:$HC$7,0)),0) -> 0.36590324 | ... BA75: =_xlfn.IFNA(INDEX(SAM!$B$8:$HC$215,MATCH($AL75,SAM!$A$8:$A$215,0),MATCH(BA$48,SAM!$B$7:$HC$7,0)),0) -> 7.2885293 | BC75: ="a"&T75 -> aoapr | BD75: =_xlfn.IFNA(INDEX(SAM!$B$8:$HC$215,MATCH($BC75,SAM!$A$8:$A$215,0),MATCH(BD$48,SAM!$B$7:$HC$7,0)),0) -> 0 | BE75: =_xlfn.IFNA(INDEX(SAM!$B$8:$HC$215,MATCH($BC75,SAM!$A$8:$A$215,0),MATCH(BE$48,SAM!$B$7:$HC$7,0)),0) -> 0 | BF75: =_xlfn.IFNA(INDEX(SAM!$B$8:$HC$215,MATCH($BC75,SAM!$A$8:$A$215,0),MATCH(BF$48,SAM!$B$7:$HC$7,0)),0) -> 0 | BG75: =_xlfn.IFNA(INDEX(SAM!$B$8:$HC$215,MATCH($BC75,SAM!$A$8:$A$215,0),MATCH(BG$48,SAM!$B$7:$HC$7,0)),0) -> 0 | BH75: =_xlfn.IFNA(INDEX(SAM!$B$8:$HC$215,MATCH($BC75,SAM!$A$8:$A$215,0),MATCH(BH$48,SAM!$B$7:$HC$7,0)),0) -> 0 | BI75: =_xlfn.IFNA(INDEX(SAM!$B$8:$HC$215,MATCH($BC75,SAM!$A$8:$A$215,0),MATCH(BI$48,SAM!$B$7:$HC$7,0)),0) -> 0 | BJ75: =_xlfn.IFNA(INDEX(SAM!$B$8:$HC$215,MATCH($BC75,SAM!$A$8:$A$215,0),MATCH(BJ$48,SAM!$B$7:$HC$7,0)),0) -> 0 | BK75: =_xlfn.IFNA(INDEX(SAM!$B$8:$HC$215,MATCH($BC75,SAM!$A$8:$A$215,0),MATCH(BK$48,SAM!$B$7:$HC$7,0)),0) -> 0 | ... BR75: =_xlfn.IFNA(INDEX(SAM!$B$8:$HC$215,MATCH($BC75,SAM!$A$8:$A$215,0),MATCH(BR$48,SAM!$B$7:$HC$7,0)),0) -> 0 | BT75: =AL75 -> coapr | BU75: =SUM(BD75:BR75,AM75:BA75) -> 22.024746 | BW75: cchem | BX75: =100*VLOOKUP(BW75,$BT$49:$BU$94,2,FALSE)/$BU$95 -> 1.8940419
A76: mining | B76: mine | C76: =IFERROR(100*U76/U$95,"") -> 0 | D76: =IFERROR(100*V76/V$95,"") -> 0 | E76: =IFERROR(100*W76/W$95,"") -> 0 | F76: =IFERROR(100*X76/X$95,"") -> 0 | G76: =IFERROR(100*Y76/Y$95,"") -> 0 | H76: =IFERROR(100*Z76/Z$95,"") -> 0 | I76: =IFERROR(100*AA76/AA$95,"") -> 0 | J76: =IFERROR(100*AB76/AB$95,"") -> 0 | ... R76: =IFERROR(100*AJ76/AJ$95,"") -> 0 | T76: =B76 -> mine | U76: =IFERROR(AM76+BD76,"") -> 0 | V76: =IFERROR(AN76+BE76,"") -> 0 | W76: =IFERROR(AO76+BF76,"") -> 0 | X76: =IFERROR(AP76+BG76,"") -> 0 | Y76: =IFERROR(AQ76+BH76,"") -> 0 | Z76: =IFERROR(AR76+BI76,"") -> 0 | AA76: =IFERROR(AS76+BJ76,"") -> 0 | AB76: =IFERROR(AT76+BK76,"") -> 0 | ... AI76: =IFERROR(BA76+BR76,"") -> 0 | AJ76: =SUM(U76:AI76) -> 0 | AL76: ="c"&T76 -> cmine | AM76: =_xlfn.IFNA(INDEX(SAM!$B$8:$HC$215,MATCH($AL76,SAM!$A$8:$A$215,0),MATCH(AM$48,SAM!$B$7:$HC$7,0)),0) -> 0 | AN76: =_xlfn.IFNA(INDEX(SAM!$B$8:$HC$215,MATCH($AL76,SAM!$A$8:$A$215,0),MATCH(AN$48,SAM!$B$7:$HC$7,0)),0) -> 0 | AO76: =_xlfn.IFNA(INDEX(SAM!$B$8:$HC$215,MATCH($AL76,SAM!$A$8:$A$215,0),MATCH(AO$48,SAM!$B$7:$HC$7,0)),0) -> 0 | AP76: =_xlfn.IFNA(INDEX(SAM!$B$8:$HC$215,MATCH($AL76,SAM!$A$8:$A$215,0),MATCH(AP$48,SAM!$B$7:$HC$7,0)),0) -> 0 | AQ76: =_xlfn.IFNA(INDEX(SAM!$B$8:$HC$215,MATCH($AL76,SAM!$A$8:$A$215,0),MATCH(AQ$48,SAM!$B$7:$HC$7,0)),0) -> 0 | AR76: =_xlfn.IFNA(INDEX(SAM!$B$8:$HC$215,MATCH($AL76,SAM!$A$8:$A$215,0),MATCH(AR$48,SAM!$B$7:$HC$7,0)),0) -> 0 | AS76: =_xlfn.IFNA(INDEX(SAM!$B$8:$HC$215,MATCH($AL76,SAM!$A$8:$A$215,0),MATCH(AS$48,SAM!$B$7:$HC$7,0)),0) -> 0 | AT76: =_xlfn.IFNA(INDEX(SAM!$B$8:$HC$215,MATCH($AL76,SAM!$A$8:$A$215,0),MATCH(AT$48,SAM!$B$7:$HC$7,0)),0) -> 0 | ... BA76: =_xlfn.IFNA(INDEX(SAM!$B$8:$HC$215,MATCH($AL76,SAM!$A$8:$A$215,0),MATCH(BA$48,SAM!$B$7:$HC$7,0)),0) -> 0 | BC76: ="a"&T76 -> amine | BD76: =_xlfn.IFNA(INDEX(SAM!$B$8:$HC$215,MATCH($BC76,SAM!$A$8:$A$215,0),MATCH(BD$48,SAM!$B$7:$HC$7,0)),0) -> 0 | BE76: =_xlfn.IFNA(INDEX(SAM!$B$8:$HC$215,MATCH($BC76,SAM!$A$8:$A$215,0),MATCH(BE$48,SAM!$B$7:$HC$7,0)),0) -> 0 | BF76: =_xlfn.IFNA(INDEX(SAM!$B$8:$HC$215,MATCH($BC76,SAM!$A$8:$A$215,0),MATCH(BF$48,SAM!$B$7:$HC$7,0)),0) -> 0 | BG76: =_xlfn.IFNA(INDEX(SAM!$B$8:$HC$215,MATCH($BC76,SAM!$A$8:$A$215,0),MATCH(BG$48,SAM!$B$7:$HC$7,0)),0) -> 0 | BH76: =_xlfn.IFNA(INDEX(SAM!$B$8:$HC$215,MATCH($BC76,SAM!$A$8:$A$215,0),MATCH(BH$48,SAM!$B$7:$HC$7,0)),0) -> 0 | BI76: =_xlfn.IFNA(INDEX(SAM!$B$8:$HC$215,MATCH($BC76,SAM!$A$8:$A$215,0),MATCH(BI$48,SAM!$B$7:$HC$7,0)),0) -> 0 | BJ76: =_xlfn.IFNA(INDEX(SAM!$B$8:$HC$215,MATCH($BC76,SAM!$A$8:$A$215,0),MATCH(BJ$48,SAM!$B$7:$HC$7,0)),0) -> 0 | BK76: =_xlfn.IFNA(INDEX(SAM!$B$8:$HC$215,MATCH($BC76,SAM!$A$8:$A$215,0),MATCH(BK$48,SAM!$B$7:$HC$7,0)),0) -> 0 | ... BR76: =_xlfn.IFNA(INDEX(SAM!$B$8:$HC$215,MATCH($BC76,SAM!$A$8:$A$215,0),MATCH(BR$48,SAM!$B$7:$HC$7,0)),0) -> 0 | BT76: =AL76 -> cmine | BU76: =SUM(BD76:BR76,AM76:BA76) -> 0 | BW76: cnmet | BX76: =100*VLOOKUP(BW76,$BT$49:$BU$94,2,FALSE)/$BU$95 -> 0.28099043
A77: mining | B77: mino | C77: =IFERROR(100*U77/U$95,"") -> 0 | D77: =IFERROR(100*V77/V$95,"") -> 0 | E77: =IFERROR(100*W77/W$95,"") -> 0 | F77: =IFERROR(100*X77/X$95,"") -> 0 | G77: =IFERROR(100*Y77/Y$95,"") -> 0 | H77: =IFERROR(100*Z77/Z$95,"") -> 0 | I77: =IFERROR(100*AA77/AA$95,"") -> 0 | J77: =IFERROR(100*AB77/AB$95,"") -> 0 | ... R77: =IFERROR(100*AJ77/AJ$95,"") -> 0 | T77: =B77 -> mino | U77: =IFERROR(AM77+BD77,"") -> 0 | V77: =IFERROR(AN77+BE77,"") -> 0 | W77: =IFERROR(AO77+BF77,"") -> 0 | X77: =IFERROR(AP77+BG77,"") -> 0 | Y77: =IFERROR(AQ77+BH77,"") -> 0 | Z77: =IFERROR(AR77+BI77,"") -> 0 | AA77: =IFERROR(AS77+BJ77,"") -> 0 | AB77: =IFERROR(AT77+BK77,"") -> 0 | ... AI77: =IFERROR(BA77+BR77,"") -> 0 | AJ77: =SUM(U77:AI77) -> 0 | AL77: ="c"&T77 -> cmino | AM77: =_xlfn.IFNA(INDEX(SAM!$B$8:$HC$215,MATCH($AL77,SAM!$A$8:$A$215,0),MATCH(AM$48,SAM!$B$7:$HC$7,0)),0) -> 0 | AN77: =_xlfn.IFNA(INDEX(SAM!$B$8:$HC$215,MATCH($AL77,SAM!$A$8:$A$215,0),MATCH(AN$48,SAM!$B$7:$HC$7,0)),0) -> 0 | AO77: =_xlfn.IFNA(INDEX(SAM!$B$8:$HC$215,MATCH($AL77,SAM!$A$8:$A$215,0),MATCH(AO$48,SAM!$B$7:$HC$7,0)),0) -> 0 | AP77: =_xlfn.IFNA(INDEX(SAM!$B$8:$HC$215,MATCH($AL77,SAM!$A$8:$A$215,0),MATCH(AP$48,SAM!$B$7:$HC$7,0)),0) -> 0 | AQ77: =_xlfn.IFNA(INDEX(SAM!$B$8:$HC$215,MATCH($AL77,SAM!$A$8:$A$215,0),MATCH(AQ$48,SAM!$B$7:$HC$7,0)),0) -> 0 | AR77: =_xlfn.IFNA(INDEX(SAM!$B$8:$HC$215,MATCH($AL77,SAM!$A$8:$A$215,0),MATCH(AR$48,SAM!$B$7:$HC$7,0)),0) -> 0 | AS77: =_xlfn.IFNA(INDEX(SAM!$B$8:$HC$215,MATCH($AL77,SAM!$A$8:$A$215,0),MATCH(AS$48,SAM!$B$7:$HC$7,0)),0) -> 0 | AT77: =_xlfn.IFNA(INDEX(SAM!$B$8:$HC$215,MATCH($AL77,SAM!$A$8:$A$215,0),MATCH(AT$48,SAM!$B$7:$HC$7,0)),0) -> 0 | ... BA77: =_xlfn.IFNA(INDEX(SAM!$B$8:$HC$215,MATCH($AL77,SAM!$A$8:$A$215,0),MATCH(BA$48,SAM!$B$7:$HC$7,0)),0) -> 0 | BC77: ="a"&T77 -> amino | BD77: =_xlfn.IFNA(INDEX(SAM!$B$8:$HC$215,MATCH($BC77,SAM!$A$8:$A$215,0),MATCH(BD$48,SAM!$B$7:$HC$7,0)),0) -> 0 | BE77: =_xlfn.IFNA(INDEX(SAM!$B$8:$HC$215,MATCH($BC77,SAM!$A$8:$A$215,0),MATCH(BE$48,SAM!$B$7:$HC$7,0)),0) -> 0 | BF77: =_xlfn.IFNA(INDEX(SAM!$B$8:$HC$215,MATCH($BC77,SAM!$A$8:$A$215,0),MATCH(BF$48,SAM!$B$7:$HC$7,0)),0) -> 0 | BG77: =_xlfn.IFNA(INDEX(SAM!$B$8:$HC$215,MATCH($BC77,SAM!$A$8:$A$215,0),MATCH(BG$48,SAM!$B$7:$HC$7,0)),0) -> 0 | BH77: =_xlfn.IFNA(INDEX(SAM!$B$8:$HC$215,MATCH($BC77,SAM!$A$8:$A$215,0),MATCH(BH$48,SAM!$B$7:$HC$7,0)),0) -> 0 | BI77: =_xlfn.IFNA(INDEX(SAM!$B$8:$HC$215,MATCH($BC77,SAM!$A$8:$A$215,0),MATCH(BI$48,SAM!$B$7:$HC$7,0)),0) -> 0 | BJ77: =_xlfn.IFNA(INDEX(SAM!$B$8:$HC$215,MATCH($BC77,SAM!$A$8:$A$215,0),MATCH(BJ$48,SAM!$B$7:$HC$7,0)),0) -> 0 | BK77: =_xlfn.IFNA(INDEX(SAM!$B$8:$HC$215,MATCH($BC77,SAM!$A$8:$A$215,0),MATCH(BK$48,SAM!$B$7:$HC$7,0)),0) -> 0 | ... BR77: =_xlfn.IFNA(INDEX(SAM!$B$8:$HC$215,MATCH($BC77,SAM!$A$8:$A$215,0),MATCH(BR$48,SAM!$B$7:$HC$7,0)),0) -> 0 | BT77: =AL77 -> cmino | BU77: =SUM(BD77:BR77,AM77:BA77) -> 0 | BW77: cmetl | BX77: =100*VLOOKUP(BW77,$BT$49:$BU$94,2,FALSE)/$BU$95 -> 0.077833288
A78: =HLOOKUP(B78,$B$6:$BR$9,4,FALSE) -> manufacturing | B78: wood | C78: =IFERROR(100*U78/U$95,"") -> 0.1563794 | D78: =IFERROR(100*V78/V$95,"") -> 0.17766725 | E78: =IFERROR(100*W78/W$95,"") -> 0.46579742 | F78: =IFERROR(100*X78/X$95,"") -> 0.39806619 | G78: =IFERROR(100*Y78/Y$95,"") -> 0.55268217 | H78: =IFERROR(100*Z78/Z$95,"") -> 0.088404812 | I78: =IFERROR(100*AA78/AA$95,"") -> 0.26438672 | J78: =IFERROR(100*AB78/AB$95,"") -> 0.28601002 | ... R78: =IFERROR(100*AJ78/AJ$95,"") -> 0.55825651 | T78: =B78 -> wood | U78: =IFERROR(AM78+BD78,"") -> 0.45978841 | V78: =IFERROR(AN78+BE78,"") -> 0.77380942 | W78: =IFERROR(AO78+BF78,"") -> 2.7834335 | X78: =IFERROR(AP78+BG78,"") -> 3.4207354 | Y78: =IFERROR(AQ78+BH78,"") -> 5.2584011 | Z78: =IFERROR(AR78+BI78,"") -> 0.050050955 | AA78: =IFERROR(AS78+BJ78,"") -> 0.22319253 | AB78: =IFERROR(AT78+BK78,"") -> 0.29253178 | ... AI78: =IFERROR(BA78+BR78,"") -> 22.697336 | AJ78: =SUM(U78:AI78) -> 39.399961 | AL78: ="c"&T78 -> cwood | AM78: =_xlfn.IFNA(INDEX(SAM!$B$8:$HC$215,MATCH($AL78,SAM!$A$8:$A$215,0),MATCH(AM$48,SAM!$B$7:$HC$7,0)),0) -> 0.45978841 | AN78: =_xlfn.IFNA(INDEX(SAM!$B$8:$HC$215,MATCH($AL78,SAM!$A$8:$A$215,0),MATCH(AN$48,SAM!$B$7:$HC$7,0)),0) -> 0.77380942 | AO78: =_xlfn.IFNA(INDEX(SAM!$B$8:$HC$215,MATCH($AL78,SAM!$A$8:$A$215,0),MATCH(AO$48,SAM!$B$7:$HC$7,0)),0) -> 2.7834335 | AP78: =_xlfn.IFNA(INDEX(SAM!$B$8:$HC$215,MATCH($AL78,SAM!$A$8:$A$215,0),MATCH(AP$48,SAM!$B$7:$HC$7,0)),0) -> 3.4207354 | AQ78: =_xlfn.IFNA(INDEX(SAM!$B$8:$HC$215,MATCH($AL78,SAM!$A$8:$A$215,0),MATCH(AQ$48,SAM!$B$7:$HC$7,0)),0) -> 5.2584011 | AR78: =_xlfn.IFNA(INDEX(SAM!$B$8:$HC$215,MATCH($AL78,SAM!$A$8:$A$215,0),MATCH(AR$48,SAM!$B$7:$HC$7,0)),0) -> 0.050050955 | AS78: =_xlfn.IFNA(INDEX(SAM!$B$8:$HC$215,MATCH($AL78,SAM!$A$8:$A$215,0),MATCH(AS$48,SAM!$B$7:$HC$7,0)),0) -> 0.22319253 | AT78: =_xlfn.IFNA(INDEX(SAM!$B$8:$HC$215,MATCH($AL78,SAM!$A$8:$A$215,0),MATCH(AT$48,SAM!$B$7:$HC$7,0)),0) -> 0.29253178 | ... BA78: =_xlfn.IFNA(INDEX(SAM!$B$8:$HC$215,MATCH($AL78,SAM!$A$8:$A$215,0),MATCH(BA$48,SAM!$B$7:$HC$7,0)),0) -> 22.697336 | BC78: ="a"&T78 -> awood | BD78: =_xlfn.IFNA(INDEX(SAM!$B$8:$HC$215,MATCH($BC78,SAM!$A$8:$A$215,0),MATCH(BD$48,SAM!$B$7:$HC$7,0)),0) -> 0 | BE78: =_xlfn.IFNA(INDEX(SAM!$B$8:$HC$215,MATCH($BC78,SAM!$A$8:$A$215,0),MATCH(BE$48,SAM!$B$7:$HC$7,0)),0) -> 0 | BF78: =_xlfn.IFNA(INDEX(SAM!$B$8:$HC$215,MATCH($BC78,SAM!$A$8:$A$215,0),MATCH(BF$48,SAM!$B$7:$HC$7,0)),0) -> 0 | BG78: =_xlfn.IFNA(INDEX(SAM!$B$8:$HC$215,MATCH($BC78,SAM!$A$8:$A$215,0),MATCH(BG$48,SAM!$B$7:$HC$7,0)),0) -> 0 | BH78: =_xlfn.IFNA(INDEX(SAM!$B$8:$HC$215,MATCH($BC78,SAM!$A$8:$A$215,0),MATCH(BH$48,SAM!$B$7:$HC$7,0)),0) -> 0 | BI78: =_xlfn.IFNA(INDEX(SAM!$B$8:$HC$215,MATCH($BC78,SAM!$A$8:$A$215,0),MATCH(BI$48,SAM!$B$7:$HC$7,0)),0) -> 0 | BJ78: =_xlfn.IFNA(INDEX(SAM!$B$8:$HC$215,MATCH($BC78,SAM!$A$8:$A$215,0),MATCH(BJ$48,SAM!$B$7:$HC$7,0)),0) -> 0 | BK78: =_xlfn.IFNA(INDEX(SAM!$B$8:$HC$215,MATCH($BC78,SAM!$A$8:$A$215,0),MATCH(BK$48,SAM!$B$7:$HC$7,0)),0) -> 0 | ... BR78: =_xlfn.IFNA(INDEX(SAM!$B$8:$HC$215,MATCH($BC78,SAM!$A$8:$A$215,0),MATCH(BR$48,SAM!$B$7:$HC$7,0)),0) -> 0 | BT78: =AL78 -> cwood | BU78: =SUM(BD78:BR78,AM78:BA78) -> 39.399961 | BW78: cmach | BX78: =100*VLOOKUP(BW78,$BT$49:$BU$94,2,FALSE)/$BU$95 -> 3.6230919
A79: =HLOOKUP(B79,$B$6:$BR$9,4,FALSE) -> manufacturing | B79: petr | C79: =IFERROR(100*U79/U$95,"") -> 0.11679847 | D79: =IFERROR(100*V79/V$95,"") -> 0.10889902 | E79: =IFERROR(100*W79/W$95,"") -> 0.12626349 | F79: =IFERROR(100*X79/X$95,"") -> 0.23207803 | G79: =IFERROR(100*Y79/Y$95,"") -> 0.86611741 | H79: =IFERROR(100*Z79/Z$95,"") -> 0.10339301 | I79: =IFERROR(100*AA79/AA$95,"") -> 0.062257759 | J79: =IFERROR(100*AB79/AB$95,"") -> 0.090911995 | ... R79: =IFERROR(100*AJ79/AJ$95,"") -> 1.22369 | T79: =B79 -> petr | U79: =IFERROR(AM79+BD79,"") -> 0.34341211 | V79: =IFERROR(AN79+BE79,"") -> 0.47429725 | W79: =IFERROR(AO79+BF79,"") -> 0.75450406 | X79: =IFERROR(AP79+BG79,"") -> 1.9943355 | Y79: =IFERROR(AQ79+BH79,"") -> 8.2405276 | Z79: =IFERROR(AR79+BI79,"") -> 0.058536622 | AA79: =IFERROR(AS79+BJ79,"") -> 0.052557356 | AB79: =IFERROR(AT79+BK79,"") -> 0.092985022 | ... AI79: =IFERROR(BA79+BR79,"") -> 72.198179 | AJ79: =SUM(U79:AI79) -> 86.36413 | AL79: ="c"&T79 -> cpetr | AM79: =_xlfn.IFNA(INDEX(SAM!$B$8:$HC$215,MATCH($AL79,SAM!$A$8:$A$215,0),MATCH(AM$48,SAM!$B$7:$HC$7,0)),0) -> 0.34341211 | AN79: =_xlfn.IFNA(INDEX(SAM!$B$8:$HC$215,MATCH($AL79,SAM!$A$8:$A$215,0),MATCH(AN$48,SAM!$B$7:$HC$7,0)),0) -> 0.47429725 | AO79: =_xlfn.IFNA(INDEX(SAM!$B$8:$HC$215,MATCH($AL79,SAM!$A$8:$A$215,0),MATCH(AO$48,SAM!$B$7:$HC$7,0)),0) -> 0.75450406 | AP79: =_xlfn.IFNA(INDEX(SAM!$B$8:$HC$215,MATCH($AL79,SAM!$A$8:$A$215,0),MATCH(AP$48,SAM!$B$7:$HC$7,0)),0) -> 1.9943355 | AQ79: =_xlfn.IFNA(INDEX(SAM!$B$8:$HC$215,MATCH($AL79,SAM!$A$8:$A$215,0),MATCH(AQ$48,SAM!$B$7:$HC$7,0)),0) -> 8.2405276 | AR79: =_xlfn.IFNA(INDEX(SAM!$B$8:$HC$215,MATCH($AL79,SAM!$A$8:$A$215,0),MATCH(AR$48,SAM!$B$7:$HC$7,0)),0) -> 0.058536622 | AS79: =_xlfn.IFNA(INDEX(SAM!$B$8:$HC$215,MATCH($AL79,SAM!$A$8:$A$215,0),MATCH(AS$48,SAM!$B$7:$HC$7,0)),0) -> 0.052557356 | AT79: =_xlfn.IFNA(INDEX(SAM!$B$8:$HC$215,MATCH($AL79,SAM!$A$8:$A$215,0),MATCH(AT$48,SAM!$B$7:$HC$7,0)),0) -> 0.092985022 | ... BA79: =_xlfn.IFNA(INDEX(SAM!$B$8:$HC$215,MATCH($AL79,SAM!$A$8:$A$215,0),MATCH(BA$48,SAM!$B$7:$HC$7,0)),0) -> 72.198179 | BC79: ="a"&T79 -> apetr | BD79: =_xlfn.IFNA(INDEX(SAM!$B$8:$HC$215,MATCH($BC79,SAM!$A$8:$A$215,0),MATCH(BD$48,SAM!$B$7:$HC$7,0)),0) -> 0 | BE79: =_xlfn.IFNA(INDEX(SAM!$B$8:$HC$215,MATCH($BC79,SAM!$A$8:$A$215,0),MATCH(BE$48,SAM!$B$7:$HC$7,0)),0) -> 0 | BF79: =_xlfn.IFNA(INDEX(SAM!$B$8:$HC$215,MATCH($BC79,SAM!$A$8:$A$215,0),MATCH(BF$48,SAM!$B$7:$HC$7,0)),0) -> 0 | BG79: =_xlfn.IFNA(INDEX(SAM!$B$8:$HC$215,MATCH($BC79,SAM!$A$8:$A$215,0),MATCH(BG$48,SAM!$B$7:$HC$7,0)),0) -> 0 | BH79: =_xlfn.IFNA(INDEX(SAM!$B$8:$HC$215,MATCH($BC79,SAM!$A$8:$A$215,0),MATCH(BH$48,SAM!$B$7:$HC$7,0)),0) -> 0 | BI79: =_xlfn.IFNA(INDEX(SAM!$B$8:$HC$215,MATCH($BC79,SAM!$A$8:$A$215,0),MATCH(BI$48,SAM!$B$7:$HC$7,0)),0) -> 0 | BJ79: =_xlfn.IFNA(INDEX(SAM!$B$8:$HC$215,MATCH($BC79,SAM!$A$8:$A$215,0),MATCH(BJ$48,SAM!$B$7:$HC$7,0)),0) -> 0 | BK79: =_xlfn.IFNA(INDEX(SAM!$B$8:$HC$215,MATCH($BC79,SAM!$A$8:$A$215,0),MATCH(BK$48,SAM!$B$7:$HC$7,0)),0) -> 0 | ... BR79: =_xlfn.IFNA(INDEX(SAM!$B$8:$HC$215,MATCH($BC79,SAM!$A$8:$A$215,0),MATCH(BR$48,SAM!$B$7:$HC$7,0)),0) -> 0 | BT79: =AL79 -> cpetr | BU79: =SUM(BD79:BR79,AM79:BA79) -> 86.36413 | BW79: coman | BX79: =100*VLOOKUP(BW79,$BT$49:$BU$94,2,FALSE)/$BU$95 -> 0.32997506
A80: =HLOOKUP(B80,$B$6:$BR$9,4,FALSE) -> manufacturing | B80: fert | C80: =IFERROR(100*U80/U$95,"") -> 0 | D80: =IFERROR(100*V80/V$95,"") -> 0 | E80: =IFERROR(100*W80/W$95,"") -> 0 | F80: =IFERROR(100*X80/X$95,"") -> 0 | G80: =IFERROR(100*Y80/Y$95,"") -> 0 | H80: =IFERROR(100*Z80/Z$95,"") -> 0 | I80: =IFERROR(100*AA80/AA$95,"") -> 0 | J80: =IFERROR(100*AB80/AB$95,"") -> 0 | ... R80: =IFERROR(100*AJ80/AJ$95,"") -> 0 | T80: =B80 -> fert | U80: =IFERROR(AM80+BD80,"") -> 0 | V80: =IFERROR(AN80+BE80,"") -> 0 | W80: =IFERROR(AO80+BF80,"") -> 0 | X80: =IFERROR(AP80+BG80,"") -> 0 | Y80: =IFERROR(AQ80+BH80,"") -> 0 | Z80: =IFERROR(AR80+BI80,"") -> 0 | AA80: =IFERROR(AS80+BJ80,"") -> 0 | AB80: =IFERROR(AT80+BK80,"") -> 0 | ... AI80: =IFERROR(BA80+BR80,"") -> 0 | AJ80: =SUM(U80:AI80) -> 0 | AL80: ="c"&T80 -> cfert | AM80: =_xlfn.IFNA(INDEX(SAM!$B$8:$HC$215,MATCH($AL80,SAM!$A$8:$A$215,0),MATCH(AM$48,SAM!$B$7:$HC$7,0)),0) -> 0 | AN80: =_xlfn.IFNA(INDEX(SAM!$B$8:$HC$215,MATCH($AL80,SAM!$A$8:$A$215,0),MATCH(AN$48,SAM!$B$7:$HC$7,0)),0) -> 0 | AO80: =_xlfn.IFNA(INDEX(SAM!$B$8:$HC$215,MATCH($AL80,SAM!$A$8:$A$215,0),MATCH(AO$48,SAM!$B$7:$HC$7,0)),0) -> 0 | AP80: =_xlfn.IFNA(INDEX(SAM!$B$8:$HC$215,MATCH($AL80,SAM!$A$8:$A$215,0),MATCH(AP$48,SAM!$B$7:$HC$7,0)),0) -> 0 | AQ80: =_xlfn.IFNA(INDEX(SAM!$B$8:$HC$215,MATCH($AL80,SAM!$A$8:$A$215,0),MATCH(AQ$48,SAM!$B$7:$HC$7,0)),0) -> 0 | AR80: =_xlfn.IFNA(INDEX(SAM!$B$8:$HC$215,MATCH($AL80,SAM!$A$8:$A$215,0),MATCH(AR$48,SAM!$B$7:$HC$7,0)),0) -> 0 | AS80: =_xlfn.IFNA(INDEX(SAM!$B$8:$HC$215,MATCH($AL80,SAM!$A$8:$A$215,0),MATCH(AS$48,SAM!$B$7:$HC$7,0)),0) -> 0 | AT80: =_xlfn.IFNA(INDEX(SAM!$B$8:$HC$215,MATCH($AL80,SAM!$A$8:$A$215,0),MATCH(AT$48,SAM!$B$7:$HC$7,0)),0) -> 0 | ... BA80: =_xlfn.IFNA(INDEX(SAM!$B$8:$HC$215,MATCH($AL80,SAM!$A$8:$A$215,0),MATCH(BA$48,SAM!$B$7:$HC$7,0)),0) -> 0 | BC80: ="a"&T80 -> afert | BD80: =_xlfn.IFNA(INDEX(SAM!$B$8:$HC$215,MATCH($BC80,SAM!$A$8:$A$215,0),MATCH(BD$48,SAM!$B$7:$HC$7,0)),0) -> 0 | BE80: =_xlfn.IFNA(INDEX(SAM!$B$8:$HC$215,MATCH($BC80,SAM!$A$8:$A$215,0),MATCH(BE$48,SAM!$B$7:$HC$7,0)),0) -> 0 | BF80: =_xlfn.IFNA(INDEX(SAM!$B$8:$HC$215,MATCH($BC80,SAM!$A$8:$A$215,0),MATCH(BF$48,SAM!$B$7:$HC$7,0)),0) -> 0 | BG80: =_xlfn.IFNA(INDEX(SAM!$B$8:$HC$215,MATCH($BC80,SAM!$A$8:$A$215,0),MATCH(BG$48,SAM!$B$7:$HC$7,0)),0) -> 0 | BH80: =_xlfn.IFNA(INDEX(SAM!$B$8:$HC$215,MATCH($BC80,SAM!$A$8:$A$215,0),MATCH(BH$48,SAM!$B$7:$HC$7,0)),0) -> 0 | BI80: =_xlfn.IFNA(INDEX(SAM!$B$8:$HC$215,MATCH($BC80,SAM!$A$8:$A$215,0),MATCH(BI$48,SAM!$B$7:$HC$7,0)),0) -> 0 | BJ80: =_xlfn.IFNA(INDEX(SAM!$B$8:$HC$215,MATCH($BC80,SAM!$A$8:$A$215,0),MATCH(BJ$48,SAM!$B$7:$HC$7,0)),0) -> 0 | BK80: =_xlfn.IFNA(INDEX(SAM!$B$8:$HC$215,MATCH($BC80,SAM!$A$8:$A$215,0),MATCH(BK$48,SAM!$B$7:$HC$7,0)),0) -> 0 | ... BR80: =_xlfn.IFNA(INDEX(SAM!$B$8:$HC$215,MATCH($BC80,SAM!$A$8:$A$215,0),MATCH(BR$48,SAM!$B$7:$HC$7,0)),0) -> 0 | BT80: =AL80 -> cfert | BU80: =SUM(BD80:BR80,AM80:BA80) -> 0 | BW80: celec | BX80: =100*VLOOKUP(BW80,$BT$49:$BU$94,2,FALSE)/$BU$95 -> 0.1603004
A81: =HLOOKUP(B81,$B$6:$BR$9,4,FALSE) -> manufacturing | B81: chem | C81: =IFERROR(100*U81/U$95,"") -> 2.3064282 | D81: =IFERROR(100*V81/V$95,"") -> 2.4217888 | E81: =IFERROR(100*W81/W$95,"") -> 2.5245926 | F81: =IFERROR(100*X81/X$95,"") -> 2.1152629 | G81: =IFERROR(100*Y81/Y$95,"") -> 1.7384369 | H81: =IFERROR(100*Z81/Z$95,"") -> 2.3684572 | I81: =IFERROR(100*AA81/AA$95,"") -> 2.5683505 | J81: =IFERROR(100*AB81/AB$95,"") -> 2.4732035 | ... R81: =IFERROR(100*AJ81/AJ$95,"") -> 1.8940419 | T81: =B81 -> chem | U81: =IFERROR(AM81+BD81,"") -> 6.7813853 | V81: =IFERROR(AN81+BE81,"") -> 10.547825 | W81: =IFERROR(AO81+BF81,"") -> 15.086034 | X81: =IFERROR(AP81+BG81,"") -> 18.177265 | Y81: =IFERROR(AQ81+BH81,"") -> 16.540064 | Z81: =IFERROR(AR81+BI81,"") -> 1.3409173 | AA81: =IFERROR(AS81+BJ81,"") -> 2.1681749 | AB81: =IFERROR(AT81+BK81,"") -> 2.5295989 | ... AI81: =IFERROR(BA81+BR81,"") -> 44.071377 | AJ81: =SUM(U81:AI81) -> 133.67543 | AL81: ="c"&T81 -> cchem | AM81: =_xlfn.IFNA(INDEX(SAM!$B$8:$HC$215,MATCH($AL81,SAM!$A$8:$A$215,0),MATCH(AM$48,SAM!$B$7:$HC$7,0)),0) -> 6.7813853 | AN81: =_xlfn.IFNA(INDEX(SAM!$B$8:$HC$215,MATCH($AL81,SAM!$A$8:$A$215,0),MATCH(AN$48,SAM!$B$7:$HC$7,0)),0) -> 10.547825 | AO81: =_xlfn.IFNA(INDEX(SAM!$B$8:$HC$215,MATCH($AL81,SAM!$A$8:$A$215,0),MATCH(AO$48,SAM!$B$7:$HC$7,0)),0) -> 15.086034 | AP81: =_xlfn.IFNA(INDEX(SAM!$B$8:$HC$215,MATCH($AL81,SAM!$A$8:$A$215,0),MATCH(AP$48,SAM!$B$7:$HC$7,0)),0) -> 18.177265 | AQ81: =_xlfn.IFNA(INDEX(SAM!$B$8:$HC$215,MATCH($AL81,SAM!$A$8:$A$215,0),MATCH(AQ$48,SAM!$B$7:$HC$7,0)),0) -> 16.540064 | AR81: =_xlfn.IFNA(INDEX(SAM!$B$8:$HC$215,MATCH($AL81,SAM!$A$8:$A$215,0),MATCH(AR$48,SAM!$B$7:$HC$7,0)),0) -> 1.3409173 | AS81: =_xlfn.IFNA(INDEX(SAM!$B$8:$HC$215,MATCH($AL81,SAM!$A$8:$A$215,0),MATCH(AS$48,SAM!$B$7:$HC$7,0)),0) -> 2.1681749 | AT81: =_xlfn.IFNA(INDEX(SAM!$B$8:$HC$215,MATCH($AL81,SAM!$A$8:$A$215,0),MATCH(AT$48,SAM!$B$7:$HC$7,0)),0) -> 2.5295989 | ... BA81: =_xlfn.IFNA(INDEX(SAM!$B$8:$HC$215,MATCH($AL81,SAM!$A$8:$A$215,0),MATCH(BA$48,SAM!$B$7:$HC$7,0)),0) -> 44.071377 | BC81: ="a"&T81 -> achem | BD81: =_xlfn.IFNA(INDEX(SAM!$B$8:$HC$215,MATCH($BC81,SAM!$A$8:$A$215,0),MATCH(BD$48,SAM!$B$7:$HC$7,0)),0) -> 0 | BE81: =_xlfn.IFNA(INDEX(SAM!$B$8:$HC$215,MATCH($BC81,SAM!$A$8:$A$215,0),MATCH(BE$48,SAM!$B$7:$HC$7,0)),0) -> 0 | BF81: =_xlfn.IFNA(INDEX(SAM!$B$8:$HC$215,MATCH($BC81,SAM!$A$8:$A$215,0),MATCH(BF$48,SAM!$B$7:$HC$7,0)),0) -> 0 | BG81: =_xlfn.IFNA(INDEX(SAM!$B$8:$HC$215,MATCH($BC81,SAM!$A$8:$A$215,0),MATCH(BG$48,SAM!$B$7:$HC$7,0)),0) -> 0 | BH81: =_xlfn.IFNA(INDEX(SAM!$B$8:$HC$215,MATCH($BC81,SAM!$A$8:$A$215,0),MATCH(BH$48,SAM!$B$7:$HC$7,0)),0) -> 0 | BI81: =_xlfn.IFNA(INDEX(SAM!$B$8:$HC$215,MATCH($BC81,SAM!$A$8:$A$215,0),MATCH(BI$48,SAM!$B$7:$HC$7,0)),0) -> 0 | BJ81: =_xlfn.IFNA(INDEX(SAM!$B$8:$HC$215,MATCH($BC81,SAM!$A$8:$A$215,0),MATCH(BJ$48,SAM!$B$7:$HC$7,0)),0) -> 0 | BK81: =_xlfn.IFNA(INDEX(SAM!$B$8:$HC$215,MATCH($BC81,SAM!$A$8:$A$215,0),MATCH(BK$48,SAM!$B$7:$HC$7,0)),0) -> 0 | ... BR81: =_xlfn.IFNA(INDEX(SAM!$B$8:$HC$215,MATCH($BC81,SAM!$A$8:$A$215,0),MATCH(BR$48,SAM!$B$7:$HC$7,0)),0) -> 0 | BT81: =AL81 -> cchem | BU81: =SUM(BD81:BR81,AM81:BA81) -> 133.67543 | BW81: cwatr | BX81: =100*VLOOKUP(BW81,$BT$49:$BU$94,2,FALSE)/$BU$95 -> 0.27385178
A82: =HLOOKUP(B82,$B$6:$BR$9,4,FALSE) -> manufacturing | B82: nmet | C82: =IFERROR(100*U82/U$95,"") -> 0.22254345 | D82: =IFERROR(100*V82/V$95,"") -> 0.22862953 | E82: =IFERROR(100*W82/W$95,"") -> 0.26744307 | F82: =IFERROR(100*X82/X$95,"") -> 0.28448855 | G82: =IFERROR(100*Y82/Y$95,"") -> 0.33929412 | H82: =IFERROR(100*Z82/Z$95,"") -> 0.22665298 | I82: =IFERROR(100*AA82/AA$95,"") -> 0.23827479 | J82: =IFERROR(100*AB82/AB$95,"") -> 0.27209798 | ... R82: =IFERROR(100*AJ82/AJ$95,"") -> 0.28099043 | T82: =B82 -> nmet | U82: =IFERROR(AM82+BD82,"") -> 0.65432465 | V82: =IFERROR(AN82+BE82,"") -> 0.99576985 | W82: =IFERROR(AO82+BF82,"") -> 1.5981411 | X82: =IFERROR(AP82+BG82,"") -> 2.4447193 | Y82: =IFERROR(AQ82+BH82,"") -> 3.2281566 | Z82: =IFERROR(AR82+BI82,"") -> 0.12832105 | AA82: =IFERROR(AS82+BJ82,"") -> 0.20114912 | AB82: =IFERROR(AT82+BK82,"") -> 0.27830251 | ... AI82: =IFERROR(BA82+BR82,"") -> 8.1987305 | AJ82: =SUM(U82:AI82) -> 19.831407 | AL82: ="c"&T82 -> cnmet | AM82: =_xlfn.IFNA(INDEX(SAM!$B$8:$HC$215,MATCH($AL82,SAM!$A$8:$A$215,0),MATCH(AM$48,SAM!$B$7:$HC$7,0)),0) -> 0.65432465 | AN82: =_xlfn.IFNA(INDEX(SAM!$B$8:$HC$215,MATCH($AL82,SAM!$A$8:$A$215,0),MATCH(AN$48,SAM!$B$7:$HC$7,0)),0) -> 0.99576985 | AO82: =_xlfn.IFNA(INDEX(SAM!$B$8:$HC$215,MATCH($AL82,SAM!$A$8:$A$215,0),MATCH(AO$48,SAM!$B$7:$HC$7,0)),0) -> 1.5981411 | AP82: =_xlfn.IFNA(INDEX(SAM!$B$8:$HC$215,MATCH($AL82,SAM!$A$8:$A$215,0),MATCH(AP$48,SAM!$B$7:$HC$7,0)),0) -> 2.4447193 | AQ82: =_xlfn.IFNA(INDEX(SAM!$B$8:$HC$215,MATCH($AL82,SAM!$A$8:$A$215,0),MATCH(AQ$48,SAM!$B$7:$HC$7,0)),0) -> 3.2281566 | AR82: =_xlfn.IFNA(INDEX(SAM!$B$8:$HC$215,MATCH($AL82,SAM!$A$8:$A$215,0),MATCH(AR$48,SAM!$B$7:$HC$7,0)),0) -> 0.12832105 | AS82: =_xlfn.IFNA(INDEX(SAM!$B$8:$HC$215,MATCH($AL82,SAM!$A$8:$A$215,0),MATCH(AS$48,SAM!$B$7:$HC$7,0)),0) -> 0.20114912 | AT82: =_xlfn.IFNA(INDEX(SAM!$B$8:$HC$215,MATCH($AL82,SAM!$A$8:$A$215,0),MATCH(AT$48,SAM!$B$7:$HC$7,0)),0) -> 0.27830251 | ... BA82: =_xlfn.IFNA(INDEX(SAM!$B$8:$HC$215,MATCH($AL82,SAM!$A$8:$A$215,0),MATCH(BA$48,SAM!$B$7:$HC$7,0)),0) -> 8.1987305 | BC82: ="a"&T82 -> anmet | BD82: =_xlfn.IFNA(INDEX(SAM!$B$8:$HC$215,MATCH($BC82,SAM!$A$8:$A$215,0),MATCH(BD$48,SAM!$B$7:$HC$7,0)),0) -> 0 | BE82: =_xlfn.IFNA(INDEX(SAM!$B$8:$HC$215,MATCH($BC82,SAM!$A$8:$A$215,0),MATCH(BE$48,SAM!$B$7:$HC$7,0)),0) -> 0 | BF82: =_xlfn.IFNA(INDEX(SAM!$B$8:$HC$215,MATCH($BC82,SAM!$A$8:$A$215,0),MATCH(BF$48,SAM!$B$7:$HC$7,0)),0) -> 0 | BG82: =_xlfn.IFNA(INDEX(SAM!$B$8:$HC$215,MATCH($BC82,SAM!$A$8:$A$215,0),MATCH(BG$48,SAM!$B$7:$HC$7,0)),0) -> 0 | BH82: =_xlfn.IFNA(INDEX(SAM!$B$8:$HC$215,MATCH($BC82,SAM!$A$8:$A$215,0),MATCH(BH$48,SAM!$B$7:$HC$7,0)),0) -> 0 | BI82: =_xlfn.IFNA(INDEX(SAM!$B$8:$HC$215,MATCH($BC82,SAM!$A$8:$A$215,0),MATCH(BI$48,SAM!$B$7:$HC$7,0)),0) -> 0 | BJ82: =_xlfn.IFNA(INDEX(SAM!$B$8:$HC$215,MATCH($BC82,SAM!$A$8:$A$215,0),MATCH(BJ$48,SAM!$B$7:$HC$7,0)),0) -> 0 | BK82: =_xlfn.IFNA(INDEX(SAM!$B$8:$HC$215,MATCH($BC82,SAM!$A$8:$A$215,0),MATCH(BK$48,SAM!$B$7:$HC$7,0)),0) -> 0 | ... BR82: =_xlfn.IFNA(INDEX(SAM!$B$8:$HC$215,MATCH($BC82,SAM!$A$8:$A$215,0),MATCH(BR$48,SAM!$B$7:$HC$7,0)),0) -> 0 | BT82: =AL82 -> cnmet | BU82: =SUM(BD82:BR82,AM82:BA82) -> 19.831407 | BW82: ccons | BX82: =100*VLOOKUP(BW82,$BT$49:$BU$94,2,FALSE)/$BU$95 -> 1.0665758
A83: =HLOOKUP(B83,$B$6:$BR$9,4,FALSE) -> manufacturing | B83: metl | C83: =IFERROR(100*U83/U$95,"") -> 0.073656655 | D83: =IFERROR(100*V83/V$95,"") -> 0.085154018 | E83: =IFERROR(100*W83/W$95,"") -> 0.086690661 | F83: =IFERROR(100*X83/X$95,"") -> 0.085098108 | G83: =IFERROR(100*Y83/Y$95,"") -> 0.085005657 | H83: =IFERROR(100*Z83/Z$95,"") -> 0.081450161 | I83: =IFERROR(100*AA83/AA$95,"") -> 0.083973678 | J83: =IFERROR(100*AB83/AB$95,"") -> 0.093608637 | ... R83: =IFERROR(100*AJ83/AJ$95,"") -> 0.077833288 | T83: =B83 -> metl | U83: =IFERROR(AM83+BD83,"") -> 0.2165661 | V83: =IFERROR(AN83+BE83,"") -> 0.37087861 | W83: =IFERROR(AO83+BF83,"") -> 0.51803141 | X83: =IFERROR(AP83+BG83,"") -> 0.73128068 | Y83: =IFERROR(AQ83+BH83,"") -> 0.80877195 | Z83: =IFERROR(AR83+BI83,"") -> 0.046113534 | AA83: =IFERROR(AS83+BJ83,"") -> 0.07088971 | AB83: =IFERROR(AT83+BK83,"") -> 0.095743153 | ... AI83: =IFERROR(BA83+BR83,"") -> 1.9903854 | AJ83: =SUM(U83:AI83) -> 5.4932249 | AL83: ="c"&T83 -> cmetl | AM83: =_xlfn.IFNA(INDEX(SAM!$B$8:$HC$215,MATCH($AL83,SAM!$A$8:$A$215,0),MATCH(AM$48,SAM!$B$7:$HC$7,0)),0) -> 0.2165661 | AN83: =_xlfn.IFNA(INDEX(SAM!$B$8:$HC$215,MATCH($AL83,SAM!$A$8:$A$215,0),MATCH(AN$48,SAM!$B$7:$HC$7,0)),0) -> 0.37087861 | AO83: =_xlfn.IFNA(INDEX(SAM!$B$8:$HC$215,MATCH($AL83,SAM!$A$8:$A$215,0),MATCH(AO$48,SAM!$B$7:$HC$7,0)),0) -> 0.51803141 | AP83: =_xlfn.IFNA(INDEX(SAM!$B$8:$HC$215,MATCH($AL83,SAM!$A$8:$A$215,0),MATCH(AP$48,SAM!$B$7:$HC$7,0)),0) -> 0.73128068 | AQ83: =_xlfn.IFNA(INDEX(SAM!$B$8:$HC$215,MATCH($AL83,SAM!$A$8:$A$215,0),MATCH(AQ$48,SAM!$B$7:$HC$7,0)),0) -> 0.80877195 | AR83: =_xlfn.IFNA(INDEX(SAM!$B$8:$HC$215,MATCH($AL83,SAM!$A$8:$A$215,0),MATCH(AR$48,SAM!$B$7:$HC$7,0)),0) -> 0.046113534 | AS83: =_xlfn.IFNA(INDEX(SAM!$B$8:$HC$215,MATCH($AL83,SAM!$A$8:$A$215,0),MATCH(AS$48,SAM!$B$7:$HC$7,0)),0) -> 0.07088971 | AT83: =_xlfn.IFNA(INDEX(SAM!$B$8:$HC$215,MATCH($AL83,SAM!$A$8:$A$215,0),MATCH(AT$48,SAM!$B$7:$HC$7,0)),0) -> 0.095743153 | ... BA83: =_xlfn.IFNA(INDEX(SAM!$B$8:$HC$215,MATCH($AL83,SAM!$A$8:$A$215,0),MATCH(BA$48,SAM!$B$7:$HC$7,0)),0) -> 1.9903854 | BC83: ="a"&T83 -> ametl | BD83: =_xlfn.IFNA(INDEX(SAM!$B$8:$HC$215,MATCH($BC83,SAM!$A$8:$A$215,0),MATCH(BD$48,SAM!$B$7:$HC$7,0)),0) -> 0 | BE83: =_xlfn.IFNA(INDEX(SAM!$B$8:$HC$215,MATCH($BC83,SAM!$A$8:$A$215,0),MATCH(BE$48,SAM!$B$7:$HC$7,0)),0) -> 0 | BF83: =_xlfn.IFNA(INDEX(SAM!$B$8:$HC$215,MATCH($BC83,SAM!$A$8:$A$215,0),MATCH(BF$48,SAM!$B$7:$HC$7,0)),0) -> 0 | BG83: =_xlfn.IFNA(INDEX(SAM!$B$8:$HC$215,MATCH($BC83,SAM!$A$8:$A$215,0),MATCH(BG$48,SAM!$B$7:$HC$7,0)),0) -> 0 | BH83: =_xlfn.IFNA(INDEX(SAM!$B$8:$HC$215,MATCH($BC83,SAM!$A$8:$A$215,0),MATCH(BH$48,SAM!$B$7:$HC$7,0)),0) -> 0 | BI83: =_xlfn.IFNA(INDEX(SAM!$B$8:$HC$215,MATCH($BC83,SAM!$A$8:$A$215,0),MATCH(BI$48,SAM!$B$7:$HC$7,0)),0) -> 0 | BJ83: =_xlfn.IFNA(INDEX(SAM!$B$8:$HC$215,MATCH($BC83,SAM!$A$8:$A$215,0),MATCH(BJ$48,SAM!$B$7:$HC$7,0)),0) -> 0 | BK83: =_xlfn.IFNA(INDEX(SAM!$B$8:$HC$215,MATCH($BC83,SAM!$A$8:$A$215,0),MATCH(BK$48,SAM!$B$7:$HC$7,0)),0) -> 0 | ... BR83: =_xlfn.IFNA(INDEX(SAM!$B$8:$HC$215,MATCH($BC83,SAM!$A$8:$A$215,0),MATCH(BR$48,SAM!$B$7:$HC$7,0)),0) -> 0 | BT83: =AL83 -> cmetl | BU83: =SUM(BD83:BR83,AM83:BA83) -> 5.4932249 | BW83: ctrad | BX83: =100*VLOOKUP(BW83,$BT$49:$BU$94,2,FALSE)/$BU$95 -> 1.3635666
A84: =HLOOKUP(B84,$B$6:$BR$9,4,FALSE) -> manufacturing | B84: mach | C84: =IFERROR(100*U84/U$95,"") -> 1.8482188 | D84: =IFERROR(100*V84/V$95,"") -> 2.1617603 | E84: =IFERROR(100*W84/W$95,"") -> 2.6320092 | F84: =IFERROR(100*X84/X$95,"") -> 3.2659893 | G84: =IFERROR(100*Y84/Y$95,"") -> 4.4862968 | H84: =IFERROR(100*Z84/Z$95,"") -> 2.2123653 | I84: =IFERROR(100*AA84/AA$95,"") -> 2.7830946 | J84: =IFERROR(100*AB84/AB$95,"") -> 2.3676374 | ... R84: =IFERROR(100*AJ84/AJ$95,"") -> 3.6230919 | T84: =B84 -> mach | U84: =IFERROR(AM84+BD84,"") -> 5.4341529 | V84: =IFERROR(AN84+BE84,"") -> 9.4153003 | W84: =IFERROR(AO84+BF84,"") -> 15.727916 | X84: =IFERROR(AP84+BG84,"") -> 28.065899 | Y84: =IFERROR(AQ84+BH84,"") -> 42.684112 | Z84: =IFERROR(AR84+BI84,"") -> 1.2525449 | AA84: =IFERROR(AS84+BJ84,"") -> 2.3494596 | AB84: =IFERROR(AT84+BK84,"") -> 2.4216256 | ... AI84: =IFERROR(BA84+BR84,"") -> 126.16127 | AJ84: =SUM(U84:AI84) -> 255.70625 | AL84: ="c"&T84 -> cmach | AM84: =_xlfn.IFNA(INDEX(SAM!$B$8:$HC$215,MATCH($AL84,SAM!$A$8:$A$215,0),MATCH(AM$48,SAM!$B$7:$HC$7,0)),0) -> 5.4341529 | AN84: =_xlfn.IFNA(INDEX(SAM!$B$8:$HC$215,MATCH($AL84,SAM!$A$8:$A$215,0),MATCH(AN$48,SAM!$B$7:$HC$7,0)),0) -> 9.4153003 | AO84: =_xlfn.IFNA(INDEX(SAM!$B$8:$HC$215,MATCH($AL84,SAM!$A$8:$A$215,0),MATCH(AO$48,SAM!$B$7:$HC$7,0)),0) -> 15.727916 | AP84: =_xlfn.IFNA(INDEX(SAM!$B$8:$HC$215,MATCH($AL84,SAM!$A$8:$A$215,0),MATCH(AP$48,SAM!$B$7:$HC$7,0)),0) -> 28.065899 | AQ84: =_xlfn.IFNA(INDEX(SAM!$B$8:$HC$215,MATCH($AL84,SAM!$A$8:$A$215,0),MATCH(AQ$48,SAM!$B$7:$HC$7,0)),0) -> 42.684112 | AR84: =_xlfn.IFNA(INDEX(SAM!$B$8:$HC$215,MATCH($AL84,SAM!$A$8:$A$215,0),MATCH(AR$48,SAM!$B$7:$HC$7,0)),0) -> 1.2525449 | AS84: =_xlfn.IFNA(INDEX(SAM!$B$8:$HC$215,MATCH($AL84,SAM!$A$8:$A$215,0),MATCH(AS$48,SAM!$B$7:$HC$7,0)),0) -> 2.3494596 | AT84: =_xlfn.IFNA(INDEX(SAM!$B$8:$HC$215,MATCH($AL84,SAM!$A$8:$A$215,0),MATCH(AT$48,SAM!$B$7:$HC$7,0)),0) -> 2.4216256 | ... BA84: =_xlfn.IFNA(INDEX(SAM!$B$8:$HC$215,MATCH($AL84,SAM!$A$8:$A$215,0),MATCH(BA$48,SAM!$B$7:$HC$7,0)),0) -> 126.16127 | BC84: ="a"&T84 -> amach | BD84: =_xlfn.IFNA(INDEX(SAM!$B$8:$HC$215,MATCH($BC84,SAM!$A$8:$A$215,0),MATCH(BD$48,SAM!$B$7:$HC$7,0)),0) -> 0 | BE84: =_xlfn.IFNA(INDEX(SAM!$B$8:$HC$215,MATCH($BC84,SAM!$A$8:$A$215,0),MATCH(BE$48,SAM!$B$7:$HC$7,0)),0) -> 0 | BF84: =_xlfn.IFNA(INDEX(SAM!$B$8:$HC$215,MATCH($BC84,SAM!$A$8:$A$215,0),MATCH(BF$48,SAM!$B$7:$HC$7,0)),0) -> 0 | BG84: =_xlfn.IFNA(INDEX(SAM!$B$8:$HC$215,MATCH($BC84,SAM!$A$8:$A$215,0),MATCH(BG$48,SAM!$B$7:$HC$7,0)),0) -> 0 | BH84: =_xlfn.IFNA(INDEX(SAM!$B$8:$HC$215,MATCH($BC84,SAM!$A$8:$A$215,0),MATCH(BH$48,SAM!$B$7:$HC$7,0)),0) -> 0 | BI84: =_xlfn.IFNA(INDEX(SAM!$B$8:$HC$215,MATCH($BC84,SAM!$A$8:$A$215,0),MATCH(BI$48,SAM!$B$7:$HC$7,0)),0) -> 0 | BJ84: =_xlfn.IFNA(INDEX(SAM!$B$8:$HC$215,MATCH($BC84,SAM!$A$8:$A$215,0),MATCH(BJ$48,SAM!$B$7:$HC$7,0)),0) -> 0 | BK84: =_xlfn.IFNA(INDEX(SAM!$B$8:$HC$215,MATCH($BC84,SAM!$A$8:$A$215,0),MATCH(BK$48,SAM!$B$7:$HC$7,0)),0) -> 0 | ... BR84: =_xlfn.IFNA(INDEX(SAM!$B$8:$HC$215,MATCH($BC84,SAM!$A$8:$A$215,0),MATCH(BR$48,SAM!$B$7:$HC$7,0)),0) -> 0 | BT84: =AL84 -> cmach | BU84: =SUM(BD84:BR84,AM84:BA84) -> 255.70625 | BW84: ctran | BX84: =100*VLOOKUP(BW84,$BT$49:$BU$94,2,FALSE)/$BU$95 -> 12.683475
A85: =HLOOKUP(B85,$B$6:$BR$9,4,FALSE) -> manufacturing | B85: oman | C85: =IFERROR(100*U85/U$95,"") -> 0.20027442 | D85: =IFERROR(100*V85/V$95,"") -> 0.21663945 | E85: =IFERROR(100*W85/W$95,"") -> 0.23565738 | F85: =IFERROR(100*X85/X$95,"") -> 0.26123012 | G85: =IFERROR(100*Y85/Y$95,"") -> 0.34316535 | H85: =IFERROR(100*Z85/Z$95,"") -> 0.24688479 | I85: =IFERROR(100*AA85/AA$95,"") -> 0.25289162 | J85: =IFERROR(100*AB85/AB$95,"") -> 0.24836169 | ... R85: =IFERROR(100*AJ85/AJ$95,"") -> 0.32997506 | T85: =B85 -> oman | U85: =IFERROR(AM85+BD85,"") -> 0.58884902 | V85: =IFERROR(AN85+BE85,"") -> 0.94354841 | W85: =IFERROR(AO85+BF85,"") -> 1.4082016 | X85: =IFERROR(AP85+BG85,"") -> 2.2448506 | Y85: =IFERROR(AQ85+BH85,"") -> 3.2649887 | Z85: =IFERROR(AR85+BI85,"") -> 0.13977542 | AA85: =IFERROR(AS85+BJ85,"") -> 0.21348849 | AB85: =IFERROR(AT85+BK85,"") -> 0.25402497 | ... AI85: =IFERROR(BA85+BR85,"") -> 12.181538 | AJ85: =SUM(U85:AI85) -> 23.288586 | AL85: ="c"&T85 -> coman | AM85: =_xlfn.IFNA(INDEX(SAM!$B$8:$HC$215,MATCH($AL85,SAM!$A$8:$A$215,0),MATCH(AM$48,SAM!$B$7:$HC$7,0)),0) -> 0.58884902 | AN85: =_xlfn.IFNA(INDEX(SAM!$B$8:$HC$215,MATCH($AL85,SAM!$A$8:$A$215,0),MATCH(AN$48,SAM!$B$7:$HC$7,0)),0) -> 0.94354841 | AO85: =_xlfn.IFNA(INDEX(SAM!$B$8:$HC$215,MATCH($AL85,SAM!$A$8:$A$215,0),MATCH(AO$48,SAM!$B$7:$HC$7,0)),0) -> 1.4082016 | AP85: =_xlfn.IFNA(INDEX(SAM!$B$8:$HC$215,MATCH($AL85,SAM!$A$8:$A$215,0),MATCH(AP$48,SAM!$B$7:$HC$7,0)),0) -> 2.2448506 | AQ85: =_xlfn.IFNA(INDEX(SAM!$B$8:$HC$215,MATCH($AL85,SAM!$A$8:$A$215,0),MATCH(AQ$48,SAM!$B$7:$HC$7,0)),0) -> 3.2649887 | AR85: =_xlfn.IFNA(INDEX(SAM!$B$8:$HC$215,MATCH($AL85,SAM!$A$8:$A$215,0),MATCH(AR$48,SAM!$B$7:$HC$7,0)),0) -> 0.13977542 | AS85: =_xlfn.IFNA(INDEX(SAM!$B$8:$HC$215,MATCH($AL85,SAM!$A$8:$A$215,0),MATCH(AS$48,SAM!$B$7:$HC$7,0)),0) -> 0.21348849 | AT85: =_xlfn.IFNA(INDEX(SAM!$B$8:$HC$215,MATCH($AL85,SAM!$A$8:$A$215,0),MATCH(AT$48,SAM!$B$7:$HC$7,0)),0) -> 0.25402497 | ... BA85: =_xlfn.IFNA(INDEX(SAM!$B$8:$HC$215,MATCH($AL85,SAM!$A$8:$A$215,0),MATCH(BA$48,SAM!$B$7:$HC$7,0)),0) -> 12.181538 | BC85: ="a"&T85 -> aoman | BD85: =_xlfn.IFNA(INDEX(SAM!$B$8:$HC$215,MATCH($BC85,SAM!$A$8:$A$215,0),MATCH(BD$48,SAM!$B$7:$HC$7,0)),0) -> 0 | BE85: =_xlfn.IFNA(INDEX(SAM!$B$8:$HC$215,MATCH($BC85,SAM!$A$8:$A$215,0),MATCH(BE$48,SAM!$B$7:$HC$7,0)),0) -> 0 | BF85: =_xlfn.IFNA(INDEX(SAM!$B$8:$HC$215,MATCH($BC85,SAM!$A$8:$A$215,0),MATCH(BF$48,SAM!$B$7:$HC$7,0)),0) -> 0 | BG85: =_xlfn.IFNA(INDEX(SAM!$B$8:$HC$215,MATCH($BC85,SAM!$A$8:$A$215,0),MATCH(BG$48,SAM!$B$7:$HC$7,0)),0) -> 0 | BH85: =_xlfn.IFNA(INDEX(SAM!$B$8:$HC$215,MATCH($BC85,SAM!$A$8:$A$215,0),MATCH(BH$48,SAM!$B$7:$HC$7,0)),0) -> 0 | BI85: =_xlfn.IFNA(INDEX(SAM!$B$8:$HC$215,MATCH($BC85,SAM!$A$8:$A$215,0),MATCH(BI$48,SAM!$B$7:$HC$7,0)),0) -> 0 | BJ85: =_xlfn.IFNA(INDEX(SAM!$B$8:$HC$215,MATCH($BC85,SAM!$A$8:$A$215,0),MATCH(BJ$48,SAM!$B$7:$HC$7,0)),0) -> 0 | BK85: =_xlfn.IFNA(INDEX(SAM!$B$8:$HC$215,MATCH($BC85,SAM!$A$8:$A$215,0),MATCH(BK$48,SAM!$B$7:$HC$7,0)),0) -> 0 | ... BR85: =_xlfn.IFNA(INDEX(SAM!$B$8:$HC$215,MATCH($BC85,SAM!$A$8:$A$215,0),MATCH(BR$48,SAM!$B$7:$HC$7,0)),0) -> 0 | BT85: =AL85 -> coman | BU85: =SUM(BD85:BR85,AM85:BA85) -> 23.288586 | BW85: chotl | BX85: =100*VLOOKUP(BW85,$BT$49:$BU$94,2,FALSE)/$BU$95 -> 0.39009893
A86: =HLOOKUP(B86,$B$6:$BR$9,4,FALSE) -> contruction | B86: cons | C86: =IFERROR(100*U86/U$95,"") -> 0.50890552 | D86: =IFERROR(100*V86/V$95,"") -> 0.688258 | E86: =IFERROR(100*W86/W$95,"") -> 0.86413519 | F86: =IFERROR(100*X86/X$95,"") -> 1.2461045 | G86: =IFERROR(100*Y86/Y$95,"") -> 1.9506874 | H86: =IFERROR(100*Z86/Z$95,"") -> 0.49434015 | I86: =IFERROR(100*AA86/AA$95,"") -> 0.76934001 | J86: =IFERROR(100*AB86/AB$95,"") -> 1.1034575 | ... R86: =IFERROR(100*AJ86/AJ$95,"") -> 1.0665758 | T86: =B86 -> cons | U86: =IFERROR(AM86+BD86,"") -> 1.4962895 | V86: =IFERROR(AN86+BE86,"") -> 2.9976292 | W86: =IFERROR(AO86+BF86,"") -> 5.1637531 | X86: =IFERROR(AP86+BG86,"") -> 10.708254 | Y86: =IFERROR(AQ86+BH86,"") -> 18.559486 | Z86: =IFERROR(AR86+BI86,"") -> 0.27987387 | AA86: =IFERROR(AS86+BJ86,"") -> 0.64946888 | AB86: =IFERROR(AT86+BK86,"") -> 1.1286191 | ... AI86: =IFERROR(BA86+BR86,"") -> 27.597149 | AJ86: =SUM(U86:AI86) -> 75.275511 | AL86: ="c"&T86 -> ccons | AM86: =_xlfn.IFNA(INDEX(SAM!$B$8:$HC$215,MATCH($AL86,SAM!$A$8:$A$215,0),MATCH(AM$48,SAM!$B$7:$HC$7,0)),0) -> 1.4962895 | AN86: =_xlfn.IFNA(INDEX(SAM!$B$8:$HC$215,MATCH($AL86,SAM!$A$8:$A$215,0),MATCH(AN$48,SAM!$B$7:$HC$7,0)),0) -> 2.9976292 | AO86: =_xlfn.IFNA(INDEX(SAM!$B$8:$HC$215,MATCH($AL86,SAM!$A$8:$A$215,0),MATCH(AO$48,SAM!$B$7:$HC$7,0)),0) -> 5.1637531 | AP86: =_xlfn.IFNA(INDEX(SAM!$B$8:$HC$215,MATCH($AL86,SAM!$A$8:$A$215,0),MATCH(AP$48,SAM!$B$7:$HC$7,0)),0) -> 10.708254 | AQ86: =_xlfn.IFNA(INDEX(SAM!$B$8:$HC$215,MATCH($AL86,SAM!$A$8:$A$215,0),MATCH(AQ$48,SAM!$B$7:$HC$7,0)),0) -> 18.559486 | AR86: =_xlfn.IFNA(INDEX(SAM!$B$8:$HC$215,MATCH($AL86,SAM!$A$8:$A$215,0),MATCH(AR$48,SAM!$B$7:$HC$7,0)),0) -> 0.27987387 | AS86: =_xlfn.IFNA(INDEX(SAM!$B$8:$HC$215,MATCH($AL86,SAM!$A$8:$A$215,0),MATCH(AS$48,SAM!$B$7:$HC$7,0)),0) -> 0.64946888 | AT86: =_xlfn.IFNA(INDEX(SAM!$B$8:$HC$215,MATCH($AL86,SAM!$A$8:$A$215,0),MATCH(AT$48,SAM!$B$7:$HC$7,0)),0) -> 1.1286191 | ... BA86: =_xlfn.IFNA(INDEX(SAM!$B$8:$HC$215,MATCH($AL86,SAM!$A$8:$A$215,0),MATCH(BA$48,SAM!$B$7:$HC$7,0)),0) -> 27.597149 | BC86: ="a"&T86 -> acons | BD86: =_xlfn.IFNA(INDEX(SAM!$B$8:$HC$215,MATCH($BC86,SAM!$A$8:$A$215,0),MATCH(BD$48,SAM!$B$7:$HC$7,0)),0) -> 0 | BE86: =_xlfn.IFNA(INDEX(SAM!$B$8:$HC$215,MATCH($BC86,SAM!$A$8:$A$215,0),MATCH(BE$48,SAM!$B$7:$HC$7,0)),0) -> 0 | BF86: =_xlfn.IFNA(INDEX(SAM!$B$8:$HC$215,MATCH($BC86,SAM!$A$8:$A$215,0),MATCH(BF$48,SAM!$B$7:$HC$7,0)),0) -> 0 | BG86: =_xlfn.IFNA(INDEX(SAM!$B$8:$HC$215,MATCH($BC86,SAM!$A$8:$A$215,0),MATCH(BG$48,SAM!$B$7:$HC$7,0)),0) -> 0 | BH86: =_xlfn.IFNA(INDEX(SAM!$B$8:$HC$215,MATCH($BC86,SAM!$A$8:$A$215,0),MATCH(BH$48,SAM!$B$7:$HC$7,0)),0) -> 0 | BI86: =_xlfn.IFNA(INDEX(SAM!$B$8:$HC$215,MATCH($BC86,SAM!$A$8:$A$215,0),MATCH(BI$48,SAM!$B$7:$HC$7,0)),0) -> 0 | BJ86: =_xlfn.IFNA(INDEX(SAM!$B$8:$HC$215,MATCH($BC86,SAM!$A$8:$A$215,0),MATCH(BJ$48,SAM!$B$7:$HC$7,0)),0) -> 0 | BK86: =_xlfn.IFNA(INDEX(SAM!$B$8:$HC$215,MATCH($BC86,SAM!$A$8:$A$215,0),MATCH(BK$48,SAM!$B$7:$HC$7,0)),0) -> 0 | ... BR86: =_xlfn.IFNA(INDEX(SAM!$B$8:$HC$215,MATCH($BC86,SAM!$A$8:$A$215,0),MATCH(BR$48,SAM!$B$7:$HC$7,0)),0) -> 0 | BT86: =AL86 -> ccons | BU86: =SUM(BD86:BR86,AM86:BA86) -> 75.275511 | BW86: crest | BX86: =100*VLOOKUP(BW86,$BT$49:$BU$94,2,FALSE)/$BU$95 -> 5.6264148
