Workbook

Sheet Notes
A1: =C4&" "&C3&" RIAPA CGE Model" -> 2019 Malawi RIAPA CGE Model
A3: * | B3: Country | C3: Malawi
A4: * | B4: Base year | C4: 2019
A5: * | B5: Units | C5: Billions of kwacha
A10: Activities (a) and commodities (c) | E10: Factors (f) | I10: Households (hhd) | M10: Other accounts
A11: cere | B11: Cereals | E11: lab-n | F11: Labor - uneducated | I11: f1 | J11: Rural farm - quintile 1 | M11: trc | N11: Transaction costs
A12: puls | B12: Pulses | E12: lab-p | F12: Labor - primary | I12: f2 | J12: Rural farm - quintile 2 | M12: ent | N12: Enterprises
A13: oils | B13: Oilseeds | E13: lab-s | F13: Labor - secondary | I13: f3 | J13: Rural farm - quintile 3 | M13: gov | N13: Government
A14: root | B14: Roots and Tubers | E14: lab-t | F14: Labor - tertiary | I14: f4 | J14: Rural farm - quintile 4 | M14: atax | N14: Taxes - activity
A15: vege | B15: Vegetables | E15: lnd | F15: Land - agricultural crops | I15: f5 | J15: Rural farm - quintile 5 | M15: dtax | N15: Taxes - direct
A16: frui | B16: Fruits | E16: cap-c | F16: Capital - crops | I16: n1 | J16: Rural nonfarm - quintile 1 | M16: etax | N16: Taxes - export
A17: becr | B17: Beverage crops | E17: cap-l | F17: Capital - livestock | I17: n2 | J17: Rural nonfarm - quintile 2 | M17: ftax | N17: Taxes - factor
A18: ocrp | B18: Other non-food crops | E18: cap-m | F18: Capital - mining | I18: n3 | J18: Rural nonfarm - quintile 3 | M18: mtax | N18: Taxes - import
A19: live | B19: Livestock | E19: cap-o | F19: Capital - other | I19: n4 | J19: Rural nonfarm - quintile 4 | M19: stax | N19: Taxes - sales
A20: milk | B20: Raw milk | I20: n5 | J20: Rural nonfarm - quintile 5 | M20: s-i | N20: Savings-investment
A21: fore | B21: Forestry | I21: u1 | J21: Urban - quintile 1 | M21: dstk | N21: Change in stocks
A22: fish | B22: Fishery | I22: u2 | J22: Urban - quintile 2 | M22: row | N22: Rest of world
A23: mine | B23: Mining - energy | I23: u3 | J23: Urban - quintile 3 | M23: total | N23: Total
A24: mino | B24: Mining - other | I24: u4 | J24: Urban - quintile 4
A25: gmll | B25: Grain milling | I25: u5 | J25: Urban - quintile 5
A26: foil | B26: Fats and oils
A27: fveg | B27: Fruit and vegetable processing
A28: meat | B28: Meat processing
A29: fsea | B29: Fish and seafood processing
A30: dair | B30: Dairy
A31: fobe | B31: Other food and beverages
A32: oapr | B32: Other processing of ag products
A33: text | B33: Textiles
A34: wood | B34: Wood products
A35: petr | B35: Petroleum products
A36: fert | B36: Fertilizers and herbicides
A37: chem | B37: Chemicals
... A56: osrv | B56: Other services

Sheet Index
A1: GAMS GDX Index
A2: Instruction | B2: Do not alter this sheet.
D7: rdim | E7: cdim
A8: par | B8: nsam | C8: sam!a7 | D8: 1 | E8: 1
D15: rdim | E15: cdim
A16: dset | B16: ac | C16: sets!a7 | D16: 1
A17: dset | B17: rg | C17: sets!b7 | D17: 1
A18: dset | B18: a | C18: sets!c7 | D18: 1
A19: dset | B19: arg | C19: sets!d7 | D19: 1
A20: dset | B20: c | C20: sets!e7 | D20: 1
A21: dset | B21: f | C21: sets!f7 | D21: 1
A22: dset | B22: flab | C22: sets!g7 | D22: 1
A23: dset | B23: flnd | C23: sets!h7 | D23: 1
A24: dset | B24: fliv | C24: sets!i7 | D24: 1
A25: dset | B25: fcap | C25: sets!j7 | D25: 1
A26: dset | B26: ins | C26: sets!k7 | D26: 1
A27: dset | B27: insd | C27: sets!l7 | D27: 1
... A33: dset | B33: ctm | C33: sets!r7 | D33: 1
A34: set | B34: mac | C34: sets!t7 | D34: 2 | F34: values=nodata
A35: set | B35: marg | C35: sets!w7 | D35: 3 | F35: values=nodata
A36: dset | B36: eagr | C36: sets!aa7 | D36: 1
A37: dset | B37: emin | C37: sets!ab7 | D37: 1
A38: dset | B38: eman | C38: sets!ac7 | D38: 1
A39: dset | B39: eutl | C39: sets!ad7 | D39: 1
A40: dset | B40: econ | C40: sets!ae7 | D40: 1
A41: dset | B41: etrd | C41: sets!af7 | D41: 1
A42: dset | B42: etrc | C42: sets!ag7 | D42: 1
A43: dset | B43: ehfs | C43: sets!ah7 | D43: 1
A44: dset | B44: efbs | C44: sets!ai7 | D44: 1
A45: dset | B45: eres | C45: sets!aj7 | D45: 1
A46: dset | B46: egsv | C46: sets!ak7 | D46: 1
A47: dset | B47: eosv | C47: sets!al7 | D47: 1
... A53: dset | B53: cer | C53: adjust!f7 | D53: 1
A54: par | B54: sam | C54: sam!a7 | D54: 1 | E54: 1
A55: par | B55: leselas1 | C55: LES!b131 | D55: 1 | E55: 1
A56: par | B56: leselas2 | C56: LES!s131 | D56: 1 | E56: 1
A57: par | B57: FRISCH | C57: LES!C206 | E57: 1
A58: par | B58: tradelas | C58: elasticities!a7 | D58: 1 | E58: 1
A59: par | B59: prodelastab | C59: elasticities!e7 | D59: 1 | E59: 1
A60: par | B60: proddata | C60: production!a7 | D60: 1 | E60: 2
A61: dset | B61: al | C61: employment!a7 | D61: 1
A62: set | B62: mala | C62: employment!c7 | D62: 2 | F62: values=nodata
A63: par | B63: wfinput | C63: employment!g6 | D63: 1 | E63: 1
A64: par | B64: qfinput | C64: employment!g50 | D64: 1 | E64: 1
A65: par | B65: poptab | C65: population!a7 | D65: 1

Sheet Sets
A1: Set Definitions
A2: Instruction | B2: Do not alter this sheet, unless you are adding new regions.
A4: Global set | B4: Regions | C4: Activities | E4: Commodities | F4: Factors | K4: Institutions | P4: Transaction costs | T4: Mapping activities to commodities | W4: Mapping activities to regions | AA4: Sectoral groups for employment calculations
C5: All | F5: All | G5: Labor | H5: Land | I5: Livestock | J5: Capital | K5: All | L5: Domestic | M5: Non-government | N5: Enterprises | O5: Households | P5: Domestic | Q5: Export | R5: Import | T5: MAC | W5: MARG | AA5: Agriculture | AB5: Industry
A6: AC | B6: RG | C6: A | D6: ARG | E6: C | F6: F | G6: FLAB | H6: FLND | I6: FLIV | J6: FCAP | K6: INS | L6: INSD | M6: INSDNG | N6: EN | O6: H | P6: CTD | Q6: CTE | R6: CTM | T6: A | U6: C | W6: ARG | X6: A | Y6: RG | AA6: EAGR | AB6: EMIN | AC6: EMAN | AD6: EUTL | AE6: ECON | AF6: ETRD | AG6: ETRC | AH6: EHFS | AI6: EFBS | AJ6: ERES | AK6: EGSV | AL6: EOSV
A7: acere | B7: x | C7: acere | D7: acere | E7: ccere | F7: flab-n | G7: flab-n | H7: flnd | I7: fcap-l | J7: fcap-c | K7: ent | L7: ent | M7: ent | N7: ent | O7: hhd-f1 | P7: trd | Q7: tre | R7: trm | T7: =C7 -> acere | U7: =E7 -> ccere | W7: =D7 -> acere | X7: =C7 -> acere | Y7: x | AA7: =W7 -> acere | AB7: =W19 -> amine | AC7: =W21 -> agmll | AD7: aelec | AE7: acons | AF7: atrad | AG7: atran | AH7: ahotl | AI7: afsrv | AJ7: areal | AK7: apadm | AL7: aosrv
A8: apuls | C8: apuls | D8: apuls | E8: cpuls | F8: flab-p | G8: flab-p | J8: fcap-m | K8: hhd-f1 | L8: hhd-f1 | M8: hhd-f1 | O8: hhd-f2 | T8: =C8 -> apuls | U8: =E8 -> cpuls | W8: =D8 -> apuls | X8: =C8 -> apuls | Y8: x | AA8: =W8 -> apuls | AB8: =W20 -> amino | AC8: =W22 -> afoil | AD8: awatr | AG8: acomm | AH8: arest | AJ8: absrv | AK8: aeduc
A9: aoils | C9: aoils | D9: aoils | E9: coils | F9: flab-s | G9: flab-s | J9: fcap-o | K9: hhd-f2 | L9: hhd-f2 | M9: hhd-f2 | O9: hhd-f3 | T9: =C9 -> aoils | U9: =E9 -> coils | W9: =D9 -> aoils | X9: =C9 -> aoils | Y9: x | AA9: =W9 -> aoils | AC9: =W23 -> afveg | AK9: aheal
A10: aroot | C10: aroot | D10: aroot | E10: croot | F10: flab-t | G10: flab-t | K10: hhd-f3 | L10: hhd-f3 | M10: hhd-f3 | O10: hhd-f4 | T10: =C10 -> aroot | U10: =E10 -> croot | W10: =D10 -> aroot | X10: =C10 -> aroot | Y10: x | AA10: =W10 -> aroot | AC10: =W24 -> ameat
A11: avege | C11: avege | D11: avege | E11: cvege | F11: flnd | K11: hhd-f4 | L11: hhd-f4 | M11: hhd-f4 | O11: hhd-f5 | T11: =C11 -> avege | U11: =E11 -> cvege | W11: =D11 -> avege | X11: =C11 -> avege | Y11: x | AA11: =W11 -> avege | AC11: =W25 -> afsea
A12: afrui | C12: afrui | D12: afrui | E12: cfrui | F12: fcap-c | K12: hhd-f5 | L12: hhd-f5 | M12: hhd-f5 | O12: hhd-n1 | T12: =C12 -> afrui | U12: =E12 -> cfrui | W12: =D12 -> afrui | X12: =C12 -> afrui | Y12: x | AA12: =W12 -> afrui | AC12: =W26 -> adair
A13: abecr | C13: abecr | D13: abecr | E13: cbecr | F13: fcap-l | K13: hhd-n1 | L13: hhd-n1 | M13: hhd-n1 | O13: hhd-n2 | T13: abecr | U13: cbecr | W13: abecr | X13: abecr | Y13: x | AA13: abecr | AC13: =W27 -> afobe
A14: aocrp | C14: aocrp | D14: aocrp | E14: cocrp | F14: fcap-m | K14: hhd-n2 | L14: hhd-n2 | M14: hhd-n2 | O14: hhd-n3 | T14: =C14 -> aocrp | U14: =E14 -> cocrp | W14: =D14 -> aocrp | X14: =C14 -> aocrp | Y14: x | AA14: =W14 -> aocrp | AC14: =W28 -> aoapr
A15: alive | C15: alive | D15: alive | E15: clive | F15: fcap-o | K15: hhd-n3 | L15: hhd-n3 | M15: hhd-n3 | O15: hhd-n4 | T15: =C15 -> alive | U15: =E15 -> clive | W15: =D15 -> alive | X15: =C15 -> alive | Y15: x | AA15: =W15 -> alive | AC15: =W29 -> atext
A16: amilk | C16: amilk | D16: amilk | E16: cmilk | K16: hhd-n4 | L16: hhd-n4 | M16: hhd-n4 | O16: hhd-n5 | T16: =C16 -> amilk | U16: =E16 -> cmilk | W16: =D16 -> amilk | X16: =C16 -> amilk | Y16: x | AA16: =W16 -> amilk | AC16: =W30 -> awood
A17: afore | C17: afore | D17: afore | E17: cfore | K17: hhd-n5 | L17: hhd-n5 | M17: hhd-n5 | O17: hhd-u1 | T17: =C17 -> afore | U17: =E17 -> cfore | W17: =D17 -> afore | X17: =C17 -> afore | Y17: x | AA17: =W17 -> afore | AC17: =W31 -> apetr
A18: afish | C18: afish | D18: afish | E18: cfish | K18: hhd-u1 | L18: hhd-u1 | M18: hhd-u1 | O18: hhd-u2 | T18: =C18 -> afish | U18: =E18 -> cfish | W18: =D18 -> afish | X18: =C18 -> afish | Y18: x | AA18: =W18 -> afish | AC18: =W32 -> afert
A19: amine | C19: amine | D19: amine | E19: cmine | K19: hhd-u2 | L19: hhd-u2 | M19: hhd-u2 | O19: hhd-u3 | T19: =C19 -> amine | U19: =E19 -> cmine | W19: =D19 -> amine | X19: =C19 -> amine | Y19: x | AC19: =W33 -> achem
A20: amino | C20: amino | D20: amino | E20: cmino | K20: hhd-u3 | L20: hhd-u3 | M20: hhd-u3 | O20: hhd-u4 | T20: =C20 -> amino | U20: =E20 -> cmino | W20: =D20 -> amino | X20: =C20 -> amino | Y20: x | AC20: =W34 -> anmet
A21: agmll | C21: agmll | D21: agmll | E21: cgmll | K21: hhd-u4 | L21: hhd-u4 | M21: hhd-u4 | O21: hhd-u5 | T21: =C21 -> agmll | U21: =E21 -> cgmll | W21: =D21 -> agmll | X21: =C21 -> agmll | Y21: x | AC21: =W35 -> ametl
A22: afoil | C22: afoil | D22: afoil | E22: cfoil | K22: hhd-u5 | L22: hhd-u5 | M22: hhd-u5 | T22: =C22 -> afoil | U22: =E22 -> cfoil | W22: =D22 -> afoil | X22: =C22 -> afoil | Y22: x | AC22: =W36 -> amach
A23: afveg | C23: afveg | D23: afveg | E23: cfveg | K23: gov | L23: gov | T23: =C23 -> afveg | U23: =E23 -> cfveg | W23: =D23 -> afveg | X23: =C23 -> afveg | Y23: x | AC23: =W37 -> aoman
A24: ameat | C24: ameat | D24: ameat | E24: cmeat | K24: row | T24: =C24 -> ameat | U24: =E24 -> cmeat | W24: =D24 -> ameat | X24: =C24 -> ameat | Y24: x
A25: afsea | C25: afsea | D25: afsea | E25: cfsea | T25: =C25 -> afsea | U25: =E25 -> cfsea | W25: =D25 -> afsea | X25: =C25 -> afsea | Y25: x
A26: adair | C26: adair | D26: adair | E26: cdair | T26: =C26 -> adair | U26: =E26 -> cdair | W26: =D26 -> adair | X26: =C26 -> adair | Y26: x
A27: afobe | C27: afobe | D27: afobe | E27: cfobe | T27: =C27 -> afobe | U27: =E27 -> cfobe | W27: =D27 -> afobe | X27: =C27 -> afobe | Y27: x
A28: aoapr | C28: aoapr | D28: aoapr | E28: coapr | T28: =C28 -> aoapr | U28: =E28 -> coapr | W28: =D28 -> aoapr | X28: =C28 -> aoapr | Y28: x
A29: atext | C29: atext | D29: atext | E29: ctext | T29: =C29 -> atext | U29: =E29 -> ctext | W29: =D29 -> atext | X29: =C29 -> atext | Y29: x
A30: awood | C30: awood | D30: awood | E30: cwood | T30: =C30 -> awood | U30: =E30 -> cwood | W30: =D30 -> awood | X30: =C30 -> awood | Y30: x
A31: apetr | C31: apetr | D31: apetr | E31: cpetr | T31: =C31 -> apetr | U31: =E31 -> cpetr | W31: =D31 -> apetr | X31: =C31 -> apetr | Y31: x
A32: afert | C32: afert | D32: afert | E32: cfert | T32: =C32 -> afert | U32: =E32 -> cfert | W32: =D32 -> afert | X32: =C32 -> afert | Y32: x
A33: achem | C33: achem | D33: achem | E33: cchem | T33: =C33 -> achem | U33: =E33 -> cchem | W33: =D33 -> achem | X33: =C33 -> achem | Y33: x
A34: anmet | C34: anmet | D34: anmet | E34: cnmet | T34: =C34 -> anmet | U34: =E34 -> cnmet | W34: =D34 -> anmet | X34: =C34 -> anmet | Y34: x
A35: ametl | C35: ametl | D35: ametl | E35: cmetl | T35: =C35 -> ametl | U35: =E35 -> cmetl | W35: =D35 -> ametl | X35: =C35 -> ametl | Y35: x
A36: amach | C36: amach | D36: amach | E36: cmach | T36: =C36 -> amach | U36: =E36 -> cmach | W36: =D36 -> amach | X36: =C36 -> amach | Y36: x
... A52: aosrv | C52: aosrv | D52: aosrv | E52: cosrv | T52: =C52 -> aosrv | U52: =E52 -> cosrv | W52: =D52 -> aosrv | X52: =C52 -> aosrv | Y52: x
A53: ccere
A54: cpuls
A55: coils
A56: croot
A57: cvege
A58: cfrui
A59: cbecr
A60: cocrp
A61: clive
A62: cmilk
A63: cfore
A64: cfish
... A151: total

Sheet Adjust
A1: Adjustments to SAM Trade Flows
A3: * | B3: * | C3: * | D3: * | E3: * | F3: *
A4: Remove small trade shares | C4: Re-exports | D4: Net out trade | F4: Perfect substitutes
A5: Exports | B5: Imports | D5: Exports | E5: Imports | F5: Exports
A6: REMEXP | B6: REMIMP | C6: REEXPORT | D6: NETEXPS | E6: NETIMPS | F6: CER | I6: VA | J6: EXP | K6: IMP | L6: VAshr | M6: PRDshr | N6: EMPshr | O6: EXPshr | P6: EXP-OUTshr | Q6: IMPshr | R6: IMP-DEMshr | S6: DEM | T6: OUT
A7: cvege | B7: croot | D7: cmetl | E7: cpuls | H7: ccere | I7: 0.68165565 | K7: 0.05015769 | L7: 6.5800251 | M7: 4.9920698 | N7: 27.753459 | Q7: 1.4184436 | R7: 4.0289023 | S7: 1.2449468 | T7: 1.0181784
A8: cfore | B8: clive | D8: ccere | E8: coils | H8: cpuls | I8: 0.22891709 | J8: 0.080288572 | L8: 2.2097378 | M8: 1.2629201 | N8: 6.7706757 | O8: 9.1414718 | P8: 31.169843 | S8: 0.20385368 | T8: 0.25758414
A9: crest | B9: cfish | D9: croot | E9: cvege | H9: coils | I9: 0.18804362 | J9: 0.11447423 | L9: 1.8151859 | M9: 1.0437559 | N9: 5.8513376 | O9: 12.464859 | P9: 53.773162 | S9: 0.10822985 | T9: 0.21288358
A10: cfsrv | B10: cmeat | D10: clive | E10: cbecr | H10: croot | I10: 0.25014028 | L10: 2.4146053 | M10: 1.3481319 | N10: 10.603419 | S10: 0.34072197 | T10: 0.27496386
B11: cheal | D11: cfish | E11: cfore | H11: cvege | I11: 0.40195429 | L11: 3.8800666 | M11: 2.0232013 | N11: 14.50321 | S11: 0.46673947 | T11: 0.41265046
B12: creal | D12: cgmll | E12: cocrp | H12: cfrui | I12: 0.13262804 | J12: 0.018113531 | K12: 0.0032240588 | L12: 1.2802591 | M12: 0.71193449 | N12: 4.7898976 | O12: 2.0753095 | P12: 12.474405 | Q12: 0.090751795 | R12: 2.1450687 | S12: 0.15030096 | T12: 0.14520556
D13: cfoil | E13: cmino | H13: cbecr | I13: 0.10730854 | J13: 0.045907101 | L13: 1.0358498 | M13: 1.0280156 | N13: 3.4068211 | O13: 5.3644092 | P13: 21.894597 | S13: 0.19328398 | T13: 0.2096732
D14: cmeat | E14: cfveg | H14: cocrp | I14: 0.18532382 | J14: 0.13896136 | L14: 1.7889317 | M14: 1.4681891 | N14: 6.0517694 | O14: 15.702465 | P14: 46.405432 | S14: 0.18298201 | T14: 0.29945063
D15: cfsea | E15: cfobe | H15: clive | I15: 0.17424401 | L15: 1.6819782 | M15: 2.8208919 | N15: 2.7913141 | S15: 0.60998449 | T15: 0.57534675
D16: cdair | E16: coapr | H16: cmilk | I16: 0.018823242 | L16: 0.18170084 | M16: 0.18634842 | N16: 0.31604142 | S16: 0.039423396 | T16: 0.038007468
D17: ceduc | E17: chotl | H17: cfore | I17: 0.014431419 | L17: 0.13930656 | M17: 0.13915377 | N17: 0.20190854 | S17: 0.028447426 | T17: 0.028381687
D18: cheal | E18: crest | H18: cfish | I18: 0.15129692 | L18: 1.4604698 | M18: 1.2623269 | N18: 3.0276434 | S18: 0.25767047 | T18: 0.25746315
D19: cbsrv | E19: ccomm | H19: cmine | I19: 0.035168195 | K19: 0.0027604343 | L19: 0.33947874 | M19: 0.37499927 | N19: 0.078480388 | Q19: 0.089772736 | R19: 3.4159234 | S19: 0.080810776 | T19: 0.076484537
D20: cpadm | E20: cfsrv | H20: cmino | I20: 0.045593835 | J20: 0.014363522 | L20: 0.4401175 | M20: 0.27971279 | N20: 0.10563807 | O20: 1.4663199 | P20: 25.177082 | S20: 0.043926373 | T20: 0.057049987
D21: cosrv | H21: cgmll | I21: 0.11606797 | K21: 0.019142336 | L21: 1.1204046 | M21: 3.8440089 | N21: 0.20075546 | Q21: 0.50242551 | R21: 2.0508595 | S21: 0.93338115 | T21: 0.78402085
D22: ctext | H22: cfoil | I22: 0.11360182 | K22: 0.047548422 | L22: 1.0965989 | M22: 1.3340414 | N22: 0.29388646 | Q22: 1.2611177 | R22: 12.956782 | S22: 0.3669771 | T22: 0.27208998
D23: cwood | H23: cfveg | I23: 0.0035630376 | J23: 0.0014947948 | L23: 0.034394019 | M23: 0.048954414 | N23: 0.0093555661 | O23: 0.16947121 | P23: 14.970851 | S23: 0.0093500965 | T23: 0.0099847014
D24: cchem | H24: cmeat | I24: 0.086063682 | L24: 0.83077312 | M24: 1.9817982 | N24: 0.095677122 | S24: 0.4891597 | T24: 0.4042059
D25: ctran | H25: cfsea | I25: 0.090677562 | K25: 0.019182631 | L25: 0.87531092 | M25: 1.0426581 | N25: 0.098534705 | Q25: 0.5061688 | R25: 6.9038959 | S25: 0.27785226 | T25: 0.21265968
H26: cdair | I26: 0.012005729 | K26: 0.012477905 | L26: 0.11589136 | M26: 0.10953571 | N26: 0.03219301 | Q26: 0.34368903 | R26: 33.155588 | S26: 0.037634393 | T26: 0.022340812
H27: cfobe | I27: 0.24047385 | J27: 0.084616745 | L27: 2.3212952 | M27: 2.5518768 | N27: 0.5581942 | O27: 11.413242 | P27: 16.257486 | S27: 0.59338998 | T27: 0.52047866
H28: coapr | I28: 0.17722806 | J28: 0.26937567 | L28: 1.7107833 | M28: 2.502254 | N28: 0.42152433 | O28: 37.387597 | P28: 52.781746 | S28: 0.33758647 | T28: 0.51035764
H29: ctext | I29: 0.046368541 | K29: 0.036774305 | L29: 0.44759574 | M29: 0.77152461 | N29: 0.11005246 | Q29: 0.5429167 | R29: 14.826841 | S29: 0.24802522 | T29: 0.15735952
H30: cwood | I30: 0.043192012 | K30: 0.24909811 | L30: 0.41693269 | M30: 0.41371522 | N30: 0.081638307 | Q30: 6.5498592 | R30: 71.616252 | S30: 0.34782343 | T30: 0.084381011
H31: cpetr | I31: 0.0059843487 | K31: 0.55720339 | L31: 0.057766945 | M31: 0.087224169 | N31: 0.015805336 | Q31: 14.438869 | R31: 96.167268 | S31: 0.57941065 | T31: 0.017790169
H32: cfert | I32: 0.066975714 | K32: 0.10051038 | L32: 0.64651687 | M32: 0.47702744 | N32: 0.018180432 | Q32: 2.8783506 | R32: 47.130043 | S32: 0.21326179 | T32: 0.097294119
H33: cchem | I33: 0.18568323 | K33: 0.35864543 | L33: 1.7924011 | M33: 1.6530691 | N33: 0.12665633 | Q33: 10.419351 | R33: 48.799724 | S33: 0.73493333 | T33: 0.33715858
H34: cnmet | I34: 0.012280095 | K34: 0.14931843 | L34: 0.11853982 | M34: 0.13006002 | N34: 0.0079594718 | Q34: 4.1098642 | R34: 83.19572 | S34: 0.17947849 | T34: 0.026526934
H35: cmetl | I35: 0.029504287 | K35: 0.40363228 | L35: 0.28480501 | M35: 0.24032248 | N35: 0.038321644 | Q35: 11.285239 | R35: 87.917668 | S35: 0.45910257 | T35: 0.049015971
H36: cmach | I36: 0.0062444288 | K36: 1.4378297 | L36: 0.0602775 | M36: 0.099632821 | N36: 0.0063812819 | Q36: 35.374966 | R36: 98.183687 | S36: 1.4644283 | T36: 0.020321027
H37: coman | I37: 0.035205294 | K37: 0.10879408 | L37: 0.33983687 | M37: 0.52745383 | N37: 0.091219985 | Q37: 2.7020852 | R37: 44.536784 | S37: 0.24427915 | T37: 0.10757904
H38: celec | I38: 0.16176708 | L38: 1.5615384 | M38: 1.628627 | N38: 0.012196752 | S38: 0.36428577 | T38: 0.33217341
H39: cwatr | I39: 0.17564306 | L39: 1.6954833 | M39: 1.1129636 | N39: 0.041385104 | S39: 0.24981394 | T39: 0.22699912
H40: ccons | I40: 0.35294432 | L40: 3.4069732 | M40: 10.725134 | N40: 0.86321855 | S40: 2.1874894 | T40: 2.1874894
H41: ctrad | I41: 1.3930216 | L41: 13.446844 | M41: 11.190746 | N41: 4.217927 | S41: 2.2824552 | T41: 2.2824552
H42: ctran | I42: 0.50757573 | K42: 0.081361037 | L42: 4.8996309 | M42: 5.9593731 | N42: 0.48649242 | Q42: 2.7001301 | R42: 6.2738409 | S42: 1.2968298 | T42: 1.2154688
H43: chotl | I43: 0.078186566 | J43: 0.024813824 | L43: 0.75473528 | M43: 0.70947162 | N43: 0.39524217 | O43: 2.4566729 | P43: 17.148078 | S43: 0.11988941 | T43: 0.14470324
H44: crest | I44: 0.078466067 | L44: 0.7574333 | M44: 1.1362662 | N44: 0.46121995 | S44: 0.23175191 | T44: 0.23175191
H45: ccomm | I45: 0.6244941 | J45: 0.023819013 | L45: 6.0282444 | M45: 4.4769068 | N45: 0.30600837 | O45: 2.3581824 | P45: 2.6085699 | S45: 0.88928716 | T45: 0.91310618
H46: cfsrv | I46: 0.59146768 | L46: 5.7094402 | M46: 4.5242907 | N46: 0.092424909 | S46: 0.92277056 | T46: 0.92277056
H47: creal | I47: 0.73690858 | L47: 7.1133819 | M47: 5.2354355 | N47: 0.20806565 | S47: 1.067815 | T47: 1.067815
H48: cbsrv | I48: 0.15728368 | K48: 0.061324279 | L48: 1.5182601 | M48: 2.3692784 | N48: 0.055806771 | Q48: 2.0351699 | R48: 11.261246 | S48: 0.54456033 | T48: 0.48323605
H49: cpadm | I49: 0.30247695 | K49: 0.021940313 | L49: 2.9198114 | M49: 2.5727421 | N49: 0.39344018 | Q49: 0.72813354 | R49: 4.0134132 | S49: 0.54667465 | T49: 0.52473434
H50: ceduc | I50: 0.31666869 | K50: 0.040108297 | L50: 3.0568043 | M50: 4.1344821 | N50: 0.48850649 | Q50: 1.3310747 | R50: 4.5403539 | S50: 0.88337381 | T50: 0.84326551
H51: cheal | I51: 0.78873454 | L51: 7.6136581 | M51: 6.0065922 | N51: 1.3396232 | S51: 1.2250995 | T51: 1.2250995
H52: cosrv | I52: 0.20718157 | K52: 0.020840143 | L52: 1.9999246 | M52: 1.4608819 | N52: 2.1804915 | Q52: 0.69162219 | R52: 6.5370507 | S52: 0.31880039 | T52: 0.29796025
H53: TOTAL-1 | L53: 100 | M53: 100 | N53: 100 | O53: 100 | P53: 4.0019205 | Q53: 100 | R53: 15.374537

Sheet SAM
A1: Nexus Social Accounting Matrix
A2: Instruction | B2: Do not alter this sheet. This data is exported from x1aggregate.gms and x1aggregate.xlsx files, which aggregates the original SAM into the standard Nexus SAM structure.
B5: =B105/SUM(B101:B109) -> 0.43618734 | C5: =C105/SUM(C101:C109) -> 0.48406848 | D5: =D105/SUM(D101:D109) -> 0.44663715 | E5: =E105/SUM(E101:E109) -> 0.38977911 | F5: =F105/SUM(F101:F109) -> 0.40192869 | G5: =G105/SUM(G101:G109) -> 0.2157556 | H5: =H105/SUM(H101:H109) -> 0.30448031 | I5: =I105/SUM(I101:I109) -> 0.44286862 | J5: =SUM(B105:I105)/SUM(B101:I109) -> 0.40878364
B7: acere | C7: apuls | D7: aoils | E7: aroot | F7: avege | G7: abecr | H7: aocrp | I7: afrui | J7: alive | K7: amilk | L7: afore | M7: afish | N7: amine | O7: amino | P7: ameat | Q7: afsea | R7: afveg | S7: afoil | T7: adair | U7: agmll | V7: afobe | W7: aoapr | X7: atext | Y7: awood | Z7: apetr | AA7: afert | AB7: achem | AC7: anmet | AD7: ametl | AE7: amach | AF7: aoman | AG7: aelec | AH7: awatr | AI7: acons | AJ7: atrad | AK7: atran | AL7: ahotl | AM7: arest | AN7: acomm | AO7: afsrv | AP7: areal | AQ7: absrv | AR7: apadm | AS7: aeduc | AT7: aheal | AU7: aosrv | AV7: ccere | AW7: cpuls | AX7: coils | AY7: croot | AZ7: cvege | BA7: cbecr | BB7: cocrp | BC7: cfrui | BD7: clive | BE7: cmilk | BF7: cfore | BG7: cfish | BH7: cmine | BI7: cmino | BJ7: cmeat | BK7: cfsea | BL7: cfveg | BM7: cfoil | BN7: cdair | BO7: cgmll | BP7: cfobe | BQ7: coapr | BR7: ctext | BS7: cwood | BT7: cpetr | BU7: cfert | BV7: cchem | BW7: cnmet | BX7: cmetl | BY7: cmach | BZ7: coman | CA7: celec | CB7: cwatr | CC7: ccons | CD7: ctrad | CE7: ctran | CF7: chotl | CG7: crest | CH7: ccomm | CI7: cfsrv | CJ7: creal | CK7: cbsrv | CL7: cpadm | CM7: ceduc | CN7: cheal | CO7: cosrv | CP7: trc | CQ7: flab-n | CR7: flab-p | CS7: flab-s | CT7: flab-t | CU7: flnd | CV7: fcap-c | CW7: fcap-l | CX7: fcap-m | CY7: fcap-o | CZ7: ent | DA7: hhd-f1 | DB7: hhd-f2 | DC7: hhd-f3 | DD7: hhd-f4 | DE7: hhd-f5 | DF7: hhd-n1 | DG7: hhd-n2 | DH7: hhd-n3 | DI7: hhd-n4 | DJ7: hhd-n5 | DK7: hhd-u1 | DL7: hhd-u2 | DM7: hhd-u3 | DN7: hhd-u4 | DO7: hhd-u5 | DP7: gov | DQ7: dtax | DR7: mtax | DS7: stax | DT7: s-i | DU7: row | DV7: total
A8: acere | AV8: 624.2428 | DA8: 12.140448 | DB8: 19.572699 | DC8: 28.176981 | DD8: 31.430103 | DE8: 37.282055 | DK8: 0.04464363 | DL8: 0.099577616 | DM8: 0.59405598 | DN8: 1.4758956 | DO8: 4.0334632 | DV8: 759.09272
A9: apuls | AW9: 161.65023 | DA9: 2.1351119 | DB9: 4.2280476 | DC9: 5.7866884 | DD9: 7.3859267 | DE9: 9.9569551 | DM9: 0.012187296 | DN9: 0.36409442 | DO9: 0.52003646 | DV9: 192.03928
A10: aoils | AX10: 125.96792 | DA10: 1.0250403 | DB10: 2.3928904 | DC10: 4.9304051 | DD10: 9.8028385 | DE10: 13.308043 | DM10: 0.036369854 | DN10: 0.29373515 | DO10: 0.95598236 | DV10: 158.71322
A11: aroot | AY11: 142.52396 | DA11: 4.7708805 | DB11: 6.9207493 | DC11: 10.486407 | DD11: 17.749953 | DE11: 21.441577 | DK11: 0.0047318941 | DL11: 0.068042602 | DM11: 0.19389883 | DN11: 0.30654053 | DO11: 0.52981221 | DV11: 204.99655
A12: avege | AZ12: 223.33712 | DA12: 10.699985 | DB12: 15.204556 | DC12: 18.111845 | DD12: 20.104999 | DE12: 17.775067 | DK12: 0.1127455 | DL12: 0.20580061 | DM12: 0.3600205 | DN12: 0.63307972 | DO12: 1.1022016 | DV12: 307.64742
A13: abecr | BA13: 146.64982 | DA13: 0.29836823 | DB13: 0.63195932 | DC13: 0.86190453 | DD13: 1.6289018 | DE13: 5.3411283 | DM13: 0.014637914 | DN13: 0.032223984 | DO13: 0.86081409 | DV13: 156.31976
A14: aocrp | BB14: 223.20082 | DB14: 0.0032235539 | DD14: 0.0013444636 | DE14: 0.0097687794 | DO14: 0.037270125 | DV14: 223.25242
A15: afrui | BC15: 82.644538 | DA15: 1.519495 | DB15: 2.1157104 | DC15: 4.3588438 | DD15: 5.4665419 | DE15: 10.236394 | DL15: 0.030084525 | DM15: 0.072296234 | DN15: 0.22241168 | DO15: 1.5902418 | DV15: 108.25656
A16: alive | BD16: 252.18407 | DA16: 4.0306935 | DB16: 13.653222 | DC16: 22.757917 | DD16: 41.41015 | DE16: 88.914667 | DL16: 0.14509513 | DM16: 0.41375178 | DN16: 1.3006383 | DO16: 4.1338071 | DV16: 428.94401
A17: amilk | BE17: 24.992526 | DA17: 0.0043846467 | DB17: 0.11092434 | DC17: 0.36478232 | DD17: 0.85900255 | DE17: 1.8604905 | DO17: 0.14397703 | DV17: 28.336088
A18: afore | BF18: 21.093185 | DA18: 0.0063761334 | DB18: 0.0080537677 | DC18: 0.0084267673 | DD18: 0.01577628 | DE18: 0.013916296 | DK18: 0.00013595168 | DL18: 0.0003936995 | DM18: 0.00033621259 | DN18: 0.00071868226 | DO18: 0.012363638 | DV18: 21.159683
A19: afish | BG19: 188.18741 | DA19: 0.2037645 | DB19: 0.2729338 | DC19: 0.34692581 | DD19: 1.0521477 | DE19: 1.588914 | DO19: 0.29698475 | DV19: 191.94908
A20: amine | BH20: 57.022282 | DV20: 57.022282
A21: amino | BI21: 42.533047 | DV21: 42.533047
A22: ameat | BJ22: 301.35167 | DV22: 301.35167
A23: afsea | BK23: 158.5463 | DV23: 158.5463
A24: afveg | BL24: 7.4439943 | DV24: 7.4439943
A25: afoil | BM25: 202.85396 | DV25: 202.85396
A26: adair | BN26: 16.655969 | DV26: 16.655969
A27: agmll | BO27: 584.5189 | DV27: 584.5189
A28: afobe | BP28: 334.34196 | DA28: 1.2761445 | DB28: 4.6227172 | DC28: 9.7417227 | DD28: 14.193873 | DE28: 20.060219 | DK28: 0.0011066193 | DL28: 0.11586351 | DM28: 0.080437461 | DN28: 0.66150583 | DO28: 2.9421102 | DV28: 388.03766
A29: aoapr | BQ29: 380.49204 | DV29: 380.49204
A30: atext | BR30: 117.31781 | DV30: 117.31781
A31: awood | BS31: 62.909419 | DV31: 62.909419
A32: apetr | BT32: 13.263282 | DV32: 13.263282
A33: afert | BU33: 72.536657 | DV33: 72.536657
A34: achem | BV34: 251.36521 | DV34: 251.36521
A35: anmet | BW35: 19.77689 | DV35: 19.77689
A36: ametl | BX36: 36.543367 | DV36: 36.543367
A37: amach | BY37: 15.150138 | DV37: 15.150138
A38: aoman | BZ38: 80.204479 | DV38: 80.204479
A39: aelec | CA39: 247.64856 | DV39: 247.64856
A40: awatr | CB40: 169.23693 | DV40: 169.23693
A41: acons | CC41: 1630.8609 | DV41: 1630.8609
A42: atrad | CD42: 1701.6616 | DV42: 1701.6616
A43: atran | CE43: 906.18057 | DV43: 906.18057
A44: ahotl | CF44: 107.88205 | DV44: 107.88205
A45: arest | CG45: 172.78032 | DV45: 172.78032
A46: acomm | CH46: 680.75718 | DV46: 680.75718
A47: afsrv | CI47: 687.96236 | DV47: 687.96236
A48: areal | CJ48: 796.09883 | DV48: 796.09883
A49: absrv | CK49: 360.2718 | DV49: 360.2718
A50: apadm | CL50: 391.21044 | DV50: 391.21044
A51: aeduc | CM51: 628.68817 | DV51: 628.68817
A52: aheal | CN52: 913.3607 | DV52: 913.3607
A53: aosrv | CO53: 222.14128 | DV53: 222.14128
A54: ccere | B54: 104.64595 | J54: 135.00961 | M54: 28.698422 | U54: 336.62819 | V54: 13.768904 | W54: 27.468182 | AJ54: 0.003801903 | AM54: 6.5672282 | AR54: 29.528005 | DA54: 9.4518884 | DB54: 14.436058 | DC54: 20.620936 | DD54: 26.930026 | DE54: 33.02801 | DH54: 0.15782146 | DI54: 0.073144636 | DJ54: 0.073855782 | DK54: 0.0444873 | DL54: 0.099229025 | DM54: 0.59198112 | DN54: 1.4707574 | DO54: 4.011247 | DU54: 4.0744297 | DV54: 797.38216
A55: cpuls | C55: 21.200456 | V55: 2.2844962 | AJ55: 0.0038554306 | AM55: 3.9367192 | DA55: 5.5598562 | DB55: 7.6090995 | DC55: 12.352471 | DD55: 14.934001 | DE55: 20.387075 | DF55: 0.28401448 | DG55: 0.50052289 | DH55: 0.53489473 | DI55: 1.0898345 | DJ55: 2.4016358 | DK55: 0.23473101 | DL55: 0.91566514 | DM55: 2.2888402 | DN55: 4.9424846 | DO55: 20.131368 | DU55: 69.158518 | DV55: 190.75054
A56: coils | D56: 18.376569 | R56: 0.0035846876 | S56: 0.085776399 | U56: 4.2523375e-05 | V56: 5.7638802 | W56: 5.1901325 | AJ56: 0.0070824252 | DA56: 0.86159658 | DB56: 0.98152285 | DC56: 1.8291439 | DD56: 3.5050147 | DE56: 4.8155546 | DF56: 0.067330413 | DG56: 0.22601209 | DH56: 0.078526105 | DI56: 0.28195481 | DJ56: 0.78178909 | DK56: 0.0099749869 | DL56: 0.039744862 | DM56: 0.1617382 | DN56: 0.76288805 | DO56: 4.1145221 | DU56: 94.891079 | DV56: 142.83546
A57: croot | E57: 17.456134 | U57: 24.168049 | AM57: 4.5327056 | DA57: 6.9201627 | DB57: 9.9414043 | DC57: 17.256105 | DD57: 21.555647 | DE57: 31.573073 | DF57: 0.41300977 | DG57: 0.71890686 | DH57: 1.1186992 | DI57: 1.6732064 | DJ57: 4.5828004 | DK57: 0.42844761 | DL57: 1.2323838 | DM57: 3.8903458 | DN57: 8.7159644 | DO57: 35.709952 | DU57: 0.014173279 | DV57: 191.90117
A58: cvege | F58: 3.5273804 | R58: 4.1805752e-05 | S58: 0.0010002179 | AJ58: 0.00033433836 | AM58: 1.1347068 | DA58: 19.095827 | DB58: 21.570688 | DC58: 29.597975 | DD58: 37.162078 | DE58: 48.698997 | DF58: 1.5842793 | DG58: 1.7113814 | DH58: 1.7125681 | DI58: 3.5519799 | DJ58: 7.4982402 | DK58: 0.99223788 | DL58: 2.7997023 | DM58: 6.6352447 | DN58: 13.883716 | DO58: 62.427713 | DU58: 1.1177648 | DV58: 264.70386
A59: cbecr | G59: 47.180433 | L59: 0.0035139945 | V59: 63.402666 | DA59: 1.2685761 | DB59: 2.0964201 | DC59: 3.3600055 | DD59: 4.906249 | DE59: 6.4692772 | DF59: 0.074237826 | DG59: 0.10550231 | DH59: 0.16234328 | DI59: 0.28730759 | DJ59: 0.59667103 | DK59: 0.0031834416 | DL59: 0.18131101 | DM59: 0.37970592 | DN59: 0.79544789 | DO59: 3.1581508 | DU59: 40.826709 | DV59: 175.25771
A60: cocrp | H60: 48.40907 | R60: 0.0026548666 | S60: 0.063534858 | W60: 80.48795 | AS60: 0.03362534 | AT60: 0.32354167 | AU60: 0.01240348 | DA60: 0.023601675 | DB60: 0.013245753 | DC60: 0.01483675 | DD60: 0.057165077 | DE60: 1.0500209 | DI60: 0.0062314731 | DJ60: 1.7067611 | DK60: 0.00096742917 | DL60: 0.0030095492 | DM60: 0.017737217 | DN60: 0.11223611 | DO60: 4.0302096 | DU60: 137.08738 | DV60: 273.45618
A61: cfrui | I61: 4.12429 | P61: 0.004277608 | Q61: 0.001647177 | AJ61: 0.0036603567 | DA61: 3.4216047 | DB61: 4.4876461 | DC61: 7.9930535 | DD61: 11.026834 | DE61: 19.70675 | DF61: 0.23478604 | DG61: 0.38080399 | DH61: 0.41844142 | DI61: 0.90956315 | DJ61: 2.6428677 | DK61: 0.09806857 | DL61: 0.55295502 | DM61: 1.5258339 | DN61: 3.5669004 | DO61: 25.343375 | DU61: 15.627885 | DV61: 102.07124
A62: clive | P62: 209.46757 | Q62: 0.79412006 | U62: 0.099431324 | V62: 1.9857923e-05 | AM62: 0.56732261 | DA62: 1.4891142 | DB62: 2.4682919 | DC62: 5.6706408 | DD62: 8.2130429 | DE62: 14.741519 | DF62: 0.091251896 | DG62: 0.1887692 | DH62: 0.24639609 | DI62: 0.97337436 | DJ62: 2.7750112 | DK62: 0.10685371 | DL62: 0.5673066 | DM62: 1.3010134 | DN62: 4.2323608 | DO62: 23.049928 | DT62: 1.6819005 | DU62: 0.46835271 | DV62: 279.19359
A63: cmilk | T63: 2.6112939 | AM63: 1.1300409 | DA63: 0.060573622 | DB63: 0.30495919 | DC63: 0.52315584 | DD63: 2.0424825 | DE63: 5.5159526 | DF63: 0.0051083497 | DG63: 0.013671824 | DH63: 0.018013853 | DI63: 0.25872091 | DJ63: 0.99560914 | DK63: 0.018629473 | DL63: 0.11931937 | DM63: 0.44083784 | DN63: 0.91420428 | DO63: 11.075584 | DV63: 26.048157
A64: cfore | X64: 0.079031739 | Y64: 7.2637417 | AJ64: 1.2246149e-05 | AM64: 0.8456399 | DA64: 1.0148704 | DB64: 1.235433 | DC64: 1.9274373 | DD64: 2.2495332 | DE64: 3.2215353 | DF64: 0.058332032 | DG64: 0.077340307 | DH64: 0.071044593 | DI64: 0.14248983 | DJ64: 0.26533396 | DK64: 0.029871011 | DL64: 0.094022062 | DM64: 0.24126497 | DN64: 0.47161601 | DO64: 1.9316894 | DU64: 0.10324153 | DV64: 21.323481
A65: cfish | M65: 33.080845 | Q65: 83.780749 | AM65: 2.2611991 | DA65: 1.5775454 | DB65: 3.2646116 | DC65: 4.9660069 | DD65: 9.215608 | DE65: 18.109645 | DF65: 0.30237967 | DG65: 0.34751716 | DH65: 0.74254484 | DI65: 1.0912863 | DJ65: 3.8581319 | DK65: 0.065324699 | DL65: 0.46282446 | DM65: 0.82562256 | DN65: 2.9358833 | DO65: 23.13402 | DU65: 0.62524802 | DV65: 190.64699
A66: cmine | R66: 0.002161754 | S66: 0.051740079 | V66: 0.0028223937 | AG66: 61.362355 | DV66: 61.41908
A67: cmino | N67: 24.260322 | O67: 6.4682468 | V67: 0.15850506 | X67: 0.032943261 | AD67: 2.6122302 | DU67: 18.169574 | DV67: 51.701821
A68: cmeat | P68: 11.183564 | X68: 0.77775589 | AM68: 3.9557798 | DA68: 3.2526125 | DB68: 9.9964334 | DC68: 21.417436 | DD68: 36.094384 | DE68: 96.683575 | DF68: 0.28997288 | DG68: 1.0524676 | DH68: 1.780801 | DI68: 3.1330229 | DJ68: 16.356244 | DK68: 0.18300376 | DL68: 1.2575782 | DM68: 3.1411349 | DN68: 15.259144 | DO68: 140.16219 | DU68: 0.12430035 | DV68: 366.1014
A69: cfsea | DA69: 10.538102 | DB69: 13.705524 | DC69: 22.982466 | DD69: 32.267527 | DE69: 48.617702 | DF69: 0.8001657 | DG69: 1.141625 | DH69: 1.3233745 | DI69: 2.3458752 | DJ69: 4.9477932 | DK69: 0.77383868 | DL69: 1.9450165 | DM69: 5.2344278 | DN69: 10.961698 | DO69: 49.564839 | DU69: 0.078246659 | DV69: 207.22822
A70: cfveg | R70: 0.00010431331 | S70: 0.002495891 | V70: 0.043908501 | AM70: 1.1683558 | DA70: 0.23728767 | DB70: 0.32707566 | DC70: 0.20863638 | DD70: 0.33412335 | DE70: 2.4105893 | DF70: 0.014157642 | DG70: 0.015260163 | DH70: 0.035486149 | DI70: 0.028796383 | DJ70: 0.96580591 | DK70: 0.01714174 | DL70: 0.016489946 | DM70: 0.012166767 | DN70: 0.065370063 | DO70: 1.7303088 | DU70: 5.6615942 | DV70: 13.295155
A71: cfoil | R71: 0.0055251802 | S71: 0.13220497 | V71: 0.34174807 | Z71: 8.2549348 | AJ71: 0.0055664507 | AM71: 0.56772534 | DA71: 3.4078449 | DB71: 6.6239769 | DC71: 11.68691 | DD71: 18.079478 | DE71: 41.181888 | DF71: 0.34445865 | DG71: 0.41679511 | DH71: 0.78160039 | DI71: 1.4632952 | DJ71: 23.745714 | DK71: 0.25523139 | DL71: 1.0199752 | DM71: 3.0788861 | DN71: 7.3463393 | DO71: 171.98465 | DU71: 0.92601774 | DV71: 301.65077
A72: cdair | T72: 0.0065945616 | U72: 0.00011676691 | V72: 1.3738088 | AM72: 4.1726152 | DA72: 0.050109123 | DB72: 0.39566731 | DC72: 0.7634997 | DD72: 2.062065 | DE72: 5.9950542 | DF72: 0.023884672 | DG72: 0.0044954854 | DH72: 0.079961656 | DI72: 0.18347938 | DJ72: 1.3955733 | DK72: 0.10095267 | DL72: 0.034621334 | DM72: 0.25340008 | DN72: 0.99379719 | DO72: 10.168249 | DU72: 0.13871815 | DV72: 28.196664
A73: cgmll | M73: 0.49817493 | U73: 31.561346 | V73: 60.804707 | W73: 24.789772 | AJ73: 0.00022055376 | AM73: 4.8562165 | DA73: 50.301185 | DB73: 54.638784 | DC73: 69.942479 | DD73: 74.652602 | DE73: 89.707608 | DF73: 3.8669753 | DG73: 4.0642792 | DH73: 5.2447279 | DI73: 8.2160445 | DJ73: 17.667663 | DK73: 2.1878396 | DL73: 6.8477269 | DM73: 15.753387 | DN73: 29.738234 | DO73: 140.53301 | DU73: 4.9231527 | DV73: 700.79613
A74: cfobe | G74: 0.028862947 | R74: 0.00039113787 | S74: 0.0093582334 | T74: 8.7417819e-05 | U74: 0.001262945 | V74: 25.7588 | W74: 18.423662 | Z74: 2.4439888e-05 | AB74: 0.00028590875 | AJ74: 0.014576423 | AK74: 19.698275 | AM74: 20.626306 | DA74: 8.7908458 | DB74: 14.097708 | DC74: 24.016985 | DD74: 42.321774 | DE74: 83.645609 | DF74: 0.82375465 | DG74: 0.91759074 | DH74: 1.6243902 | DI74: 3.7870227 | DJ74: 15.146439 | DK74: 0.54547106 | DL74: 2.3568859 | DM74: 7.1050478 | DN74: 19.000322 | DO74: 154.6929 | DU74: 91.877897 | DV74: 555.31254
A75: coapr | J75: 160.41318 | K75: 12.921229 | M75: 1.199852 | U75: 14.345205 | X75: 13.366099 | AR75: 0.015945982 | DA75: 5.5567058 | DB75: 4.0979836 | DC75: 6.0905517 | DD75: 11.82907 | DE75: 13.656472 | DF75: 0.22528807 | DG75: 0.097219674 | DH75: 0.39394379 | DI75: 1.6864862 | DJ75: 2.906917 | DK75: 0.61002652 | DL75: 0.58599203 | DM75: 0.57745494 | DN75: 1.6468489 | DO75: 16.174769 | DU75: 295.61786 | DV75: 564.0151
A76: ctext | C76: 0.097124868 | D76: 0.08150946 | E76: 0.90974806 | G76: 0.012583684 | X76: 33.872862 | AE76: 0.10627914 | AF76: 0.35324374 | AL76: 9.6056657 | AQ76: 0.001357778 | AR76: 4.2507011 | AS76: 0.10078331 | AT76: 0.10397746 | AU76: 0.0074397081 | DA76: 4.855713 | DB76: 7.1776645 | DC76: 12.551015 | DD76: 18.028446 | DE76: 32.965974 | DF76: 0.30547387 | DG76: 0.40604317 | DH76: 0.48454834 | DI76: 1.2733875 | DJ76: 5.6114082 | DK76: 0.13505419 | DL76: 0.81923195 | DM76: 1.9218995 | DN76: 5.9719435 | DO76: 49.783177 | DU76: 40.380082 | DV76: 232.17434
A77: cwood | G77: 0.013597347 | L77: 0.00011824972 | M77: 0.02490777 | T77: 0.0050482674 | W77: 0.13909248 | X77: 0.2184338 | Y77: 0.067496344 | AA77: 0.46986866 | AE77: 0.58779985 | AF77: 2.9763674 | AH77: 0.077455031 | AI77: 82.168706 | AJ77: 39.275792 | AK77: 30.152599 | AL77: 7.2080853 | AN77: 8.0438054 | AO77: 13.189778 | AQ77: 4.096497 | AR77: 3.3485106 | AS77: 18.778108 | AT77: 14.751723 | AU77: 0.97052437 | DA77: 2.286448 | DB77: 2.4520964 | DC77: 3.2540283 | DD77: 3.7393054 | DE77: 5.6985687 | DF77: 0.10864194 | DG77: 0.12884055 | DH77: 0.15138155 | DI77: 0.1797735 | DJ77: 0.71631271 | DK77: 0.11655347 | DL77: 0.28603414 | DM77: 0.63437856 | DN77: 1.5612587 | DO77: 15.451157 | DU77: 1.9164371 | DV77: 265.24553
A78: cpetr | G78: 0.22252637 | L78: 0.0091003343 | M78: 2.6025798 | N78: 1.0526666 | O78: 0.33372904 | P78: 1.6478745 | Q78: 0.63559148 | R78: 0.048757891 | S78: 1.1665079 | T78: 0.00057431176 | V78: 0.70933229 | W78: 0.7261261 | X78: 0.58367299 | Y78: 1.3180059 | Z78: 0.0091171288 | AA78: 0.47237528 | AB78: 0.31415457 | AC78: 0.27874839 | AD78: 0.20462053 | AE78: 0.28566458 | AF78: 1.2618956 | AG78: 19.861136 | AH78: 1.6799848 | AI78: 47.033203 | AJ78: 20.164591 | AK78: 313.52001 | AL78: 0.58059122 | AM78: 0.28580121 | AN78: 3.8296635 | AO78: 0.35551354 | AP78: 0.37120299 | AQ78: 16.79751 | AR78: 6.4040264 | AS78: 3.5052684 | AT78: 2.2038771 | AU78: 2.0526226 | DA78: 0.017611274 | DB78: 0.061314015 | DC78: 0.41619436 | DD78: 1.211869 | DE78: 7.3660141 | DI78: 0.053840049 | DJ78: 1.566179 | DK78: 0.011022106 | DM78: 0.012492767 | DN78: 0.038097643 | DO78: 30.060321 | DV78: 493.34358
A79: cfert | B79: 144.86402 | C79: 0.0072185393 | D79: 0.0058936895 | E79: 0.013609244 | F79: 0.022074714 | G79: 2.8907633 | H79: 11.165331 | I79: 0.026292322 | DV79: 158.9952
A80: cchem | B80: 0.16457953 | F80: 4.2132217 | G80: 4.4284022 | H80: 0.88519163 | I80: 4.9742731 | J80: 2.2707078 | K80: 0.21126381 | M80: 0.39840988 | N80: 1.1234532 | O80: 0.35644135 | P80: 0.00041157779 | Q80: 0.00015848559 | T80: 0.0136206 | U80: 0.00018859689 | V80: 6.0709893 | W80: 1.4795374 | X80: 1.1983498 | Y80: 1.8295061 | Z80: 1.8264973e-05 | AA80: 1.0464189 | AB80: 101.87526 | AC80: 3.6825206 | AD80: 0.088914983 | AE80: 0.30763153 | AF80: 0.18655588 | AG80: 17.280104 | AH80: 29.141762 | AI80: 238.08039 | AJ80: 0.74666476 | AN80: 4.0320263 | AO80: 0.17186222 | AQ80: 0.14442366 | AR80: 10.061346 | AS80: 0.058733819 | AT80: 10.307766 | AU80: 0.0072887404 | DA80: 7.0099682 | DB80: 9.0761263 | DC80: 13.280896 | DD80: 16.576823 | DE80: 23.929792 | DF80: 0.49887197 | DG80: 0.54082842 | DH80: 0.6491327 | DI80: 1.3295846 | DJ80: 3.8207364 | DK80: 0.39098045 | DL80: 1.2076607 | DM80: 3.253654 | DN80: 6.4706063 | DO80: 34.992713 | DU80: 60.105418 | DV80: 629.97218
A81: cnmet | V81: 2.4762621 | X81: 0.00010398251 | AC81: 2.5602935 | AI81: 116.34647 | AJ81: 0.65281748 | AO81: 0.085941522 | DA81: 0.19559062 | DB81: 0.38780936 | DC81: 0.69195543 | DD81: 1.8554826 | DE81: 7.1490982 | DF81: 0.012319355 | DG81: 0.01204633 | DH81: 0.037841826 | DI81: 0.12067501 | DJ81: 0.66972961 | DK81: 0.014068479 | DL81: 0.0321892 | DM81: 0.28901924 | DN81: 0.72638053 | DO81: 13.54004 | DV81: 147.85613
A82: cmetl | G82: 1.3351339 | W82: 0.57362422 | X82: 1.1175198 | AA82: 1.6667536 | AD82: 4.3897792 | AE82: 3.9632953 | AF82: 21.973014 | AI82: 300.84604 | AJ82: 0.00019587666 | AO82: 0.085919458 | DA82: 0.20705245 | DB82: 0.31867195 | DC82: 0.54792762 | DD82: 0.82344139 | DE82: 1.5106143 | DF82: 0.015875288 | DG82: 0.015138809 | DH82: 0.020383246 | DI82: 0.049175292 | DJ82: 0.66149005 | DK82: 0.01548495 | DL82: 0.0096130884 | DM82: 0.046858799 | DN82: 0.10299575 | DO82: 3.1429152 | DT82: 24.096753 | DU82: 16.28718 | DV82: 383.82285
A83: cmach | B83: 1.1138348e-05 | F83: 0.0049404387 | G83: 0.0032240154 | H83: 0.00030583259 | I83: 0.0057430207 | M83: 11.194203 | T83: 3.4685319e-06 | V83: 0.00087610442 | W83: 1.7996082 | X83: 3.722772 | AA83: 8.8265695 | AD83: 3.4227659 | AE83: 1.5322084 | AF83: 14.554273 | AG83: 22.098522 | AI83: 117.52063 | AJ83: 13.564523 | AN83: 74.756637 | AO83: 26.015955 | AP83: 2.1583933 | AR83: 0.17423764 | AS83: 0.00011872233 | AT83: 0.0098554214 | AU83: 0.00026165923 | DA83: 0.39717791 | DB83: 0.8573226 | DC83: 1.2284779 | DD83: 2.6850068 | DE83: 21.327526 | DF83: 0.017763396 | DG83: 0.029170315 | DH83: 0.031182088 | DI83: 0.67945789 | DJ83: 1.9469788 | DK83: 0.0079529581 | DL83: 0.062449494 | DM83: 0.31815528 | DN83: 0.82754139 | DO83: 47.867727 | DT83: 751.80035 | DV83: 1131.4509
A84: coman | M84: 0.28712428 | P84: 0.0037484838 | Q84: 0.0014434323 | T84: 8.8826894e-05 | V84: 0.085718939 | X84: 3.5732084 | AD84: 0.012796722 | AF84: 0.33596203 | AH84: 0.013166214 | AI84: 70.33159 | AJ84: 4.0719405 | AK84: 17.994251 | AL84: 10.484805 | AN84: 3.9998802 | AO84: 3.0960147 | AP84: 3.691891 | AQ84: 0.31158936 | AR84: 9.5606259 | AS84: 2.9295429 | AT84: 3.3531634 | AU84: 8.4561433 | DA84: 0.080696178 | DB84: 0.15433482 | DC84: 0.35715228 | DD84: 0.93448944 | DE84: 3.1009563 | DF84: 0.0046446596 | DG84: 0.024103754 | DH84: 0.013179633 | DI84: 0.061507 | DJ84: 1.1179643 | DK84: 0.0034265439 | DL84: 0.046655941 | DM84: 0.23567333 | DN84: 0.4358154 | DO84: 6.3984279 | DT84: 61.121725 | DV84: 216.68545
A85: celec | B85: 0.66268688 | G85: 10.986708 | H85: 1.727608 | J85: 0.5861555 | L85: 5.6706877 | N85: 0.14103441 | O85: 0.044449511 | P85: 0.22451546 | Q85: 0.086429657 | R85: 0.29548683 | S85: 7.2458882 | T85: 0.78946609 | U85: 2.1632042 | V85: 1.5059045 | W85: 0.50090047 | X85: 3.7239852 | Y85: 0.56855991 | Z85: 0.0064303229 | AA85: 0.053480362 | AB85: 0.6248134 | AC85: 0.24157802 | AD85: 0.18630548 | AE85: 0.29912945 | AG85: 0.068186372 | AH85: 3.9869369 | AI85: 4.1490929 | AJ85: 86.063065 | AK85: 30.311978 | AL85: 1.4634951 | AM85: 0.58260004 | AN85: 1.647255 | AO85: 20.014425 | AP85: 1.2363317 | AQ85: 6.1021975 | AR85: 1.4477597 | AS85: 3.3483252 | AT85: 6.1036925 | AU85: 1.0937102 | DA85: 0.11827481 | DB85: 0.64201083 | DC85: 1.2855901 | DD85: 2.8911462 | DE85: 15.013949 | DF85: 0.053730338 | DG85: 0.10380059 | DH85: 0.14181316 | DI85: 0.51825952 | DJ85: 5.2384899 | DK85: 0.0075720891 | DL85: 0.55543386 | DM85: 1.6469833 | DN85: 6.2540936 | DO85: 84.496598 | DV85: 324.9222
A86: cwatr | G86: 4.7712884 | H86: 3.4424064 | L86: 4.5663218 | N86: 0.051977568 | O86: 0.016378324 | P86: 0.0035666885 | Q86: 0.0013734173 | R86: 0.13349519 | S86: 3.2135593 | T86: 0.71471062 | U86: 2.1010255 | V86: 0.80227331 | W86: 0.18289978 | X86: 2.1004737 | Y86: 0.28698493 | Z86: 0.0094965073 | AA86: 0.83838519 | AB86: 0.20438653 | AC86: 0.10054283 | AD86: 0.050791682 | AE86: 0.14411713 | AG86: 4.0497497 | AH86: 0.52291803 | AI86: 5.416796 | AJ86: 45.564521 | AK86: 52.326176 | AL86: 0.66877807 | AM86: 0.3003824 | AN86: 1.0284371 | AO86: 6.5202615 | AP86: 0.42749047 | AQ86: 2.9026399 | AR86: 1.837605 | AS86: 2.1853585 | AT86: 4.034967 | AU86: 0.4065023 | DA86: 0.8004495 | DB86: 1.2047217 | DC86: 1.6748493 | DD86: 2.1903182 | DE86: 5.4261029 | DF86: 0.053799607 | DG86: 0.16136867 | DH86: 0.18488292 | DI86: 0.5299118 | DJ86: 1.7791125 | DK86: 0.24678143 | DL86: 1.1575406 | DM86: 2.6683862 | DN86: 6.7179565 | DO86: 37.455172 | DV86: 214.18039
A87: ccons | W87: 0.35609169 | X87: 0.14867306 | AA87: 0.056384072 | AE87: 0.028314585 | AF87: 0.11283003 | DT87: 1630.1586 | DV87: 1630.8609
A88: ctrad | AH88: 0.035078423 | AI88: 0.068184561 | AJ88: 3.7794095 | AO88: 1.1124946 | AQ88: 0.10088976 | AR88: 3.0442045 | AS88: 1.1133699 | AT88: 3.3695834 | AU88: 0.71119224 | CP88: 1555.6357 | DA88: 0.99415772 | DB88: 2.0120665 | DC88: 4.2279116 | DD88: 5.901329 | DE88: 29.362261 | DF88: 0.037718707 | DG88: 0.10584539 | DH88: 0.019711379 | DI88: 0.24006027 | DJ88: 3.2481593 | DL88: 0.11499318 | DM88: 0.64253397 | DN88: 1.2308456 | DO88: 84.553908 | DV88: 1701.6616
A89: ctran | L89: 0.0039335446 | N89: 1.2893658 | O89: 0.40931634 | P89: 0.58502989 | Q89: 0.22539807 | R89: 1.0925767 | S89: 26.206158 | T89: 0.36600043 | U89: 49.139755 | V89: 9.8887241 | W89: 7.9457114 | Y89: 11.1731 | Z89: 0.15020009 | AB89: 3.63856 | AC89: 2.3326054 | AD89: 2.0213973 | AG89: 0.69875234 | AH89: 0.10089363 | AI89: 327.89984 | AJ89: 138.33974 | AK89: 15.418389 | AL89: 2.6035953 | AM89: 3.6459506 | AN89: 12.816932 | AO89: 53.324471 | AQ89: 0.00059742276 | AR89: 2.4530964 | AS89: 55.706915 | AT89: 69.289958 | AU89: 2.8158367 | DA89: 1.9459728 | DB89: 4.4172547 | DC89: 10.322869 | DD89: 19.629666 | DE89: 44.440275 | DF89: 0.14392488 | DG89: 0.23724643 | DH89: 0.71049175 | DI89: 1.7775488 | DJ89: 7.2947578 | DK89: 0.045003397 | DL89: 0.5854536 | DM89: 1.8987288 | DN89: 6.1927146 | DO89: 65.613782 | DU89: 18.780448 | DV89: 985.61893
A90: chotl | B90: 0.04448191 | C90: 0.0054015164 | D90: 0.0044083899 | E90: 0.010178021 | F90: 0.016506937 | G90: 0.012358263 | H90: 0.023600625 | I90: 0.019671172 | J90: 0.037410595 | K90: 0.0011993083 | M90: 0.00019247918 | P90: 0.40411473 | Q90: 0.15560431 | W90: 2.0168169 | X90: 6.021138 | AA90: 1.2159556 | AE90: 1.3396872 | AF90: 5.1939714 | AH90: 0.19425372 | AI90: 0.16447372 | AJ90: 2.628513 | AK90: 1.1569191 | AL90: 0.68456337 | AO90: 2.8382752 | AQ90: 0.42044196 | AR90: 19.407958 | AS90: 1.1593649 | AT90: 2.1990192 | AU90: 7.4859211 | DD90: 0.019685335 | DE90: 2.0368932 | DJ90: 0.32018129 | DO90: 32.143194 | DU90: 64.193715 | DV90: 153.57607
A91: crest | P91: 0.52565772 | Q91: 0.20233517 | W91: 2.2049688 | AJ91: 0.27410281 | AM91: 39.064517 | AO91: 0.42232899 | AS91: 28.926776 | AT91: 12.4883 | DA91: 2.2065795 | DB91: 4.4068486 | DC91: 7.6626882 | DD91: 11.176548 | DE91: 19.379873 | DF91: 0.26905942 | DG91: 0.38072817 | DH91: 0.52026791 | DI91: 1.0447785 | DJ91: 4.0946826 | DK91: 0.19078227 | DL91: 0.57992246 | DM91: 1.6874392 | DN91: 5.690933 | DO91: 29.066511 | DU91: 7.9396889 | DV91: 180.40632
A92: ccomm | B92: 0.47049102 | C92: 0.057466225 | D92: 0.046915775 | E92: 0.10832351 | F92: 0.1757409 | G92: 0.13151709 | H92: 0.27743059 | I92: 0.20943987 | J92: 0.39816169 | K92: 0.012782867 | L92: 0.00023653306 | M92: 0.0020468499 | P92: 1.4872405 | Q92: 0.57244775 | R92: 0.838499 | S92: 20.8911 | T92: 1.3827643 | U92: 11.068746 | V92: 5.5168133 | W92: 36.445209 | X92: 5.3377848 | Y92: 2.6874287 | Z92: 0.1017492 | AB92: 1.4735073 | AC92: 0.49094899 | AD92: 0.53330544 | AE92: 0.22343385 | AG92: 0.34391147 | AH92: 0.17387836 | AI92: 0.11942648 | AJ92: 58.807265 | AK92: 31.854151 | AL92: 5.4939566 | AM92: 1.8386758 | AN92: 48.76797 | AO92: 51.995886 | AP92: 5.3372186 | AQ92: 44.833555 | AR92: 2.4716192 | AS92: 25.816222 | AT92: 10.213411 | AU92: 1.8522967 | DA92: 3.7278748 | DB92: 7.9289465 | DC92: 14.747553 | DD92: 20.694823 | DE92: 57.769837 | DF92: 0.38232624 | DG92: 0.4584927 | DH92: 0.84179694 | DI92: 1.8907693 | DJ92: 10.762559 | DK92: 0.54734922 | DL92: 1.4883405 | DM92: 6.033612 | DN92: 16.043401 | DO92: 140.16358 | DU92: 36.678133 | DV92: 701.02036
A93: cfsrv | G93: 2.6925145 | H93: 18.921605 | K93: 0.43814375 | L93: 0.14531614 | M93: 1.0526382 | N93: 1.3339959 | O93: 0.42269862 | P93: 5.5393764 | Q93: 2.1298257 | R93: 1.2798511 | S93: 32.60614 | T93: 0.76529499 | U93: 4.1515466 | V93: 2.7299803 | W93: 3.8522939 | X93: 2.0724333 | Y93: 2.2496555 | Z93: 0.17555706 | AA93: 7.8318079 | AB93: 2.828858 | AC93: 0.37761136 | AD93: 0.54257583 | AE93: 0.36738565 | AF93: 1.5901571 | AG93: 0.049152875 | AH93: 0.043041133 | AI93: 41.384164 | AJ93: 101.09091 | AK93: 4.6758795 | AL93: 9.7459329 | AM93: 10.729087 | AN93: 25.672949 | AO93: 31.60955 | AP93: 225.41136 | AQ93: 52.731139 | AR93: 8.7356074 | AS93: 3.5146873 | AT93: 5.0500276 | AU93: 4.5886694 | DD93: 0.045452341 | DE93: 0.73785036 | DJ93: 0.051686962 | DM93: 0.0021524282 | DN93: 0.018527228 | DO93: 62.841711 | DU93: 30.280016 | DV93: 715.10681
A94: creal | L94: 0.0003800938 | P94: 3.7457664 | Q94: 1.4429549 | R94: 0.64933495 | S94: 15.874025 | T94: 0.87447187 | U94: 14.870332 | V94: 0.96283147 | X94: 2.7643076 | Z94: 0.0091987263 | AB94: 0.10762552 | AE94: 0.054461526 | AI94: 0.0085448908 | AJ94: 66.665895 | AM94: 0.69780036 | AN94: 13.740784 | AO94: 20.009063 | AQ94: 51.297543 | AR94: 13.966135 | AS94: 5.0654948 | AT94: 6.9755904 | AU94: 0.85343102 | DA94: 27.274212 | DB94: 33.200979 | DC94: 46.529317 | DD94: 55.687398 | DE94: 90.09504 | DF94: 1.9028314 | DG94: 2.1010684 | DH94: 2.5249546 | DI94: 4.8962667 | DJ94: 36.692997 | DK94: 1.7615528 | DL94: 4.2812342 | DM94: 12.315122 | DN94: 28.237301 | DO94: 232.56001 | DV94: 800.69626
A95: cbsrv | G95: 1.5961441 | H95: 0.21033505 | K95: 0.47814814 | N95: 0.46111485 | O95: 0.14564908 | P95: 2.3650357 | Q95: 0.91247177 | U95: 2.1952067 | V95: 3.271843 | W95: 32.728178 | X95: 0.4610981 | Y95: 2.309797 | Z95: 0.082984786 | AB95: 1.3188966 | AC95: 0.5567387 | AD95: 0.48125815 | AE95: 0.13174256 | AF95: 0.4975018 | AG95: 1.2205707 | AH95: 2.2160414 | AI95: 16.16441 | AJ95: 34.520282 | AK95: 10.36185 | AL95: 0.72447061 | AM95: 0.8133547 | AN95: 16.325886 | AO95: 9.304368 | AP95: 8.0701143 | AQ95: 63.002658 | AR95: 28.890634 | AS95: 24.59 | AT95: 53.522356 | AU95: 1.5069829 | DA95: 6.5524189 | DB95: 8.2543926 | DC95: 12.262 | DD95: 14.437756 | DE95: 18.039995 | DF95: 0.39465941 | DG95: 0.42258352 | DH95: 0.4533187 | DI95: 0.83346447 | DJ95: 1.5765648 | DK95: 0.25537592 | DL95: 0.71889008 | DM95: 1.6396805 | DN95: 3.6763039 | DO95: 15.035978 | DU95: 4.0619152 | DV95: 410.05342
A96: cpadm | AR96: 9.4289737 | DP96: 398.13885 | DU96: 5.2715533 | DV96: 412.83937
A97: ceduc | B97: 0.028489298 | C97: 0.0034807642 | D97: 0.0028419232 | E97: 0.0065624084 | F97: 0.010644445 | G97: 0.0079665475 | H97: 0.016980142 | I97: 0.012677684 | J97: 0.024121935 | K97: 0.00077441456 | M97: 0.00012398576 | W97: 0.13843234 | X97: 1.2381108 | AA97: 0.1100603 | AE97: 0.084522851 | AF97: 0.32725108 | AH97: 0.052473456 | AI97: 0.024809957 | AO97: 0.28226808 | AQ97: 0.17929695 | AR97: 9.3046151 | AS97: 194.24833 | AT97: 53.658453 | AU97: 4.9062053 | DA97: 2.35929 | DB97: 3.2785796 | DC97: 5.370859 | DD97: 7.5604533 | DE97: 25.238194 | DF97: 0.14595438 | DG97: 0.13876251 | DH97: 0.37270509 | DI97: 0.41691597 | DJ97: 2.5960128 | DK97: 0.15106604 | DL97: 0.5641632 | DM97: 1.6024095 | DN97: 5.155216 | DO97: 70.719728 | DP97: 268.2507 | DU97: 1.5077344 | DV97: 660.09824
A98: cheal | B98: 0.010465885 | C98: 0.001278745 | D98: 0.0010440558 | E98: 0.0024108842 | F98: 0.0039104888 | G98: 0.0029267164 | H98: 0.0062406116 | I98: 0.0046573229 | J98: 0.0088618084 | K98: 0.00028450342 | M98: 4.5549488e-05 | N98: 0.29395717 | O98: 0.092741974 | W98: 0.068122275 | X98: 0.17413017 | AA98: 0.015524293 | AE98: 0.011921708 | AF98: 0.04609548 | AJ98: 45.398062 | AO98: 2.1451478 | AR98: 1.0433417 | AS98: 4.2353553 | AT98: 62.039499 | AU98: 0.25624076 | DA98: 29.40248 | DB98: 43.601221 | DC98: 73.037068 | DD98: 94.530732 | DE98: 169.70769 | DF98: 3.3736464 | DG98: 4.8715921 | DH98: 3.6156026 | DI98: 6.8321807 | DJ98: 15.050768 | DK98: 1.1395705 | DL98: 1.868205 | DM98: 10.352497 | DN98: 18.044894 | DO98: 271.55239 | DP98: 53.764017 | DU98: 0.079468797 | DV98: 916.6863
A99: cosrv | J99: 0.28993598 | K99: 0.23878248 | L99: 0.00087416643 | M99: 0.11160678 | N99: 0.79509866 | O99: 0.25136829 | R99: 0.43514175 | S99: 10.609772 | T99: 0.17519767 | U99: 5.4919443 | V99: 1.0289654 | W99: 0.84411446 | X99: 0.16332416 | Y99: 0.95377024 | Z99: 0.0019997089 | AB99: 0.54459112 | AE99: 1.0270718 | AF99: 4.5484062 | AG99: 0.012288912 | AH99: 0.050113197 | AJ99: 1.4609301 | AK99: 0.29208449 | AL99: 0.32690018 | AN99: 0.50962301 | AO99: 4.4200279 | AQ99: 0.088193579 | AR99: 0.32682348 | AS99: 17.28261 | AT99: 5.3287887 | AU99: 29.695465 | DA99: 1.0029048 | DB99: 2.370662 | DC99: 4.2996077 | DD99: 7.4846753 | DE99: 32.448996 | DF99: 0.055878229 | DG99: 0.18630709 | DH99: 0.17847224 | DI99: 0.30720758 | DJ99: 3.783282 | DK99: 0.029825012 | DL99: 0.23672421 | DM99: 0.65046211 | DN99: 2.6440058 | DO99: 94.693619 | DU99: 4.5384873 | DV99: 242.21693
A100: trc | AV100: 137.19793 | AW100: 28.766655 | AX100: 15.838376 | AY100: 49.025304 | AZ100: 40.325527 | BA100: 28.175723 | BB100: 31.289063 | BC100: 17.349652 | BD100: 25.82382 | BE100: 1.0556309 | BF100: 0.049011435 | BG100: 0.15456675 | BH100: 1.2086569 | BI100: 1.235451 | BJ100: 63.336452 | BK100: 36.846072 | BL100: 0.75421897 | BM100: 40.546407 | BN100: 3.140427 | BO100: 99.115417 | BP100: 140.24355 | BQ100: 152.53109 | BR100: 47.172367 | BS100: 37.677407 | BT100: 85.92083 | BU100: 21.796945 | BV100: 56.977164 | BW100: 16.118794 | BX100: 39.826402 | BY100: 257.67492 | BZ100: 37.511461 | CA100: 23.941053 | CB100: 17.009361 | DV100: 1555.6357
A101: flab-n | B101: 155.70648 | C101: 15.97872 | D101: 13.809092 | E101: 50.743437 | F101: 61.248916 | G101: 10.062788 | H101: 18.302743 | I101: 20.613654 | J101: 12.018308 | K101: 1.3929358 | L101: 0.75190491 | M101: 5.928371 | N101: 2.7436948 | O101: 3.6931344 | P101: 1.9819532 | Q101: 2.0411481 | R101: 0.19380071 | S101: 6.0878631 | T101: 0.66687875 | U101: 4.1586529 | V101: 13.706674 | W101: 11.486123 | X101: 1.8031328 | Y101: 0.72169411 | Z101: 0.1314012 | AA101: 0.15114709 | AB101: 1.0529858 | AC101: 0.066172849 | AD101: 0.31859556 | AE101: 0.053052215 | AF101: 1.8103332 | AG101: 0.54435459 | AH101: 1.8470632 | AI101: 28.339224 | AJ101: 123.09826 | AK101: 7.1604119 | AL101: 3.2105824 | AM101: 3.7465249 | AN101: 4.5039674 | AO101: 3.7134819 | AP101: 3.9995128 | AQ101: 1.0727378 | AR101: 8.4898065 | AS101: 6.1094299 | AT101: 16.753787 | AU101: 14.321901 | DU101: 0.36721693 | DV101: 646.70406
A102: flab-p | B102: 60.805696 | C102: 53.292839 | D102: 46.056613 | E102: 38.514417 | F102: 66.93481 | G102: 23.280672 | H102: 40.607927 | I102: 21.432863 | J102: 12.480054 | K102: 1.3567859 | L102: 1.1079634 | M102: 25.957455 | N102: 5.9830875 | O102: 8.0535002 | P102: 6.1067344 | Q102: 6.2891239 | R102: 0.5971329 | S102: 18.75774 | T102: 2.0547667 | U102: 12.813516 | V102: 33.702812 | W102: 23.928874 | X102: 5.6285979 | Y102: 3.4475901 | Z102: 1.1298851 | AA102: 1.2996749 | AB102: 9.0543536 | AC102: 0.5690033 | AD102: 2.7395213 | AE102: 0.45618234 | AF102: 5.0833548 | AG102: 14.49727 | AH102: 49.191052 | AI102: 95.269632 | AJ102: 397.52236 | AK102: 86.795237 | AL102: 9.2126865 | AM102: 10.75056 | AN102: 54.595033 | AO102: 18.166544 | AP102: 19.565822 | AQ102: 5.2478884 | AR102: 37.483106 | AS102: 91.046099 | AT102: 249.67419 | AU102: 37.091908 | DU102: 0.97473858 | DV102: 1716.6077
A103: flab-s | P103: 1.0600711 | Q103: 1.0917322 | R103: 0.1036566 | S103: 3.2561654 | T103: 0.35668797 | U103: 2.2243046 | V103: 4.8089945 | W103: 2.6838135 | X103: 0.40851569 | Y103: 3.8844941 | Z103: 0.25290729 | AA103: 0.29091211 | AB103: 2.0266769 | AC103: 0.12736258 | AD103: 0.61319942 | AE103: 0.10210935 | AF103: 1.8614932 | AG103: 2.7224425 | AH103: 9.2375879 | AI103: 4.9607338 | AJ103: 9.8904259 | AK103: 8.1461727 | AL103: 5.5538158 | AM103: 6.4809142 | AN103: 5.1240204 | AO103: 8.4603026 | AP103: 9.1119573 | AQ103: 2.443983 | AR103: 98.713341 | AS103: 25.119151 | AT103: 68.883825 | AU103: 3.6816203 | DU103: 0.16685651 | DV103: 293.85025
...

Sheet LES
A1: Households LES parametrization | R1: abecr | S1: cbecr
A2: DO NOT CHANGE ANYTHING UNLESS INSTRUCTED (BLACK cells should NOT be changed; color cells CAN be changed). Follow steps. | R2: aocrp | S2: cocrp
A4: STEP 0: classification
A6: SAM 4 letters | B6: cere | C6: gmll | D6: root | E6: puls | F6: vege | G6: frui | H6: fveg | I6: live | J6: fish | K6: meat | L6: fsea | M6: milk | N6: dair | O6: oils | P6: foil | Q6: fobe | R6: text | S6: elec | T6: watr | U6: real | V6: educ | W6: heal | X6: padm | Y6: becr | Z6: ocrp | AA6: fore | AB6: oapr | AC6: mine | AD6: mino | AE6: wood | AF6: petr | AG6: fert | AH6: chem | AI6: nmet | AJ6: metl | AK6: mach | AL6: oman | AM6: cons | AN6: hotl | AO6: rest | AP6: trad | AQ6: tran | AR6: comm | AS6: fsrv | AT6: bsrv | AU6: osrv
A7: SAM commodities | B7: ="c"&B6 -> ccere | C7: ="c"&C6 -> cgmll | D7: ="c"&D6 -> croot | E7: ="c"&E6 -> cpuls | F7: ="c"&F6 -> cvege | G7: ="c"&G6 -> cfrui | H7: ="c"&H6 -> cfveg | I7: ="c"&I6 -> clive | ... X7: ="c"&X6 -> cpadm | Y7: cbecr | Z7: ="c"&Z6 -> cocrp | AA7: ="c"&AA6 -> cfore | AB7: ="c"&AB6 -> coapr | AC7: ="c"&AC6 -> cmine | AD7: ="c"&AD6 -> cmino | AE7: ="c"&AE6 -> cwood | AF7: ="c"&AF6 -> cpetr | AG7: ="c"&AG6 -> cfert | ... AU7: ="c"&AU6 -> cosrv
A8: SAM activities | B8: ="a"&B6 -> acere | C8: ="a"&C6 -> agmll | D8: ="a"&D6 -> aroot | E8: ="a"&E6 -> apuls | F8: ="a"&F6 -> avege | G8: ="a"&G6 -> afrui | H8: ="a"&H6 -> afveg | I8: ="a"&I6 -> alive | ... X8: ="a"&X6 -> apadm | Y8: abecr | Z8: ="a"&Z6 -> aocrp | AA8: ="a"&AA6 -> afore | AB8: ="a"&AB6 -> aoapr | AC8: ="a"&AC6 -> amine | AD8: ="a"&AD6 -> amino | AE8: ="a"&AE6 -> awood | AF8: ="a"&AF6 -> apetr | AG8: ="a"&AG6 -> afert | ... AU8: ="a"&AU6 -> aosrv
A9: broad categories | B9: cereals | C9: cereals | D9: roots | E9: pulses | F9: vegetables | G9: fruits | H9: fruits | I9: fish-meat-egg | J9: fish-meat-egg | K9: fish-meat-egg | L9: fish-meat-egg | M9: diary | N9: diary | O9: fats & oils | P9: fats & oils | Q9: other food | R9: clothing and textile | S9: utilities | T9: utilities | U9: housing | V9: education, health and public | W9: education, health and public | X9: education, health and public | Y9: other ag | Z9: other ag | AA9: other ag | AB9: other ag | AC9: mining | AD9: mining | AE9: manufacturing | AF9: manufacturing | AG9: manufacturing | AH9: manufacturing | AI9: manufacturing | AJ9: manufacturing | AK9: manufacturing | AL9: manufacturing | AM9: contruction | AN9: hotels and restaurants | AO9: hotels and restaurants | AP9: trade, transport and comm | AQ9: trade, transport and comm | AR9: other services | AS9: other services | AT9: other services | AU9: other services
A10: given - residual categories | B10: =VLOOKUP(B9,$R$102:$S$122,2,FALSE) -> given | C10: =VLOOKUP(C9,$R$102:$S$122,2,FALSE) -> given | D10: =VLOOKUP(D9,$R$102:$S$122,2,FALSE) -> given | E10: =VLOOKUP(E9,$R$102:$S$122,2,FALSE) -> given | F10: =VLOOKUP(F9,$R$102:$S$122,2,FALSE) -> given | G10: =VLOOKUP(G9,$R$102:$S$122,2,FALSE) -> given | H10: =VLOOKUP(H9,$R$102:$S$122,2,FALSE) -> given | I10: =VLOOKUP(I9,$R$102:$S$122,2,FALSE) -> given | ... AU10: =VLOOKUP(AU9,$R$102:$S$122,2,FALSE) -> residual
A12: given=income elasticity WILL bew given
A13: residual = income elasticity WILL be calculated/calibrated as a residual
A15: STEP 1: calculate ABS - average budget shares (based on SAM).
A16: 20 groups - ABS | U16: SAM values
A17: given - residual categories | B17: caregory | C17: Rural farm | H17: Rural nonfarm | M17: Urban | R17: Total national | U17: Rural farm | Z17: Rural nonfarm | AE17: Urban | AJ17: total
C18: hhd-f1 | D18: hhd-f2 | E18: hhd-f3 | F18: hhd-f4 | G18: hhd-f5 | H18: hhd-n1 | I18: hhd-n2 | J18: hhd-n3 | K18: hhd-n4 | L18: hhd-n5 | M18: hhd-u1 | N18: hhd-u2 | O18: hhd-u3 | P18: hhd-u4 | Q18: hhd-u5 | U18: hhd-f1 | V18: hhd-f2 | W18: hhd-f3 | X18: hhd-f4 | Y18: hhd-f5 | Z18: hhd-n1 | AA18: hhd-n2 | AB18: hhd-n3 | AC18: hhd-n4 | AD18: hhd-n5 | AE18: hhd-u1 | AF18: hhd-u2 | AG18: hhd-u3 | AH18: hhd-u4 | AI18: hhd-u5
A19: =S102 -> given | B19: cereals | C19: =SUM(C49:C50) -> 27.395786 | D19: =SUM(D49:D50) -> 23.713124 | E19: =SUM(E49:E50) -> 20.370575 | F19: =SUM(F49:F50) -> 16.654798 | G19: =SUM(G49:G50) -> 11.191999 | H19: =SUM(H49:H50) -> 22.377673 | I19: =SUM(I49:I50) -> 18.222094 | J19: =SUM(J49:J50) -> 19.661903 | ... R19: =SUM(R49:R50) -> 12.541841 | T19: cereals | U19: =SUM(U49:U50) -> 71.893521 | V19: =SUM(V49:V50) -> 88.647541 | W19: =SUM(W49:W50) -> 118.7404 | X19: =SUM(X49:X50) -> 133.01273 | Y19: =SUM(Y49:Y50) -> 160.01767 | Z19: =SUM(Z49:Z50) -> 3.8669753 | AA19: =SUM(AA49:AA50) -> 4.0642792 | AB19: =SUM(AB49:AB50) -> 5.4025494 | ... AJ19: =SUM(AJ49:AJ50) -> 819.20191
A20: =S103 -> given | B20: roots | C20: =SUM(C51:C51) -> 4.4549956 | D20: =SUM(D51:D51) -> 4.5106084 | E20: =SUM(E51:E51) -> 4.7593821 | F20: =SUM(F51:F51) -> 4.9215352 | G20: =SUM(G51:G51) -> 3.7079649 | H20: =SUM(H51:H51) -> 2.3900328 | I20: =SUM(I51:I51) -> 3.2232009 | J20: =SUM(J51:J51) -> 4.0713657 | ... R20: =SUM(R51:R51) -> 3.1875478 | T20: roots | U20: =SUM(U51:U51) -> 11.691043 | V20: =SUM(V51:V51) -> 16.862154 | W20: =SUM(W51:W51) -> 27.742512 | X20: =SUM(X51:X51) -> 39.305601 | Y20: =SUM(Y51:Y51) -> 53.01465 | Z20: =SUM(Z51:Z51) -> 0.41300977 | AA20: =SUM(AA51:AA51) -> 0.71890686 | AB20: =SUM(AB51:AB51) -> 1.1186992 | ... AJ20: =SUM(AJ51:AJ51) -> 208.2027
A21: =S104 -> given | B21: pulses | C21: =C52 -> 2.9322489 | D21: =D52 -> 3.1664244 | E21: =E52 -> 3.1118736 | F21: =F52 -> 2.7947241 | G21: =G52 -> 2.1223303 | H21: =H52 -> 1.6435541 | I21: =I52 -> 2.2440819 | J21: =J52 -> 1.9466825 | ... R21: =R52 -> 1.9069241 | T21: pulses | U21: =U52 -> 7.6949681 | V21: =V52 -> 11.837147 | W21: =W52 -> 18.139159 | X21: =X52 -> 22.319927 | Y21: =Y52 -> 30.344031 | Z21: =Z52 -> 0.28401448 | AA21: =AA52 -> 0.50052289 | AB21: =AB52 -> 0.53489473 | ... AJ21: =AJ52 -> 124.55554
A22: =S105 -> given | B22: vegetables | C22: =SUM(C53:C53) -> 11.354009 | D22: =SUM(D53:D53) -> 9.837339 | E22: =SUM(E53:E53) -> 8.1848849 | F22: =SUM(F53:F53) -> 7.1705287 | G22: =SUM(G53:G53) -> 4.6493467 | H22: =SUM(H53:H53) -> 9.1680143 | I22: =SUM(I53:I53) -> 7.6729356 | J22: =SUM(J53:J53) -> 6.2326773 | ... R22: =SUM(R53:R53) -> 5.2548374 | T22: vegetables | U22: =SUM(U53:U53) -> 29.795811 | V22: =SUM(V53:V53) -> 36.775244 | W22: =SUM(W53:W53) -> 47.70982 | X22: =SUM(X53:X53) -> 57.267077 | Y22: =SUM(Y53:Y53) -> 66.474063 | Z22: =SUM(Z53:Z53) -> 1.5842793 | AA22: =SUM(AA53:AA53) -> 1.7113814 | AB22: =SUM(AB53:AB53) -> 1.7125681 | ... AJ22: =SUM(AJ53:AJ53) -> 343.23293
A23: =S106 -> given | B23: fruits | C23: =SUM(C54:C55) -> 1.9732792 | D23: =SUM(D54:D55) -> 1.8538833 | E23: =SUM(E54:E55) -> 2.1548294 | F23: =SUM(F54:F55) -> 2.1070058 | G23: =SUM(G54:G55) -> 2.2628935 | H23: =SUM(H54:H55) -> 1.4406041 | I23: =SUM(I54:I55) -> 1.7757437 | J23: =SUM(J54:J55) -> 1.6520126 | ... R23: =SUM(R54:R55) -> 1.7505289 | T23: fruits | U23: =SUM(U54:U55) -> 5.1783874 | V23: =SUM(V54:V55) -> 6.9304322 | W23: =SUM(W54:W55) -> 12.560534 | X23: =SUM(X54:X55) -> 16.827499 | Y23: =SUM(Y54:Y55) -> 32.353733 | Z23: =SUM(Z54:Z55) -> 0.24894369 | AA23: =SUM(AA54:AA55) -> 0.39606415 | AB23: =SUM(AB54:AB55) -> 0.45392757 | ... AJ23: =SUM(AJ54:AJ55) -> 114.3402
A24: =S107 -> given | B24: fish-meat-egg | C24: =SUM(C56:C59) -> 8.0372657 | D24: =SUM(D56:D59) -> 11.599026 | E24: =SUM(E56:E59) -> 13.40559 | F24: =SUM(F56:F59) -> 16.058805 | G24: =SUM(G56:G59) -> 18.790411 | H24: =SUM(H56:H59) -> 8.586381 | I24: =SUM(I56:I59) -> 12.241586 | J24: =SUM(J56:J59) -> 14.896385 | ... R24: =SUM(R56:R59) -> 13.392203 | T24: fish-meat-egg | U24: =SUM(U56:U59) -> 21.091833 | V24: =SUM(V56:V59) -> 43.361017 | W24: =SUM(W56:W59) -> 78.141393 | X24: =SUM(X56:X59) -> 128.25286 | Y24: =SUM(Y56:Y59) -> 268.65602 | Z24: =SUM(Z56:Z59) -> 1.4837701 | AA24: =SUM(AA56:AA59) -> 2.730379 | AB24: =SUM(AB56:AB59) -> 4.0931164 | ... AJ24: =SUM(AJ56:AJ59) -> 874.74541
A25: =S108 -> given | B25: diary | C25: =SUM(C60:C61) -> 0.043847645 | D25: =SUM(D60:D61) -> 0.217089 | E25: =SUM(E60:E61) -> 0.28331335 | F25: =SUM(F60:F61) -> 0.62149634 | G25: =SUM(G60:G61) -> 0.93523285 | H25: =SUM(H60:H61) -> 0.16777877 | I25: =SUM(I60:I61) -> 0.081452677 | J25: =SUM(J60:J61) -> 0.35656961 | ... R25: =SUM(R60:R61) -> 0.73724779 | T25: diary | U25: =SUM(U60:U61) -> 0.11506739 | V25: =SUM(V60:V61) -> 0.81155083 | W25: =SUM(W60:W61) -> 1.6514379 | X25: =SUM(X60:X61) -> 4.9635501 | Y25: =SUM(Y60:Y61) -> 13.371497 | Z25: =SUM(Z60:Z61) -> 0.028993022 | AA25: =SUM(AA60:AA61) -> 0.018167309 | AB25: =SUM(AB60:AB61) -> 0.097975508 | ... AJ25: =SUM(AJ60:AJ61) -> 48.155194
A26: =S109 -> given | B26: fats & oils | C26: =SUM(C62:C63) -> 2.0175182 | D26: =SUM(D62:D63) -> 2.6745589 | E26: =SUM(E62:E63) -> 3.1645926 | F26: =SUM(F62:F63) -> 3.9300724 | G26: =SUM(G62:G63) -> 4.1479601 | H26: =SUM(H62:H63) -> 2.3829687 | I26: =SUM(I62:I63) -> 2.88201 | J26: =SUM(J62:J63) -> 3.1303228 | ... R26: =SUM(R62:R63) -> 5.2463671 | T26: fats & oils | U26: =SUM(U62:U63) -> 5.2944818 | V26: =SUM(V62:V63) -> 9.9983902 | W26: =SUM(W62:W63) -> 18.446459 | X26: =SUM(X62:X63) -> 31.387331 | Y26: =SUM(Y62:Y63) -> 59.305485 | Z26: =SUM(Z62:Z63) -> 0.41178907 | AA26: =SUM(AA62:AA63) -> 0.64280719 | AB26: =SUM(AB62:AB63) -> 0.8601265 | ... AJ26: =SUM(AJ62:AJ63) -> 342.67966
A27: =S110 -> given | B27: other food | C27: =SUM(C64:C64) -> 3.836133 | D27: =SUM(D64:D64) -> 5.0076941 | E27: =SUM(E64:E64) -> 5.791494 | F27: =SUM(F64:F64) -> 7.0764406 | G27: =SUM(G64:G64) -> 7.2534209 | H27: =SUM(H64:H64) -> 4.7669589 | I27: =SUM(I64:I64) -> 4.1139952 | J27: =SUM(J64:J64) -> 5.9117649 | ... R27: =SUM(R64:R64) -> 6.622549 | T27: other food | U27: =SUM(U64:U64) -> 10.06699 | V27: =SUM(V64:V64) -> 18.720425 | W27: =SUM(W64:W64) -> 33.758708 | X27: =SUM(X64:X64) -> 56.515647 | Y27: =SUM(Y64:Y64) -> 103.70583 | Z27: =SUM(Z64:Z64) -> 0.82375465 | AA27: =SUM(AA64:AA64) -> 0.91759074 | AB27: =SUM(AB64:AB64) -> 1.6243902 | ... AJ27: =SUM(AJ64:AJ64) -> 432.56845
A28: =S111 -> given | B28: clothing and textile | C28: =SUM(C65:C65) -> 1.8503207 | D28: =SUM(D65:D65) -> 1.9200177 | E28: =SUM(E65:E65) -> 2.1531963 | F28: =SUM(F65:F65) -> 2.2573789 | G28: =SUM(G65:G65) -> 2.305715 | H28: =SUM(H65:H65) -> 1.7677368 | I28: =SUM(I65:I65) -> 1.8204844 | J28: =SUM(J65:J65) -> 1.7634531 | ... R28: =SUM(R65:R65) -> 2.1784506 | T28: clothing and textile | U28: =SUM(U65:U65) -> 4.855713 | V28: =SUM(V65:V65) -> 7.1776645 | W28: =SUM(W65:W65) -> 12.551015 | X28: =SUM(X65:X65) -> 18.028446 | Y28: =SUM(Y65:Y65) -> 32.965974 | Z28: =SUM(Z65:Z65) -> 0.30547387 | AA28: =SUM(AA65:AA65) -> 0.40604317 | AB28: =SUM(AB65:AB65) -> 0.48454834 | ... AJ28: =SUM(AJ65:AJ65) -> 142.29098
A29: =S112 -> given | B29: utilities | C29: =SUM(C66:C67) -> 0.35008961 | D29: =SUM(D66:D67) -> 0.493999 | E29: =SUM(E66:E67) -> 0.50787984 | F29: =SUM(F66:F67) -> 0.63626062 | G29: =SUM(G66:G67) -> 1.4296236 | H29: =SUM(H66:H67) -> 0.62226152 | I29: =SUM(I66:I67) -> 1.1888797 | J29: =SUM(J66:J67) -> 1.1889695 | ... R29: =SUM(R66:R67) -> 2.7744334 | T29: utilities | U29: =SUM(U66:U67) -> 0.91872431 | V29: =SUM(V66:V67) -> 1.8467325 | W29: =SUM(W66:W67) -> 2.9604394 | X29: =SUM(X66:X67) -> 5.0814643 | Y29: =SUM(Y66:Y67) -> 20.440052 | Z29: =SUM(Z66:Z67) -> 0.10752994 | AA29: =SUM(AA66:AA67) -> 0.26516925 | AB29: =SUM(AB66:AB67) -> 0.32669608 | ... AJ29: =SUM(AJ66:AJ67) -> 181.2191
A30: =S113 -> given | B30: housing | C30: =C68 -> 10.393127 | D30: =D68 -> 8.881227 | E30: =E68 -> 7.9823631 | F30: =F68 -> 6.9727339 | G30: =G68 -> 6.3014515 | H30: =H68 -> 11.011433 | I30: =I68 -> 9.4200876 | J30: =J68 -> 9.1892564 | ... R30: =R68 -> 8.8806238 | T30: housing | U30: =U68 -> 27.274212 | V30: =V68 -> 33.200979 | W30: =W68 -> 46.529317 | X30: =X68 -> 55.687398 | Y30: =Y68 -> 90.09504 | Z30: =Z68 -> 1.9028314 | AA30: =AA68 -> 2.1010684 | AB30: =AB68 -> 2.5249546 | ... AJ30: =AJ68 -> 580.06028
A31: =S114 -> given | B31: education, health and public | C31: =SUM(C69:C71) -> 12.103158 | D31: =SUM(D69:D71) -> 12.540297 | E31: =SUM(E69:E71) -> 13.451316 | F31: =SUM(F69:F71) -> 12.783048 | G31: =SUM(G69:G71) -> 13.634957 | H31: =SUM(H69:H71) -> 20.367463 | I31: =SUM(I69:I71) -> 22.4638 | J31: =SUM(J69:J71) -> 14.514947 | ... R31: =SUM(R69:R71) -> 13.360135 | T31: education, health and public | U31: =SUM(U69:U71) -> 31.76177 | V31: =SUM(V69:V71) -> 46.8798 | W31: =SUM(W69:W71) -> 78.407927 | X31: =SUM(X69:X71) -> 102.09119 | Y31: =SUM(Y69:Y71) -> 194.94589 | Z31: =SUM(Z69:Z71) -> 3.5196007 | AA31: =SUM(AA69:AA71) -> 5.0103546 | AB31: =SUM(AB69:AB71) -> 3.9883077 | ... AJ31: =SUM(AJ69:AJ71) -> 872.65085
A32: =S116 -> residual | B32: other ag | C32: =SUM(C72:C75) -> 3.1126926 | D32: =SUM(D72:D75) -> 2.1630819 | E32: =SUM(E72:E75) -> 2.1038137 | F32: =SUM(F72:F75) -> 2.5903922 | G32: =SUM(G72:G75) -> 2.0816301 | H32: =SUM(H72:H75) -> 2.0708763 | I32: =SUM(I72:I75) -> 1.2556523 | J32: =SUM(J72:J75) -> 2.2830951 | ... R32: =SUM(R72:R75) -> 1.8346686 | T32: other ag | U32: =SUM(U72:U75) -> 8.1684983 | V32: =SUM(V72:V75) -> 8.0863191 | W32: =SUM(W72:W75) -> 12.263163 | X32: =SUM(X72:X75) -> 20.68804 | Y32: =SUM(Y72:Y75) -> 29.762119 | Z32: =SUM(Z72:Z75) -> 0.35785793 | AA32: =SUM(AA72:AA75) -> 0.28006229 | AB32: =SUM(AB72:AB75) -> 0.62733166 | ... AJ32: =SUM(AJ72:AJ75) -> 119.836
A33: =S117 -> residual | B33: mining | C33: =SUM(C76:C77) -> 0 | D33: =SUM(D76:D77) -> 0 | E33: =SUM(E76:E77) -> 0 | F33: =SUM(F76:F77) -> 0 | G33: =SUM(G76:G77) -> 0 | H33: =SUM(H76:H77) -> 0 | I33: =SUM(I76:I77) -> 0 | J33: =SUM(J76:J77) -> 0 | ... R33: =SUM(R76:R77) -> 0 | T33: mining | U33: =SUM(U76:U77) -> 0 | V33: =SUM(V76:V77) -> 0 | W33: =SUM(W76:W77) -> 0 | X33: =SUM(X76:X77) -> 0 | Y33: =SUM(Y76:Y77) -> 0 | Z33: =SUM(Z76:Z77) -> 0 | AA33: =SUM(AA76:AA77) -> 0 | AB33: =SUM(AB76:AB77) -> 0 | ... AJ33: =SUM(AJ76:AJ77) -> 0
A34: =S118 -> residual | B34: manufacturing | C34: =SUM(C78:C85) -> 3.884739 | D34: =SUM(D78:D85) -> 3.5597892 | E34: =SUM(E78:E85) -> 3.3927911 | F34: =SUM(F78:F85) -> 3.4842031 | G34: =SUM(G78:G85) -> 4.9017339 | H34: =SUM(H78:H85) -> 3.8084335 | I34: =SUM(I78:I85) -> 3.3631809 | J34: =SUM(J78:J85) -> 3.2867233 | ... R34: =SUM(R78:R85) -> 4.9769638 | T34: manufacturing | U34: =SUM(U78:U85) -> 10.194545 | V34: =SUM(V78:V85) -> 13.307675 | W34: =SUM(W78:W85) -> 19.776631 | X34: =SUM(X78:X85) -> 27.826417 | Y34: =SUM(Y78:Y85) -> 70.08257 | Z34: =SUM(Z78:Z85) -> 0.6581166 | AA34: =SUM(AA78:AA85) -> 0.75012817 | AB34: =SUM(AB78:AB85) -> 0.90310104 | ... AJ34: =SUM(AJ78:AJ85) -> 325.08291
A35: =S119 -> residual | B35: contruction | C35: =C86 -> 0 | D35: =D86 -> 0 | E35: =E86 -> 0 | F35: =F86 -> 0 | G35: =G86 -> 0 | H35: =H86 -> 0 | I35: =I86 -> 0 | J35: =J86 -> 0 | ... R35: =R86 -> 0 | T35: contruction | U35: =U86 -> 0 | V35: =V86 -> 0 | W35: =W86 -> 0 | X35: =X86 -> 0 | Y35: =Y86 -> 0 | Z35: =Z86 -> 0 | AA35: =AA86 -> 0 | AB35: =AB86 -> 0 | ... AJ35: =AJ86 -> 0
A36: =S120 -> residual | B36: hotels and restaurants | C36: =SUM(C87,C88) -> 0.84084045 | D36: =SUM(D87,D88) -> 1.1788274 | E36: =SUM(E87,E88) -> 1.3145768 | F36: =SUM(F87,F88) -> 1.4019035 | G36: =SUM(G87,G88) -> 1.4979372 | H36: =SUM(H87,H88) -> 1.5570112 | I36: =SUM(I87,I88) -> 1.7069852 | J36: =SUM(J87,J88) -> 1.89345 | ... R36: =SUM(R87,R88) -> 1.881235 | T36: hotels and restaurants | U36: =SUM(U87,U88) -> 2.2065795 | V36: =SUM(V87,V88) -> 4.4068486 | W36: =SUM(W87,W88) -> 7.6626882 | X36: =SUM(X87,X88) -> 11.196234 | Y36: =SUM(Y87,Y88) -> 21.416767 | Z36: =SUM(Z87,Z88) -> 0.26905942 | AA36: =SUM(AA87,AA88) -> 0.38072817 | AB36: =SUM(AB87,AB88) -> 0.52026791 | ... AJ36: =SUM(AJ87,AJ88) -> 122.8776
A37: =S121 -> residual | B37: trade, transport and comm | C37: =SUM(C89:C91) -> 2.5409139 | D37: =SUM(D89:D91) -> 3.8408215 | E37: =SUM(E89:E91) -> 5.026292 | F37: =SUM(F89:F91) -> 5.7880299 | G37: =SUM(G89:G91) -> 9.2024702 | H37: =SUM(H89:H91) -> 3.2636186 | I37: =SUM(I89:I91) -> 3.5938841 | J37: =SUM(J89:J91) -> 5.7210977 | ... R37: =SUM(R89:R91) -> 8.9015702 | T37: trade, transport and comm | U37: =SUM(U89:U91) -> 6.6680054 | V37: =SUM(V89:V91) -> 14.358268 | W37: =SUM(W89:W91) -> 29.298334 | X37: =SUM(X89:X91) -> 46.225818 | Y37: =SUM(Y89:Y91) -> 131.57237 | Z37: =SUM(Z89:Z91) -> 0.56396983 | AA37: =SUM(AA89:AA91) -> 0.80158451 | AB37: =SUM(AB89:AB91) -> 1.5720001 | ... AJ37: =SUM(AJ89:AJ91) -> 581.42845
A38: =S122 -> residual | B38: other services | C38: =SUM(C92:C94) -> 2.8790359 | D38: =SUM(D92:D94) -> 2.8421909 | E38: =SUM(E92:E94) -> 2.841236 | F38: =SUM(F92:F94) -> 2.750644 | G38: =SUM(G92:G94) -> 3.5829215 | H38: =SUM(H92:H94) -> 2.6072015 | I38: =SUM(I92:I94) -> 2.7299458 | J38: =SUM(J92:J94) -> 2.2993241 | ... R38: =SUM(R92:R94) -> 4.5718731 | T38: other services | U38: =SUM(U92:U94) -> 7.5553237 | V38: =SUM(V92:V94) -> 10.625055 | W38: =SUM(W92:W94) -> 16.561608 | X38: =SUM(X92:X94) -> 21.967884 | Y38: =SUM(Y92:Y94) -> 51.226842 | Z38: =SUM(Z92:Z94) -> 0.45053764 | AA38: =SUM(AA92:AA94) -> 0.60889061 | AB38: =SUM(AB92:AB94) -> 0.63179095 | ... AJ38: =SUM(AJ92:AJ94) -> 298.62339
A39: Total food | C39: =SUM(C19:C27) -> 62.045083 | D39: =SUM(D19:D27) -> 62.579748 | E39: =SUM(E19:E27) -> 61.226535 | F39: =SUM(F19:F27) -> 61.335406 | G39: =SUM(G19:G27) -> 55.06156 | H39: =SUM(H19:H27) -> 52.923965 | I39: =SUM(I19:I27) -> 52.4571 | J39: =SUM(J19:J27) -> 57.859684 | ... R39: =SUM(R19:R27) -> 50.640046 | T39: Total food | U39: =SUM(U19:U27) -> 162.8221 | V39: =SUM(V19:V27) -> 233.9439 | W39: =SUM(W19:W27) -> 356.89042 | X39: =SUM(X19:X27) -> 489.85222 | Y39: =SUM(Y19:Y27) -> 787.24298 | Z39: =SUM(Z19:Z27) -> 9.1455294 | AA39: =SUM(AA19:AA27) -> 11.700099 | AB39: =SUM(AB19:AB27) -> 15.898247 | ... AJ39: =SUM(AJ19:AJ27) -> 3307.682
A40: Total nonfood | C40: =SUM(C28:C38) -> 37.954917 | D40: =SUM(D28:D38) -> 37.420252 | E40: =SUM(E28:E38) -> 38.773465 | F40: =SUM(F28:F38) -> 38.664594 | G40: =SUM(G28:G38) -> 44.93844 | H40: =SUM(H28:H38) -> 47.076035 | I40: =SUM(I28:I38) -> 47.5429 | J40: =SUM(J28:J38) -> 42.140316 | ... R40: =SUM(R28:R38) -> 49.359954 | T40: Total nonfood | U40: =SUM(U29:U38) -> 94.747659 | V40: =SUM(V29:V38) -> 132.71168 | W40: =SUM(W29:W38) -> 213.46011 | X40: =SUM(X29:X38) -> 290.76444 | Y40: =SUM(Y29:Y38) -> 609.54165 | Z40: =SUM(Z29:Z38) -> 7.8295034 | AA40: =SUM(AA29:AA38) -> 10.197986 | AB40: =SUM(AB29:AB38) -> 11.09445 | ... AJ40: =SUM(AJ29:AJ38) -> 3081.7786
A41: Total given | C41: =SUM(C19:C31) -> 86.741778 | D41: =SUM(D19:D31) -> 86.415289 | E41: =SUM(E19:E31) -> 85.32129 | F41: =SUM(F19:F31) -> 83.984827 | G41: =SUM(G19:G31) -> 78.733307 | H41: =SUM(H19:H31) -> 86.692859 | I41: =SUM(I19:I31) -> 87.350352 | J41: =SUM(J19:J31) -> 84.51631 | ... R41: =SUM(R19:R31) -> 77.833689
A42: Total residual | C42: =SUM(C32:C38) -> 13.258222 | D42: =SUM(D32:D38) -> 13.584711 | E42: =SUM(E32:E38) -> 14.67871 | F42: =SUM(F32:F38) -> 16.015173 | G42: =SUM(G32:G38) -> 21.266693 | H42: =SUM(H32:H38) -> 13.307141 | I42: =SUM(I32:I38) -> 12.649648 | J42: =SUM(J32:J38) -> 15.48369 | ... R42: =SUM(R32:R38) -> 22.166311
A43: Total | C43: =C39+C40 -> 100 | D43: =D39+D40 -> 100 | E43: =E39+E40 -> 100 | F43: =F39+F40 -> 100 | G43: =G39+G40 -> 100 | H43: =H39+H40 -> 100 | I43: =I39+I40 -> 100 | J43: =J39+J40 -> 100 | ... R43: =R39+R40 -> 100 | T43: Total | U43: =U39+U40 -> 257.56976 | V43: =V39+V40 -> 366.65558 | W43: =W39+W40 -> 570.35053 | X43: =X39+X40 -> 780.61666 | Y43: =Y39+Y40 -> 1396.7846 | Z43: =Z39+Z40 -> 16.975033 | AA43: =AA39+AA40 -> 21.898085 | AB43: =AB39+AB40 -> 26.992697 | ... AJ43: =AJ39+AJ40 -> 6389.4606
A46: ABS - disagg
U47: Extract SAM values - total | AL47: Extract SAM values - marketed | BC47: Extract SAM values - home
A48: category | B48: sam | C48: hhd-f1 | D48: hhd-f2 | E48: hhd-f3 | F48: hhd-f4 | G48: hhd-f5 | H48: hhd-n1 | I48: hhd-n2 | J48: hhd-n3 | K48: hhd-n4 | L48: hhd-n5 | M48: hhd-u1 | N48: hhd-u2 | O48: hhd-u3 | P48: hhd-u4 | Q48: hhd-u5 | R48: total | U48: hhd-f1 | V48: hhd-f2 | W48: hhd-f3 | X48: hhd-f4 | Y48: hhd-f5 | Z48: hhd-n1 | AA48: hhd-n2 | AB48: hhd-n3 | AC48: hhd-n4 | AD48: hhd-n5 | AE48: hhd-u1 | AF48: hhd-u2 | AG48: hhd-u3 | AH48: hhd-u4 | AI48: hhd-u5 | AJ48: total | AM48: hhd-f1 | AN48: hhd-f2 | AO48: hhd-f3 | AP48: hhd-f4 | AQ48: hhd-f5 | AR48: hhd-n1 | AS48: hhd-n2 | AT48: hhd-n3 | AU48: hhd-n4 | AV48: hhd-n5 | AW48: hhd-u1 | AX48: hhd-u2 | AY48: hhd-u3 | AZ48: hhd-u4 | BA48: hhd-u5 | BD48: hhd-f1 | BE48: hhd-f2 | BF48: hhd-f3 | BG48: hhd-f4 | BH48: hhd-f5 | BI48: hhd-n1 | BJ48: hhd-n2 | BK48: hhd-n3 | BL48: hhd-n4 | BM48: hhd-n5 | BN48: hhd-u1 | BO48: hhd-u2 | BP48: hhd-u3 | BQ48: hhd-u4 | BR48: hhd-u5 | BW48: shares rearranged
A49: =HLOOKUP(B49,$B$6:$BR$9,4,FALSE) -> cereals | B49: cere | C49: =IFERROR(100*U49/U$95,"") -> 8.2279879 | D49: =IFERROR(100*V49/V$95,"") -> 9.0973069 | E49: =IFERROR(100*W49/W$95,"") -> 8.371554 | F49: =IFERROR(100*X49/X$95,"") -> 7.3073921 | G49: =IFERROR(100*Y49/Y$95,"") -> 4.9176454 | H49: =IFERROR(100*Z49/Z$95,"") -> 0 | I49: =IFERROR(100*AA49/AA$95,"") -> 0 | J49: =IFERROR(100*AB49/AB$95,"") -> 0.57437148 | ... R49: =IFERROR(100*AJ49/AJ$95,"") -> 3.7637587 | T49: =B49 -> cere | U49: =IFERROR(AM49+BD49,"") -> 21.592336 | V49: =IFERROR(AN49+BE49,"") -> 34.008757 | W49: =IFERROR(AO49+BF49,"") -> 48.797917 | X49: =IFERROR(AP49+BG49,"") -> 58.36013 | Y49: =IFERROR(AQ49+BH49,"") -> 70.310065 | Z49: =IFERROR(AR49+BI49,"") -> 0 | AA49: =IFERROR(AS49+BJ49,"") -> 0 | AB49: =IFERROR(AT49+BK49,"") -> 0.15782146 | ... AI49: =IFERROR(BA49+BR49,"") -> 8.0447102 | AJ49: =SUM(U49:AI49) -> 245.83937 | AL49: ="c"&T49 -> ccere | AM49: =_xlfn.IFNA(INDEX(SAM!$B$8:$HA$215,MATCH($AL49,SAM!$A$8:$A$215,0),MATCH(AM$48,SAM!$B$7:$HA$7,0)),0) -> 9.4518884 | AN49: =_xlfn.IFNA(INDEX(SAM!$B$8:$HA$215,MATCH($AL49,SAM!$A$8:$A$215,0),MATCH(AN$48,SAM!$B$7:$HA$7,0)),0) -> 14.436058 | AO49: =_xlfn.IFNA(INDEX(SAM!$B$8:$HA$215,MATCH($AL49,SAM!$A$8:$A$215,0),MATCH(AO$48,SAM!$B$7:$HA$7,0)),0) -> 20.620936 | AP49: =_xlfn.IFNA(INDEX(SAM!$B$8:$HA$215,MATCH($AL49,SAM!$A$8:$A$215,0),MATCH(AP$48,SAM!$B$7:$HA$7,0)),0) -> 26.930026 | AQ49: =_xlfn.IFNA(INDEX(SAM!$B$8:$HA$215,MATCH($AL49,SAM!$A$8:$A$215,0),MATCH(AQ$48,SAM!$B$7:$HA$7,0)),0) -> 33.02801 | AR49: =_xlfn.IFNA(INDEX(SAM!$B$8:$HA$215,MATCH($AL49,SAM!$A$8:$A$215,0),MATCH(AR$48,SAM!$B$7:$HA$7,0)),0) -> 0 | AS49: =_xlfn.IFNA(INDEX(SAM!$B$8:$HA$215,MATCH($AL49,SAM!$A$8:$A$215,0),MATCH(AS$48,SAM!$B$7:$HA$7,0)),0) -> 0 | AT49: =_xlfn.IFNA(INDEX(SAM!$B$8:$HA$215,MATCH($AL49,SAM!$A$8:$A$215,0),MATCH(AT$48,SAM!$B$7:$HA$7,0)),0) -> 0.15782146 | ... BA49: =_xlfn.IFNA(INDEX(SAM!$B$8:$HA$215,MATCH($AL49,SAM!$A$8:$A$215,0),MATCH(BA$48,SAM!$B$7:$HA$7,0)),0) -> 4.011247 | BC49: ="a"&T49 -> acere | BD49: =_xlfn.IFNA(INDEX(SAM!$B$8:$HA$215,MATCH($BC49,SAM!$A$8:$A$215,0),MATCH(BD$48,SAM!$B$7:$HA$7,0)),0) -> 12.140448 | BE49: =_xlfn.IFNA(INDEX(SAM!$B$8:$HA$215,MATCH($BC49,SAM!$A$8:$A$215,0),MATCH(BE$48,SAM!$B$7:$HA$7,0)),0) -> 19.572699 | BF49: =_xlfn.IFNA(INDEX(SAM!$B$8:$HA$215,MATCH($BC49,SAM!$A$8:$A$215,0),MATCH(BF$48,SAM!$B$7:$HA$7,0)),0) -> 28.176981 | BG49: =_xlfn.IFNA(INDEX(SAM!$B$8:$HA$215,MATCH($BC49,SAM!$A$8:$A$215,0),MATCH(BG$48,SAM!$B$7:$HA$7,0)),0) -> 31.430103 | BH49: =_xlfn.IFNA(INDEX(SAM!$B$8:$HA$215,MATCH($BC49,SAM!$A$8:$A$215,0),MATCH(BH$48,SAM!$B$7:$HA$7,0)),0) -> 37.282055 | BI49: =_xlfn.IFNA(INDEX(SAM!$B$8:$HA$215,MATCH($BC49,SAM!$A$8:$A$215,0),MATCH(BI$48,SAM!$B$7:$HA$7,0)),0) -> 0 | BJ49: =_xlfn.IFNA(INDEX(SAM!$B$8:$HA$215,MATCH($BC49,SAM!$A$8:$A$215,0),MATCH(BJ$48,SAM!$B$7:$HA$7,0)),0) -> 0 | BK49: =_xlfn.IFNA(INDEX(SAM!$B$8:$HA$215,MATCH($BC49,SAM!$A$8:$A$215,0),MATCH(BK$48,SAM!$B$7:$HA$7,0)),0) -> 0 | ... BR49: =_xlfn.IFNA(INDEX(SAM!$B$8:$HA$215,MATCH($BC49,SAM!$A$8:$A$215,0),MATCH(BR$48,SAM!$B$7:$HA$7,0)),0) -> 4.0334632 | BT49: =AL49 -> ccere | BU49: =SUM(BD49:BR49,AM49:BA49) -> 245.83937 | BW49: ccere | BX49: =100*VLOOKUP(BW49,$BT$49:$BU$94,2,FALSE)/$BU$95 -> 3.7637587
A50: =HLOOKUP(B50,$B$6:$BR$9,4,FALSE) -> cereals | B50: gmll | C50: =IFERROR(100*U50/U$95,"") -> 19.167798 | D50: =IFERROR(100*V50/V$95,"") -> 14.615817 | E50: =IFERROR(100*W50/W$95,"") -> 11.999021 | F50: =IFERROR(100*X50/X$95,"") -> 9.3474061 | G50: =IFERROR(100*Y50/Y$95,"") -> 6.2743535 | H50: =IFERROR(100*Z50/Z$95,"") -> 22.377673 | I50: =IFERROR(100*AA50/AA$95,"") -> 18.222094 | J50: =IFERROR(100*AB50/AB$95,"") -> 19.087531 | ... R50: =IFERROR(100*AJ50/AJ$95,"") -> 8.7780825 | T50: =B50 -> gmll | U50: =IFERROR(AM50+BD50,"") -> 50.301185 | V50: =IFERROR(AN50+BE50,"") -> 54.638784 | W50: =IFERROR(AO50+BF50,"") -> 69.942479 | X50: =IFERROR(AP50+BG50,"") -> 74.652602 | Y50: =IFERROR(AQ50+BH50,"") -> 89.707608 | Z50: =IFERROR(AR50+BI50,"") -> 3.8669753 | AA50: =IFERROR(AS50+BJ50,"") -> 4.0642792 | AB50: =IFERROR(AT50+BK50,"") -> 5.2447279 | ... AI50: =IFERROR(BA50+BR50,"") -> 140.53301 | AJ50: =SUM(U50:AI50) -> 573.36254 | AL50: ="c"&T50 -> cgmll | AM50: =_xlfn.IFNA(INDEX(SAM!$B$8:$HA$215,MATCH($AL50,SAM!$A$8:$A$215,0),MATCH(AM$48,SAM!$B$7:$HA$7,0)),0) -> 50.301185 | AN50: =_xlfn.IFNA(INDEX(SAM!$B$8:$HA$215,MATCH($AL50,SAM!$A$8:$A$215,0),MATCH(AN$48,SAM!$B$7:$HA$7,0)),0) -> 54.638784 | AO50: =_xlfn.IFNA(INDEX(SAM!$B$8:$HA$215,MATCH($AL50,SAM!$A$8:$A$215,0),MATCH(AO$48,SAM!$B$7:$HA$7,0)),0) -> 69.942479 | AP50: =_xlfn.IFNA(INDEX(SAM!$B$8:$HA$215,MATCH($AL50,SAM!$A$8:$A$215,0),MATCH(AP$48,SAM!$B$7:$HA$7,0)),0) -> 74.652602 | AQ50: =_xlfn.IFNA(INDEX(SAM!$B$8:$HA$215,MATCH($AL50,SAM!$A$8:$A$215,0),MATCH(AQ$48,SAM!$B$7:$HA$7,0)),0) -> 89.707608 | AR50: =_xlfn.IFNA(INDEX(SAM!$B$8:$HA$215,MATCH($AL50,SAM!$A$8:$A$215,0),MATCH(AR$48,SAM!$B$7:$HA$7,0)),0) -> 3.8669753 | AS50: =_xlfn.IFNA(INDEX(SAM!$B$8:$HA$215,MATCH($AL50,SAM!$A$8:$A$215,0),MATCH(AS$48,SAM!$B$7:$HA$7,0)),0) -> 4.0642792 | AT50: =_xlfn.IFNA(INDEX(SAM!$B$8:$HA$215,MATCH($AL50,SAM!$A$8:$A$215,0),MATCH(AT$48,SAM!$B$7:$HA$7,0)),0) -> 5.2447279 | ... BA50: =_xlfn.IFNA(INDEX(SAM!$B$8:$HA$215,MATCH($AL50,SAM!$A$8:$A$215,0),MATCH(BA$48,SAM!$B$7:$HA$7,0)),0) -> 140.53301 | BC50: ="a"&T50 -> agmll | BD50: =_xlfn.IFNA(INDEX(SAM!$B$8:$HA$215,MATCH($BC50,SAM!$A$8:$A$215,0),MATCH(BD$48,SAM!$B$7:$HA$7,0)),0) -> 0 | BE50: =_xlfn.IFNA(INDEX(SAM!$B$8:$HA$215,MATCH($BC50,SAM!$A$8:$A$215,0),MATCH(BE$48,SAM!$B$7:$HA$7,0)),0) -> 0 | BF50: =_xlfn.IFNA(INDEX(SAM!$B$8:$HA$215,MATCH($BC50,SAM!$A$8:$A$215,0),MATCH(BF$48,SAM!$B$7:$HA$7,0)),0) -> 0 | BG50: =_xlfn.IFNA(INDEX(SAM!$B$8:$HA$215,MATCH($BC50,SAM!$A$8:$A$215,0),MATCH(BG$48,SAM!$B$7:$HA$7,0)),0) -> 0 | BH50: =_xlfn.IFNA(INDEX(SAM!$B$8:$HA$215,MATCH($BC50,SAM!$A$8:$A$215,0),MATCH(BH$48,SAM!$B$7:$HA$7,0)),0) -> 0 | BI50: =_xlfn.IFNA(INDEX(SAM!$B$8:$HA$215,MATCH($BC50,SAM!$A$8:$A$215,0),MATCH(BI$48,SAM!$B$7:$HA$7,0)),0) -> 0 | BJ50: =_xlfn.IFNA(INDEX(SAM!$B$8:$HA$215,MATCH($BC50,SAM!$A$8:$A$215,0),MATCH(BJ$48,SAM!$B$7:$HA$7,0)),0) -> 0 | BK50: =_xlfn.IFNA(INDEX(SAM!$B$8:$HA$215,MATCH($BC50,SAM!$A$8:$A$215,0),MATCH(BK$48,SAM!$B$7:$HA$7,0)),0) -> 0 | ... BR50: =_xlfn.IFNA(INDEX(SAM!$B$8:$HA$215,MATCH($BC50,SAM!$A$8:$A$215,0),MATCH(BR$48,SAM!$B$7:$HA$7,0)),0) -> 0 | BT50: =AL50 -> cgmll | BU50: =SUM(BD50:BR50,AM50:BA50) -> 573.36254 | BW50: cpuls | BX50: =100*VLOOKUP(BW50,$BT$49:$BU$94,2,FALSE)/$BU$95 -> 1.9069241
A51: =HLOOKUP(B51,$B$6:$BR$9,4,FALSE) -> roots | B51: root | C51: =IFERROR(100*U51/U$95,"") -> 4.4549956 | D51: =IFERROR(100*V51/V$95,"") -> 4.5106084 | E51: =IFERROR(100*W51/W$95,"") -> 4.7593821 | F51: =IFERROR(100*X51/X$95,"") -> 4.9215352 | G51: =IFERROR(100*Y51/Y$95,"") -> 3.7079649 | H51: =IFERROR(100*Z51/Z$95,"") -> 2.3900328 | I51: =IFERROR(100*AA51/AA$95,"") -> 3.2232009 | J51: =IFERROR(100*AB51/AB$95,"") -> 4.0713657 | ... R51: =IFERROR(100*AJ51/AJ$95,"") -> 3.1875478 | T51: =B51 -> root | U51: =IFERROR(AM51+BD51,"") -> 11.691043 | V51: =IFERROR(AN51+BE51,"") -> 16.862154 | W51: =IFERROR(AO51+BF51,"") -> 27.742512 | X51: =IFERROR(AP51+BG51,"") -> 39.305601 | Y51: =IFERROR(AQ51+BH51,"") -> 53.01465 | Z51: =IFERROR(AR51+BI51,"") -> 0.41300977 | AA51: =IFERROR(AS51+BJ51,"") -> 0.71890686 | AB51: =IFERROR(AT51+BK51,"") -> 1.1186992 | ... AI51: =IFERROR(BA51+BR51,"") -> 36.239764 | AJ51: =SUM(U51:AI51) -> 208.2027 | AL51: ="c"&T51 -> croot | AM51: =_xlfn.IFNA(INDEX(SAM!$B$8:$HA$215,MATCH($AL51,SAM!$A$8:$A$215,0),MATCH(AM$48,SAM!$B$7:$HA$7,0)),0) -> 6.9201627 | AN51: =_xlfn.IFNA(INDEX(SAM!$B$8:$HA$215,MATCH($AL51,SAM!$A$8:$A$215,0),MATCH(AN$48,SAM!$B$7:$HA$7,0)),0) -> 9.9414043 | AO51: =_xlfn.IFNA(INDEX(SAM!$B$8:$HA$215,MATCH($AL51,SAM!$A$8:$A$215,0),MATCH(AO$48,SAM!$B$7:$HA$7,0)),0) -> 17.256105 | AP51: =_xlfn.IFNA(INDEX(SAM!$B$8:$HA$215,MATCH($AL51,SAM!$A$8:$A$215,0),MATCH(AP$48,SAM!$B$7:$HA$7,0)),0) -> 21.555647 | AQ51: =_xlfn.IFNA(INDEX(SAM!$B$8:$HA$215,MATCH($AL51,SAM!$A$8:$A$215,0),MATCH(AQ$48,SAM!$B$7:$HA$7,0)),0) -> 31.573073 | AR51: =_xlfn.IFNA(INDEX(SAM!$B$8:$HA$215,MATCH($AL51,SAM!$A$8:$A$215,0),MATCH(AR$48,SAM!$B$7:$HA$7,0)),0) -> 0.41300977 | AS51: =_xlfn.IFNA(INDEX(SAM!$B$8:$HA$215,MATCH($AL51,SAM!$A$8:$A$215,0),MATCH(AS$48,SAM!$B$7:$HA$7,0)),0) -> 0.71890686 | AT51: =_xlfn.IFNA(INDEX(SAM!$B$8:$HA$215,MATCH($AL51,SAM!$A$8:$A$215,0),MATCH(AT$48,SAM!$B$7:$HA$7,0)),0) -> 1.1186992 | ... BA51: =_xlfn.IFNA(INDEX(SAM!$B$8:$HA$215,MATCH($AL51,SAM!$A$8:$A$215,0),MATCH(BA$48,SAM!$B$7:$HA$7,0)),0) -> 35.709952 | BC51: ="a"&T51 -> aroot | BD51: =_xlfn.IFNA(INDEX(SAM!$B$8:$HA$215,MATCH($BC51,SAM!$A$8:$A$215,0),MATCH(BD$48,SAM!$B$7:$HA$7,0)),0) -> 4.7708805 | BE51: =_xlfn.IFNA(INDEX(SAM!$B$8:$HA$215,MATCH($BC51,SAM!$A$8:$A$215,0),MATCH(BE$48,SAM!$B$7:$HA$7,0)),0) -> 6.9207493 | BF51: =_xlfn.IFNA(INDEX(SAM!$B$8:$HA$215,MATCH($BC51,SAM!$A$8:$A$215,0),MATCH(BF$48,SAM!$B$7:$HA$7,0)),0) -> 10.486407 | BG51: =_xlfn.IFNA(INDEX(SAM!$B$8:$HA$215,MATCH($BC51,SAM!$A$8:$A$215,0),MATCH(BG$48,SAM!$B$7:$HA$7,0)),0) -> 17.749953 | BH51: =_xlfn.IFNA(INDEX(SAM!$B$8:$HA$215,MATCH($BC51,SAM!$A$8:$A$215,0),MATCH(BH$48,SAM!$B$7:$HA$7,0)),0) -> 21.441577 | BI51: =_xlfn.IFNA(INDEX(SAM!$B$8:$HA$215,MATCH($BC51,SAM!$A$8:$A$215,0),MATCH(BI$48,SAM!$B$7:$HA$7,0)),0) -> 0 | BJ51: =_xlfn.IFNA(INDEX(SAM!$B$8:$HA$215,MATCH($BC51,SAM!$A$8:$A$215,0),MATCH(BJ$48,SAM!$B$7:$HA$7,0)),0) -> 0 | BK51: =_xlfn.IFNA(INDEX(SAM!$B$8:$HA$215,MATCH($BC51,SAM!$A$8:$A$215,0),MATCH(BK$48,SAM!$B$7:$HA$7,0)),0) -> 0 | ... BR51: =_xlfn.IFNA(INDEX(SAM!$B$8:$HA$215,MATCH($BC51,SAM!$A$8:$A$215,0),MATCH(BR$48,SAM!$B$7:$HA$7,0)),0) -> 0.52981221 | BT51: =AL51 -> croot | BU51: =SUM(BD51:BR51,AM51:BA51) -> 208.2027 | BW51: coils | BX51: =100*VLOOKUP(BW51,$BT$49:$BU$94,2,FALSE)/$BU$95 -> 0.78482192
A52: =HLOOKUP(B52,$B$6:$BR$9,4,FALSE) -> pulses | B52: puls | C52: =IFERROR(100*U52/U$95,"") -> 2.9322489 | D52: =IFERROR(100*V52/V$95,"") -> 3.1664244 | E52: =IFERROR(100*W52/W$95,"") -> 3.1118736 | F52: =IFERROR(100*X52/X$95,"") -> 2.7947241 | G52: =IFERROR(100*Y52/Y$95,"") -> 2.1223303 | H52: =IFERROR(100*Z52/Z$95,"") -> 1.6435541 | I52: =IFERROR(100*AA52/AA$95,"") -> 2.2440819 | J52: =IFERROR(100*AB52/AB$95,"") -> 1.9466825 | ... R52: =IFERROR(100*AJ52/AJ$95,"") -> 1.9069241 | T52: =B52 -> puls | U52: =IFERROR(AM52+BD52,"") -> 7.6949681 | V52: =IFERROR(AN52+BE52,"") -> 11.837147 | W52: =IFERROR(AO52+BF52,"") -> 18.139159 | X52: =IFERROR(AP52+BG52,"") -> 22.319927 | Y52: =IFERROR(AQ52+BH52,"") -> 30.344031 | Z52: =IFERROR(AR52+BI52,"") -> 0.28401448 | AA52: =IFERROR(AS52+BJ52,"") -> 0.50052289 | AB52: =IFERROR(AT52+BK52,"") -> 0.53489473 | ... AI52: =IFERROR(BA52+BR52,"") -> 20.651405 | AJ52: =SUM(U52:AI52) -> 124.55554 | AL52: ="c"&T52 -> cpuls | AM52: =_xlfn.IFNA(INDEX(SAM!$B$8:$HA$215,MATCH($AL52,SAM!$A$8:$A$215,0),MATCH(AM$48,SAM!$B$7:$HA$7,0)),0) -> 5.5598562 | AN52: =_xlfn.IFNA(INDEX(SAM!$B$8:$HA$215,MATCH($AL52,SAM!$A$8:$A$215,0),MATCH(AN$48,SAM!$B$7:$HA$7,0)),0) -> 7.6090995 | AO52: =_xlfn.IFNA(INDEX(SAM!$B$8:$HA$215,MATCH($AL52,SAM!$A$8:$A$215,0),MATCH(AO$48,SAM!$B$7:$HA$7,0)),0) -> 12.352471 | AP52: =_xlfn.IFNA(INDEX(SAM!$B$8:$HA$215,MATCH($AL52,SAM!$A$8:$A$215,0),MATCH(AP$48,SAM!$B$7:$HA$7,0)),0) -> 14.934001 | AQ52: =_xlfn.IFNA(INDEX(SAM!$B$8:$HA$215,MATCH($AL52,SAM!$A$8:$A$215,0),MATCH(AQ$48,SAM!$B$7:$HA$7,0)),0) -> 20.387075 | AR52: =_xlfn.IFNA(INDEX(SAM!$B$8:$HA$215,MATCH($AL52,SAM!$A$8:$A$215,0),MATCH(AR$48,SAM!$B$7:$HA$7,0)),0) -> 0.28401448 | AS52: =_xlfn.IFNA(INDEX(SAM!$B$8:$HA$215,MATCH($AL52,SAM!$A$8:$A$215,0),MATCH(AS$48,SAM!$B$7:$HA$7,0)),0) -> 0.50052289 | AT52: =_xlfn.IFNA(INDEX(SAM!$B$8:$HA$215,MATCH($AL52,SAM!$A$8:$A$215,0),MATCH(AT$48,SAM!$B$7:$HA$7,0)),0) -> 0.53489473 | ... BA52: =_xlfn.IFNA(INDEX(SAM!$B$8:$HA$215,MATCH($AL52,SAM!$A$8:$A$215,0),MATCH(BA$48,SAM!$B$7:$HA$7,0)),0) -> 20.131368 | BC52: ="a"&T52 -> apuls | BD52: =_xlfn.IFNA(INDEX(SAM!$B$8:$HA$215,MATCH($BC52,SAM!$A$8:$A$215,0),MATCH(BD$48,SAM!$B$7:$HA$7,0)),0) -> 2.1351119 | BE52: =_xlfn.IFNA(INDEX(SAM!$B$8:$HA$215,MATCH($BC52,SAM!$A$8:$A$215,0),MATCH(BE$48,SAM!$B$7:$HA$7,0)),0) -> 4.2280476 | BF52: =_xlfn.IFNA(INDEX(SAM!$B$8:$HA$215,MATCH($BC52,SAM!$A$8:$A$215,0),MATCH(BF$48,SAM!$B$7:$HA$7,0)),0) -> 5.7866884 | BG52: =_xlfn.IFNA(INDEX(SAM!$B$8:$HA$215,MATCH($BC52,SAM!$A$8:$A$215,0),MATCH(BG$48,SAM!$B$7:$HA$7,0)),0) -> 7.3859267 | BH52: =_xlfn.IFNA(INDEX(SAM!$B$8:$HA$215,MATCH($BC52,SAM!$A$8:$A$215,0),MATCH(BH$48,SAM!$B$7:$HA$7,0)),0) -> 9.9569551 | BI52: =_xlfn.IFNA(INDEX(SAM!$B$8:$HA$215,MATCH($BC52,SAM!$A$8:$A$215,0),MATCH(BI$48,SAM!$B$7:$HA$7,0)),0) -> 0 | BJ52: =_xlfn.IFNA(INDEX(SAM!$B$8:$HA$215,MATCH($BC52,SAM!$A$8:$A$215,0),MATCH(BJ$48,SAM!$B$7:$HA$7,0)),0) -> 0 | BK52: =_xlfn.IFNA(INDEX(SAM!$B$8:$HA$215,MATCH($BC52,SAM!$A$8:$A$215,0),MATCH(BK$48,SAM!$B$7:$HA$7,0)),0) -> 0 | ... BR52: =_xlfn.IFNA(INDEX(SAM!$B$8:$HA$215,MATCH($BC52,SAM!$A$8:$A$215,0),MATCH(BR$48,SAM!$B$7:$HA$7,0)),0) -> 0.52003646 | BT52: =AL52 -> cpuls | BU52: =SUM(BD52:BR52,AM52:BA52) -> 124.55554 | BW52: croot | BX52: =100*VLOOKUP(BW52,$BT$49:$BU$94,2,FALSE)/$BU$95 -> 3.1875478
A53: =HLOOKUP(B53,$B$6:$BR$9,4,FALSE) -> vegetables | B53: vege | C53: =IFERROR(100*U53/U$95,"") -> 11.354009 | D53: =IFERROR(100*V53/V$95,"") -> 9.837339 | E53: =IFERROR(100*W53/W$95,"") -> 8.1848849 | F53: =IFERROR(100*X53/X$95,"") -> 7.1705287 | G53: =IFERROR(100*Y53/Y$95,"") -> 4.6493467 | H53: =IFERROR(100*Z53/Z$95,"") -> 9.1680143 | I53: =IFERROR(100*AA53/AA$95,"") -> 7.6729356 | J53: =IFERROR(100*AB53/AB$95,"") -> 6.2326773 | ... R53: =IFERROR(100*AJ53/AJ$95,"") -> 5.2548374 | T53: =B53 -> vege | U53: =IFERROR(AM53+BD53,"") -> 29.795811 | V53: =IFERROR(AN53+BE53,"") -> 36.775244 | W53: =IFERROR(AO53+BF53,"") -> 47.70982 | X53: =IFERROR(AP53+BG53,"") -> 57.267077 | Y53: =IFERROR(AQ53+BH53,"") -> 66.474063 | Z53: =IFERROR(AR53+BI53,"") -> 1.5842793 | AA53: =IFERROR(AS53+BJ53,"") -> 1.7113814 | AB53: =IFERROR(AT53+BK53,"") -> 1.7125681 | ... AI53: =IFERROR(BA53+BR53,"") -> 63.529915 | AJ53: =SUM(U53:AI53) -> 343.23293 | AL53: ="c"&T53 -> cvege | AM53: =_xlfn.IFNA(INDEX(SAM!$B$8:$HA$215,MATCH($AL53,SAM!$A$8:$A$215,0),MATCH(AM$48,SAM!$B$7:$HA$7,0)),0) -> 19.095827 | AN53: =_xlfn.IFNA(INDEX(SAM!$B$8:$HA$215,MATCH($AL53,SAM!$A$8:$A$215,0),MATCH(AN$48,SAM!$B$7:$HA$7,0)),0) -> 21.570688 | AO53: =_xlfn.IFNA(INDEX(SAM!$B$8:$HA$215,MATCH($AL53,SAM!$A$8:$A$215,0),MATCH(AO$48,SAM!$B$7:$HA$7,0)),0) -> 29.597975 | AP53: =_xlfn.IFNA(INDEX(SAM!$B$8:$HA$215,MATCH($AL53,SAM!$A$8:$A$215,0),MATCH(AP$48,SAM!$B$7:$HA$7,0)),0) -> 37.162078 | AQ53: =_xlfn.IFNA(INDEX(SAM!$B$8:$HA$215,MATCH($AL53,SAM!$A$8:$A$215,0),MATCH(AQ$48,SAM!$B$7:$HA$7,0)),0) -> 48.698997 | AR53: =_xlfn.IFNA(INDEX(SAM!$B$8:$HA$215,MATCH($AL53,SAM!$A$8:$A$215,0),MATCH(AR$48,SAM!$B$7:$HA$7,0)),0) -> 1.5842793 | AS53: =_xlfn.IFNA(INDEX(SAM!$B$8:$HA$215,MATCH($AL53,SAM!$A$8:$A$215,0),MATCH(AS$48,SAM!$B$7:$HA$7,0)),0) -> 1.7113814 | AT53: =_xlfn.IFNA(INDEX(SAM!$B$8:$HA$215,MATCH($AL53,SAM!$A$8:$A$215,0),MATCH(AT$48,SAM!$B$7:$HA$7,0)),0) -> 1.7125681 | ... BA53: =_xlfn.IFNA(INDEX(SAM!$B$8:$HA$215,MATCH($AL53,SAM!$A$8:$A$215,0),MATCH(BA$48,SAM!$B$7:$HA$7,0)),0) -> 62.427713 | BC53: ="a"&T53 -> avege | BD53: =_xlfn.IFNA(INDEX(SAM!$B$8:$HA$215,MATCH($BC53,SAM!$A$8:$A$215,0),MATCH(BD$48,SAM!$B$7:$HA$7,0)),0) -> 10.699985 | BE53: =_xlfn.IFNA(INDEX(SAM!$B$8:$HA$215,MATCH($BC53,SAM!$A$8:$A$215,0),MATCH(BE$48,SAM!$B$7:$HA$7,0)),0) -> 15.204556 | BF53: =_xlfn.IFNA(INDEX(SAM!$B$8:$HA$215,MATCH($BC53,SAM!$A$8:$A$215,0),MATCH(BF$48,SAM!$B$7:$HA$7,0)),0) -> 18.111845 | BG53: =_xlfn.IFNA(INDEX(SAM!$B$8:$HA$215,MATCH($BC53,SAM!$A$8:$A$215,0),MATCH(BG$48,SAM!$B$7:$HA$7,0)),0) -> 20.104999 | BH53: =_xlfn.IFNA(INDEX(SAM!$B$8:$HA$215,MATCH($BC53,SAM!$A$8:$A$215,0),MATCH(BH$48,SAM!$B$7:$HA$7,0)),0) -> 17.775067 | BI53: =_xlfn.IFNA(INDEX(SAM!$B$8:$HA$215,MATCH($BC53,SAM!$A$8:$A$215,0),MATCH(BI$48,SAM!$B$7:$HA$7,0)),0) -> 0 | BJ53: =_xlfn.IFNA(INDEX(SAM!$B$8:$HA$215,MATCH($BC53,SAM!$A$8:$A$215,0),MATCH(BJ$48,SAM!$B$7:$HA$7,0)),0) -> 0 | BK53: =_xlfn.IFNA(INDEX(SAM!$B$8:$HA$215,MATCH($BC53,SAM!$A$8:$A$215,0),MATCH(BK$48,SAM!$B$7:$HA$7,0)),0) -> 0 | ... BR53: =_xlfn.IFNA(INDEX(SAM!$B$8:$HA$215,MATCH($BC53,SAM!$A$8:$A$215,0),MATCH(BR$48,SAM!$B$7:$HA$7,0)),0) -> 1.1022016 | BT53: =AL53 -> cvege | BU53: =SUM(BD53:BR53,AM53:BA53) -> 343.23293 | BW53: cvege | BX53: =100*VLOOKUP(BW53,$BT$49:$BU$94,2,FALSE)/$BU$95 -> 5.2548374
A54: =HLOOKUP(B54,$B$6:$BR$9,4,FALSE) -> fruits | B54: frui | C54: =IFERROR(100*U54/U$95,"") -> 1.8828582 | D54: =IFERROR(100*V54/V$95,"") -> 1.7663909 | E54: =IFERROR(100*W54/W$95,"") -> 2.1190367 | F54: =IFERROR(100*X54/X$95,"") -> 2.0651695 | G54: =IFERROR(100*Y54/Y$95,"") -> 2.0942914 | H54: =IFERROR(100*Z54/Z$95,"") -> 1.3586757 | I54: =IFERROR(100*AA54/AA$95,"") -> 1.7073252 | J54: =IFERROR(100*AB54/AB$95,"") -> 1.5228652 | ... R54: =IFERROR(100*AJ54/AJ$95,"") -> 1.6522598 | T54: =B54 -> frui | U54: =IFERROR(AM54+BD54,"") -> 4.9410997 | V54: =IFERROR(AN54+BE54,"") -> 6.6033565 | W54: =IFERROR(AO54+BF54,"") -> 12.351897 | X54: =IFERROR(AP54+BG54,"") -> 16.493375 | Y54: =IFERROR(AQ54+BH54,"") -> 29.943144 | Z54: =IFERROR(AR54+BI54,"") -> 0.23478604 | AA54: =IFERROR(AS54+BJ54,"") -> 0.38080399 | AB54: =IFERROR(AT54+BK54,"") -> 0.41844142 | ... AI54: =IFERROR(BA54+BR54,"") -> 26.933617 | AJ54: =SUM(U54:AI54) -> 107.9215 | AL54: ="c"&T54 -> cfrui | AM54: =_xlfn.IFNA(INDEX(SAM!$B$8:$HA$215,MATCH($AL54,SAM!$A$8:$A$215,0),MATCH(AM$48,SAM!$B$7:$HA$7,0)),0) -> 3.4216047 | AN54: =_xlfn.IFNA(INDEX(SAM!$B$8:$HA$215,MATCH($AL54,SAM!$A$8:$A$215,0),MATCH(AN$48,SAM!$B$7:$HA$7,0)),0) -> 4.4876461 | AO54: =_xlfn.IFNA(INDEX(SAM!$B$8:$HA$215,MATCH($AL54,SAM!$A$8:$A$215,0),MATCH(AO$48,SAM!$B$7:$HA$7,0)),0) -> 7.9930535 | AP54: =_xlfn.IFNA(INDEX(SAM!$B$8:$HA$215,MATCH($AL54,SAM!$A$8:$A$215,0),MATCH(AP$48,SAM!$B$7:$HA$7,0)),0) -> 11.026834 | AQ54: =_xlfn.IFNA(INDEX(SAM!$B$8:$HA$215,MATCH($AL54,SAM!$A$8:$A$215,0),MATCH(AQ$48,SAM!$B$7:$HA$7,0)),0) -> 19.70675 | AR54: =_xlfn.IFNA(INDEX(SAM!$B$8:$HA$215,MATCH($AL54,SAM!$A$8:$A$215,0),MATCH(AR$48,SAM!$B$7:$HA$7,0)),0) -> 0.23478604 | AS54: =_xlfn.IFNA(INDEX(SAM!$B$8:$HA$215,MATCH($AL54,SAM!$A$8:$A$215,0),MATCH(AS$48,SAM!$B$7:$HA$7,0)),0) -> 0.38080399 | AT54: =_xlfn.IFNA(INDEX(SAM!$B$8:$HA$215,MATCH($AL54,SAM!$A$8:$A$215,0),MATCH(AT$48,SAM!$B$7:$HA$7,0)),0) -> 0.41844142 | ... BA54: =_xlfn.IFNA(INDEX(SAM!$B$8:$HA$215,MATCH($AL54,SAM!$A$8:$A$215,0),MATCH(BA$48,SAM!$B$7:$HA$7,0)),0) -> 25.343375 | BC54: ="a"&T54 -> afrui | BD54: =_xlfn.IFNA(INDEX(SAM!$B$8:$HA$215,MATCH($BC54,SAM!$A$8:$A$215,0),MATCH(BD$48,SAM!$B$7:$HA$7,0)),0) -> 1.519495 | BE54: =_xlfn.IFNA(INDEX(SAM!$B$8:$HA$215,MATCH($BC54,SAM!$A$8:$A$215,0),MATCH(BE$48,SAM!$B$7:$HA$7,0)),0) -> 2.1157104 | BF54: =_xlfn.IFNA(INDEX(SAM!$B$8:$HA$215,MATCH($BC54,SAM!$A$8:$A$215,0),MATCH(BF$48,SAM!$B$7:$HA$7,0)),0) -> 4.3588438 | BG54: =_xlfn.IFNA(INDEX(SAM!$B$8:$HA$215,MATCH($BC54,SAM!$A$8:$A$215,0),MATCH(BG$48,SAM!$B$7:$HA$7,0)),0) -> 5.4665419 | BH54: =_xlfn.IFNA(INDEX(SAM!$B$8:$HA$215,MATCH($BC54,SAM!$A$8:$A$215,0),MATCH(BH$48,SAM!$B$7:$HA$7,0)),0) -> 10.236394 | BI54: =_xlfn.IFNA(INDEX(SAM!$B$8:$HA$215,MATCH($BC54,SAM!$A$8:$A$215,0),MATCH(BI$48,SAM!$B$7:$HA$7,0)),0) -> 0 | BJ54: =_xlfn.IFNA(INDEX(SAM!$B$8:$HA$215,MATCH($BC54,SAM!$A$8:$A$215,0),MATCH(BJ$48,SAM!$B$7:$HA$7,0)),0) -> 0 | BK54: =_xlfn.IFNA(INDEX(SAM!$B$8:$HA$215,MATCH($BC54,SAM!$A$8:$A$215,0),MATCH(BK$48,SAM!$B$7:$HA$7,0)),0) -> 0 | ... BR54: =_xlfn.IFNA(INDEX(SAM!$B$8:$HA$215,MATCH($BC54,SAM!$A$8:$A$215,0),MATCH(BR$48,SAM!$B$7:$HA$7,0)),0) -> 1.5902418 | BT54: =AL54 -> cfrui | BU54: =SUM(BD54:BR54,AM54:BA54) -> 107.9215 | BW54: cfrui | BX54: =100*VLOOKUP(BW54,$BT$49:$BU$94,2,FALSE)/$BU$95 -> 1.6522598
A55: =HLOOKUP(B55,$B$6:$BR$9,4,FALSE) -> fruits | B55: fveg | C55: =IFERROR(100*U55/U$95,"") -> 0.090420975 | D55: =IFERROR(100*V55/V$95,"") -> 0.087492397 | E55: =IFERROR(100*W55/W$95,"") -> 0.035792732 | F55: =IFERROR(100*X55/X$95,"") -> 0.041836273 | G55: =IFERROR(100*Y55/Y$95,"") -> 0.16860208 | H55: =IFERROR(100*Z55/Z$95,"") -> 0.081928398 | I55: =IFERROR(100*AA55/AA$95,"") -> 0.068418557 | J55: =IFERROR(100*AB55/AB$95,"") -> 0.1291474 | ... R55: =IFERROR(100*AJ55/AJ$95,"") -> 0.098269137 | T55: =B55 -> fveg | U55: =IFERROR(AM55+BD55,"") -> 0.23728767 | V55: =IFERROR(AN55+BE55,"") -> 0.32707566 | W55: =IFERROR(AO55+BF55,"") -> 0.20863638 | X55: =IFERROR(AP55+BG55,"") -> 0.33412335 | Y55: =IFERROR(AQ55+BH55,"") -> 2.4105893 | Z55: =IFERROR(AR55+BI55,"") -> 0.014157642 | AA55: =IFERROR(AS55+BJ55,"") -> 0.015260163 | AB55: =IFERROR(AT55+BK55,"") -> 0.035486149 | ... AI55: =IFERROR(BA55+BR55,"") -> 1.7303088 | AJ55: =SUM(U55:AI55) -> 6.4186959 | AL55: ="c"&T55 -> cfveg | AM55: =_xlfn.IFNA(INDEX(SAM!$B$8:$HA$215,MATCH($AL55,SAM!$A$8:$A$215,0),MATCH(AM$48,SAM!$B$7:$HA$7,0)),0) -> 0.23728767 | AN55: =_xlfn.IFNA(INDEX(SAM!$B$8:$HA$215,MATCH($AL55,SAM!$A$8:$A$215,0),MATCH(AN$48,SAM!$B$7:$HA$7,0)),0) -> 0.32707566 | AO55: =_xlfn.IFNA(INDEX(SAM!$B$8:$HA$215,MATCH($AL55,SAM!$A$8:$A$215,0),MATCH(AO$48,SAM!$B$7:$HA$7,0)),0) -> 0.20863638 | AP55: =_xlfn.IFNA(INDEX(SAM!$B$8:$HA$215,MATCH($AL55,SAM!$A$8:$A$215,0),MATCH(AP$48,SAM!$B$7:$HA$7,0)),0) -> 0.33412335 | AQ55: =_xlfn.IFNA(INDEX(SAM!$B$8:$HA$215,MATCH($AL55,SAM!$A$8:$A$215,0),MATCH(AQ$48,SAM!$B$7:$HA$7,0)),0) -> 2.4105893 | AR55: =_xlfn.IFNA(INDEX(SAM!$B$8:$HA$215,MATCH($AL55,SAM!$A$8:$A$215,0),MATCH(AR$48,SAM!$B$7:$HA$7,0)),0) -> 0.014157642 | AS55: =_xlfn.IFNA(INDEX(SAM!$B$8:$HA$215,MATCH($AL55,SAM!$A$8:$A$215,0),MATCH(AS$48,SAM!$B$7:$HA$7,0)),0) -> 0.015260163 | AT55: =_xlfn.IFNA(INDEX(SAM!$B$8:$HA$215,MATCH($AL55,SAM!$A$8:$A$215,0),MATCH(AT$48,SAM!$B$7:$HA$7,0)),0) -> 0.035486149 | ... BA55: =_xlfn.IFNA(INDEX(SAM!$B$8:$HA$215,MATCH($AL55,SAM!$A$8:$A$215,0),MATCH(BA$48,SAM!$B$7:$HA$7,0)),0) -> 1.7303088 | BC55: ="a"&T55 -> afveg | BD55: =_xlfn.IFNA(INDEX(SAM!$B$8:$HA$215,MATCH($BC55,SAM!$A$8:$A$215,0),MATCH(BD$48,SAM!$B$7:$HA$7,0)),0) -> 0 | BE55: =_xlfn.IFNA(INDEX(SAM!$B$8:$HA$215,MATCH($BC55,SAM!$A$8:$A$215,0),MATCH(BE$48,SAM!$B$7:$HA$7,0)),0) -> 0 | BF55: =_xlfn.IFNA(INDEX(SAM!$B$8:$HA$215,MATCH($BC55,SAM!$A$8:$A$215,0),MATCH(BF$48,SAM!$B$7:$HA$7,0)),0) -> 0 | BG55: =_xlfn.IFNA(INDEX(SAM!$B$8:$HA$215,MATCH($BC55,SAM!$A$8:$A$215,0),MATCH(BG$48,SAM!$B$7:$HA$7,0)),0) -> 0 | BH55: =_xlfn.IFNA(INDEX(SAM!$B$8:$HA$215,MATCH($BC55,SAM!$A$8:$A$215,0),MATCH(BH$48,SAM!$B$7:$HA$7,0)),0) -> 0 | BI55: =_xlfn.IFNA(INDEX(SAM!$B$8:$HA$215,MATCH($BC55,SAM!$A$8:$A$215,0),MATCH(BI$48,SAM!$B$7:$HA$7,0)),0) -> 0 | BJ55: =_xlfn.IFNA(INDEX(SAM!$B$8:$HA$215,MATCH($BC55,SAM!$A$8:$A$215,0),MATCH(BJ$48,SAM!$B$7:$HA$7,0)),0) -> 0 | BK55: =_xlfn.IFNA(INDEX(SAM!$B$8:$HA$215,MATCH($BC55,SAM!$A$8:$A$215,0),MATCH(BK$48,SAM!$B$7:$HA$7,0)),0) -> 0 | ... BR55: =_xlfn.IFNA(INDEX(SAM!$B$8:$HA$215,MATCH($BC55,SAM!$A$8:$A$215,0),MATCH(BR$48,SAM!$B$7:$HA$7,0)),0) -> 0 | BT55: =AL55 -> cfveg | BU55: =SUM(BD55:BR55,AM55:BA55) -> 6.4186959 | BW55: cbecr | BX55: =100*VLOOKUP(BW55,$BT$49:$BU$94,2,FALSE)/$BU$95 -> 0.51309862
A56: fish-meat-egg | B56: live | C56: =IFERROR(100*U56/U$95,"") -> 2.1033811 | D56: =IFERROR(100*V56/V$95,"") -> 4.3124879 | E56: =IFERROR(100*W56/W$95,"") -> 4.8770772 | F56: =IFERROR(100*X56/X$95,"") -> 6.2134222 | G56: =IFERROR(100*Y56/Y$95,"") -> 7.2499487 | H56: =IFERROR(100*Z56/Z$95,"") -> 0.52806262 | I56: =IFERROR(100*AA56/AA$95,"") -> 0.84634198 | J56: =IFERROR(100*AB56/AB$95,"") -> 0.89672774 | ... R56: =IFERROR(100*AJ56/AJ$95,"") -> 3.7183719 | T56: =B56 -> live | U56: =IFERROR(AM56+BD56,"") -> 5.5198077 | V56: =IFERROR(AN56+BE56,"") -> 16.121514 | W56: =IFERROR(AO56+BF56,"") -> 28.428558 | X56: =IFERROR(AP56+BG56,"") -> 49.623193 | Y56: =IFERROR(AQ56+BH56,"") -> 103.65619 | Z56: =IFERROR(AR56+BI56,"") -> 0.091251896 | AA56: =IFERROR(AS56+BJ56,"") -> 0.1887692 | AB56: =IFERROR(AT56+BK56,"") -> 0.24639609 | ... AI56: =IFERROR(BA56+BR56,"") -> 27.183735 | AJ56: =SUM(U56:AI56) -> 242.87482 | AL56: ="c"&T56 -> clive | AM56: =_xlfn.IFNA(INDEX(SAM!$B$8:$HA$215,MATCH($AL56,SAM!$A$8:$A$215,0),MATCH(AM$48,SAM!$B$7:$HA$7,0)),0) -> 1.4891142 | AN56: =_xlfn.IFNA(INDEX(SAM!$B$8:$HA$215,MATCH($AL56,SAM!$A$8:$A$215,0),MATCH(AN$48,SAM!$B$7:$HA$7,0)),0) -> 2.4682919 | AO56: =_xlfn.IFNA(INDEX(SAM!$B$8:$HA$215,MATCH($AL56,SAM!$A$8:$A$215,0),MATCH(AO$48,SAM!$B$7:$HA$7,0)),0) -> 5.6706408 | AP56: =_xlfn.IFNA(INDEX(SAM!$B$8:$HA$215,MATCH($AL56,SAM!$A$8:$A$215,0),MATCH(AP$48,SAM!$B$7:$HA$7,0)),0) -> 8.2130429 | AQ56: =_xlfn.IFNA(INDEX(SAM!$B$8:$HA$215,MATCH($AL56,SAM!$A$8:$A$215,0),MATCH(AQ$48,SAM!$B$7:$HA$7,0)),0) -> 14.741519 | AR56: =_xlfn.IFNA(INDEX(SAM!$B$8:$HA$215,MATCH($AL56,SAM!$A$8:$A$215,0),MATCH(AR$48,SAM!$B$7:$HA$7,0)),0) -> 0.091251896 | AS56: =_xlfn.IFNA(INDEX(SAM!$B$8:$HA$215,MATCH($AL56,SAM!$A$8:$A$215,0),MATCH(AS$48,SAM!$B$7:$HA$7,0)),0) -> 0.1887692 | AT56: =_xlfn.IFNA(INDEX(SAM!$B$8:$HA$215,MATCH($AL56,SAM!$A$8:$A$215,0),MATCH(AT$48,SAM!$B$7:$HA$7,0)),0) -> 0.24639609 | ... BA56: =_xlfn.IFNA(INDEX(SAM!$B$8:$HA$215,MATCH($AL56,SAM!$A$8:$A$215,0),MATCH(BA$48,SAM!$B$7:$HA$7,0)),0) -> 23.049928 | BC56: ="a"&T56 -> alive | BD56: =_xlfn.IFNA(INDEX(SAM!$B$8:$HA$215,MATCH($BC56,SAM!$A$8:$A$215,0),MATCH(BD$48,SAM!$B$7:$HA$7,0)),0) -> 4.0306935 | BE56: =_xlfn.IFNA(INDEX(SAM!$B$8:$HA$215,MATCH($BC56,SAM!$A$8:$A$215,0),MATCH(BE$48,SAM!$B$7:$HA$7,0)),0) -> 13.653222 | BF56: =_xlfn.IFNA(INDEX(SAM!$B$8:$HA$215,MATCH($BC56,SAM!$A$8:$A$215,0),MATCH(BF$48,SAM!$B$7:$HA$7,0)),0) -> 22.757917 | BG56: =_xlfn.IFNA(INDEX(SAM!$B$8:$HA$215,MATCH($BC56,SAM!$A$8:$A$215,0),MATCH(BG$48,SAM!$B$7:$HA$7,0)),0) -> 41.41015 | BH56: =_xlfn.IFNA(INDEX(SAM!$B$8:$HA$215,MATCH($BC56,SAM!$A$8:$A$215,0),MATCH(BH$48,SAM!$B$7:$HA$7,0)),0) -> 88.914667 | BI56: =_xlfn.IFNA(INDEX(SAM!$B$8:$HA$215,MATCH($BC56,SAM!$A$8:$A$215,0),MATCH(BI$48,SAM!$B$7:$HA$7,0)),0) -> 0 | BJ56: =_xlfn.IFNA(INDEX(SAM!$B$8:$HA$215,MATCH($BC56,SAM!$A$8:$A$215,0),MATCH(BJ$48,SAM!$B$7:$HA$7,0)),0) -> 0 | BK56: =_xlfn.IFNA(INDEX(SAM!$B$8:$HA$215,MATCH($BC56,SAM!$A$8:$A$215,0),MATCH(BK$48,SAM!$B$7:$HA$7,0)),0) -> 0 | ... BR56: =_xlfn.IFNA(INDEX(SAM!$B$8:$HA$215,MATCH($BC56,SAM!$A$8:$A$215,0),MATCH(BR$48,SAM!$B$7:$HA$7,0)),0) -> 4.1338071 | BT56: =AL56 -> clive | BU56: =SUM(BD56:BR56,AM56:BA56) -> 242.87482 | BW56: cocrp | BX56: =100*VLOOKUP(BW56,$BT$49:$BU$94,2,FALSE)/$BU$95 -> 0.1085104
A57: =HLOOKUP(B57,$B$6:$BR$9,4,FALSE) -> fish-meat-egg | B57: fish | C57: =IFERROR(100*U57/U$95,"") -> 0.67878696 | D57: =IFERROR(100*V57/V$95,"") -> 0.94628967 | E57: =IFERROR(100*W57/W$95,"") -> 0.91146314 | F57: =IFERROR(100*X57/X$95,"") -> 1.2856469 | G57: =IFERROR(100*Y57/Y$95,"") -> 1.3777619 | H57: =IFERROR(100*Z57/Z$95,"") -> 1.7498311 | I57: =IFERROR(100*AA57/AA$95,"") -> 1.5580845 | J57: =IFERROR(100*AB57/AB$95,"") -> 2.7023991 | ... R57: =IFERROR(100*AJ57/AJ$95,"") -> 1.1430414 | T57: =B57 -> fish | U57: =IFERROR(AM57+BD57,"") -> 1.7813099 | V57: =IFERROR(AN57+BE57,"") -> 3.5375454 | W57: =IFERROR(AO57+BF57,"") -> 5.3129327 | X57: =IFERROR(AP57+BG57,"") -> 10.267756 | Y57: =IFERROR(AQ57+BH57,"") -> 19.698559 | Z57: =IFERROR(AR57+BI57,"") -> 0.30237967 | AA57: =IFERROR(AS57+BJ57,"") -> 0.34751716 | AB57: =IFERROR(AT57+BK57,"") -> 0.74254484 | ... AI57: =IFERROR(BA57+BR57,"") -> 23.431005 | AJ57: =SUM(U57:AI57) -> 74.660622 | AL57: ="c"&T57 -> cfish | AM57: =_xlfn.IFNA(INDEX(SAM!$B$8:$HA$215,MATCH($AL57,SAM!$A$8:$A$215,0),MATCH(AM$48,SAM!$B$7:$HA$7,0)),0) -> 1.5775454 | AN57: =_xlfn.IFNA(INDEX(SAM!$B$8:$HA$215,MATCH($AL57,SAM!$A$8:$A$215,0),MATCH(AN$48,SAM!$B$7:$HA$7,0)),0) -> 3.2646116 | AO57: =_xlfn.IFNA(INDEX(SAM!$B$8:$HA$215,MATCH($AL57,SAM!$A$8:$A$215,0),MATCH(AO$48,SAM!$B$7:$HA$7,0)),0) -> 4.9660069 | AP57: =_xlfn.IFNA(INDEX(SAM!$B$8:$HA$215,MATCH($AL57,SAM!$A$8:$A$215,0),MATCH(AP$48,SAM!$B$7:$HA$7,0)),0) -> 9.215608 | AQ57: =_xlfn.IFNA(INDEX(SAM!$B$8:$HA$215,MATCH($AL57,SAM!$A$8:$A$215,0),MATCH(AQ$48,SAM!$B$7:$HA$7,0)),0) -> 18.109645 | AR57: =_xlfn.IFNA(INDEX(SAM!$B$8:$HA$215,MATCH($AL57,SAM!$A$8:$A$215,0),MATCH(AR$48,SAM!$B$7:$HA$7,0)),0) -> 0.30237967 | AS57: =_xlfn.IFNA(INDEX(SAM!$B$8:$HA$215,MATCH($AL57,SAM!$A$8:$A$215,0),MATCH(AS$48,SAM!$B$7:$HA$7,0)),0) -> 0.34751716 | AT57: =_xlfn.IFNA(INDEX(SAM!$B$8:$HA$215,MATCH($AL57,SAM!$A$8:$A$215,0),MATCH(AT$48,SAM!$B$7:$HA$7,0)),0) -> 0.74254484 | ... BA57: =_xlfn.IFNA(INDEX(SAM!$B$8:$HA$215,MATCH($AL57,SAM!$A$8:$A$215,0),MATCH(BA$48,SAM!$B$7:$HA$7,0)),0) -> 23.13402 | BC57: ="a"&T57 -> afish | BD57: =_xlfn.IFNA(INDEX(SAM!$B$8:$HA$215,MATCH($BC57,SAM!$A$8:$A$215,0),MATCH(BD$48,SAM!$B$7:$HA$7,0)),0) -> 0.2037645 | BE57: =_xlfn.IFNA(INDEX(SAM!$B$8:$HA$215,MATCH($BC57,SAM!$A$8:$A$215,0),MATCH(BE$48,SAM!$B$7:$HA$7,0)),0) -> 0.2729338 | BF57: =_xlfn.IFNA(INDEX(SAM!$B$8:$HA$215,MATCH($BC57,SAM!$A$8:$A$215,0),MATCH(BF$48,SAM!$B$7:$HA$7,0)),0) -> 0.34692581 | BG57: =_xlfn.IFNA(INDEX(SAM!$B$8:$HA$215,MATCH($BC57,SAM!$A$8:$A$215,0),MATCH(BG$48,SAM!$B$7:$HA$7,0)),0) -> 1.0521477 | BH57: =_xlfn.IFNA(INDEX(SAM!$B$8:$HA$215,MATCH($BC57,SAM!$A$8:$A$215,0),MATCH(BH$48,SAM!$B$7:$HA$7,0)),0) -> 1.588914 | BI57: =_xlfn.IFNA(INDEX(SAM!$B$8:$HA$215,MATCH($BC57,SAM!$A$8:$A$215,0),MATCH(BI$48,SAM!$B$7:$HA$7,0)),0) -> 0 | BJ57: =_xlfn.IFNA(INDEX(SAM!$B$8:$HA$215,MATCH($BC57,SAM!$A$8:$A$215,0),MATCH(BJ$48,SAM!$B$7:$HA$7,0)),0) -> 0 | BK57: =_xlfn.IFNA(INDEX(SAM!$B$8:$HA$215,MATCH($BC57,SAM!$A$8:$A$215,0),MATCH(BK$48,SAM!$B$7:$HA$7,0)),0) -> 0 | ... BR57: =_xlfn.IFNA(INDEX(SAM!$B$8:$HA$215,MATCH($BC57,SAM!$A$8:$A$215,0),MATCH(BR$48,SAM!$B$7:$HA$7,0)),0) -> 0.29698475 | BT57: =AL57 -> cfish | BU57: =SUM(BD57:BR57,AM57:BA57) -> 74.660622 | BW57: clive | BX57: =100*VLOOKUP(BW57,$BT$49:$BU$94,2,FALSE)/$BU$95 -> 3.7183719
A58: =HLOOKUP(B58,$B$6:$BR$9,4,FALSE) -> fish-meat-egg | B58: meat | C58: =IFERROR(100*U58/U$95,"") -> 1.2394424 | D58: =IFERROR(100*V58/V$95,"") -> 2.6740354 | E58: =IFERROR(100*W58/W$95,"") -> 3.6742802 | F58: =IFERROR(100*X58/X$95,"") -> 4.5194522 | G58: =IFERROR(100*Y58/Y$95,"") -> 6.7622685 | H58: =IFERROR(100*Z58/Z$95,"") -> 1.6780346 | I58: =IFERROR(100*AA58/AA$95,"") -> 4.7187122 | J58: =IFERROR(100*AB58/AB$95,"") -> 6.4810024 | ... R58: =IFERROR(100*AJ58/AJ$95,"") -> 5.3593587 | T58: =B58 -> meat | U58: =IFERROR(AM58+BD58,"") -> 3.2526125 | V58: =IFERROR(AN58+BE58,"") -> 9.9964334 | W58: =IFERROR(AO58+BF58,"") -> 21.417436 | X58: =IFERROR(AP58+BG58,"") -> 36.094384 | Y58: =IFERROR(AQ58+BH58,"") -> 96.683575 | Z58: =IFERROR(AR58+BI58,"") -> 0.28997288 | AA58: =IFERROR(AS58+BJ58,"") -> 1.0524676 | AB58: =IFERROR(AT58+BK58,"") -> 1.780801 | ... AI58: =IFERROR(BA58+BR58,"") -> 140.16219 | AJ58: =SUM(U58:AI58) -> 350.06 | AL58: ="c"&T58 -> cmeat | AM58: =_xlfn.IFNA(INDEX(SAM!$B$8:$HA$215,MATCH($AL58,SAM!$A$8:$A$215,0),MATCH(AM$48,SAM!$B$7:$HA$7,0)),0) -> 3.2526125 | AN58: =_xlfn.IFNA(INDEX(SAM!$B$8:$HA$215,MATCH($AL58,SAM!$A$8:$A$215,0),MATCH(AN$48,SAM!$B$7:$HA$7,0)),0) -> 9.9964334 | AO58: =_xlfn.IFNA(INDEX(SAM!$B$8:$HA$215,MATCH($AL58,SAM!$A$8:$A$215,0),MATCH(AO$48,SAM!$B$7:$HA$7,0)),0) -> 21.417436 | AP58: =_xlfn.IFNA(INDEX(SAM!$B$8:$HA$215,MATCH($AL58,SAM!$A$8:$A$215,0),MATCH(AP$48,SAM!$B$7:$HA$7,0)),0) -> 36.094384 | AQ58: =_xlfn.IFNA(INDEX(SAM!$B$8:$HA$215,MATCH($AL58,SAM!$A$8:$A$215,0),MATCH(AQ$48,SAM!$B$7:$HA$7,0)),0) -> 96.683575 | AR58: =_xlfn.IFNA(INDEX(SAM!$B$8:$HA$215,MATCH($AL58,SAM!$A$8:$A$215,0),MATCH(AR$48,SAM!$B$7:$HA$7,0)),0) -> 0.28997288 | AS58: =_xlfn.IFNA(INDEX(SAM!$B$8:$HA$215,MATCH($AL58,SAM!$A$8:$A$215,0),MATCH(AS$48,SAM!$B$7:$HA$7,0)),0) -> 1.0524676 | AT58: =_xlfn.IFNA(INDEX(SAM!$B$8:$HA$215,MATCH($AL58,SAM!$A$8:$A$215,0),MATCH(AT$48,SAM!$B$7:$HA$7,0)),0) -> 1.780801 | ... BA58: =_xlfn.IFNA(INDEX(SAM!$B$8:$HA$215,MATCH($AL58,SAM!$A$8:$A$215,0),MATCH(BA$48,SAM!$B$7:$HA$7,0)),0) -> 140.16219 | BC58: ="a"&T58 -> ameat | BD58: =_xlfn.IFNA(INDEX(SAM!$B$8:$HA$215,MATCH($BC58,SAM!$A$8:$A$215,0),MATCH(BD$48,SAM!$B$7:$HA$7,0)),0) -> 0 | BE58: =_xlfn.IFNA(INDEX(SAM!$B$8:$HA$215,MATCH($BC58,SAM!$A$8:$A$215,0),MATCH(BE$48,SAM!$B$7:$HA$7,0)),0) -> 0 | BF58: =_xlfn.IFNA(INDEX(SAM!$B$8:$HA$215,MATCH($BC58,SAM!$A$8:$A$215,0),MATCH(BF$48,SAM!$B$7:$HA$7,0)),0) -> 0 | BG58: =_xlfn.IFNA(INDEX(SAM!$B$8:$HA$215,MATCH($BC58,SAM!$A$8:$A$215,0),MATCH(BG$48,SAM!$B$7:$HA$7,0)),0) -> 0 | BH58: =_xlfn.IFNA(INDEX(SAM!$B$8:$HA$215,MATCH($BC58,SAM!$A$8:$A$215,0),MATCH(BH$48,SAM!$B$7:$HA$7,0)),0) -> 0 | BI58: =_xlfn.IFNA(INDEX(SAM!$B$8:$HA$215,MATCH($BC58,SAM!$A$8:$A$215,0),MATCH(BI$48,SAM!$B$7:$HA$7,0)),0) -> 0 | BJ58: =_xlfn.IFNA(INDEX(SAM!$B$8:$HA$215,MATCH($BC58,SAM!$A$8:$A$215,0),MATCH(BJ$48,SAM!$B$7:$HA$7,0)),0) -> 0 | BK58: =_xlfn.IFNA(INDEX(SAM!$B$8:$HA$215,MATCH($BC58,SAM!$A$8:$A$215,0),MATCH(BK$48,SAM!$B$7:$HA$7,0)),0) -> 0 | ... BR58: =_xlfn.IFNA(INDEX(SAM!$B$8:$HA$215,MATCH($BC58,SAM!$A$8:$A$215,0),MATCH(BR$48,SAM!$B$7:$HA$7,0)),0) -> 0 | BT58: =AL58 -> cmeat | BU58: =SUM(BD58:BR58,AM58:BA58) -> 350.06 | BW58: cmilk | BX58: =100*VLOOKUP(BW58,$BT$49:$BU$94,2,FALSE)/$BU$95 -> 0.39270299
A59: =HLOOKUP(B59,$B$6:$BR$9,4,FALSE) -> fish-meat-egg | B59: fsea | C59: =IFERROR(100*U59/U$95,"") -> 4.0156553 | D59: =IFERROR(100*V59/V$95,"") -> 3.6662134 | E59: =IFERROR(100*W59/W$95,"") -> 3.9427699 | F59: =IFERROR(100*X59/X$95,"") -> 4.0402836 | G59: =IFERROR(100*Y59/Y$95,"") -> 3.4004323 | H59: =IFERROR(100*Z59/Z$95,"") -> 4.6304527 | I59: =IFERROR(100*AA59/AA$95,"") -> 5.1184472 | J59: =IFERROR(100*AB59/AB$95,"") -> 4.8162561 | ... R59: =IFERROR(100*AJ59/AJ$95,"") -> 3.1714307 | T59: =B59 -> fsea | U59: =IFERROR(AM59+BD59,"") -> 10.538102 | V59: =IFERROR(AN59+BE59,"") -> 13.705524 | W59: =IFERROR(AO59+BF59,"") -> 22.982466 | X59: =IFERROR(AP59+BG59,"") -> 32.267527 | Y59: =IFERROR(AQ59+BH59,"") -> 48.617702 | Z59: =IFERROR(AR59+BI59,"") -> 0.8001657 | AA59: =IFERROR(AS59+BJ59,"") -> 1.141625 | AB59: =IFERROR(AT59+BK59,"") -> 1.3233745 | ... AI59: =IFERROR(BA59+BR59,"") -> 49.564839 | AJ59: =SUM(U59:AI59) -> 207.14998 | AL59: ="c"&T59 -> cfsea | AM59: =_xlfn.IFNA(INDEX(SAM!$B$8:$HA$215,MATCH($AL59,SAM!$A$8:$A$215,0),MATCH(AM$48,SAM!$B$7:$HA$7,0)),0) -> 10.538102 | AN59: =_xlfn.IFNA(INDEX(SAM!$B$8:$HA$215,MATCH($AL59,SAM!$A$8:$A$215,0),MATCH(AN$48,SAM!$B$7:$HA$7,0)),0) -> 13.705524 | AO59: =_xlfn.IFNA(INDEX(SAM!$B$8:$HA$215,MATCH($AL59,SAM!$A$8:$A$215,0),MATCH(AO$48,SAM!$B$7:$HA$7,0)),0) -> 22.982466 | AP59: =_xlfn.IFNA(INDEX(SAM!$B$8:$HA$215,MATCH($AL59,SAM!$A$8:$A$215,0),MATCH(AP$48,SAM!$B$7:$HA$7,0)),0) -> 32.267527 | AQ59: =_xlfn.IFNA(INDEX(SAM!$B$8:$HA$215,MATCH($AL59,SAM!$A$8:$A$215,0),MATCH(AQ$48,SAM!$B$7:$HA$7,0)),0) -> 48.617702 | AR59: =_xlfn.IFNA(INDEX(SAM!$B$8:$HA$215,MATCH($AL59,SAM!$A$8:$A$215,0),MATCH(AR$48,SAM!$B$7:$HA$7,0)),0) -> 0.8001657 | AS59: =_xlfn.IFNA(INDEX(SAM!$B$8:$HA$215,MATCH($AL59,SAM!$A$8:$A$215,0),MATCH(AS$48,SAM!$B$7:$HA$7,0)),0) -> 1.141625 | AT59: =_xlfn.IFNA(INDEX(SAM!$B$8:$HA$215,MATCH($AL59,SAM!$A$8:$A$215,0),MATCH(AT$48,SAM!$B$7:$HA$7,0)),0) -> 1.3233745 | ... BA59: =_xlfn.IFNA(INDEX(SAM!$B$8:$HA$215,MATCH($AL59,SAM!$A$8:$A$215,0),MATCH(BA$48,SAM!$B$7:$HA$7,0)),0) -> 49.564839 | BC59: ="a"&T59 -> afsea | BD59: =_xlfn.IFNA(INDEX(SAM!$B$8:$HA$215,MATCH($BC59,SAM!$A$8:$A$215,0),MATCH(BD$48,SAM!$B$7:$HA$7,0)),0) -> 0 | BE59: =_xlfn.IFNA(INDEX(SAM!$B$8:$HA$215,MATCH($BC59,SAM!$A$8:$A$215,0),MATCH(BE$48,SAM!$B$7:$HA$7,0)),0) -> 0 | BF59: =_xlfn.IFNA(INDEX(SAM!$B$8:$HA$215,MATCH($BC59,SAM!$A$8:$A$215,0),MATCH(BF$48,SAM!$B$7:$HA$7,0)),0) -> 0 | BG59: =_xlfn.IFNA(INDEX(SAM!$B$8:$HA$215,MATCH($BC59,SAM!$A$8:$A$215,0),MATCH(BG$48,SAM!$B$7:$HA$7,0)),0) -> 0 | BH59: =_xlfn.IFNA(INDEX(SAM!$B$8:$HA$215,MATCH($BC59,SAM!$A$8:$A$215,0),MATCH(BH$48,SAM!$B$7:$HA$7,0)),0) -> 0 | BI59: =_xlfn.IFNA(INDEX(SAM!$B$8:$HA$215,MATCH($BC59,SAM!$A$8:$A$215,0),MATCH(BI$48,SAM!$B$7:$HA$7,0)),0) -> 0 | BJ59: =_xlfn.IFNA(INDEX(SAM!$B$8:$HA$215,MATCH($BC59,SAM!$A$8:$A$215,0),MATCH(BJ$48,SAM!$B$7:$HA$7,0)),0) -> 0 | BK59: =_xlfn.IFNA(INDEX(SAM!$B$8:$HA$215,MATCH($BC59,SAM!$A$8:$A$215,0),MATCH(BK$48,SAM!$B$7:$HA$7,0)),0) -> 0 | ... BR59: =_xlfn.IFNA(INDEX(SAM!$B$8:$HA$215,MATCH($BC59,SAM!$A$8:$A$215,0),MATCH(BR$48,SAM!$B$7:$HA$7,0)),0) -> 0 | BT59: =AL59 -> cfsea | BU59: =SUM(BD59:BR59,AM59:BA59) -> 207.14998 | BW59: cfore | BX59: =100*VLOOKUP(BW59,$BT$49:$BU$94,2,FALSE)/$BU$95 -> 0.2005329
A60: =HLOOKUP(B60,$B$6:$BR$9,4,FALSE) -> diary | B60: milk | C60: =IFERROR(100*U60/U$95,"") -> 0.024753035 | D60: =IFERROR(100*V60/V$95,"") -> 0.11124841 | E60: =IFERROR(100*W60/W$95,"") -> 0.15233073 | F60: =IFERROR(100*X60/X$95,"") -> 0.36330092 | G60: =IFERROR(100*Y60/Y$95,"") -> 0.51592516 | H60: =IFERROR(100*Z60/Z$95,"") -> 0.029561342 | I60: =IFERROR(100*AA60/AA$95,"") -> 0.061297281 | J60: =IFERROR(100*AB60/AB$95,"") -> 0.065559164 | ... R60: =IFERROR(100*AJ60/AJ$95,"") -> 0.39270299 | T60: =B60 -> milk | U60: =IFERROR(AM60+BD60,"") -> 0.064958268 | V60: =IFERROR(AN60+BE60,"") -> 0.41588353 | W60: =IFERROR(AO60+BF60,"") -> 0.88793817 | X60: =IFERROR(AP60+BG60,"") -> 2.9014851 | Y60: =IFERROR(AQ60+BH60,"") -> 7.3764432 | Z60: =IFERROR(AR60+BI60,"") -> 0.0051083497 | AA60: =IFERROR(AS60+BJ60,"") -> 0.013671824 | AB60: =IFERROR(AT60+BK60,"") -> 0.018013853 | ... AI60: =IFERROR(BA60+BR60,"") -> 11.219561 | AJ60: =SUM(U60:AI60) -> 25.650384 | AL60: ="c"&T60 -> cmilk | AM60: =_xlfn.IFNA(INDEX(SAM!$B$8:$HA$215,MATCH($AL60,SAM!$A$8:$A$215,0),MATCH(AM$48,SAM!$B$7:$HA$7,0)),0) -> 0.060573622 | AN60: =_xlfn.IFNA(INDEX(SAM!$B$8:$HA$215,MATCH($AL60,SAM!$A$8:$A$215,0),MATCH(AN$48,SAM!$B$7:$HA$7,0)),0) -> 0.30495919 | AO60: =_xlfn.IFNA(INDEX(SAM!$B$8:$HA$215,MATCH($AL60,SAM!$A$8:$A$215,0),MATCH(AO$48,SAM!$B$7:$HA$7,0)),0) -> 0.52315584 | AP60: =_xlfn.IFNA(INDEX(SAM!$B$8:$HA$215,MATCH($AL60,SAM!$A$8:$A$215,0),MATCH(AP$48,SAM!$B$7:$HA$7,0)),0) -> 2.0424825 | AQ60: =_xlfn.IFNA(INDEX(SAM!$B$8:$HA$215,MATCH($AL60,SAM!$A$8:$A$215,0),MATCH(AQ$48,SAM!$B$7:$HA$7,0)),0) -> 5.5159526 | AR60: =_xlfn.IFNA(INDEX(SAM!$B$8:$HA$215,MATCH($AL60,SAM!$A$8:$A$215,0),MATCH(AR$48,SAM!$B$7:$HA$7,0)),0) -> 0.0051083497 | AS60: =_xlfn.IFNA(INDEX(SAM!$B$8:$HA$215,MATCH($AL60,SAM!$A$8:$A$215,0),MATCH(AS$48,SAM!$B$7:$HA$7,0)),0) -> 0.013671824 | AT60: =_xlfn.IFNA(INDEX(SAM!$B$8:$HA$215,MATCH($AL60,SAM!$A$8:$A$215,0),MATCH(AT$48,SAM!$B$7:$HA$7,0)),0) -> 0.018013853 | ... BA60: =_xlfn.IFNA(INDEX(SAM!$B$8:$HA$215,MATCH($AL60,SAM!$A$8:$A$215,0),MATCH(BA$48,SAM!$B$7:$HA$7,0)),0) -> 11.075584 | BC60: ="a"&T60 -> amilk | BD60: =_xlfn.IFNA(INDEX(SAM!$B$8:$HA$215,MATCH($BC60,SAM!$A$8:$A$215,0),MATCH(BD$48,SAM!$B$7:$HA$7,0)),0) -> 0.0043846467 | BE60: =_xlfn.IFNA(INDEX(SAM!$B$8:$HA$215,MATCH($BC60,SAM!$A$8:$A$215,0),MATCH(BE$48,SAM!$B$7:$HA$7,0)),0) -> 0.11092434 | BF60: =_xlfn.IFNA(INDEX(SAM!$B$8:$HA$215,MATCH($BC60,SAM!$A$8:$A$215,0),MATCH(BF$48,SAM!$B$7:$HA$7,0)),0) -> 0.36478232 | BG60: =_xlfn.IFNA(INDEX(SAM!$B$8:$HA$215,MATCH($BC60,SAM!$A$8:$A$215,0),MATCH(BG$48,SAM!$B$7:$HA$7,0)),0) -> 0.85900255 | BH60: =_xlfn.IFNA(INDEX(SAM!$B$8:$HA$215,MATCH($BC60,SAM!$A$8:$A$215,0),MATCH(BH$48,SAM!$B$7:$HA$7,0)),0) -> 1.8604905 | BI60: =_xlfn.IFNA(INDEX(SAM!$B$8:$HA$215,MATCH($BC60,SAM!$A$8:$A$215,0),MATCH(BI$48,SAM!$B$7:$HA$7,0)),0) -> 0 | BJ60: =_xlfn.IFNA(INDEX(SAM!$B$8:$HA$215,MATCH($BC60,SAM!$A$8:$A$215,0),MATCH(BJ$48,SAM!$B$7:$HA$7,0)),0) -> 0 | BK60: =_xlfn.IFNA(INDEX(SAM!$B$8:$HA$215,MATCH($BC60,SAM!$A$8:$A$215,0),MATCH(BK$48,SAM!$B$7:$HA$7,0)),0) -> 0 | ... BR60: =_xlfn.IFNA(INDEX(SAM!$B$8:$HA$215,MATCH($BC60,SAM!$A$8:$A$215,0),MATCH(BR$48,SAM!$B$7:$HA$7,0)),0) -> 0.14397703 | BT60: =AL60 -> cmilk | BU60: =SUM(BD60:BR60,AM60:BA60) -> 25.650384 | BW60: cfish | BX60: =100*VLOOKUP(BW60,$BT$49:$BU$94,2,FALSE)/$BU$95 -> 1.1430414
A61: =HLOOKUP(B61,$B$6:$BR$9,4,FALSE) -> diary | B61: dair | C61: =IFERROR(100*U61/U$95,"") -> 0.019094611 | D61: =IFERROR(100*V61/V$95,"") -> 0.10584059 | E61: =IFERROR(100*W61/W$95,"") -> 0.13098262 | F61: =IFERROR(100*X61/X$95,"") -> 0.25819541 | G61: =IFERROR(100*Y61/Y$95,"") -> 0.41930769 | H61: =IFERROR(100*Z61/Z$95,"") -> 0.13821743 | I61: =IFERROR(100*AA61/AA$95,"") -> 0.020155396 | J61: =IFERROR(100*AB61/AB$95,"") -> 0.29101045 | ... R61: =IFERROR(100*AJ61/AJ$95,"") -> 0.3445448 | T61: =B61 -> dair | U61: =IFERROR(AM61+BD61,"") -> 0.050109123 | V61: =IFERROR(AN61+BE61,"") -> 0.39566731 | W61: =IFERROR(AO61+BF61,"") -> 0.7634997 | X61: =IFERROR(AP61+BG61,"") -> 2.062065 | Y61: =IFERROR(AQ61+BH61,"") -> 5.9950542 | Z61: =IFERROR(AR61+BI61,"") -> 0.023884672 | AA61: =IFERROR(AS61+BJ61,"") -> 0.0044954854 | AB61: =IFERROR(AT61+BK61,"") -> 0.079961656 | ... AI61: =IFERROR(BA61+BR61,"") -> 10.168249 | AJ61: =SUM(U61:AI61) -> 22.50481 | AL61: ="c"&T61 -> cdair | AM61: =_xlfn.IFNA(INDEX(SAM!$B$8:$HA$215,MATCH($AL61,SAM!$A$8:$A$215,0),MATCH(AM$48,SAM!$B$7:$HA$7,0)),0) -> 0.050109123 | AN61: =_xlfn.IFNA(INDEX(SAM!$B$8:$HA$215,MATCH($AL61,SAM!$A$8:$A$215,0),MATCH(AN$48,SAM!$B$7:$HA$7,0)),0) -> 0.39566731 | AO61: =_xlfn.IFNA(INDEX(SAM!$B$8:$HA$215,MATCH($AL61,SAM!$A$8:$A$215,0),MATCH(AO$48,SAM!$B$7:$HA$7,0)),0) -> 0.7634997 | AP61: =_xlfn.IFNA(INDEX(SAM!$B$8:$HA$215,MATCH($AL61,SAM!$A$8:$A$215,0),MATCH(AP$48,SAM!$B$7:$HA$7,0)),0) -> 2.062065 | AQ61: =_xlfn.IFNA(INDEX(SAM!$B$8:$HA$215,MATCH($AL61,SAM!$A$8:$A$215,0),MATCH(AQ$48,SAM!$B$7:$HA$7,0)),0) -> 5.9950542 | AR61: =_xlfn.IFNA(INDEX(SAM!$B$8:$HA$215,MATCH($AL61,SAM!$A$8:$A$215,0),MATCH(AR$48,SAM!$B$7:$HA$7,0)),0) -> 0.023884672 | AS61: =_xlfn.IFNA(INDEX(SAM!$B$8:$HA$215,MATCH($AL61,SAM!$A$8:$A$215,0),MATCH(AS$48,SAM!$B$7:$HA$7,0)),0) -> 0.0044954854 | AT61: =_xlfn.IFNA(INDEX(SAM!$B$8:$HA$215,MATCH($AL61,SAM!$A$8:$A$215,0),MATCH(AT$48,SAM!$B$7:$HA$7,0)),0) -> 0.079961656 | ... BA61: =_xlfn.IFNA(INDEX(SAM!$B$8:$HA$215,MATCH($AL61,SAM!$A$8:$A$215,0),MATCH(BA$48,SAM!$B$7:$HA$7,0)),0) -> 10.168249 | BC61: ="a"&T61 -> adair | BD61: =_xlfn.IFNA(INDEX(SAM!$B$8:$HA$215,MATCH($BC61,SAM!$A$8:$A$215,0),MATCH(BD$48,SAM!$B$7:$HA$7,0)),0) -> 0 | BE61: =_xlfn.IFNA(INDEX(SAM!$B$8:$HA$215,MATCH($BC61,SAM!$A$8:$A$215,0),MATCH(BE$48,SAM!$B$7:$HA$7,0)),0) -> 0 | BF61: =_xlfn.IFNA(INDEX(SAM!$B$8:$HA$215,MATCH($BC61,SAM!$A$8:$A$215,0),MATCH(BF$48,SAM!$B$7:$HA$7,0)),0) -> 0 | BG61: =_xlfn.IFNA(INDEX(SAM!$B$8:$HA$215,MATCH($BC61,SAM!$A$8:$A$215,0),MATCH(BG$48,SAM!$B$7:$HA$7,0)),0) -> 0 | BH61: =_xlfn.IFNA(INDEX(SAM!$B$8:$HA$215,MATCH($BC61,SAM!$A$8:$A$215,0),MATCH(BH$48,SAM!$B$7:$HA$7,0)),0) -> 0 | BI61: =_xlfn.IFNA(INDEX(SAM!$B$8:$HA$215,MATCH($BC61,SAM!$A$8:$A$215,0),MATCH(BI$48,SAM!$B$7:$HA$7,0)),0) -> 0 | BJ61: =_xlfn.IFNA(INDEX(SAM!$B$8:$HA$215,MATCH($BC61,SAM!$A$8:$A$215,0),MATCH(BJ$48,SAM!$B$7:$HA$7,0)),0) -> 0 | BK61: =_xlfn.IFNA(INDEX(SAM!$B$8:$HA$215,MATCH($BC61,SAM!$A$8:$A$215,0),MATCH(BK$48,SAM!$B$7:$HA$7,0)),0) -> 0 | ... BR61: =_xlfn.IFNA(INDEX(SAM!$B$8:$HA$215,MATCH($BC61,SAM!$A$8:$A$215,0),MATCH(BR$48,SAM!$B$7:$HA$7,0)),0) -> 0 | BT61: =AL61 -> cdair | BU61: =SUM(BD61:BR61,AM61:BA61) -> 22.50481 | BW61: cmine | BX61: =100*VLOOKUP(BW61,$BT$49:$BU$94,2,FALSE)/$BU$95 -> 0
A62: =HLOOKUP(B62,$B$6:$BR$9,4,FALSE) -> fats & oils | B62: oils | C62: =IFERROR(100*U62/U$95,"") -> 0.71892293 | D62: =IFERROR(100*V62/V$95,"") -> 0.90265201 | E62: =IFERROR(100*W62/W$95,"") -> 1.1596382 | F62: =IFERROR(100*X62/X$95,"") -> 1.6663037 | G62: =IFERROR(100*Y62/Y$95,"") -> 1.2676055 | H62: =IFERROR(100*Z62/Z$95,"") -> 0.38963217 | I62: =IFERROR(100*AA62/AA$95,"") -> 1.0133195 | J62: =IFERROR(100*AB62/AB$95,"") -> 0.28578594 | ... R62: =IFERROR(100*AJ62/AJ$95,"") -> 0.78482192 | T62: =B62 -> oils | U62: =IFERROR(AM62+BD62,"") -> 1.8866369 | V62: =IFERROR(AN62+BE62,"") -> 3.3744133 | W62: =IFERROR(AO62+BF62,"") -> 6.759549 | X62: =IFERROR(AP62+BG62,"") -> 13.307853 | Y62: =IFERROR(AQ62+BH62,"") -> 18.123597 | Z62: =IFERROR(AR62+BI62,"") -> 0.067330413 | AA62: =IFERROR(AS62+BJ62,"") -> 0.22601209 | AB62: =IFERROR(AT62+BK62,"") -> 0.078526105 | ... AI62: =IFERROR(BA62+BR62,"") -> 5.0705045 | AJ62: =SUM(U62:AI62) -> 51.262618 | AL62: ="c"&T62 -> coils | AM62: =_xlfn.IFNA(INDEX(SAM!$B$8:$HA$215,MATCH($AL62,SAM!$A$8:$A$215,0),MATCH(AM$48,SAM!$B$7:$HA$7,0)),0) -> 0.86159658 | AN62: =_xlfn.IFNA(INDEX(SAM!$B$8:$HA$215,MATCH($AL62,SAM!$A$8:$A$215,0),MATCH(AN$48,SAM!$B$7:$HA$7,0)),0) -> 0.98152285 | AO62: =_xlfn.IFNA(INDEX(SAM!$B$8:$HA$215,MATCH($AL62,SAM!$A$8:$A$215,0),MATCH(AO$48,SAM!$B$7:$HA$7,0)),0) -> 1.8291439 | AP62: =_xlfn.IFNA(INDEX(SAM!$B$8:$HA$215,MATCH($AL62,SAM!$A$8:$A$215,0),MATCH(AP$48,SAM!$B$7:$HA$7,0)),0) -> 3.5050147 | AQ62: =_xlfn.IFNA(INDEX(SAM!$B$8:$HA$215,MATCH($AL62,SAM!$A$8:$A$215,0),MATCH(AQ$48,SAM!$B$7:$HA$7,0)),0) -> 4.8155546 | AR62: =_xlfn.IFNA(INDEX(SAM!$B$8:$HA$215,MATCH($AL62,SAM!$A$8:$A$215,0),MATCH(AR$48,SAM!$B$7:$HA$7,0)),0) -> 0.067330413 | AS62: =_xlfn.IFNA(INDEX(SAM!$B$8:$HA$215,MATCH($AL62,SAM!$A$8:$A$215,0),MATCH(AS$48,SAM!$B$7:$HA$7,0)),0) -> 0.22601209 | AT62: =_xlfn.IFNA(INDEX(SAM!$B$8:$HA$215,MATCH($AL62,SAM!$A$8:$A$215,0),MATCH(AT$48,SAM!$B$7:$HA$7,0)),0) -> 0.078526105 | ... BA62: =_xlfn.IFNA(INDEX(SAM!$B$8:$HA$215,MATCH($AL62,SAM!$A$8:$A$215,0),MATCH(BA$48,SAM!$B$7:$HA$7,0)),0) -> 4.1145221 | BC62: ="a"&T62 -> aoils | BD62: =_xlfn.IFNA(INDEX(SAM!$B$8:$HA$215,MATCH($BC62,SAM!$A$8:$A$215,0),MATCH(BD$48,SAM!$B$7:$HA$7,0)),0) -> 1.0250403 | BE62: =_xlfn.IFNA(INDEX(SAM!$B$8:$HA$215,MATCH($BC62,SAM!$A$8:$A$215,0),MATCH(BE$48,SAM!$B$7:$HA$7,0)),0) -> 2.3928904 | BF62: =_xlfn.IFNA(INDEX(SAM!$B$8:$HA$215,MATCH($BC62,SAM!$A$8:$A$215,0),MATCH(BF$48,SAM!$B$7:$HA$7,0)),0) -> 4.9304051 | BG62: =_xlfn.IFNA(INDEX(SAM!$B$8:$HA$215,MATCH($BC62,SAM!$A$8:$A$215,0),MATCH(BG$48,SAM!$B$7:$HA$7,0)),0) -> 9.8028385 | BH62: =_xlfn.IFNA(INDEX(SAM!$B$8:$HA$215,MATCH($BC62,SAM!$A$8:$A$215,0),MATCH(BH$48,SAM!$B$7:$HA$7,0)),0) -> 13.308043 | BI62: =_xlfn.IFNA(INDEX(SAM!$B$8:$HA$215,MATCH($BC62,SAM!$A$8:$A$215,0),MATCH(BI$48,SAM!$B$7:$HA$7,0)),0) -> 0 | BJ62: =_xlfn.IFNA(INDEX(SAM!$B$8:$HA$215,MATCH($BC62,SAM!$A$8:$A$215,0),MATCH(BJ$48,SAM!$B$7:$HA$7,0)),0) -> 0 | BK62: =_xlfn.IFNA(INDEX(SAM!$B$8:$HA$215,MATCH($BC62,SAM!$A$8:$A$215,0),MATCH(BK$48,SAM!$B$7:$HA$7,0)),0) -> 0 | ... BR62: =_xlfn.IFNA(INDEX(SAM!$B$8:$HA$215,MATCH($BC62,SAM!$A$8:$A$215,0),MATCH(BR$48,SAM!$B$7:$HA$7,0)),0) -> 0.95598236 | BT62: =AL62 -> coils | BU62: =SUM(BD62:BR62,AM62:BA62) -> 51.262618 | BW62: cmino | BX62: =100*VLOOKUP(BW62,$BT$49:$BU$94,2,FALSE)/$BU$95 -> 0
A63: =HLOOKUP(B63,$B$6:$BR$9,4,FALSE) -> fats & oils | B63: foil | C63: =IFERROR(100*U63/U$95,"") -> 1.2985953 | D63: =IFERROR(100*V63/V$95,"") -> 1.7719069 | E63: =IFERROR(100*W63/W$95,"") -> 2.0049544 | F63: =IFERROR(100*X63/X$95,"") -> 2.2637687 | G63: =IFERROR(100*Y63/Y$95,"") -> 2.8803546 | H63: =IFERROR(100*Z63/Z$95,"") -> 1.9933365 | I63: =IFERROR(100*AA63/AA$95,"") -> 1.8686904 | J63: =IFERROR(100*AB63/AB$95,"") -> 2.8445369 | ... R63: =IFERROR(100*AJ63/AJ$95,"") -> 4.4615452 | T63: =B63 -> foil | U63: =IFERROR(AM63+BD63,"") -> 3.4078449 | V63: =IFERROR(AN63+BE63,"") -> 6.6239769 | W63: =IFERROR(AO63+BF63,"") -> 11.68691 | X63: =IFERROR(AP63+BG63,"") -> 18.079478 | Y63: =IFERROR(AQ63+BH63,"") -> 41.181888 | Z63: =IFERROR(AR63+BI63,"") -> 0.34445865 | AA63: =IFERROR(AS63+BJ63,"") -> 0.41679511 | AB63: =IFERROR(AT63+BK63,"") -> 0.78160039 | ... AI63: =IFERROR(BA63+BR63,"") -> 171.98465 | AJ63: =SUM(U63:AI63) -> 291.41705 | AL63: ="c"&T63 -> cfoil | AM63: =_xlfn.IFNA(INDEX(SAM!$B$8:$HA$215,MATCH($AL63,SAM!$A$8:$A$215,0),MATCH(AM$48,SAM!$B$7:$HA$7,0)),0) -> 3.4078449 | AN63: =_xlfn.IFNA(INDEX(SAM!$B$8:$HA$215,MATCH($AL63,SAM!$A$8:$A$215,0),MATCH(AN$48,SAM!$B$7:$HA$7,0)),0) -> 6.6239769 | AO63: =_xlfn.IFNA(INDEX(SAM!$B$8:$HA$215,MATCH($AL63,SAM!$A$8:$A$215,0),MATCH(AO$48,SAM!$B$7:$HA$7,0)),0) -> 11.68691 | AP63: =_xlfn.IFNA(INDEX(SAM!$B$8:$HA$215,MATCH($AL63,SAM!$A$8:$A$215,0),MATCH(AP$48,SAM!$B$7:$HA$7,0)),0) -> 18.079478 | AQ63: =_xlfn.IFNA(INDEX(SAM!$B$8:$HA$215,MATCH($AL63,SAM!$A$8:$A$215,0),MATCH(AQ$48,SAM!$B$7:$HA$7,0)),0) -> 41.181888 | AR63: =_xlfn.IFNA(INDEX(SAM!$B$8:$HA$215,MATCH($AL63,SAM!$A$8:$A$215,0),MATCH(AR$48,SAM!$B$7:$HA$7,0)),0) -> 0.34445865 | AS63: =_xlfn.IFNA(INDEX(SAM!$B$8:$HA$215,MATCH($AL63,SAM!$A$8:$A$215,0),MATCH(AS$48,SAM!$B$7:$HA$7,0)),0) -> 0.41679511 | AT63: =_xlfn.IFNA(INDEX(SAM!$B$8:$HA$215,MATCH($AL63,SAM!$A$8:$A$215,0),MATCH(AT$48,SAM!$B$7:$HA$7,0)),0) -> 0.78160039 | ... BA63: =_xlfn.IFNA(INDEX(SAM!$B$8:$HA$215,MATCH($AL63,SAM!$A$8:$A$215,0),MATCH(BA$48,SAM!$B$7:$HA$7,0)),0) -> 171.98465 | BC63: ="a"&T63 -> afoil | BD63: =_xlfn.IFNA(INDEX(SAM!$B$8:$HA$215,MATCH($BC63,SAM!$A$8:$A$215,0),MATCH(BD$48,SAM!$B$7:$HA$7,0)),0) -> 0 | BE63: =_xlfn.IFNA(INDEX(SAM!$B$8:$HA$215,MATCH($BC63,SAM!$A$8:$A$215,0),MATCH(BE$48,SAM!$B$7:$HA$7,0)),0) -> 0 | BF63: =_xlfn.IFNA(INDEX(SAM!$B$8:$HA$215,MATCH($BC63,SAM!$A$8:$A$215,0),MATCH(BF$48,SAM!$B$7:$HA$7,0)),0) -> 0 | BG63: =_xlfn.IFNA(INDEX(SAM!$B$8:$HA$215,MATCH($BC63,SAM!$A$8:$A$215,0),MATCH(BG$48,SAM!$B$7:$HA$7,0)),0) -> 0 | BH63: =_xlfn.IFNA(INDEX(SAM!$B$8:$HA$215,MATCH($BC63,SAM!$A$8:$A$215,0),MATCH(BH$48,SAM!$B$7:$HA$7,0)),0) -> 0 | BI63: =_xlfn.IFNA(INDEX(SAM!$B$8:$HA$215,MATCH($BC63,SAM!$A$8:$A$215,0),MATCH(BI$48,SAM!$B$7:$HA$7,0)),0) -> 0 | BJ63: =_xlfn.IFNA(INDEX(SAM!$B$8:$HA$215,MATCH($BC63,SAM!$A$8:$A$215,0),MATCH(BJ$48,SAM!$B$7:$HA$7,0)),0) -> 0 | BK63: =_xlfn.IFNA(INDEX(SAM!$B$8:$HA$215,MATCH($BC63,SAM!$A$8:$A$215,0),MATCH(BK$48,SAM!$B$7:$HA$7,0)),0) -> 0 | ... BR63: =_xlfn.IFNA(INDEX(SAM!$B$8:$HA$215,MATCH($BC63,SAM!$A$8:$A$215,0),MATCH(BR$48,SAM!$B$7:$HA$7,0)),0) -> 0 | BT63: =AL63 -> cfoil | BU63: =SUM(BD63:BR63,AM63:BA63) -> 291.41705 | BW63: cgmll | BX63: =100*VLOOKUP(BW63,$BT$49:$BU$94,2,FALSE)/$BU$95 -> 8.7780825
A64: other food | B64: fobe | C64: =IFERROR(100*U64/U$95,"") -> 3.836133 | D64: =IFERROR(100*V64/V$95,"") -> 5.0076941 | E64: =IFERROR(100*W64/W$95,"") -> 5.791494 | F64: =IFERROR(100*X64/X$95,"") -> 7.0764406 | G64: =IFERROR(100*Y64/Y$95,"") -> 7.2534209 | H64: =IFERROR(100*Z64/Z$95,"") -> 4.7669589 | I64: =IFERROR(100*AA64/AA$95,"") -> 4.1139952 | J64: =IFERROR(100*AB64/AB$95,"") -> 5.9117649 | ... R64: =IFERROR(100*AJ64/AJ$95,"") -> 6.622549 | T64: =B64 -> fobe | U64: =IFERROR(AM64+BD64,"") -> 10.06699 | V64: =IFERROR(AN64+BE64,"") -> 18.720425 | W64: =IFERROR(AO64+BF64,"") -> 33.758708 | X64: =IFERROR(AP64+BG64,"") -> 56.515647 | Y64: =IFERROR(AQ64+BH64,"") -> 103.70583 | Z64: =IFERROR(AR64+BI64,"") -> 0.82375465 | AA64: =IFERROR(AS64+BJ64,"") -> 0.91759074 | AB64: =IFERROR(AT64+BK64,"") -> 1.6243902 | ... AI64: =IFERROR(BA64+BR64,"") -> 157.63501 | AJ64: =SUM(U64:AI64) -> 432.56845 | AL64: ="c"&T64 -> cfobe | AM64: =_xlfn.IFNA(INDEX(SAM!$B$8:$HA$215,MATCH($AL64,SAM!$A$8:$A$215,0),MATCH(AM$48,SAM!$B$7:$HA$7,0)),0) -> 8.7908458 | AN64: =_xlfn.IFNA(INDEX(SAM!$B$8:$HA$215,MATCH($AL64,SAM!$A$8:$A$215,0),MATCH(AN$48,SAM!$B$7:$HA$7,0)),0) -> 14.097708 | AO64: =_xlfn.IFNA(INDEX(SAM!$B$8:$HA$215,MATCH($AL64,SAM!$A$8:$A$215,0),MATCH(AO$48,SAM!$B$7:$HA$7,0)),0) -> 24.016985 | AP64: =_xlfn.IFNA(INDEX(SAM!$B$8:$HA$215,MATCH($AL64,SAM!$A$8:$A$215,0),MATCH(AP$48,SAM!$B$7:$HA$7,0)),0) -> 42.321774 | AQ64: =_xlfn.IFNA(INDEX(SAM!$B$8:$HA$215,MATCH($AL64,SAM!$A$8:$A$215,0),MATCH(AQ$48,SAM!$B$7:$HA$7,0)),0) -> 83.645609 | AR64: =_xlfn.IFNA(INDEX(SAM!$B$8:$HA$215,MATCH($AL64,SAM!$A$8:$A$215,0),MATCH(AR$48,SAM!$B$7:$HA$7,0)),0) -> 0.82375465 | AS64: =_xlfn.IFNA(INDEX(SAM!$B$8:$HA$215,MATCH($AL64,SAM!$A$8:$A$215,0),MATCH(AS$48,SAM!$B$7:$HA$7,0)),0) -> 0.91759074 | AT64: =_xlfn.IFNA(INDEX(SAM!$B$8:$HA$215,MATCH($AL64,SAM!$A$8:$A$215,0),MATCH(AT$48,SAM!$B$7:$HA$7,0)),0) -> 1.6243902 | ... BA64: =_xlfn.IFNA(INDEX(SAM!$B$8:$HA$215,MATCH($AL64,SAM!$A$8:$A$215,0),MATCH(BA$48,SAM!$B$7:$HA$7,0)),0) -> 154.6929 | BC64: ="a"&T64 -> afobe | BD64: =_xlfn.IFNA(INDEX(SAM!$B$8:$HA$215,MATCH($BC64,SAM!$A$8:$A$215,0),MATCH(BD$48,SAM!$B$7:$HA$7,0)),0) -> 1.2761445 | BE64: =_xlfn.IFNA(INDEX(SAM!$B$8:$HA$215,MATCH($BC64,SAM!$A$8:$A$215,0),MATCH(BE$48,SAM!$B$7:$HA$7,0)),0) -> 4.6227172 | BF64: =_xlfn.IFNA(INDEX(SAM!$B$8:$HA$215,MATCH($BC64,SAM!$A$8:$A$215,0),MATCH(BF$48,SAM!$B$7:$HA$7,0)),0) -> 9.7417227 | BG64: =_xlfn.IFNA(INDEX(SAM!$B$8:$HA$215,MATCH($BC64,SAM!$A$8:$A$215,0),MATCH(BG$48,SAM!$B$7:$HA$7,0)),0) -> 14.193873 | BH64: =_xlfn.IFNA(INDEX(SAM!$B$8:$HA$215,MATCH($BC64,SAM!$A$8:$A$215,0),MATCH(BH$48,SAM!$B$7:$HA$7,0)),0) -> 20.060219 | BI64: =_xlfn.IFNA(INDEX(SAM!$B$8:$HA$215,MATCH($BC64,SAM!$A$8:$A$215,0),MATCH(BI$48,SAM!$B$7:$HA$7,0)),0) -> 0 | BJ64: =_xlfn.IFNA(INDEX(SAM!$B$8:$HA$215,MATCH($BC64,SAM!$A$8:$A$215,0),MATCH(BJ$48,SAM!$B$7:$HA$7,0)),0) -> 0 | BK64: =_xlfn.IFNA(INDEX(SAM!$B$8:$HA$215,MATCH($BC64,SAM!$A$8:$A$215,0),MATCH(BK$48,SAM!$B$7:$HA$7,0)),0) -> 0 | ... BR64: =_xlfn.IFNA(INDEX(SAM!$B$8:$HA$215,MATCH($BC64,SAM!$A$8:$A$215,0),MATCH(BR$48,SAM!$B$7:$HA$7,0)),0) -> 2.9421102 | BT64: =AL64 -> cfobe | BU64: =SUM(BD64:BR64,AM64:BA64) -> 432.56845 | BW64: cfoil | BX64: =100*VLOOKUP(BW64,$BT$49:$BU$94,2,FALSE)/$BU$95 -> 4.4615452
A65: =HLOOKUP(B65,$B$6:$BR$9,4,FALSE) -> clothing and textile | B65: text | C65: =IFERROR(100*U65/U$95,"") -> 1.8503207 | D65: =IFERROR(100*V65/V$95,"") -> 1.9200177 | E65: =IFERROR(100*W65/W$95,"") -> 2.1531963 | F65: =IFERROR(100*X65/X$95,"") -> 2.2573789 | G65: =IFERROR(100*Y65/Y$95,"") -> 2.305715 | H65: =IFERROR(100*Z65/Z$95,"") -> 1.7677368 | I65: =IFERROR(100*AA65/AA$95,"") -> 1.8204844 | J65: =IFERROR(100*AB65/AB$95,"") -> 1.7634531 | ... R65: =IFERROR(100*AJ65/AJ$95,"") -> 2.1784506 | T65: =B65 -> text | U65: =IFERROR(AM65+BD65,"") -> 4.855713 | V65: =IFERROR(AN65+BE65,"") -> 7.1776645 | W65: =IFERROR(AO65+BF65,"") -> 12.551015 | X65: =IFERROR(AP65+BG65,"") -> 18.028446 | Y65: =IFERROR(AQ65+BH65,"") -> 32.965974 | Z65: =IFERROR(AR65+BI65,"") -> 0.30547387 | AA65: =IFERROR(AS65+BJ65,"") -> 0.40604317 | AB65: =IFERROR(AT65+BK65,"") -> 0.48454834 | ... AI65: =IFERROR(BA65+BR65,"") -> 49.783177 | AJ65: =SUM(U65:AI65) -> 142.29098 | AL65: ="c"&T65 -> ctext | AM65: =_xlfn.IFNA(INDEX(SAM!$B$8:$HA$215,MATCH($AL65,SAM!$A$8:$A$215,0),MATCH(AM$48,SAM!$B$7:$HA$7,0)),0) -> 4.855713 | AN65: =_xlfn.IFNA(INDEX(SAM!$B$8:$HA$215,MATCH($AL65,SAM!$A$8:$A$215,0),MATCH(AN$48,SAM!$B$7:$HA$7,0)),0) -> 7.1776645 | AO65: =_xlfn.IFNA(INDEX(SAM!$B$8:$HA$215,MATCH($AL65,SAM!$A$8:$A$215,0),MATCH(AO$48,SAM!$B$7:$HA$7,0)),0) -> 12.551015 | AP65: =_xlfn.IFNA(INDEX(SAM!$B$8:$HA$215,MATCH($AL65,SAM!$A$8:$A$215,0),MATCH(AP$48,SAM!$B$7:$HA$7,0)),0) -> 18.028446 | AQ65: =_xlfn.IFNA(INDEX(SAM!$B$8:$HA$215,MATCH($AL65,SAM!$A$8:$A$215,0),MATCH(AQ$48,SAM!$B$7:$HA$7,0)),0) -> 32.965974 | AR65: =_xlfn.IFNA(INDEX(SAM!$B$8:$HA$215,MATCH($AL65,SAM!$A$8:$A$215,0),MATCH(AR$48,SAM!$B$7:$HA$7,0)),0) -> 0.30547387 | AS65: =_xlfn.IFNA(INDEX(SAM!$B$8:$HA$215,MATCH($AL65,SAM!$A$8:$A$215,0),MATCH(AS$48,SAM!$B$7:$HA$7,0)),0) -> 0.40604317 | AT65: =_xlfn.IFNA(INDEX(SAM!$B$8:$HA$215,MATCH($AL65,SAM!$A$8:$A$215,0),MATCH(AT$48,SAM!$B$7:$HA$7,0)),0) -> 0.48454834 | ... BA65: =_xlfn.IFNA(INDEX(SAM!$B$8:$HA$215,MATCH($AL65,SAM!$A$8:$A$215,0),MATCH(BA$48,SAM!$B$7:$HA$7,0)),0) -> 49.783177 | BC65: ="a"&T65 -> atext | BD65: =_xlfn.IFNA(INDEX(SAM!$B$8:$HA$215,MATCH($BC65,SAM!$A$8:$A$215,0),MATCH(BD$48,SAM!$B$7:$HA$7,0)),0) -> 0 | BE65: =_xlfn.IFNA(INDEX(SAM!$B$8:$HA$215,MATCH($BC65,SAM!$A$8:$A$215,0),MATCH(BE$48,SAM!$B$7:$HA$7,0)),0) -> 0 | BF65: =_xlfn.IFNA(INDEX(SAM!$B$8:$HA$215,MATCH($BC65,SAM!$A$8:$A$215,0),MATCH(BF$48,SAM!$B$7:$HA$7,0)),0) -> 0 | BG65: =_xlfn.IFNA(INDEX(SAM!$B$8:$HA$215,MATCH($BC65,SAM!$A$8:$A$215,0),MATCH(BG$48,SAM!$B$7:$HA$7,0)),0) -> 0 | BH65: =_xlfn.IFNA(INDEX(SAM!$B$8:$HA$215,MATCH($BC65,SAM!$A$8:$A$215,0),MATCH(BH$48,SAM!$B$7:$HA$7,0)),0) -> 0 | BI65: =_xlfn.IFNA(INDEX(SAM!$B$8:$HA$215,MATCH($BC65,SAM!$A$8:$A$215,0),MATCH(BI$48,SAM!$B$7:$HA$7,0)),0) -> 0 | BJ65: =_xlfn.IFNA(INDEX(SAM!$B$8:$HA$215,MATCH($BC65,SAM!$A$8:$A$215,0),MATCH(BJ$48,SAM!$B$7:$HA$7,0)),0) -> 0 | BK65: =_xlfn.IFNA(INDEX(SAM!$B$8:$HA$215,MATCH($BC65,SAM!$A$8:$A$215,0),MATCH(BK$48,SAM!$B$7:$HA$7,0)),0) -> 0 | ... BR65: =_xlfn.IFNA(INDEX(SAM!$B$8:$HA$215,MATCH($BC65,SAM!$A$8:$A$215,0),MATCH(BR$48,SAM!$B$7:$HA$7,0)),0) -> 0 | BT65: =AL65 -> ctext | BU65: =SUM(BD65:BR65,AM65:BA65) -> 142.29098 | BW65: cfveg | BX65: =100*VLOOKUP(BW65,$BT$49:$BU$94,2,FALSE)/$BU$95 -> 0.098269137
A66: =HLOOKUP(B66,$B$6:$BR$9,4,FALSE) -> utilities | B66: elec | C66: =IFERROR(100*U66/U$95,"") -> 0.045069865 | D66: =IFERROR(100*V66/V$95,"") -> 0.17173722 | E66: =IFERROR(100*W66/W$95,"") -> 0.22055013 | F66: =IFERROR(100*X66/X$95,"") -> 0.36200637 | G66: =IFERROR(100*Y66/Y$95,"") -> 1.0501096 | H66: =IFERROR(100*Z66/Z$95,"") -> 0.31093034 | I66: =IFERROR(100*AA66/AA$95,"") -> 0.46538734 | J66: =IFERROR(100*AB66/AB$95,"") -> 0.51611126 | ... R66: =IFERROR(100*AJ66/AJ$95,"") -> 1.8213759 | T66: =B66 -> elec | U66: =IFERROR(AM66+BD66,"") -> 0.11827481 | V66: =IFERROR(AN66+BE66,"") -> 0.64201083 | W66: =IFERROR(AO66+BF66,"") -> 1.2855901 | X66: =IFERROR(AP66+BG66,"") -> 2.8911462 | Y66: =IFERROR(AQ66+BH66,"") -> 15.013949 | Z66: =IFERROR(AR66+BI66,"") -> 0.053730338 | AA66: =IFERROR(AS66+BJ66,"") -> 0.10380059 | AB66: =IFERROR(AT66+BK66,"") -> 0.14181316 | ... AI66: =IFERROR(BA66+BR66,"") -> 84.496598 | AJ66: =SUM(U66:AI66) -> 118.96775 | AL66: ="c"&T66 -> celec | AM66: =_xlfn.IFNA(INDEX(SAM!$B$8:$HA$215,MATCH($AL66,SAM!$A$8:$A$215,0),MATCH(AM$48,SAM!$B$7:$HA$7,0)),0) -> 0.11827481 | AN66: =_xlfn.IFNA(INDEX(SAM!$B$8:$HA$215,MATCH($AL66,SAM!$A$8:$A$215,0),MATCH(AN$48,SAM!$B$7:$HA$7,0)),0) -> 0.64201083 | AO66: =_xlfn.IFNA(INDEX(SAM!$B$8:$HA$215,MATCH($AL66,SAM!$A$8:$A$215,0),MATCH(AO$48,SAM!$B$7:$HA$7,0)),0) -> 1.2855901 | AP66: =_xlfn.IFNA(INDEX(SAM!$B$8:$HA$215,MATCH($AL66,SAM!$A$8:$A$215,0),MATCH(AP$48,SAM!$B$7:$HA$7,0)),0) -> 2.8911462 | AQ66: =_xlfn.IFNA(INDEX(SAM!$B$8:$HA$215,MATCH($AL66,SAM!$A$8:$A$215,0),MATCH(AQ$48,SAM!$B$7:$HA$7,0)),0) -> 15.013949 | AR66: =_xlfn.IFNA(INDEX(SAM!$B$8:$HA$215,MATCH($AL66,SAM!$A$8:$A$215,0),MATCH(AR$48,SAM!$B$7:$HA$7,0)),0) -> 0.053730338 | AS66: =_xlfn.IFNA(INDEX(SAM!$B$8:$HA$215,MATCH($AL66,SAM!$A$8:$A$215,0),MATCH(AS$48,SAM!$B$7:$HA$7,0)),0) -> 0.10380059 | AT66: =_xlfn.IFNA(INDEX(SAM!$B$8:$HA$215,MATCH($AL66,SAM!$A$8:$A$215,0),MATCH(AT$48,SAM!$B$7:$HA$7,0)),0) -> 0.14181316 | ... BA66: =_xlfn.IFNA(INDEX(SAM!$B$8:$HA$215,MATCH($AL66,SAM!$A$8:$A$215,0),MATCH(BA$48,SAM!$B$7:$HA$7,0)),0) -> 84.496598 | BC66: ="a"&T66 -> aelec | BD66: =_xlfn.IFNA(INDEX(SAM!$B$8:$HA$215,MATCH($BC66,SAM!$A$8:$A$215,0),MATCH(BD$48,SAM!$B$7:$HA$7,0)),0) -> 0 | BE66: =_xlfn.IFNA(INDEX(SAM!$B$8:$HA$215,MATCH($BC66,SAM!$A$8:$A$215,0),MATCH(BE$48,SAM!$B$7:$HA$7,0)),0) -> 0 | BF66: =_xlfn.IFNA(INDEX(SAM!$B$8:$HA$215,MATCH($BC66,SAM!$A$8:$A$215,0),MATCH(BF$48,SAM!$B$7:$HA$7,0)),0) -> 0 | BG66: =_xlfn.IFNA(INDEX(SAM!$B$8:$HA$215,MATCH($BC66,SAM!$A$8:$A$215,0),MATCH(BG$48,SAM!$B$7:$HA$7,0)),0) -> 0 | BH66: =_xlfn.IFNA(INDEX(SAM!$B$8:$HA$215,MATCH($BC66,SAM!$A$8:$A$215,0),MATCH(BH$48,SAM!$B$7:$HA$7,0)),0) -> 0 | BI66: =_xlfn.IFNA(INDEX(SAM!$B$8:$HA$215,MATCH($BC66,SAM!$A$8:$A$215,0),MATCH(BI$48,SAM!$B$7:$HA$7,0)),0) -> 0 | BJ66: =_xlfn.IFNA(INDEX(SAM!$B$8:$HA$215,MATCH($BC66,SAM!$A$8:$A$215,0),MATCH(BJ$48,SAM!$B$7:$HA$7,0)),0) -> 0 | BK66: =_xlfn.IFNA(INDEX(SAM!$B$8:$HA$215,MATCH($BC66,SAM!$A$8:$A$215,0),MATCH(BK$48,SAM!$B$7:$HA$7,0)),0) -> 0 | ... BR66: =_xlfn.IFNA(INDEX(SAM!$B$8:$HA$215,MATCH($BC66,SAM!$A$8:$A$215,0),MATCH(BR$48,SAM!$B$7:$HA$7,0)),0) -> 0 | BT66: =AL66 -> celec | BU66: =SUM(BD66:BR66,AM66:BA66) -> 118.96775 | BW66: cmeat | BX66: =100*VLOOKUP(BW66,$BT$49:$BU$94,2,FALSE)/$BU$95 -> 5.3593587
A67: =HLOOKUP(B67,$B$6:$BR$9,4,FALSE) -> utilities | B67: watr | C67: =IFERROR(100*U67/U$95,"") -> 0.30501974 | D67: =IFERROR(100*V67/V$95,"") -> 0.32226178 | E67: =IFERROR(100*W67/W$95,"") -> 0.28732971 | F67: =IFERROR(100*X67/X$95,"") -> 0.27425425 | G67: =IFERROR(100*Y67/Y$95,"") -> 0.37951394 | H67: =IFERROR(100*Z67/Z$95,"") -> 0.31133119 | I67: =IFERROR(100*AA67/AA$95,"") -> 0.72349238 | J67: =IFERROR(100*AB67/AB$95,"") -> 0.67285828 | ... R67: =IFERROR(100*AJ67/AJ$95,"") -> 0.95305759 | T67: =B67 -> watr | U67: =IFERROR(AM67+BD67,"") -> 0.8004495 | V67: =IFERROR(AN67+BE67,"") -> 1.2047217 | W67: =IFERROR(AO67+BF67,"") -> 1.6748493 | X67: =IFERROR(AP67+BG67,"") -> 2.1903182 | Y67: =IFERROR(AQ67+BH67,"") -> 5.4261029 | Z67: =IFERROR(AR67+BI67,"") -> 0.053799607 | AA67: =IFERROR(AS67+BJ67,"") -> 0.16136867 | AB67: =IFERROR(AT67+BK67,"") -> 0.18488292 | ... AI67: =IFERROR(BA67+BR67,"") -> 37.455172 | AJ67: =SUM(U67:AI67) -> 62.251354 | AL67: ="c"&T67 -> cwatr | AM67: =_xlfn.IFNA(INDEX(SAM!$B$8:$HA$215,MATCH($AL67,SAM!$A$8:$A$215,0),MATCH(AM$48,SAM!$B$7:$HA$7,0)),0) -> 0.8004495 | AN67: =_xlfn.IFNA(INDEX(SAM!$B$8:$HA$215,MATCH($AL67,SAM!$A$8:$A$215,0),MATCH(AN$48,SAM!$B$7:$HA$7,0)),0) -> 1.2047217 | AO67: =_xlfn.IFNA(INDEX(SAM!$B$8:$HA$215,MATCH($AL67,SAM!$A$8:$A$215,0),MATCH(AO$48,SAM!$B$7:$HA$7,0)),0) -> 1.6748493 | AP67: =_xlfn.IFNA(INDEX(SAM!$B$8:$HA$215,MATCH($AL67,SAM!$A$8:$A$215,0),MATCH(AP$48,SAM!$B$7:$HA$7,0)),0) -> 2.1903182 | AQ67: =_xlfn.IFNA(INDEX(SAM!$B$8:$HA$215,MATCH($AL67,SAM!$A$8:$A$215,0),MATCH(AQ$48,SAM!$B$7:$HA$7,0)),0) -> 5.4261029 | AR67: =_xlfn.IFNA(INDEX(SAM!$B$8:$HA$215,MATCH($AL67,SAM!$A$8:$A$215,0),MATCH(AR$48,SAM!$B$7:$HA$7,0)),0) -> 0.053799607 | AS67: =_xlfn.IFNA(INDEX(SAM!$B$8:$HA$215,MATCH($AL67,SAM!$A$8:$A$215,0),MATCH(AS$48,SAM!$B$7:$HA$7,0)),0) -> 0.16136867 | AT67: =_xlfn.IFNA(INDEX(SAM!$B$8:$HA$215,MATCH($AL67,SAM!$A$8:$A$215,0),MATCH(AT$48,SAM!$B$7:$HA$7,0)),0) -> 0.18488292 | ... BA67: =_xlfn.IFNA(INDEX(SAM!$B$8:$HA$215,MATCH($AL67,SAM!$A$8:$A$215,0),MATCH(BA$48,SAM!$B$7:$HA$7,0)),0) -> 37.455172 | BC67: ="a"&T67 -> awatr | BD67: =_xlfn.IFNA(INDEX(SAM!$B$8:$HA$215,MATCH($BC67,SAM!$A$8:$A$215,0),MATCH(BD$48,SAM!$B$7:$HA$7,0)),0) -> 0 | BE67: =_xlfn.IFNA(INDEX(SAM!$B$8:$HA$215,MATCH($BC67,SAM!$A$8:$A$215,0),MATCH(BE$48,SAM!$B$7:$HA$7,0)),0) -> 0 | BF67: =_xlfn.IFNA(INDEX(SAM!$B$8:$HA$215,MATCH($BC67,SAM!$A$8:$A$215,0),MATCH(BF$48,SAM!$B$7:$HA$7,0)),0) -> 0 | BG67: =_xlfn.IFNA(INDEX(SAM!$B$8:$HA$215,MATCH($BC67,SAM!$A$8:$A$215,0),MATCH(BG$48,SAM!$B$7:$HA$7,0)),0) -> 0 | BH67: =_xlfn.IFNA(INDEX(SAM!$B$8:$HA$215,MATCH($BC67,SAM!$A$8:$A$215,0),MATCH(BH$48,SAM!$B$7:$HA$7,0)),0) -> 0 | BI67: =_xlfn.IFNA(INDEX(SAM!$B$8:$HA$215,MATCH($BC67,SAM!$A$8:$A$215,0),MATCH(BI$48,SAM!$B$7:$HA$7,0)),0) -> 0 | BJ67: =_xlfn.IFNA(INDEX(SAM!$B$8:$HA$215,MATCH($BC67,SAM!$A$8:$A$215,0),MATCH(BJ$48,SAM!$B$7:$HA$7,0)),0) -> 0 | BK67: =_xlfn.IFNA(INDEX(SAM!$B$8:$HA$215,MATCH($BC67,SAM!$A$8:$A$215,0),MATCH(BK$48,SAM!$B$7:$HA$7,0)),0) -> 0 | ... BR67: =_xlfn.IFNA(INDEX(SAM!$B$8:$HA$215,MATCH($BC67,SAM!$A$8:$A$215,0),MATCH(BR$48,SAM!$B$7:$HA$7,0)),0) -> 0 | BT67: =AL67 -> cwatr | BU67: =SUM(BD67:BR67,AM67:BA67) -> 62.251354 | BW67: cfsea | BX67: =100*VLOOKUP(BW67,$BT$49:$BU$94,2,FALSE)/$BU$95 -> 3.1714307
A68: =HLOOKUP(B68,$B$6:$BR$9,4,FALSE) -> housing | B68: real | C68: =IFERROR(100*U68/U$95,"") -> 10.393127 | D68: =IFERROR(100*V68/V$95,"") -> 8.881227 | E68: =IFERROR(100*W68/W$95,"") -> 7.9823631 | F68: =IFERROR(100*X68/X$95,"") -> 6.9727339 | G68: =IFERROR(100*Y68/Y$95,"") -> 6.3014515 | H68: =IFERROR(100*Z68/Z$95,"") -> 11.011433 | I68: =IFERROR(100*AA68/AA$95,"") -> 9.4200876 | J68: =IFERROR(100*AB68/AB$95,"") -> 9.1892564 | ... R68: =IFERROR(100*AJ68/AJ$95,"") -> 8.8806238 | T68: =B68 -> real | U68: =IFERROR(AM68+BD68,"") -> 27.274212 | V68: =IFERROR(AN68+BE68,"") -> 33.200979 | W68: =IFERROR(AO68+BF68,"") -> 46.529317 | X68: =IFERROR(AP68+BG68,"") -> 55.687398 | Y68: =IFERROR(AQ68+BH68,"") -> 90.09504 | Z68: =IFERROR(AR68+BI68,"") -> 1.9028314 | AA68: =IFERROR(AS68+BJ68,"") -> 2.1010684 | AB68: =IFERROR(AT68+BK68,"") -> 2.5249546 | ... AI68: =IFERROR(BA68+BR68,"") -> 232.56001 | AJ68: =SUM(U68:AI68) -> 580.06028 | AL68: ="c"&T68 -> creal | AM68: =_xlfn.IFNA(INDEX(SAM!$B$8:$HA$215,MATCH($AL68,SAM!$A$8:$A$215,0),MATCH(AM$48,SAM!$B$7:$HA$7,0)),0) -> 27.274212 | AN68: =_xlfn.IFNA(INDEX(SAM!$B$8:$HA$215,MATCH($AL68,SAM!$A$8:$A$215,0),MATCH(AN$48,SAM!$B$7:$HA$7,0)),0) -> 33.200979 | AO68: =_xlfn.IFNA(INDEX(SAM!$B$8:$HA$215,MATCH($AL68,SAM!$A$8:$A$215,0),MATCH(AO$48,SAM!$B$7:$HA$7,0)),0) -> 46.529317 | AP68: =_xlfn.IFNA(INDEX(SAM!$B$8:$HA$215,MATCH($AL68,SAM!$A$8:$A$215,0),MATCH(AP$48,SAM!$B$7:$HA$7,0)),0) -> 55.687398 | AQ68: =_xlfn.IFNA(INDEX(SAM!$B$8:$HA$215,MATCH($AL68,SAM!$A$8:$A$215,0),MATCH(AQ$48,SAM!$B$7:$HA$7,0)),0) -> 90.09504 | AR68: =_xlfn.IFNA(INDEX(SAM!$B$8:$HA$215,MATCH($AL68,SAM!$A$8:$A$215,0),MATCH(AR$48,SAM!$B$7:$HA$7,0)),0) -> 1.9028314 | AS68: =_xlfn.IFNA(INDEX(SAM!$B$8:$HA$215,MATCH($AL68,SAM!$A$8:$A$215,0),MATCH(AS$48,SAM!$B$7:$HA$7,0)),0) -> 2.1010684 | AT68: =_xlfn.IFNA(INDEX(SAM!$B$8:$HA$215,MATCH($AL68,SAM!$A$8:$A$215,0),MATCH(AT$48,SAM!$B$7:$HA$7,0)),0) -> 2.5249546 | ... BA68: =_xlfn.IFNA(INDEX(SAM!$B$8:$HA$215,MATCH($AL68,SAM!$A$8:$A$215,0),MATCH(BA$48,SAM!$B$7:$HA$7,0)),0) -> 232.56001 | BC68: ="a"&T68 -> areal | BD68: =_xlfn.IFNA(INDEX(SAM!$B$8:$HA$215,MATCH($BC68,SAM!$A$8:$A$215,0),MATCH(BD$48,SAM!$B$7:$HA$7,0)),0) -> 0 | BE68: =_xlfn.IFNA(INDEX(SAM!$B$8:$HA$215,MATCH($BC68,SAM!$A$8:$A$215,0),MATCH(BE$48,SAM!$B$7:$HA$7,0)),0) -> 0 | BF68: =_xlfn.IFNA(INDEX(SAM!$B$8:$HA$215,MATCH($BC68,SAM!$A$8:$A$215,0),MATCH(BF$48,SAM!$B$7:$HA$7,0)),0) -> 0 | BG68: =_xlfn.IFNA(INDEX(SAM!$B$8:$HA$215,MATCH($BC68,SAM!$A$8:$A$215,0),MATCH(BG$48,SAM!$B$7:$HA$7,0)),0) -> 0 | BH68: =_xlfn.IFNA(INDEX(SAM!$B$8:$HA$215,MATCH($BC68,SAM!$A$8:$A$215,0),MATCH(BH$48,SAM!$B$7:$HA$7,0)),0) -> 0 | BI68: =_xlfn.IFNA(INDEX(SAM!$B$8:$HA$215,MATCH($BC68,SAM!$A$8:$A$215,0),MATCH(BI$48,SAM!$B$7:$HA$7,0)),0) -> 0 | BJ68: =_xlfn.IFNA(INDEX(SAM!$B$8:$HA$215,MATCH($BC68,SAM!$A$8:$A$215,0),MATCH(BJ$48,SAM!$B$7:$HA$7,0)),0) -> 0 | BK68: =_xlfn.IFNA(INDEX(SAM!$B$8:$HA$215,MATCH($BC68,SAM!$A$8:$A$215,0),MATCH(BK$48,SAM!$B$7:$HA$7,0)),0) -> 0 | ... BR68: =_xlfn.IFNA(INDEX(SAM!$B$8:$HA$215,MATCH($BC68,SAM!$A$8:$A$215,0),MATCH(BR$48,SAM!$B$7:$HA$7,0)),0) -> 0 | BT68: =AL68 -> creal | BU68: =SUM(BD68:BR68,AM68:BA68) -> 580.06028 | BW68: cdair | BX68: =100*VLOOKUP(BW68,$BT$49:$BU$94,2,FALSE)/$BU$95 -> 0.3445448
A69: =HLOOKUP(B69,$B$6:$BR$9,4,FALSE) -> education, health and public | B69: educ | C69: =IFERROR(100*U69/U$95,"") -> 0.8990324 | D69: =IFERROR(100*V69/V$95,"") -> 0.87701659 | E69: =IFERROR(100*W69/W$95,"") -> 0.92140073 | F69: =IFERROR(100*X69/X$95,"") -> 0.94665994 | G69: =IFERROR(100*Y69/Y$95,"") -> 1.7652165 | H69: =IFERROR(100*Z69/Z$95,"") -> 0.84461863 | I69: =IFERROR(100*AA69/AA$95,"") -> 0.62213825 | J69: =IFERROR(100*AB69/AB$95,"") -> 1.3564136 | ... R69: =IFERROR(100*AJ69/AJ$95,"") -> 1.923991 | T69: =B69 -> educ | U69: =IFERROR(AM69+BD69,"") -> 2.35929 | V69: =IFERROR(AN69+BE69,"") -> 3.2785796 | W69: =IFERROR(AO69+BF69,"") -> 5.370859 | X69: =IFERROR(AP69+BG69,"") -> 7.5604533 | Y69: =IFERROR(AQ69+BH69,"") -> 25.238194 | Z69: =IFERROR(AR69+BI69,"") -> 0.14595438 | AA69: =IFERROR(AS69+BJ69,"") -> 0.13876251 | AB69: =IFERROR(AT69+BK69,"") -> 0.37270509 | ... AI69: =IFERROR(BA69+BR69,"") -> 70.719728 | AJ69: =SUM(U69:AI69) -> 125.67031 | AL69: ="c"&T69 -> ceduc | AM69: =_xlfn.IFNA(INDEX(SAM!$B$8:$HA$215,MATCH($AL69,SAM!$A$8:$A$215,0),MATCH(AM$48,SAM!$B$7:$HA$7,0)),0) -> 2.35929 | AN69: =_xlfn.IFNA(INDEX(SAM!$B$8:$HA$215,MATCH($AL69,SAM!$A$8:$A$215,0),MATCH(AN$48,SAM!$B$7:$HA$7,0)),0) -> 3.2785796 | AO69: =_xlfn.IFNA(INDEX(SAM!$B$8:$HA$215,MATCH($AL69,SAM!$A$8:$A$215,0),MATCH(AO$48,SAM!$B$7:$HA$7,0)),0) -> 5.370859 | AP69: =_xlfn.IFNA(INDEX(SAM!$B$8:$HA$215,MATCH($AL69,SAM!$A$8:$A$215,0),MATCH(AP$48,SAM!$B$7:$HA$7,0)),0) -> 7.5604533 | AQ69: =_xlfn.IFNA(INDEX(SAM!$B$8:$HA$215,MATCH($AL69,SAM!$A$8:$A$215,0),MATCH(AQ$48,SAM!$B$7:$HA$7,0)),0) -> 25.238194 | AR69: =_xlfn.IFNA(INDEX(SAM!$B$8:$HA$215,MATCH($AL69,SAM!$A$8:$A$215,0),MATCH(AR$48,SAM!$B$7:$HA$7,0)),0) -> 0.14595438 | AS69: =_xlfn.IFNA(INDEX(SAM!$B$8:$HA$215,MATCH($AL69,SAM!$A$8:$A$215,0),MATCH(AS$48,SAM!$B$7:$HA$7,0)),0) -> 0.13876251 | AT69: =_xlfn.IFNA(INDEX(SAM!$B$8:$HA$215,MATCH($AL69,SAM!$A$8:$A$215,0),MATCH(AT$48,SAM!$B$7:$HA$7,0)),0) -> 0.37270509 | ... BA69: =_xlfn.IFNA(INDEX(SAM!$B$8:$HA$215,MATCH($AL69,SAM!$A$8:$A$215,0),MATCH(BA$48,SAM!$B$7:$HA$7,0)),0) -> 70.719728 | BC69: ="a"&T69 -> aeduc | BD69: =_xlfn.IFNA(INDEX(SAM!$B$8:$HA$215,MATCH($BC69,SAM!$A$8:$A$215,0),MATCH(BD$48,SAM!$B$7:$HA$7,0)),0) -> 0 | BE69: =_xlfn.IFNA(INDEX(SAM!$B$8:$HA$215,MATCH($BC69,SAM!$A$8:$A$215,0),MATCH(BE$48,SAM!$B$7:$HA$7,0)),0) -> 0 | BF69: =_xlfn.IFNA(INDEX(SAM!$B$8:$HA$215,MATCH($BC69,SAM!$A$8:$A$215,0),MATCH(BF$48,SAM!$B$7:$HA$7,0)),0) -> 0 | BG69: =_xlfn.IFNA(INDEX(SAM!$B$8:$HA$215,MATCH($BC69,SAM!$A$8:$A$215,0),MATCH(BG$48,SAM!$B$7:$HA$7,0)),0) -> 0 | BH69: =_xlfn.IFNA(INDEX(SAM!$B$8:$HA$215,MATCH($BC69,SAM!$A$8:$A$215,0),MATCH(BH$48,SAM!$B$7:$HA$7,0)),0) -> 0 | BI69: =_xlfn.IFNA(INDEX(SAM!$B$8:$HA$215,MATCH($BC69,SAM!$A$8:$A$215,0),MATCH(BI$48,SAM!$B$7:$HA$7,0)),0) -> 0 | BJ69: =_xlfn.IFNA(INDEX(SAM!$B$8:$HA$215,MATCH($BC69,SAM!$A$8:$A$215,0),MATCH(BJ$48,SAM!$B$7:$HA$7,0)),0) -> 0 | BK69: =_xlfn.IFNA(INDEX(SAM!$B$8:$HA$215,MATCH($BC69,SAM!$A$8:$A$215,0),MATCH(BK$48,SAM!$B$7:$HA$7,0)),0) -> 0 | ... BR69: =_xlfn.IFNA(INDEX(SAM!$B$8:$HA$215,MATCH($BC69,SAM!$A$8:$A$215,0),MATCH(BR$48,SAM!$B$7:$HA$7,0)),0) -> 0 | BT69: =AL69 -> ceduc | BU69: =SUM(BD69:BR69,AM69:BA69) -> 125.67031 | BW69: cfobe | BX69: =100*VLOOKUP(BW69,$BT$49:$BU$94,2,FALSE)/$BU$95 -> 6.622549
A70: =HLOOKUP(B70,$B$6:$BR$9,4,FALSE) -> education, health and public | B70: heal | C70: =IFERROR(100*U70/U$95,"") -> 11.204126 | D70: =IFERROR(100*V70/V$95,"") -> 11.663281 | E70: =IFERROR(100*W70/W$95,"") -> 12.529915 | F70: =IFERROR(100*X70/X$95,"") -> 11.836388 | G70: =IFERROR(100*Y70/Y$95,"") -> 11.869741 | H70: =IFERROR(100*Z70/Z$95,"") -> 19.522844 | I70: =IFERROR(100*AA70/AA$95,"") -> 21.841662 | J70: =IFERROR(100*AB70/AB$95,"") -> 13.158534 | ... R70: =IFERROR(100*AJ70/AJ$95,"") -> 11.436144 | T70: =B70 -> heal | U70: =IFERROR(AM70+BD70,"") -> 29.40248 | V70: =IFERROR(AN70+BE70,"") -> 43.601221 | W70: =IFERROR(AO70+BF70,"") -> 73.037068 | X70: =IFERROR(AP70+BG70,"") -> 94.530732 | Y70: =IFERROR(AQ70+BH70,"") -> 169.70769 | Z70: =IFERROR(AR70+BI70,"") -> 3.3736464 | AA70: =IFERROR(AS70+BJ70,"") -> 4.8715921 | AB70: =IFERROR(AT70+BK70,"") -> 3.6156026 | ... AI70: =IFERROR(BA70+BR70,"") -> 271.55239 | AJ70: =SUM(U70:AI70) -> 746.98055 | AL70: ="c"&T70 -> cheal | AM70: =_xlfn.IFNA(INDEX(SAM!$B$8:$HA$215,MATCH($AL70,SAM!$A$8:$A$215,0),MATCH(AM$48,SAM!$B$7:$HA$7,0)),0) -> 29.40248 | AN70: =_xlfn.IFNA(INDEX(SAM!$B$8:$HA$215,MATCH($AL70,SAM!$A$8:$A$215,0),MATCH(AN$48,SAM!$B$7:$HA$7,0)),0) -> 43.601221 | AO70: =_xlfn.IFNA(INDEX(SAM!$B$8:$HA$215,MATCH($AL70,SAM!$A$8:$A$215,0),MATCH(AO$48,SAM!$B$7:$HA$7,0)),0) -> 73.037068 | AP70: =_xlfn.IFNA(INDEX(SAM!$B$8:$HA$215,MATCH($AL70,SAM!$A$8:$A$215,0),MATCH(AP$48,SAM!$B$7:$HA$7,0)),0) -> 94.530732 | AQ70: =_xlfn.IFNA(INDEX(SAM!$B$8:$HA$215,MATCH($AL70,SAM!$A$8:$A$215,0),MATCH(AQ$48,SAM!$B$7:$HA$7,0)),0) -> 169.70769 | AR70: =_xlfn.IFNA(INDEX(SAM!$B$8:$HA$215,MATCH($AL70,SAM!$A$8:$A$215,0),MATCH(AR$48,SAM!$B$7:$HA$7,0)),0) -> 3.3736464 | AS70: =_xlfn.IFNA(INDEX(SAM!$B$8:$HA$215,MATCH($AL70,SAM!$A$8:$A$215,0),MATCH(AS$48,SAM!$B$7:$HA$7,0)),0) -> 4.8715921 | AT70: =_xlfn.IFNA(INDEX(SAM!$B$8:$HA$215,MATCH($AL70,SAM!$A$8:$A$215,0),MATCH(AT$48,SAM!$B$7:$HA$7,0)),0) -> 3.6156026 | ... BA70: =_xlfn.IFNA(INDEX(SAM!$B$8:$HA$215,MATCH($AL70,SAM!$A$8:$A$215,0),MATCH(BA$48,SAM!$B$7:$HA$7,0)),0) -> 271.55239 | BC70: ="a"&T70 -> aheal | BD70: =_xlfn.IFNA(INDEX(SAM!$B$8:$HA$215,MATCH($BC70,SAM!$A$8:$A$215,0),MATCH(BD$48,SAM!$B$7:$HA$7,0)),0) -> 0 | BE70: =_xlfn.IFNA(INDEX(SAM!$B$8:$HA$215,MATCH($BC70,SAM!$A$8:$A$215,0),MATCH(BE$48,SAM!$B$7:$HA$7,0)),0) -> 0 | BF70: =_xlfn.IFNA(INDEX(SAM!$B$8:$HA$215,MATCH($BC70,SAM!$A$8:$A$215,0),MATCH(BF$48,SAM!$B$7:$HA$7,0)),0) -> 0 | BG70: =_xlfn.IFNA(INDEX(SAM!$B$8:$HA$215,MATCH($BC70,SAM!$A$8:$A$215,0),MATCH(BG$48,SAM!$B$7:$HA$7,0)),0) -> 0 | BH70: =_xlfn.IFNA(INDEX(SAM!$B$8:$HA$215,MATCH($BC70,SAM!$A$8:$A$215,0),MATCH(BH$48,SAM!$B$7:$HA$7,0)),0) -> 0 | BI70: =_xlfn.IFNA(INDEX(SAM!$B$8:$HA$215,MATCH($BC70,SAM!$A$8:$A$215,0),MATCH(BI$48,SAM!$B$7:$HA$7,0)),0) -> 0 | BJ70: =_xlfn.IFNA(INDEX(SAM!$B$8:$HA$215,MATCH($BC70,SAM!$A$8:$A$215,0),MATCH(BJ$48,SAM!$B$7:$HA$7,0)),0) -> 0 | BK70: =_xlfn.IFNA(INDEX(SAM!$B$8:$HA$215,MATCH($BC70,SAM!$A$8:$A$215,0),MATCH(BK$48,SAM!$B$7:$HA$7,0)),0) -> 0 | ... BR70: =_xlfn.IFNA(INDEX(SAM!$B$8:$HA$215,MATCH($BC70,SAM!$A$8:$A$215,0),MATCH(BR$48,SAM!$B$7:$HA$7,0)),0) -> 0 | BT70: =AL70 -> cheal | BU70: =SUM(BD70:BR70,AM70:BA70) -> 746.98055 | BW70: coapr | BX70: =100*VLOOKUP(BW70,$BT$49:$BU$94,2,FALSE)/$BU$95 -> 1.0125267
A71: =HLOOKUP(B71,$B$6:$BR$9,4,FALSE) -> education, health and public | B71: padm | C71: =IFERROR(100*U71/U$95,"") -> 0 | D71: =IFERROR(100*V71/V$95,"") -> 0 | E71: =IFERROR(100*W71/W$95,"") -> 0 | F71: =IFERROR(100*X71/X$95,"") -> 0 | G71: =IFERROR(100*Y71/Y$95,"") -> 0 | H71: =IFERROR(100*Z71/Z$95,"") -> 0 | I71: =IFERROR(100*AA71/AA$95,"") -> 0 | J71: =IFERROR(100*AB71/AB$95,"") -> 0 | ... R71: =IFERROR(100*AJ71/AJ$95,"") -> 0 | T71: =B71 -> padm | U71: =IFERROR(AM71+BD71,"") -> 0 | V71: =IFERROR(AN71+BE71,"") -> 0 | W71: =IFERROR(AO71+BF71,"") -> 0 | X71: =IFERROR(AP71+BG71,"") -> 0 | Y71: =IFERROR(AQ71+BH71,"") -> 0 | Z71: =IFERROR(AR71+BI71,"") -> 0 | AA71: =IFERROR(AS71+BJ71,"") -> 0 | AB71: =IFERROR(AT71+BK71,"") -> 0 | ... AI71: =IFERROR(BA71+BR71,"") -> 0 | AJ71: =SUM(U71:AI71) -> 0 | AL71: ="c"&T71 -> cpadm | AM71: =_xlfn.IFNA(INDEX(SAM!$B$8:$HA$215,MATCH($AL71,SAM!$A$8:$A$215,0),MATCH(AM$48,SAM!$B$7:$HA$7,0)),0) -> 0 | AN71: =_xlfn.IFNA(INDEX(SAM!$B$8:$HA$215,MATCH($AL71,SAM!$A$8:$A$215,0),MATCH(AN$48,SAM!$B$7:$HA$7,0)),0) -> 0 | AO71: =_xlfn.IFNA(INDEX(SAM!$B$8:$HA$215,MATCH($AL71,SAM!$A$8:$A$215,0),MATCH(AO$48,SAM!$B$7:$HA$7,0)),0) -> 0 | AP71: =_xlfn.IFNA(INDEX(SAM!$B$8:$HA$215,MATCH($AL71,SAM!$A$8:$A$215,0),MATCH(AP$48,SAM!$B$7:$HA$7,0)),0) -> 0 | AQ71: =_xlfn.IFNA(INDEX(SAM!$B$8:$HA$215,MATCH($AL71,SAM!$A$8:$A$215,0),MATCH(AQ$48,SAM!$B$7:$HA$7,0)),0) -> 0 | AR71: =_xlfn.IFNA(INDEX(SAM!$B$8:$HA$215,MATCH($AL71,SAM!$A$8:$A$215,0),MATCH(AR$48,SAM!$B$7:$HA$7,0)),0) -> 0 | AS71: =_xlfn.IFNA(INDEX(SAM!$B$8:$HA$215,MATCH($AL71,SAM!$A$8:$A$215,0),MATCH(AS$48,SAM!$B$7:$HA$7,0)),0) -> 0 | AT71: =_xlfn.IFNA(INDEX(SAM!$B$8:$HA$215,MATCH($AL71,SAM!$A$8:$A$215,0),MATCH(AT$48,SAM!$B$7:$HA$7,0)),0) -> 0 | ... BA71: =_xlfn.IFNA(INDEX(SAM!$B$8:$HA$215,MATCH($AL71,SAM!$A$8:$A$215,0),MATCH(BA$48,SAM!$B$7:$HA$7,0)),0) -> 0 | BC71: ="a"&T71 -> apadm | BD71: =_xlfn.IFNA(INDEX(SAM!$B$8:$HA$215,MATCH($BC71,SAM!$A$8:$A$215,0),MATCH(BD$48,SAM!$B$7:$HA$7,0)),0) -> 0 | BE71: =_xlfn.IFNA(INDEX(SAM!$B$8:$HA$215,MATCH($BC71,SAM!$A$8:$A$215,0),MATCH(BE$48,SAM!$B$7:$HA$7,0)),0) -> 0 | BF71: =_xlfn.IFNA(INDEX(SAM!$B$8:$HA$215,MATCH($BC71,SAM!$A$8:$A$215,0),MATCH(BF$48,SAM!$B$7:$HA$7,0)),0) -> 0 | BG71: =_xlfn.IFNA(INDEX(SAM!$B$8:$HA$215,MATCH($BC71,SAM!$A$8:$A$215,0),MATCH(BG$48,SAM!$B$7:$HA$7,0)),0) -> 0 | BH71: =_xlfn.IFNA(INDEX(SAM!$B$8:$HA$215,MATCH($BC71,SAM!$A$8:$A$215,0),MATCH(BH$48,SAM!$B$7:$HA$7,0)),0) -> 0 | BI71: =_xlfn.IFNA(INDEX(SAM!$B$8:$HA$215,MATCH($BC71,SAM!$A$8:$A$215,0),MATCH(BI$48,SAM!$B$7:$HA$7,0)),0) -> 0 | BJ71: =_xlfn.IFNA(INDEX(SAM!$B$8:$HA$215,MATCH($BC71,SAM!$A$8:$A$215,0),MATCH(BJ$48,SAM!$B$7:$HA$7,0)),0) -> 0 | BK71: =_xlfn.IFNA(INDEX(SAM!$B$8:$HA$215,MATCH($BC71,SAM!$A$8:$A$215,0),MATCH(BK$48,SAM!$B$7:$HA$7,0)),0) -> 0 | ... BR71: =_xlfn.IFNA(INDEX(SAM!$B$8:$HA$215,MATCH($BC71,SAM!$A$8:$A$215,0),MATCH(BR$48,SAM!$B$7:$HA$7,0)),0) -> 0 | BT71: =AL71 -> cpadm | BU71: =SUM(BD71:BR71,AM71:BA71) -> 0 | BW71: ctext | BX71: =100*VLOOKUP(BW71,$BT$49:$BU$94,2,FALSE)/$BU$95 -> 2.1784506
A72: =HLOOKUP(B72,$B$6:$BR$9,4,FALSE) -> other ag | B72: ocrp | C72: =IFERROR(100*U72/U$95,"") -> 0.0089936677 | D72: =IFERROR(100*V72/V$95,"") -> 0.0044055222 | E72: =IFERROR(100*W72/W$95,"") -> 0.0025453269 | F72: =IFERROR(100*X72/X$95,"") -> 0.0073261002 | G72: =IFERROR(100*Y72/Y$95,"") -> 0.074124095 | H72: =IFERROR(100*Z72/Z$95,"") -> 0 | I72: =IFERROR(100*AA72/AA$95,"") -> 0 | J72: =IFERROR(100*AB72/AB$95,"") -> 0 | ... R72: =IFERROR(100*AJ72/AJ$95,"") -> 0.1085104 | T72: =B72 -> ocrp | U72: =IFERROR(AM72+BD72,"") -> 0.023601675 | V72: =IFERROR(AN72+BE72,"") -> 0.016469306 | W72: =IFERROR(AO72+BF72,"") -> 0.01483675 | X72: =IFERROR(AP72+BG72,"") -> 0.058509541 | Y72: =IFERROR(AQ72+BH72,"") -> 1.0597897 | Z72: =IFERROR(AR72+BI72,"") -> 0 | AA72: =IFERROR(AS72+BJ72,"") -> 0 | AB72: =IFERROR(AT72+BK72,"") -> 0 | ... AI72: =IFERROR(BA72+BR72,"") -> 4.0674797 | AJ72: =SUM(U72:AI72) -> 7.0876296 | AL72: ="c"&T72 -> cocrp | AM72: =_xlfn.IFNA(INDEX(SAM!$B$8:$HA$215,MATCH($AL72,SAM!$A$8:$A$215,0),MATCH(AM$48,SAM!$B$7:$HA$7,0)),0) -> 0.023601675 | AN72: =_xlfn.IFNA(INDEX(SAM!$B$8:$HA$215,MATCH($AL72,SAM!$A$8:$A$215,0),MATCH(AN$48,SAM!$B$7:$HA$7,0)),0) -> 0.013245753 | AO72: =_xlfn.IFNA(INDEX(SAM!$B$8:$HA$215,MATCH($AL72,SAM!$A$8:$A$215,0),MATCH(AO$48,SAM!$B$7:$HA$7,0)),0) -> 0.01483675 | AP72: =_xlfn.IFNA(INDEX(SAM!$B$8:$HA$215,MATCH($AL72,SAM!$A$8:$A$215,0),MATCH(AP$48,SAM!$B$7:$HA$7,0)),0) -> 0.057165077 | AQ72: =_xlfn.IFNA(INDEX(SAM!$B$8:$HA$215,MATCH($AL72,SAM!$A$8:$A$215,0),MATCH(AQ$48,SAM!$B$7:$HA$7,0)),0) -> 1.0500209 | AR72: =_xlfn.IFNA(INDEX(SAM!$B$8:$HA$215,MATCH($AL72,SAM!$A$8:$A$215,0),MATCH(AR$48,SAM!$B$7:$HA$7,0)),0) -> 0 | AS72: =_xlfn.IFNA(INDEX(SAM!$B$8:$HA$215,MATCH($AL72,SAM!$A$8:$A$215,0),MATCH(AS$48,SAM!$B$7:$HA$7,0)),0) -> 0 | AT72: =_xlfn.IFNA(INDEX(SAM!$B$8:$HA$215,MATCH($AL72,SAM!$A$8:$A$215,0),MATCH(AT$48,SAM!$B$7:$HA$7,0)),0) -> 0 | ... BA72: =_xlfn.IFNA(INDEX(SAM!$B$8:$HA$215,MATCH($AL72,SAM!$A$8:$A$215,0),MATCH(BA$48,SAM!$B$7:$HA$7,0)),0) -> 4.0302096 | BC72: ="a"&T72 -> aocrp | BD72: =_xlfn.IFNA(INDEX(SAM!$B$8:$HA$215,MATCH($BC72,SAM!$A$8:$A$215,0),MATCH(BD$48,SAM!$B$7:$HA$7,0)),0) -> 0 | BE72: =_xlfn.IFNA(INDEX(SAM!$B$8:$HA$215,MATCH($BC72,SAM!$A$8:$A$215,0),MATCH(BE$48,SAM!$B$7:$HA$7,0)),0) -> 0.0032235539 | BF72: =_xlfn.IFNA(INDEX(SAM!$B$8:$HA$215,MATCH($BC72,SAM!$A$8:$A$215,0),MATCH(BF$48,SAM!$B$7:$HA$7,0)),0) -> 0 | BG72: =_xlfn.IFNA(INDEX(SAM!$B$8:$HA$215,MATCH($BC72,SAM!$A$8:$A$215,0),MATCH(BG$48,SAM!$B$7:$HA$7,0)),0) -> 0.0013444636 | BH72: =_xlfn.IFNA(INDEX(SAM!$B$8:$HA$215,MATCH($BC72,SAM!$A$8:$A$215,0),MATCH(BH$48,SAM!$B$7:$HA$7,0)),0) -> 0.0097687794 | BI72: =_xlfn.IFNA(INDEX(SAM!$B$8:$HA$215,MATCH($BC72,SAM!$A$8:$A$215,0),MATCH(BI$48,SAM!$B$7:$HA$7,0)),0) -> 0 | BJ72: =_xlfn.IFNA(INDEX(SAM!$B$8:$HA$215,MATCH($BC72,SAM!$A$8:$A$215,0),MATCH(BJ$48,SAM!$B$7:$HA$7,0)),0) -> 0 | BK72: =_xlfn.IFNA(INDEX(SAM!$B$8:$HA$215,MATCH($BC72,SAM!$A$8:$A$215,0),MATCH(BK$48,SAM!$B$7:$HA$7,0)),0) -> 0 | ... BR72: =_xlfn.IFNA(INDEX(SAM!$B$8:$HA$215,MATCH($BC72,SAM!$A$8:$A$215,0),MATCH(BR$48,SAM!$B$7:$HA$7,0)),0) -> 0.037270125 | BT72: =AL72 -> cocrp | BU72: =SUM(BD72:BR72,AM72:BA72) -> 7.0876296 | BW72: cwood | BX72: =100*VLOOKUP(BW72,$BT$49:$BU$94,2,FALSE)/$BU$95 -> 0.56286248
A73: other ag | B73: becr | C73: =IFERROR(100*U73/U$95,"") -> 0.5971007 | D73: =IFERROR(100*V73/V$95,"") -> 0.72983863 | E73: =IFERROR(100*W73/W$95,"") -> 0.72429214 | F73: =IFERROR(100*X73/X$95,"") -> 0.8182797 | G73: =IFERROR(100*Y73/Y$95,"") -> 0.82604655 | H73: =IFERROR(100*Z73/Z$95,"") -> 0.42960445 | I73: =IFERROR(100*AA73/AA$95,"") -> 0.47301696 | J73: =IFERROR(100*AB73/AB$95,"") -> 0.59082806 | ... R73: =IFERROR(100*AJ73/AJ$95,"") -> 0.51309862 | T73: =B73 -> becr | U73: =IFERROR(AM73+BD73,"") -> 1.5669443 | V73: =IFERROR(AN73+BE73,"") -> 2.7283794 | W73: =IFERROR(AO73+BF73,"") -> 4.2219101 | X73: =IFERROR(AP73+BG73,"") -> 6.5351508 | Y73: =IFERROR(AQ73+BH73,"") -> 11.810405 | Z73: =IFERROR(AR73+BI73,"") -> 0.074237826 | AA73: =IFERROR(AS73+BJ73,"") -> 0.10550231 | AB73: =IFERROR(AT73+BK73,"") -> 0.16234328 | ... AI73: =IFERROR(BA73+BR73,"") -> 4.0189649 | AJ73: =SUM(U73:AI73) -> 33.514327 | AL73: ="c"&T73 -> cbecr | AM73: =_xlfn.IFNA(INDEX(SAM!$B$8:$HA$215,MATCH($AL73,SAM!$A$8:$A$215,0),MATCH(AM$48,SAM!$B$7:$HA$7,0)),0) -> 1.2685761 | AN73: =_xlfn.IFNA(INDEX(SAM!$B$8:$HA$215,MATCH($AL73,SAM!$A$8:$A$215,0),MATCH(AN$48,SAM!$B$7:$HA$7,0)),0) -> 2.0964201 | AO73: =_xlfn.IFNA(INDEX(SAM!$B$8:$HA$215,MATCH($AL73,SAM!$A$8:$A$215,0),MATCH(AO$48,SAM!$B$7:$HA$7,0)),0) -> 3.3600055 | AP73: =_xlfn.IFNA(INDEX(SAM!$B$8:$HA$215,MATCH($AL73,SAM!$A$8:$A$215,0),MATCH(AP$48,SAM!$B$7:$HA$7,0)),0) -> 4.906249 | AQ73: =_xlfn.IFNA(INDEX(SAM!$B$8:$HA$215,MATCH($AL73,SAM!$A$8:$A$215,0),MATCH(AQ$48,SAM!$B$7:$HA$7,0)),0) -> 6.4692772 | AR73: =_xlfn.IFNA(INDEX(SAM!$B$8:$HA$215,MATCH($AL73,SAM!$A$8:$A$215,0),MATCH(AR$48,SAM!$B$7:$HA$7,0)),0) -> 0.074237826 | AS73: =_xlfn.IFNA(INDEX(SAM!$B$8:$HA$215,MATCH($AL73,SAM!$A$8:$A$215,0),MATCH(AS$48,SAM!$B$7:$HA$7,0)),0) -> 0.10550231 | AT73: =_xlfn.IFNA(INDEX(SAM!$B$8:$HA$215,MATCH($AL73,SAM!$A$8:$A$215,0),MATCH(AT$48,SAM!$B$7:$HA$7,0)),0) -> 0.16234328 | ... BA73: =_xlfn.IFNA(INDEX(SAM!$B$8:$HA$215,MATCH($AL73,SAM!$A$8:$A$215,0),MATCH(BA$48,SAM!$B$7:$HA$7,0)),0) -> 3.1581508 | BC73: ="a"&T73 -> abecr | BD73: =_xlfn.IFNA(INDEX(SAM!$B$8:$HA$215,MATCH($BC73,SAM!$A$8:$A$215,0),MATCH(BD$48,SAM!$B$7:$HA$7,0)),0) -> 0.29836823 | BE73: =_xlfn.IFNA(INDEX(SAM!$B$8:$HA$215,MATCH($BC73,SAM!$A$8:$A$215,0),MATCH(BE$48,SAM!$B$7:$HA$7,0)),0) -> 0.63195932 | BF73: =_xlfn.IFNA(INDEX(SAM!$B$8:$HA$215,MATCH($BC73,SAM!$A$8:$A$215,0),MATCH(BF$48,SAM!$B$7:$HA$7,0)),0) -> 0.86190453 | BG73: =_xlfn.IFNA(INDEX(SAM!$B$8:$HA$215,MATCH($BC73,SAM!$A$8:$A$215,0),MATCH(BG$48,SAM!$B$7:$HA$7,0)),0) -> 1.6289018 | BH73: =_xlfn.IFNA(INDEX(SAM!$B$8:$HA$215,MATCH($BC73,SAM!$A$8:$A$215,0),MATCH(BH$48,SAM!$B$7:$HA$7,0)),0) -> 5.3411283 | BI73: =_xlfn.IFNA(INDEX(SAM!$B$8:$HA$215,MATCH($BC73,SAM!$A$8:$A$215,0),MATCH(BI$48,SAM!$B$7:$HA$7,0)),0) -> 0 | BJ73: =_xlfn.IFNA(INDEX(SAM!$B$8:$HA$215,MATCH($BC73,SAM!$A$8:$A$215,0),MATCH(BJ$48,SAM!$B$7:$HA$7,0)),0) -> 0 | BK73: =_xlfn.IFNA(INDEX(SAM!$B$8:$HA$215,MATCH($BC73,SAM!$A$8:$A$215,0),MATCH(BK$48,SAM!$B$7:$HA$7,0)),0) -> 0 | ... BR73: =_xlfn.IFNA(INDEX(SAM!$B$8:$HA$215,MATCH($BC73,SAM!$A$8:$A$215,0),MATCH(BR$48,SAM!$B$7:$HA$7,0)),0) -> 0.86081409 | BT73: =AL73 -> cbecr | BU73: =SUM(BD73:BR73,AM73:BA73) -> 33.514327 | BW73: cpetr | BX73: =100*VLOOKUP(BW73,$BT$49:$BU$94,2,FALSE)/$BU$95 -> 0.62486999
A74: other ag | B74: fore | C74: =IFERROR(100*U74/U$95,"") -> 0.38915679 | D74: =IFERROR(100*V74/V$95,"") -> 0.33263141 | E74: =IFERROR(100*W74/W$95,"") -> 0.33210824 | F74: =IFERROR(100*X74/X$95,"") -> 0.28364407 | G74: =IFERROR(100*Y74/Y$95,"") -> 0.22629482 | H74: =IFERROR(100*Z74/Z$95,"") -> 0.33755973 | I74: =IFERROR(100*AA74/AA$95,"") -> 0.34675333 | J74: =IFERROR(100*AB74/AB$95,"") -> 0.25855791 | ... R74: =IFERROR(100*AJ74/AJ$95,"") -> 0.2005329 | T74: =B74 -> fore | U74: =IFERROR(AM74+BD74,"") -> 1.0212466 | V74: =IFERROR(AN74+BE74,"") -> 1.2434868 | W74: =IFERROR(AO74+BF74,"") -> 1.935864 | X74: =IFERROR(AP74+BG74,"") -> 2.2653095 | Y74: =IFERROR(AQ74+BH74,"") -> 3.2354516 | Z74: =IFERROR(AR74+BI74,"") -> 0.058332032 | AA74: =IFERROR(AS74+BJ74,"") -> 0.077340307 | AB74: =IFERROR(AT74+BK74,"") -> 0.071044593 | ... AI74: =IFERROR(BA74+BR74,"") -> 1.944053 | AJ74: =SUM(U74:AI74) -> 13.098311 | AL74: ="c"&T74 -> cfore | AM74: =_xlfn.IFNA(INDEX(SAM!$B$8:$HA$215,MATCH($AL74,SAM!$A$8:$A$215,0),MATCH(AM$48,SAM!$B$7:$HA$7,0)),0) -> 1.0148704 | AN74: =_xlfn.IFNA(INDEX(SAM!$B$8:$HA$215,MATCH($AL74,SAM!$A$8:$A$215,0),MATCH(AN$48,SAM!$B$7:$HA$7,0)),0) -> 1.235433 | AO74: =_xlfn.IFNA(INDEX(SAM!$B$8:$HA$215,MATCH($AL74,SAM!$A$8:$A$215,0),MATCH(AO$48,SAM!$B$7:$HA$7,0)),0) -> 1.9274373 | AP74: =_xlfn.IFNA(INDEX(SAM!$B$8:$HA$215,MATCH($AL74,SAM!$A$8:$A$215,0),MATCH(AP$48,SAM!$B$7:$HA$7,0)),0) -> 2.2495332 | AQ74: =_xlfn.IFNA(INDEX(SAM!$B$8:$HA$215,MATCH($AL74,SAM!$A$8:$A$215,0),MATCH(AQ$48,SAM!$B$7:$HA$7,0)),0) -> 3.2215353 | AR74: =_xlfn.IFNA(INDEX(SAM!$B$8:$HA$215,MATCH($AL74,SAM!$A$8:$A$215,0),MATCH(AR$48,SAM!$B$7:$HA$7,0)),0) -> 0.058332032 | AS74: =_xlfn.IFNA(INDEX(SAM!$B$8:$HA$215,MATCH($AL74,SAM!$A$8:$A$215,0),MATCH(AS$48,SAM!$B$7:$HA$7,0)),0) -> 0.077340307 | AT74: =_xlfn.IFNA(INDEX(SAM!$B$8:$HA$215,MATCH($AL74,SAM!$A$8:$A$215,0),MATCH(AT$48,SAM!$B$7:$HA$7,0)),0) -> 0.071044593 | ... BA74: =_xlfn.IFNA(INDEX(SAM!$B$8:$HA$215,MATCH($AL74,SAM!$A$8:$A$215,0),MATCH(BA$48,SAM!$B$7:$HA$7,0)),0) -> 1.9316894 | BC74: ="a"&T74 -> afore | BD74: =_xlfn.IFNA(INDEX(SAM!$B$8:$HA$215,MATCH($BC74,SAM!$A$8:$A$215,0),MATCH(BD$48,SAM!$B$7:$HA$7,0)),0) -> 0.0063761334 | BE74: =_xlfn.IFNA(INDEX(SAM!$B$8:$HA$215,MATCH($BC74,SAM!$A$8:$A$215,0),MATCH(BE$48,SAM!$B$7:$HA$7,0)),0) -> 0.0080537677 | BF74: =_xlfn.IFNA(INDEX(SAM!$B$8:$HA$215,MATCH($BC74,SAM!$A$8:$A$215,0),MATCH(BF$48,SAM!$B$7:$HA$7,0)),0) -> 0.0084267673 | BG74: =_xlfn.IFNA(INDEX(SAM!$B$8:$HA$215,MATCH($BC74,SAM!$A$8:$A$215,0),MATCH(BG$48,SAM!$B$7:$HA$7,0)),0) -> 0.01577628 | BH74: =_xlfn.IFNA(INDEX(SAM!$B$8:$HA$215,MATCH($BC74,SAM!$A$8:$A$215,0),MATCH(BH$48,SAM!$B$7:$HA$7,0)),0) -> 0.013916296 | BI74: =_xlfn.IFNA(INDEX(SAM!$B$8:$HA$215,MATCH($BC74,SAM!$A$8:$A$215,0),MATCH(BI$48,SAM!$B$7:$HA$7,0)),0) -> 0 | BJ74: =_xlfn.IFNA(INDEX(SAM!$B$8:$HA$215,MATCH($BC74,SAM!$A$8:$A$215,0),MATCH(BJ$48,SAM!$B$7:$HA$7,0)),0) -> 0 | BK74: =_xlfn.IFNA(INDEX(SAM!$B$8:$HA$215,MATCH($BC74,SAM!$A$8:$A$215,0),MATCH(BK$48,SAM!$B$7:$HA$7,0)),0) -> 0 | ... BR74: =_xlfn.IFNA(INDEX(SAM!$B$8:$HA$215,MATCH($BC74,SAM!$A$8:$A$215,0),MATCH(BR$48,SAM!$B$7:$HA$7,0)),0) -> 0.012363638 | BT74: =AL74 -> cfore | BU74: =SUM(BD74:BR74,AM74:BA74) -> 13.098311 | BW74: cfert | BX74: =100*VLOOKUP(BW74,$BT$49:$BU$94,2,FALSE)/$BU$95 -> 0
A75: other ag | B75: oapr | C75: =IFERROR(100*U75/U$95,"") -> 2.1174414 | D75: =IFERROR(100*V75/V$95,"") -> 1.0962063 | E75: =IFERROR(100*W75/W$95,"") -> 1.044868 | F75: =IFERROR(100*X75/X$95,"") -> 1.4811423 | G75: =IFERROR(100*Y75/Y$95,"") -> 0.95516463 | H75: =IFERROR(100*Z75/Z$95,"") -> 1.3037122 | I75: =IFERROR(100*AA75/AA$95,"") -> 0.43588198 | J75: =IFERROR(100*AB75/AB$95,"") -> 1.4337092 | ... R75: =IFERROR(100*AJ75/AJ$95,"") -> 1.0125267 | T75: =B75 -> oapr | U75: =IFERROR(AM75+BD75,"") -> 5.5567058 | V75: =IFERROR(AN75+BE75,"") -> 4.0979836 | W75: =IFERROR(AO75+BF75,"") -> 6.0905517 | X75: =IFERROR(AP75+BG75,"") -> 11.82907 | Y75: =IFERROR(AQ75+BH75,"") -> 13.656472 | Z75: =IFERROR(AR75+BI75,"") -> 0.22528807 | AA75: =IFERROR(AS75+BJ75,"") -> 0.097219674 | AB75: =IFERROR(AT75+BK75,"") -> 0.39394379 | ... AI75: =IFERROR(BA75+BR75,"") -> 16.174769 | AJ75: =SUM(U75:AI75) -> 66.13573 | AL75: ="c"&T75 -> coapr | AM75: =_xlfn.IFNA(INDEX(SAM!$B$8:$HA$215,MATCH($AL75,SAM!$A$8:$A$215,0),MATCH(AM$48,SAM!$B$7:$HA$7,0)),0) -> 5.5567058 | AN75: =_xlfn.IFNA(INDEX(SAM!$B$8:$HA$215,MATCH($AL75,SAM!$A$8:$A$215,0),MATCH(AN$48,SAM!$B$7:$HA$7,0)),0) -> 4.0979836 | AO75: =_xlfn.IFNA(INDEX(SAM!$B$8:$HA$215,MATCH($AL75,SAM!$A$8:$A$215,0),MATCH(AO$48,SAM!$B$7:$HA$7,0)),0) -> 6.0905517 | AP75: =_xlfn.IFNA(INDEX(SAM!$B$8:$HA$215,MATCH($AL75,SAM!$A$8:$A$215,0),MATCH(AP$48,SAM!$B$7:$HA$7,0)),0) -> 11.82907 | AQ75: =_xlfn.IFNA(INDEX(SAM!$B$8:$HA$215,MATCH($AL75,SAM!$A$8:$A$215,0),MATCH(AQ$48,SAM!$B$7:$HA$7,0)),0) -> 13.656472 | AR75: =_xlfn.IFNA(INDEX(SAM!$B$8:$HA$215,MATCH($AL75,SAM!$A$8:$A$215,0),MATCH(AR$48,SAM!$B$7:$HA$7,0)),0) -> 0.22528807 | AS75: =_xlfn.IFNA(INDEX(SAM!$B$8:$HA$215,MATCH($AL75,SAM!$A$8:$A$215,0),MATCH(AS$48,SAM!$B$7:$HA$7,0)),0) -> 0.097219674 | AT75: =_xlfn.IFNA(INDEX(SAM!$B$8:$HA$215,MATCH($AL75,SAM!$A$8:$A$215,0),MATCH(AT$48,SAM!$B$7:$HA$7,0)),0) -> 0.39394379 | ... BA75: =_xlfn.IFNA(INDEX(SAM!$B$8:$HA$215,MATCH($AL75,SAM!$A$8:$A$215,0),MATCH(BA$48,SAM!$B$7:$HA$7,0)),0) -> 16.174769 | BC75: ="a"&T75 -> aoapr | BD75: =_xlfn.IFNA(INDEX(SAM!$B$8:$HA$215,MATCH($BC75,SAM!$A$8:$A$215,0),MATCH(BD$48,SAM!$B$7:$HA$7,0)),0) -> 0 | BE75: =_xlfn.IFNA(INDEX(SAM!$B$8:$HA$215,MATCH($BC75,SAM!$A$8:$A$215,0),MATCH(BE$48,SAM!$B$7:$HA$7,0)),0) -> 0 | BF75: =_xlfn.IFNA(INDEX(SAM!$B$8:$HA$215,MATCH($BC75,SAM!$A$8:$A$215,0),MATCH(BF$48,SAM!$B$7:$HA$7,0)),0) -> 0 | BG75: =_xlfn.IFNA(INDEX(SAM!$B$8:$HA$215,MATCH($BC75,SAM!$A$8:$A$215,0),MATCH(BG$48,SAM!$B$7:$HA$7,0)),0) -> 0 | BH75: =_xlfn.IFNA(INDEX(SAM!$B$8:$HA$215,MATCH($BC75,SAM!$A$8:$A$215,0),MATCH(BH$48,SAM!$B$7:$HA$7,0)),0) -> 0 | BI75: =_xlfn.IFNA(INDEX(SAM!$B$8:$HA$215,MATCH($BC75,SAM!$A$8:$A$215,0),MATCH(BI$48,SAM!$B$7:$HA$7,0)),0) -> 0 | BJ75: =_xlfn.IFNA(INDEX(SAM!$B$8:$HA$215,MATCH($BC75,SAM!$A$8:$A$215,0),MATCH(BJ$48,SAM!$B$7:$HA$7,0)),0) -> 0 | BK75: =_xlfn.IFNA(INDEX(SAM!$B$8:$HA$215,MATCH($BC75,SAM!$A$8:$A$215,0),MATCH(BK$48,SAM!$B$7:$HA$7,0)),0) -> 0 | ... BR75: =_xlfn.IFNA(INDEX(SAM!$B$8:$HA$215,MATCH($BC75,SAM!$A$8:$A$215,0),MATCH(BR$48,SAM!$B$7:$HA$7,0)),0) -> 0 | BT75: =AL75 -> coapr | BU75: =SUM(BD75:BR75,AM75:BA75) -> 66.13573 | BW75: cchem | BX75: =100*VLOOKUP(BW75,$BT$49:$BU$94,2,FALSE)/$BU$95 -> 1.8835434
A76: mining | B76: mine | C76: =IFERROR(100*U76/U$95,"") -> 0 | D76: =IFERROR(100*V76/V$95,"") -> 0 | E76: =IFERROR(100*W76/W$95,"") -> 0 | F76: =IFERROR(100*X76/X$95,"") -> 0 | G76: =IFERROR(100*Y76/Y$95,"") -> 0 | H76: =IFERROR(100*Z76/Z$95,"") -> 0 | I76: =IFERROR(100*AA76/AA$95,"") -> 0 | J76: =IFERROR(100*AB76/AB$95,"") -> 0 | ... R76: =IFERROR(100*AJ76/AJ$95,"") -> 0 | T76: =B76 -> mine | U76: =IFERROR(AM76+BD76,"") -> 0 | V76: =IFERROR(AN76+BE76,"") -> 0 | W76: =IFERROR(AO76+BF76,"") -> 0 | X76: =IFERROR(AP76+BG76,"") -> 0 | Y76: =IFERROR(AQ76+BH76,"") -> 0 | Z76: =IFERROR(AR76+BI76,"") -> 0 | AA76: =IFERROR(AS76+BJ76,"") -> 0 | AB76: =IFERROR(AT76+BK76,"") -> 0 | ... AI76: =IFERROR(BA76+BR76,"") -> 0 | AJ76: =SUM(U76:AI76) -> 0 | AL76: ="c"&T76 -> cmine | AM76: =_xlfn.IFNA(INDEX(SAM!$B$8:$HA$215,MATCH($AL76,SAM!$A$8:$A$215,0),MATCH(AM$48,SAM!$B$7:$HA$7,0)),0) -> 0 | AN76: =_xlfn.IFNA(INDEX(SAM!$B$8:$HA$215,MATCH($AL76,SAM!$A$8:$A$215,0),MATCH(AN$48,SAM!$B$7:$HA$7,0)),0) -> 0 | AO76: =_xlfn.IFNA(INDEX(SAM!$B$8:$HA$215,MATCH($AL76,SAM!$A$8:$A$215,0),MATCH(AO$48,SAM!$B$7:$HA$7,0)),0) -> 0 | AP76: =_xlfn.IFNA(INDEX(SAM!$B$8:$HA$215,MATCH($AL76,SAM!$A$8:$A$215,0),MATCH(AP$48,SAM!$B$7:$HA$7,0)),0) -> 0 | AQ76: =_xlfn.IFNA(INDEX(SAM!$B$8:$HA$215,MATCH($AL76,SAM!$A$8:$A$215,0),MATCH(AQ$48,SAM!$B$7:$HA$7,0)),0) -> 0 | AR76: =_xlfn.IFNA(INDEX(SAM!$B$8:$HA$215,MATCH($AL76,SAM!$A$8:$A$215,0),MATCH(AR$48,SAM!$B$7:$HA$7,0)),0) -> 0 | AS76: =_xlfn.IFNA(INDEX(SAM!$B$8:$HA$215,MATCH($AL76,SAM!$A$8:$A$215,0),MATCH(AS$48,SAM!$B$7:$HA$7,0)),0) -> 0 | AT76: =_xlfn.IFNA(INDEX(SAM!$B$8:$HA$215,MATCH($AL76,SAM!$A$8:$A$215,0),MATCH(AT$48,SAM!$B$7:$HA$7,0)),0) -> 0 | ... BA76: =_xlfn.IFNA(INDEX(SAM!$B$8:$HA$215,MATCH($AL76,SAM!$A$8:$A$215,0),MATCH(BA$48,SAM!$B$7:$HA$7,0)),0) -> 0 | BC76: ="a"&T76 -> amine | BD76: =_xlfn.IFNA(INDEX(SAM!$B$8:$HA$215,MATCH($BC76,SAM!$A$8:$A$215,0),MATCH(BD$48,SAM!$B$7:$HA$7,0)),0) -> 0 | BE76: =_xlfn.IFNA(INDEX(SAM!$B$8:$HA$215,MATCH($BC76,SAM!$A$8:$A$215,0),MATCH(BE$48,SAM!$B$7:$HA$7,0)),0) -> 0 | BF76: =_xlfn.IFNA(INDEX(SAM!$B$8:$HA$215,MATCH($BC76,SAM!$A$8:$A$215,0),MATCH(BF$48,SAM!$B$7:$HA$7,0)),0) -> 0 | BG76: =_xlfn.IFNA(INDEX(SAM!$B$8:$HA$215,MATCH($BC76,SAM!$A$8:$A$215,0),MATCH(BG$48,SAM!$B$7:$HA$7,0)),0) -> 0 | BH76: =_xlfn.IFNA(INDEX(SAM!$B$8:$HA$215,MATCH($BC76,SAM!$A$8:$A$215,0),MATCH(BH$48,SAM!$B$7:$HA$7,0)),0) -> 0 | BI76: =_xlfn.IFNA(INDEX(SAM!$B$8:$HA$215,MATCH($BC76,SAM!$A$8:$A$215,0),MATCH(BI$48,SAM!$B$7:$HA$7,0)),0) -> 0 | BJ76: =_xlfn.IFNA(INDEX(SAM!$B$8:$HA$215,MATCH($BC76,SAM!$A$8:$A$215,0),MATCH(BJ$48,SAM!$B$7:$HA$7,0)),0) -> 0 | BK76: =_xlfn.IFNA(INDEX(SAM!$B$8:$HA$215,MATCH($BC76,SAM!$A$8:$A$215,0),MATCH(BK$48,SAM!$B$7:$HA$7,0)),0) -> 0 | ... BR76: =_xlfn.IFNA(INDEX(SAM!$B$8:$HA$215,MATCH($BC76,SAM!$A$8:$A$215,0),MATCH(BR$48,SAM!$B$7:$HA$7,0)),0) -> 0 | BT76: =AL76 -> cmine | BU76: =SUM(BD76:BR76,AM76:BA76) -> 0 | BW76: cnmet | BX76: =100*VLOOKUP(BW76,$BT$49:$BU$94,2,FALSE)/$BU$95 -> 0.39398691
A77: mining | B77: mino | C77: =IFERROR(100*U77/U$95,"") -> 0 | D77: =IFERROR(100*V77/V$95,"") -> 0 | E77: =IFERROR(100*W77/W$95,"") -> 0 | F77: =IFERROR(100*X77/X$95,"") -> 0 | G77: =IFERROR(100*Y77/Y$95,"") -> 0 | H77: =IFERROR(100*Z77/Z$95,"") -> 0 | I77: =IFERROR(100*AA77/AA$95,"") -> 0 | J77: =IFERROR(100*AB77/AB$95,"") -> 0 | ... R77: =IFERROR(100*AJ77/AJ$95,"") -> 0 | T77: =B77 -> mino | U77: =IFERROR(AM77+BD77,"") -> 0 | V77: =IFERROR(AN77+BE77,"") -> 0 | W77: =IFERROR(AO77+BF77,"") -> 0 | X77: =IFERROR(AP77+BG77,"") -> 0 | Y77: =IFERROR(AQ77+BH77,"") -> 0 | Z77: =IFERROR(AR77+BI77,"") -> 0 | AA77: =IFERROR(AS77+BJ77,"") -> 0 | AB77: =IFERROR(AT77+BK77,"") -> 0 | ... AI77: =IFERROR(BA77+BR77,"") -> 0 | AJ77: =SUM(U77:AI77) -> 0 | AL77: ="c"&T77 -> cmino | AM77: =_xlfn.IFNA(INDEX(SAM!$B$8:$HA$215,MATCH($AL77,SAM!$A$8:$A$215,0),MATCH(AM$48,SAM!$B$7:$HA$7,0)),0) -> 0 | AN77: =_xlfn.IFNA(INDEX(SAM!$B$8:$HA$215,MATCH($AL77,SAM!$A$8:$A$215,0),MATCH(AN$48,SAM!$B$7:$HA$7,0)),0) -> 0 | AO77: =_xlfn.IFNA(INDEX(SAM!$B$8:$HA$215,MATCH($AL77,SAM!$A$8:$A$215,0),MATCH(AO$48,SAM!$B$7:$HA$7,0)),0) -> 0 | AP77: =_xlfn.IFNA(INDEX(SAM!$B$8:$HA$215,MATCH($AL77,SAM!$A$8:$A$215,0),MATCH(AP$48,SAM!$B$7:$HA$7,0)),0) -> 0 | AQ77: =_xlfn.IFNA(INDEX(SAM!$B$8:$HA$215,MATCH($AL77,SAM!$A$8:$A$215,0),MATCH(AQ$48,SAM!$B$7:$HA$7,0)),0) -> 0 | AR77: =_xlfn.IFNA(INDEX(SAM!$B$8:$HA$215,MATCH($AL77,SAM!$A$8:$A$215,0),MATCH(AR$48,SAM!$B$7:$HA$7,0)),0) -> 0 | AS77: =_xlfn.IFNA(INDEX(SAM!$B$8:$HA$215,MATCH($AL77,SAM!$A$8:$A$215,0),MATCH(AS$48,SAM!$B$7:$HA$7,0)),0) -> 0 | AT77: =_xlfn.IFNA(INDEX(SAM!$B$8:$HA$215,MATCH($AL77,SAM!$A$8:$A$215,0),MATCH(AT$48,SAM!$B$7:$HA$7,0)),0) -> 0 | ... BA77: =_xlfn.IFNA(INDEX(SAM!$B$8:$HA$215,MATCH($AL77,SAM!$A$8:$A$215,0),MATCH(BA$48,SAM!$B$7:$HA$7,0)),0) -> 0 | BC77: ="a"&T77 -> amino | BD77: =_xlfn.IFNA(INDEX(SAM!$B$8:$HA$215,MATCH($BC77,SAM!$A$8:$A$215,0),MATCH(BD$48,SAM!$B$7:$HA$7,0)),0) -> 0 | BE77: =_xlfn.IFNA(INDEX(SAM!$B$8:$HA$215,MATCH($BC77,SAM!$A$8:$A$215,0),MATCH(BE$48,SAM!$B$7:$HA$7,0)),0) -> 0 | BF77: =_xlfn.IFNA(INDEX(SAM!$B$8:$HA$215,MATCH($BC77,SAM!$A$8:$A$215,0),MATCH(BF$48,SAM!$B$7:$HA$7,0)),0) -> 0 | BG77: =_xlfn.IFNA(INDEX(SAM!$B$8:$HA$215,MATCH($BC77,SAM!$A$8:$A$215,0),MATCH(BG$48,SAM!$B$7:$HA$7,0)),0) -> 0 | BH77: =_xlfn.IFNA(INDEX(SAM!$B$8:$HA$215,MATCH($BC77,SAM!$A$8:$A$215,0),MATCH(BH$48,SAM!$B$7:$HA$7,0)),0) -> 0 | BI77: =_xlfn.IFNA(INDEX(SAM!$B$8:$HA$215,MATCH($BC77,SAM!$A$8:$A$215,0),MATCH(BI$48,SAM!$B$7:$HA$7,0)),0) -> 0 | BJ77: =_xlfn.IFNA(INDEX(SAM!$B$8:$HA$215,MATCH($BC77,SAM!$A$8:$A$215,0),MATCH(BJ$48,SAM!$B$7:$HA$7,0)),0) -> 0 | BK77: =_xlfn.IFNA(INDEX(SAM!$B$8:$HA$215,MATCH($BC77,SAM!$A$8:$A$215,0),MATCH(BK$48,SAM!$B$7:$HA$7,0)),0) -> 0 | ... BR77: =_xlfn.IFNA(INDEX(SAM!$B$8:$HA$215,MATCH($BC77,SAM!$A$8:$A$215,0),MATCH(BR$48,SAM!$B$7:$HA$7,0)),0) -> 0 | BT77: =AL77 -> cmino | BU77: =SUM(BD77:BR77,AM77:BA77) -> 0 | BW77: cmetl | BX77: =100*VLOOKUP(BW77,$BT$49:$BU$94,2,FALSE)/$BU$95 -> 0.11463446
A78: =HLOOKUP(B78,$B$6:$BR$9,4,FALSE) -> manufacturing | B78: wood | C78: =IFERROR(100*U78/U$95,"") -> 0.87127517 | D78: =IFERROR(100*V78/V$95,"") -> 0.65593321 | E78: =IFERROR(100*W78/W$95,"") -> 0.55824665 | F78: =IFERROR(100*X78/X$95,"") -> 0.46820614 | G78: =IFERROR(100*Y78/Y$95,"") -> 0.39857082 | H78: =IFERROR(100*Z78/Z$95,"") -> 0.62869649 | I78: =IFERROR(100*AA78/AA$95,"") -> 0.57765338 | J78: =IFERROR(100*AB78/AB$95,"") -> 0.55093422 | ... R78: =IFERROR(100*AJ78/AJ$95,"") -> 0.56286248 | T78: =B78 -> wood | U78: =IFERROR(AM78+BD78,"") -> 2.286448 | V78: =IFERROR(AN78+BE78,"") -> 2.4520964 | W78: =IFERROR(AO78+BF78,"") -> 3.2540283 | X78: =IFERROR(AP78+BG78,"") -> 3.7393054 | Y78: =IFERROR(AQ78+BH78,"") -> 5.6985687 | Z78: =IFERROR(AR78+BI78,"") -> 0.10864194 | AA78: =IFERROR(AS78+BJ78,"") -> 0.12884055 | AB78: =IFERROR(AT78+BK78,"") -> 0.15138155 | ... AI78: =IFERROR(BA78+BR78,"") -> 15.451157 | AJ78: =SUM(U78:AI78) -> 36.764779 | AL78: ="c"&T78 -> cwood | AM78: =_xlfn.IFNA(INDEX(SAM!$B$8:$HA$215,MATCH($AL78,SAM!$A$8:$A$215,0),MATCH(AM$48,SAM!$B$7:$HA$7,0)),0) -> 2.286448 | AN78: =_xlfn.IFNA(INDEX(SAM!$B$8:$HA$215,MATCH($AL78,SAM!$A$8:$A$215,0),MATCH(AN$48,SAM!$B$7:$HA$7,0)),0) -> 2.4520964 | AO78: =_xlfn.IFNA(INDEX(SAM!$B$8:$HA$215,MATCH($AL78,SAM!$A$8:$A$215,0),MATCH(AO$48,SAM!$B$7:$HA$7,0)),0) -> 3.2540283 | AP78: =_xlfn.IFNA(INDEX(SAM!$B$8:$HA$215,MATCH($AL78,SAM!$A$8:$A$215,0),MATCH(AP$48,SAM!$B$7:$HA$7,0)),0) -> 3.7393054 | AQ78: =_xlfn.IFNA(INDEX(SAM!$B$8:$HA$215,MATCH($AL78,SAM!$A$8:$A$215,0),MATCH(AQ$48,SAM!$B$7:$HA$7,0)),0) -> 5.6985687 | AR78: =_xlfn.IFNA(INDEX(SAM!$B$8:$HA$215,MATCH($AL78,SAM!$A$8:$A$215,0),MATCH(AR$48,SAM!$B$7:$HA$7,0)),0) -> 0.10864194 | AS78: =_xlfn.IFNA(INDEX(SAM!$B$8:$HA$215,MATCH($AL78,SAM!$A$8:$A$215,0),MATCH(AS$48,SAM!$B$7:$HA$7,0)),0) -> 0.12884055 | AT78: =_xlfn.IFNA(INDEX(SAM!$B$8:$HA$215,MATCH($AL78,SAM!$A$8:$A$215,0),MATCH(AT$48,SAM!$B$7:$HA$7,0)),0) -> 0.15138155 | ... BA78: =_xlfn.IFNA(INDEX(SAM!$B$8:$HA$215,MATCH($AL78,SAM!$A$8:$A$215,0),MATCH(BA$48,SAM!$B$7:$HA$7,0)),0) -> 15.451157 | BC78: ="a"&T78 -> awood | BD78: =_xlfn.IFNA(INDEX(SAM!$B$8:$HA$215,MATCH($BC78,SAM!$A$8:$A$215,0),MATCH(BD$48,SAM!$B$7:$HA$7,0)),0) -> 0 | BE78: =_xlfn.IFNA(INDEX(SAM!$B$8:$HA$215,MATCH($BC78,SAM!$A$8:$A$215,0),MATCH(BE$48,SAM!$B$7:$HA$7,0)),0) -> 0 | BF78: =_xlfn.IFNA(INDEX(SAM!$B$8:$HA$215,MATCH($BC78,SAM!$A$8:$A$215,0),MATCH(BF$48,SAM!$B$7:$HA$7,0)),0) -> 0 | BG78: =_xlfn.IFNA(INDEX(SAM!$B$8:$HA$215,MATCH($BC78,SAM!$A$8:$A$215,0),MATCH(BG$48,SAM!$B$7:$HA$7,0)),0) -> 0 | BH78: =_xlfn.IFNA(INDEX(SAM!$B$8:$HA$215,MATCH($BC78,SAM!$A$8:$A$215,0),MATCH(BH$48,SAM!$B$7:$HA$7,0)),0) -> 0 | BI78: =_xlfn.IFNA(INDEX(SAM!$B$8:$HA$215,MATCH($BC78,SAM!$A$8:$A$215,0),MATCH(BI$48,SAM!$B$7:$HA$7,0)),0) -> 0 | BJ78: =_xlfn.IFNA(INDEX(SAM!$B$8:$HA$215,MATCH($BC78,SAM!$A$8:$A$215,0),MATCH(BJ$48,SAM!$B$7:$HA$7,0)),0) -> 0 | BK78: =_xlfn.IFNA(INDEX(SAM!$B$8:$HA$215,MATCH($BC78,SAM!$A$8:$A$215,0),MATCH(BK$48,SAM!$B$7:$HA$7,0)),0) -> 0 | ... BR78: =_xlfn.IFNA(INDEX(SAM!$B$8:$HA$215,MATCH($BC78,SAM!$A$8:$A$215,0),MATCH(BR$48,SAM!$B$7:$HA$7,0)),0) -> 0 | BT78: =AL78 -> cwood | BU78: =SUM(BD78:BR78,AM78:BA78) -> 36.764779 | BW78: cmach | BX78: =100*VLOOKUP(BW78,$BT$49:$BU$94,2,FALSE)/$BU$95 -> 1.198513
A79: =HLOOKUP(B79,$B$6:$BR$9,4,FALSE) -> manufacturing | B79: petr | C79: =IFERROR(100*U79/U$95,"") -> 0.0067109621 | D79: =IFERROR(100*V79/V$95,"") -> 0.016401435 | E79: =IFERROR(100*W79/W$95,"") -> 0.071400456 | F79: =IFERROR(100*X79/X$95,"") -> 0.15174062 | G79: =IFERROR(100*Y79/Y$95,"") -> 0.51519573 | H79: =IFERROR(100*Z79/Z$95,"") -> 0 | I79: =IFERROR(100*AA79/AA$95,"") -> 0 | J79: =IFERROR(100*AB79/AB$95,"") -> 0 | ... R79: =IFERROR(100*AJ79/AJ$95,"") -> 0.62486999 | T79: =B79 -> petr | U79: =IFERROR(AM79+BD79,"") -> 0.017611274 | V79: =IFERROR(AN79+BE79,"") -> 0.061314015 | W79: =IFERROR(AO79+BF79,"") -> 0.41619436 | X79: =IFERROR(AP79+BG79,"") -> 1.211869 | Y79: =IFERROR(AQ79+BH79,"") -> 7.3660141 | Z79: =IFERROR(AR79+BI79,"") -> 0 | AA79: =IFERROR(AS79+BJ79,"") -> 0 | AB79: =IFERROR(AT79+BK79,"") -> 0 | ... AI79: =IFERROR(BA79+BR79,"") -> 30.060321 | AJ79: =SUM(U79:AI79) -> 40.814955 | AL79: ="c"&T79 -> cpetr | AM79: =_xlfn.IFNA(INDEX(SAM!$B$8:$HA$215,MATCH($AL79,SAM!$A$8:$A$215,0),MATCH(AM$48,SAM!$B$7:$HA$7,0)),0) -> 0.017611274 | AN79: =_xlfn.IFNA(INDEX(SAM!$B$8:$HA$215,MATCH($AL79,SAM!$A$8:$A$215,0),MATCH(AN$48,SAM!$B$7:$HA$7,0)),0) -> 0.061314015 | AO79: =_xlfn.IFNA(INDEX(SAM!$B$8:$HA$215,MATCH($AL79,SAM!$A$8:$A$215,0),MATCH(AO$48,SAM!$B$7:$HA$7,0)),0) -> 0.41619436 | AP79: =_xlfn.IFNA(INDEX(SAM!$B$8:$HA$215,MATCH($AL79,SAM!$A$8:$A$215,0),MATCH(AP$48,SAM!$B$7:$HA$7,0)),0) -> 1.211869 | AQ79: =_xlfn.IFNA(INDEX(SAM!$B$8:$HA$215,MATCH($AL79,SAM!$A$8:$A$215,0),MATCH(AQ$48,SAM!$B$7:$HA$7,0)),0) -> 7.3660141 | AR79: =_xlfn.IFNA(INDEX(SAM!$B$8:$HA$215,MATCH($AL79,SAM!$A$8:$A$215,0),MATCH(AR$48,SAM!$B$7:$HA$7,0)),0) -> 0 | AS79: =_xlfn.IFNA(INDEX(SAM!$B$8:$HA$215,MATCH($AL79,SAM!$A$8:$A$215,0),MATCH(AS$48,SAM!$B$7:$HA$7,0)),0) -> 0 | AT79: =_xlfn.IFNA(INDEX(SAM!$B$8:$HA$215,MATCH($AL79,SAM!$A$8:$A$215,0),MATCH(AT$48,SAM!$B$7:$HA$7,0)),0) -> 0 | ... BA79: =_xlfn.IFNA(INDEX(SAM!$B$8:$HA$215,MATCH($AL79,SAM!$A$8:$A$215,0),MATCH(BA$48,SAM!$B$7:$HA$7,0)),0) -> 30.060321 | BC79: ="a"&T79 -> apetr | BD79: =_xlfn.IFNA(INDEX(SAM!$B$8:$HA$215,MATCH($BC79,SAM!$A$8:$A$215,0),MATCH(BD$48,SAM!$B$7:$HA$7,0)),0) -> 0 | BE79: =_xlfn.IFNA(INDEX(SAM!$B$8:$HA$215,MATCH($BC79,SAM!$A$8:$A$215,0),MATCH(BE$48,SAM!$B$7:$HA$7,0)),0) -> 0 | BF79: =_xlfn.IFNA(INDEX(SAM!$B$8:$HA$215,MATCH($BC79,SAM!$A$8:$A$215,0),MATCH(BF$48,SAM!$B$7:$HA$7,0)),0) -> 0 | BG79: =_xlfn.IFNA(INDEX(SAM!$B$8:$HA$215,MATCH($BC79,SAM!$A$8:$A$215,0),MATCH(BG$48,SAM!$B$7:$HA$7,0)),0) -> 0 | BH79: =_xlfn.IFNA(INDEX(SAM!$B$8:$HA$215,MATCH($BC79,SAM!$A$8:$A$215,0),MATCH(BH$48,SAM!$B$7:$HA$7,0)),0) -> 0 | BI79: =_xlfn.IFNA(INDEX(SAM!$B$8:$HA$215,MATCH($BC79,SAM!$A$8:$A$215,0),MATCH(BI$48,SAM!$B$7:$HA$7,0)),0) -> 0 | BJ79: =_xlfn.IFNA(INDEX(SAM!$B$8:$HA$215,MATCH($BC79,SAM!$A$8:$A$215,0),MATCH(BJ$48,SAM!$B$7:$HA$7,0)),0) -> 0 | BK79: =_xlfn.IFNA(INDEX(SAM!$B$8:$HA$215,MATCH($BC79,SAM!$A$8:$A$215,0),MATCH(BK$48,SAM!$B$7:$HA$7,0)),0) -> 0 | ... BR79: =_xlfn.IFNA(INDEX(SAM!$B$8:$HA$215,MATCH($BC79,SAM!$A$8:$A$215,0),MATCH(BR$48,SAM!$B$7:$HA$7,0)),0) -> 0 | BT79: =AL79 -> cpetr | BU79: =SUM(BD79:BR79,AM79:BA79) -> 40.814955 | BW79: coman | BX79: =100*VLOOKUP(BW79,$BT$49:$BU$94,2,FALSE)/$BU$95 -> 0.19855359
A80: =HLOOKUP(B80,$B$6:$BR$9,4,FALSE) -> manufacturing | B80: fert | C80: =IFERROR(100*U80/U$95,"") -> 0 | D80: =IFERROR(100*V80/V$95,"") -> 0 | E80: =IFERROR(100*W80/W$95,"") -> 0 | F80: =IFERROR(100*X80/X$95,"") -> 0 | G80: =IFERROR(100*Y80/Y$95,"") -> 0 | H80: =IFERROR(100*Z80/Z$95,"") -> 0 | I80: =IFERROR(100*AA80/AA$95,"") -> 0 | J80: =IFERROR(100*AB80/AB$95,"") -> 0 | ... R80: =IFERROR(100*AJ80/AJ$95,"") -> 0 | T80: =B80 -> fert | U80: =IFERROR(AM80+BD80,"") -> 0 | V80: =IFERROR(AN80+BE80,"") -> 0 | W80: =IFERROR(AO80+BF80,"") -> 0 | X80: =IFERROR(AP80+BG80,"") -> 0 | Y80: =IFERROR(AQ80+BH80,"") -> 0 | Z80: =IFERROR(AR80+BI80,"") -> 0 | AA80: =IFERROR(AS80+BJ80,"") -> 0 | AB80: =IFERROR(AT80+BK80,"") -> 0 | ... AI80: =IFERROR(BA80+BR80,"") -> 0 | AJ80: =SUM(U80:AI80) -> 0 | AL80: ="c"&T80 -> cfert | AM80: =_xlfn.IFNA(INDEX(SAM!$B$8:$HA$215,MATCH($AL80,SAM!$A$8:$A$215,0),MATCH(AM$48,SAM!$B$7:$HA$7,0)),0) -> 0 | AN80: =_xlfn.IFNA(INDEX(SAM!$B$8:$HA$215,MATCH($AL80,SAM!$A$8:$A$215,0),MATCH(AN$48,SAM!$B$7:$HA$7,0)),0) -> 0 | AO80: =_xlfn.IFNA(INDEX(SAM!$B$8:$HA$215,MATCH($AL80,SAM!$A$8:$A$215,0),MATCH(AO$48,SAM!$B$7:$HA$7,0)),0) -> 0 | AP80: =_xlfn.IFNA(INDEX(SAM!$B$8:$HA$215,MATCH($AL80,SAM!$A$8:$A$215,0),MATCH(AP$48,SAM!$B$7:$HA$7,0)),0) -> 0 | AQ80: =_xlfn.IFNA(INDEX(SAM!$B$8:$HA$215,MATCH($AL80,SAM!$A$8:$A$215,0),MATCH(AQ$48,SAM!$B$7:$HA$7,0)),0) -> 0 | AR80: =_xlfn.IFNA(INDEX(SAM!$B$8:$HA$215,MATCH($AL80,SAM!$A$8:$A$215,0),MATCH(AR$48,SAM!$B$7:$HA$7,0)),0) -> 0 | AS80: =_xlfn.IFNA(INDEX(SAM!$B$8:$HA$215,MATCH($AL80,SAM!$A$8:$A$215,0),MATCH(AS$48,SAM!$B$7:$HA$7,0)),0) -> 0 | AT80: =_xlfn.IFNA(INDEX(SAM!$B$8:$HA$215,MATCH($AL80,SAM!$A$8:$A$215,0),MATCH(AT$48,SAM!$B$7:$HA$7,0)),0) -> 0 | ... BA80: =_xlfn.IFNA(INDEX(SAM!$B$8:$HA$215,MATCH($AL80,SAM!$A$8:$A$215,0),MATCH(BA$48,SAM!$B$7:$HA$7,0)),0) -> 0 | BC80: ="a"&T80 -> afert | BD80: =_xlfn.IFNA(INDEX(SAM!$B$8:$HA$215,MATCH($BC80,SAM!$A$8:$A$215,0),MATCH(BD$48,SAM!$B$7:$HA$7,0)),0) -> 0 | BE80: =_xlfn.IFNA(INDEX(SAM!$B$8:$HA$215,MATCH($BC80,SAM!$A$8:$A$215,0),MATCH(BE$48,SAM!$B$7:$HA$7,0)),0) -> 0 | BF80: =_xlfn.IFNA(INDEX(SAM!$B$8:$HA$215,MATCH($BC80,SAM!$A$8:$A$215,0),MATCH(BF$48,SAM!$B$7:$HA$7,0)),0) -> 0 | BG80: =_xlfn.IFNA(INDEX(SAM!$B$8:$HA$215,MATCH($BC80,SAM!$A$8:$A$215,0),MATCH(BG$48,SAM!$B$7:$HA$7,0)),0) -> 0 | BH80: =_xlfn.IFNA(INDEX(SAM!$B$8:$HA$215,MATCH($BC80,SAM!$A$8:$A$215,0),MATCH(BH$48,SAM!$B$7:$HA$7,0)),0) -> 0 | BI80: =_xlfn.IFNA(INDEX(SAM!$B$8:$HA$215,MATCH($BC80,SAM!$A$8:$A$215,0),MATCH(BI$48,SAM!$B$7:$HA$7,0)),0) -> 0 | BJ80: =_xlfn.IFNA(INDEX(SAM!$B$8:$HA$215,MATCH($BC80,SAM!$A$8:$A$215,0),MATCH(BJ$48,SAM!$B$7:$HA$7,0)),0) -> 0 | BK80: =_xlfn.IFNA(INDEX(SAM!$B$8:$HA$215,MATCH($BC80,SAM!$A$8:$A$215,0),MATCH(BK$48,SAM!$B$7:$HA$7,0)),0) -> 0 | ... BR80: =_xlfn.IFNA(INDEX(SAM!$B$8:$HA$215,MATCH($BC80,SAM!$A$8:$A$215,0),MATCH(BR$48,SAM!$B$7:$HA$7,0)),0) -> 0 | BT80: =AL80 -> cfert | BU80: =SUM(BD80:BR80,AM80:BA80) -> 0 | BW80: celec | BX80: =100*VLOOKUP(BW80,$BT$49:$BU$94,2,FALSE)/$BU$95 -> 1.8213759
A81: =HLOOKUP(B81,$B$6:$BR$9,4,FALSE) -> manufacturing | B81: chem | C81: =IFERROR(100*U81/U$95,"") -> 2.6712225 | D81: =IFERROR(100*V81/V$95,"") -> 2.4278543 | E81: =IFERROR(100*W81/W$95,"") -> 2.2784115 | F81: =IFERROR(100*X81/X$95,"") -> 2.0756181 | G81: =IFERROR(100*Y81/Y$95,"") -> 1.6737039 | H81: =IFERROR(100*Z81/Z$95,"") -> 2.8869059 | I81: =IFERROR(100*AA81/AA$95,"") -> 2.4247907 | J81: =IFERROR(100*AB81/AB$95,"") -> 2.3624373 | ... R81: =IFERROR(100*AJ81/AJ$95,"") -> 1.8835434 | T81: =B81 -> chem | U81: =IFERROR(AM81+BD81,"") -> 7.0099682 | V81: =IFERROR(AN81+BE81,"") -> 9.0761263 | W81: =IFERROR(AO81+BF81,"") -> 13.280896 | X81: =IFERROR(AP81+BG81,"") -> 16.576823 | Y81: =IFERROR(AQ81+BH81,"") -> 23.929792 | Z81: =IFERROR(AR81+BI81,"") -> 0.49887197 | AA81: =IFERROR(AS81+BJ81,"") -> 0.54082842 | AB81: =IFERROR(AT81+BK81,"") -> 0.6491327 | ... AI81: =IFERROR(BA81+BR81,"") -> 34.992713 | AJ81: =SUM(U81:AI81) -> 123.02837 | AL81: ="c"&T81 -> cchem | AM81: =_xlfn.IFNA(INDEX(SAM!$B$8:$HA$215,MATCH($AL81,SAM!$A$8:$A$215,0),MATCH(AM$48,SAM!$B$7:$HA$7,0)),0) -> 7.0099682 | AN81: =_xlfn.IFNA(INDEX(SAM!$B$8:$HA$215,MATCH($AL81,SAM!$A$8:$A$215,0),MATCH(AN$48,SAM!$B$7:$HA$7,0)),0) -> 9.0761263 | AO81: =_xlfn.IFNA(INDEX(SAM!$B$8:$HA$215,MATCH($AL81,SAM!$A$8:$A$215,0),MATCH(AO$48,SAM!$B$7:$HA$7,0)),0) -> 13.280896 | AP81: =_xlfn.IFNA(INDEX(SAM!$B$8:$HA$215,MATCH($AL81,SAM!$A$8:$A$215,0),MATCH(AP$48,SAM!$B$7:$HA$7,0)),0) -> 16.576823 | AQ81: =_xlfn.IFNA(INDEX(SAM!$B$8:$HA$215,MATCH($AL81,SAM!$A$8:$A$215,0),MATCH(AQ$48,SAM!$B$7:$HA$7,0)),0) -> 23.929792 | AR81: =_xlfn.IFNA(INDEX(SAM!$B$8:$HA$215,MATCH($AL81,SAM!$A$8:$A$215,0),MATCH(AR$48,SAM!$B$7:$HA$7,0)),0) -> 0.49887197 | AS81: =_xlfn.IFNA(INDEX(SAM!$B$8:$HA$215,MATCH($AL81,SAM!$A$8:$A$215,0),MATCH(AS$48,SAM!$B$7:$HA$7,0)),0) -> 0.54082842 | AT81: =_xlfn.IFNA(INDEX(SAM!$B$8:$HA$215,MATCH($AL81,SAM!$A$8:$A$215,0),MATCH(AT$48,SAM!$B$7:$HA$7,0)),0) -> 0.6491327 | ... BA81: =_xlfn.IFNA(INDEX(SAM!$B$8:$HA$215,MATCH($AL81,SAM!$A$8:$A$215,0),MATCH(BA$48,SAM!$B$7:$HA$7,0)),0) -> 34.992713 | BC81: ="a"&T81 -> achem | BD81: =_xlfn.IFNA(INDEX(SAM!$B$8:$HA$215,MATCH($BC81,SAM!$A$8:$A$215,0),MATCH(BD$48,SAM!$B$7:$HA$7,0)),0) -> 0 | BE81: =_xlfn.IFNA(INDEX(SAM!$B$8:$HA$215,MATCH($BC81,SAM!$A$8:$A$215,0),MATCH(BE$48,SAM!$B$7:$HA$7,0)),0) -> 0 | BF81: =_xlfn.IFNA(INDEX(SAM!$B$8:$HA$215,MATCH($BC81,SAM!$A$8:$A$215,0),MATCH(BF$48,SAM!$B$7:$HA$7,0)),0) -> 0 | BG81: =_xlfn.IFNA(INDEX(SAM!$B$8:$HA$215,MATCH($BC81,SAM!$A$8:$A$215,0),MATCH(BG$48,SAM!$B$7:$HA$7,0)),0) -> 0 | BH81: =_xlfn.IFNA(INDEX(SAM!$B$8:$HA$215,MATCH($BC81,SAM!$A$8:$A$215,0),MATCH(BH$48,SAM!$B$7:$HA$7,0)),0) -> 0 | BI81: =_xlfn.IFNA(INDEX(SAM!$B$8:$HA$215,MATCH($BC81,SAM!$A$8:$A$215,0),MATCH(BI$48,SAM!$B$7:$HA$7,0)),0) -> 0 | BJ81: =_xlfn.IFNA(INDEX(SAM!$B$8:$HA$215,MATCH($BC81,SAM!$A$8:$A$215,0),MATCH(BJ$48,SAM!$B$7:$HA$7,0)),0) -> 0 | BK81: =_xlfn.IFNA(INDEX(SAM!$B$8:$HA$215,MATCH($BC81,SAM!$A$8:$A$215,0),MATCH(BK$48,SAM!$B$7:$HA$7,0)),0) -> 0 | ... BR81: =_xlfn.IFNA(INDEX(SAM!$B$8:$HA$215,MATCH($BC81,SAM!$A$8:$A$215,0),MATCH(BR$48,SAM!$B$7:$HA$7,0)),0) -> 0 | BT81: =AL81 -> cchem | BU81: =SUM(BD81:BR81,AM81:BA81) -> 123.02837 | BW81: cwatr | BX81: =100*VLOOKUP(BW81,$BT$49:$BU$94,2,FALSE)/$BU$95 -> 0.95305759
A82: =HLOOKUP(B82,$B$6:$BR$9,4,FALSE) -> manufacturing | B82: nmet | C82: =IFERROR(100*U82/U$95,"") -> 0.074531874 | D82: =IFERROR(100*V82/V$95,"") -> 0.1037386 | E82: =IFERROR(100*W82/W$95,"") -> 0.1187088 | F82: =IFERROR(100*X82/X$95,"") -> 0.2323288 | G82: =IFERROR(100*Y82/Y$95,"") -> 0.50002414 | H82: =IFERROR(100*Z82/Z$95,"") -> 0.071290471 | I82: =IFERROR(100*AA82/AA$95,"") -> 0.054009419 | J82: =IFERROR(100*AB82/AB$95,"") -> 0.13772059 | ... R82: =IFERROR(100*AJ82/AJ$95,"") -> 0.39398691 | T82: =B82 -> nmet | U82: =IFERROR(AM82+BD82,"") -> 0.19559062 | V82: =IFERROR(AN82+BE82,"") -> 0.38780936 | W82: =IFERROR(AO82+BF82,"") -> 0.69195543 | X82: =IFERROR(AP82+BG82,"") -> 1.8554826 | Y82: =IFERROR(AQ82+BH82,"") -> 7.1490982 | Z82: =IFERROR(AR82+BI82,"") -> 0.012319355 | AA82: =IFERROR(AS82+BJ82,"") -> 0.01204633 | AB82: =IFERROR(AT82+BK82,"") -> 0.037841826 | ... AI82: =IFERROR(BA82+BR82,"") -> 13.54004 | AJ82: =SUM(U82:AI82) -> 25.734246 | AL82: ="c"&T82 -> cnmet | AM82: =_xlfn.IFNA(INDEX(SAM!$B$8:$HA$215,MATCH($AL82,SAM!$A$8:$A$215,0),MATCH(AM$48,SAM!$B$7:$HA$7,0)),0) -> 0.19559062 | AN82: =_xlfn.IFNA(INDEX(SAM!$B$8:$HA$215,MATCH($AL82,SAM!$A$8:$A$215,0),MATCH(AN$48,SAM!$B$7:$HA$7,0)),0) -> 0.38780936 | AO82: =_xlfn.IFNA(INDEX(SAM!$B$8:$HA$215,MATCH($AL82,SAM!$A$8:$A$215,0),MATCH(AO$48,SAM!$B$7:$HA$7,0)),0) -> 0.69195543 | AP82: =_xlfn.IFNA(INDEX(SAM!$B$8:$HA$215,MATCH($AL82,SAM!$A$8:$A$215,0),MATCH(AP$48,SAM!$B$7:$HA$7,0)),0) -> 1.8554826 | AQ82: =_xlfn.IFNA(INDEX(SAM!$B$8:$HA$215,MATCH($AL82,SAM!$A$8:$A$215,0),MATCH(AQ$48,SAM!$B$7:$HA$7,0)),0) -> 7.1490982 | AR82: =_xlfn.IFNA(INDEX(SAM!$B$8:$HA$215,MATCH($AL82,SAM!$A$8:$A$215,0),MATCH(AR$48,SAM!$B$7:$HA$7,0)),0) -> 0.012319355 | AS82: =_xlfn.IFNA(INDEX(SAM!$B$8:$HA$215,MATCH($AL82,SAM!$A$8:$A$215,0),MATCH(AS$48,SAM!$B$7:$HA$7,0)),0) -> 0.01204633 | AT82: =_xlfn.IFNA(INDEX(SAM!$B$8:$HA$215,MATCH($AL82,SAM!$A$8:$A$215,0),MATCH(AT$48,SAM!$B$7:$HA$7,0)),0) -> 0.037841826 | ... BA82: =_xlfn.IFNA(INDEX(SAM!$B$8:$HA$215,MATCH($AL82,SAM!$A$8:$A$215,0),MATCH(BA$48,SAM!$B$7:$HA$7,0)),0) -> 13.54004 | BC82: ="a"&T82 -> anmet | BD82: =_xlfn.IFNA(INDEX(SAM!$B$8:$HA$215,MATCH($BC82,SAM!$A$8:$A$215,0),MATCH(BD$48,SAM!$B$7:$HA$7,0)),0) -> 0 | BE82: =_xlfn.IFNA(INDEX(SAM!$B$8:$HA$215,MATCH($BC82,SAM!$A$8:$A$215,0),MATCH(BE$48,SAM!$B$7:$HA$7,0)),0) -> 0 | BF82: =_xlfn.IFNA(INDEX(SAM!$B$8:$HA$215,MATCH($BC82,SAM!$A$8:$A$215,0),MATCH(BF$48,SAM!$B$7:$HA$7,0)),0) -> 0 | BG82: =_xlfn.IFNA(INDEX(SAM!$B$8:$HA$215,MATCH($BC82,SAM!$A$8:$A$215,0),MATCH(BG$48,SAM!$B$7:$HA$7,0)),0) -> 0 | BH82: =_xlfn.IFNA(INDEX(SAM!$B$8:$HA$215,MATCH($BC82,SAM!$A$8:$A$215,0),MATCH(BH$48,SAM!$B$7:$HA$7,0)),0) -> 0 | BI82: =_xlfn.IFNA(INDEX(SAM!$B$8:$HA$215,MATCH($BC82,SAM!$A$8:$A$215,0),MATCH(BI$48,SAM!$B$7:$HA$7,0)),0) -> 0 | BJ82: =_xlfn.IFNA(INDEX(SAM!$B$8:$HA$215,MATCH($BC82,SAM!$A$8:$A$215,0),MATCH(BJ$48,SAM!$B$7:$HA$7,0)),0) -> 0 | BK82: =_xlfn.IFNA(INDEX(SAM!$B$8:$HA$215,MATCH($BC82,SAM!$A$8:$A$215,0),MATCH(BK$48,SAM!$B$7:$HA$7,0)),0) -> 0 | ... BR82: =_xlfn.IFNA(INDEX(SAM!$B$8:$HA$215,MATCH($BC82,SAM!$A$8:$A$215,0),MATCH(BR$48,SAM!$B$7:$HA$7,0)),0) -> 0 | BT82: =AL82 -> cnmet | BU82: =SUM(BD82:BR82,AM82:BA82) -> 25.734246 | BW82: ccons | BX82: =100*VLOOKUP(BW82,$BT$49:$BU$94,2,FALSE)/$BU$95 -> 0
A83: =HLOOKUP(B83,$B$6:$BR$9,4,FALSE) -> manufacturing | B83: metl | C83: =IFERROR(100*U83/U$95,"") -> 0.078899525 | D83: =IFERROR(100*V83/V$95,"") -> 0.085244413 | E83: =IFERROR(100*W83/W$95,"") -> 0.09400003 | F83: =IFERROR(100*X83/X$95,"") -> 0.10310479 | G83: =IFERROR(100*Y83/Y$95,"") -> 0.10565579 | H83: =IFERROR(100*Z83/Z$95,"") -> 0.091868186 | I83: =IFERROR(100*AA83/AA$95,"") -> 0.06787447 | J83: =IFERROR(100*AB83/AB$95,"") -> 0.074182275 | ... R83: =IFERROR(100*AJ83/AJ$95,"") -> 0.11463446 | T83: =B83 -> metl | U83: =IFERROR(AM83+BD83,"") -> 0.20705245 | V83: =IFERROR(AN83+BE83,"") -> 0.31867195 | W83: =IFERROR(AO83+BF83,"") -> 0.54792762 | X83: =IFERROR(AP83+BG83,"") -> 0.82344139 | Y83: =IFERROR(AQ83+BH83,"") -> 1.5106143 | Z83: =IFERROR(AR83+BI83,"") -> 0.015875288 | AA83: =IFERROR(AS83+BJ83,"") -> 0.015138809 | AB83: =IFERROR(AT83+BK83,"") -> 0.020383246 | ... AI83: =IFERROR(BA83+BR83,"") -> 3.1429152 | AJ83: =SUM(U83:AI83) -> 7.4876382 | AL83: ="c"&T83 -> cmetl | AM83: =_xlfn.IFNA(INDEX(SAM!$B$8:$HA$215,MATCH($AL83,SAM!$A$8:$A$215,0),MATCH(AM$48,SAM!$B$7:$HA$7,0)),0) -> 0.20705245 | AN83: =_xlfn.IFNA(INDEX(SAM!$B$8:$HA$215,MATCH($AL83,SAM!$A$8:$A$215,0),MATCH(AN$48,SAM!$B$7:$HA$7,0)),0) -> 0.31867195 | AO83: =_xlfn.IFNA(INDEX(SAM!$B$8:$HA$215,MATCH($AL83,SAM!$A$8:$A$215,0),MATCH(AO$48,SAM!$B$7:$HA$7,0)),0) -> 0.54792762 | AP83: =_xlfn.IFNA(INDEX(SAM!$B$8:$HA$215,MATCH($AL83,SAM!$A$8:$A$215,0),MATCH(AP$48,SAM!$B$7:$HA$7,0)),0) -> 0.82344139 | AQ83: =_xlfn.IFNA(INDEX(SAM!$B$8:$HA$215,MATCH($AL83,SAM!$A$8:$A$215,0),MATCH(AQ$48,SAM!$B$7:$HA$7,0)),0) -> 1.5106143 | AR83: =_xlfn.IFNA(INDEX(SAM!$B$8:$HA$215,MATCH($AL83,SAM!$A$8:$A$215,0),MATCH(AR$48,SAM!$B$7:$HA$7,0)),0) -> 0.015875288 | AS83: =_xlfn.IFNA(INDEX(SAM!$B$8:$HA$215,MATCH($AL83,SAM!$A$8:$A$215,0),MATCH(AS$48,SAM!$B$7:$HA$7,0)),0) -> 0.015138809 | AT83: =_xlfn.IFNA(INDEX(SAM!$B$8:$HA$215,MATCH($AL83,SAM!$A$8:$A$215,0),MATCH(AT$48,SAM!$B$7:$HA$7,0)),0) -> 0.020383246 | ... BA83: =_xlfn.IFNA(INDEX(SAM!$B$8:$HA$215,MATCH($AL83,SAM!$A$8:$A$215,0),MATCH(BA$48,SAM!$B$7:$HA$7,0)),0) -> 3.1429152 | BC83: ="a"&T83 -> ametl | BD83: =_xlfn.IFNA(INDEX(SAM!$B$8:$HA$215,MATCH($BC83,SAM!$A$8:$A$215,0),MATCH(BD$48,SAM!$B$7:$HA$7,0)),0) -> 0 | BE83: =_xlfn.IFNA(INDEX(SAM!$B$8:$HA$215,MATCH($BC83,SAM!$A$8:$A$215,0),MATCH(BE$48,SAM!$B$7:$HA$7,0)),0) -> 0 | BF83: =_xlfn.IFNA(INDEX(SAM!$B$8:$HA$215,MATCH($BC83,SAM!$A$8:$A$215,0),MATCH(BF$48,SAM!$B$7:$HA$7,0)),0) -> 0 | BG83: =_xlfn.IFNA(INDEX(SAM!$B$8:$HA$215,MATCH($BC83,SAM!$A$8:$A$215,0),MATCH(BG$48,SAM!$B$7:$HA$7,0)),0) -> 0 | BH83: =_xlfn.IFNA(INDEX(SAM!$B$8:$HA$215,MATCH($BC83,SAM!$A$8:$A$215,0),MATCH(BH$48,SAM!$B$7:$HA$7,0)),0) -> 0 | BI83: =_xlfn.IFNA(INDEX(SAM!$B$8:$HA$215,MATCH($BC83,SAM!$A$8:$A$215,0),MATCH(BI$48,SAM!$B$7:$HA$7,0)),0) -> 0 | BJ83: =_xlfn.IFNA(INDEX(SAM!$B$8:$HA$215,MATCH($BC83,SAM!$A$8:$A$215,0),MATCH(BJ$48,SAM!$B$7:$HA$7,0)),0) -> 0 | BK83: =_xlfn.IFNA(INDEX(SAM!$B$8:$HA$215,MATCH($BC83,SAM!$A$8:$A$215,0),MATCH(BK$48,SAM!$B$7:$HA$7,0)),0) -> 0 | ... BR83: =_xlfn.IFNA(INDEX(SAM!$B$8:$HA$215,MATCH($BC83,SAM!$A$8:$A$215,0),MATCH(BR$48,SAM!$B$7:$HA$7,0)),0) -> 0 | BT83: =AL83 -> cmetl | BU83: =SUM(BD83:BR83,AM83:BA83) -> 7.4876382 | BW83: ctrad | BX83: =100*VLOOKUP(BW83,$BT$49:$BU$94,2,FALSE)/$BU$95 -> 2.0314842
A84: =HLOOKUP(B84,$B$6:$BR$9,4,FALSE) -> manufacturing | B84: mach | C84: =IFERROR(100*U84/U$95,"") -> 0.15134884 | D84: =IFERROR(100*V84/V$95,"") -> 0.2293329 | E84: =IFERROR(100*W84/W$95,"") -> 0.21075221 | F84: =IFERROR(100*X84/X$95,"") -> 0.33619523 | G84: =IFERROR(100*Y84/Y$95,"") -> 1.4916955 | H84: =IFERROR(100*Z84/Z$95,"") -> 0.10279441 | I84: =IFERROR(100*AA84/AA$95,"") -> 0.13078438 | J84: =IFERROR(100*AB84/AB$95,"") -> 0.11348331 | ... R84: =IFERROR(100*AJ84/AJ$95,"") -> 1.198513 | T84: =B84 -> mach | U84: =IFERROR(AM84+BD84,"") -> 0.39717791 | V84: =IFERROR(AN84+BE84,"") -> 0.8573226 | W84: =IFERROR(AO84+BF84,"") -> 1.2284779 | X84: =IFERROR(AP84+BG84,"") -> 2.6850068 | Y84: =IFERROR(AQ84+BH84,"") -> 21.327526 | Z84: =IFERROR(AR84+BI84,"") -> 0.017763396 | AA84: =IFERROR(AS84+BJ84,"") -> 0.029170315 | AB84: =IFERROR(AT84+BK84,"") -> 0.031182088 | ... AI84: =IFERROR(BA84+BR84,"") -> 47.867727 | AJ84: =SUM(U84:AI84) -> 78.283889 | AL84: ="c"&T84 -> cmach | AM84: =_xlfn.IFNA(INDEX(SAM!$B$8:$HA$215,MATCH($AL84,SAM!$A$8:$A$215,0),MATCH(AM$48,SAM!$B$7:$HA$7,0)),0) -> 0.39717791 | AN84: =_xlfn.IFNA(INDEX(SAM!$B$8:$HA$215,MATCH($AL84,SAM!$A$8:$A$215,0),MATCH(AN$48,SAM!$B$7:$HA$7,0)),0) -> 0.8573226 | AO84: =_xlfn.IFNA(INDEX(SAM!$B$8:$HA$215,MATCH($AL84,SAM!$A$8:$A$215,0),MATCH(AO$48,SAM!$B$7:$HA$7,0)),0) -> 1.2284779 | AP84: =_xlfn.IFNA(INDEX(SAM!$B$8:$HA$215,MATCH($AL84,SAM!$A$8:$A$215,0),MATCH(AP$48,SAM!$B$7:$HA$7,0)),0) -> 2.6850068 | AQ84: =_xlfn.IFNA(INDEX(SAM!$B$8:$HA$215,MATCH($AL84,SAM!$A$8:$A$215,0),MATCH(AQ$48,SAM!$B$7:$HA$7,0)),0) -> 21.327526 | AR84: =_xlfn.IFNA(INDEX(SAM!$B$8:$HA$215,MATCH($AL84,SAM!$A$8:$A$215,0),MATCH(AR$48,SAM!$B$7:$HA$7,0)),0) -> 0.017763396 | AS84: =_xlfn.IFNA(INDEX(SAM!$B$8:$HA$215,MATCH($AL84,SAM!$A$8:$A$215,0),MATCH(AS$48,SAM!$B$7:$HA$7,0)),0) -> 0.029170315 | AT84: =_xlfn.IFNA(INDEX(SAM!$B$8:$HA$215,MATCH($AL84,SAM!$A$8:$A$215,0),MATCH(AT$48,SAM!$B$7:$HA$7,0)),0) -> 0.031182088 | ... BA84: =_xlfn.IFNA(INDEX(SAM!$B$8:$HA$215,MATCH($AL84,SAM!$A$8:$A$215,0),MATCH(BA$48,SAM!$B$7:$HA$7,0)),0) -> 47.867727 | BC84: ="a"&T84 -> amach | BD84: =_xlfn.IFNA(INDEX(SAM!$B$8:$HA$215,MATCH($BC84,SAM!$A$8:$A$215,0),MATCH(BD$48,SAM!$B$7:$HA$7,0)),0) -> 0 | BE84: =_xlfn.IFNA(INDEX(SAM!$B$8:$HA$215,MATCH($BC84,SAM!$A$8:$A$215,0),MATCH(BE$48,SAM!$B$7:$HA$7,0)),0) -> 0 | BF84: =_xlfn.IFNA(INDEX(SAM!$B$8:$HA$215,MATCH($BC84,SAM!$A$8:$A$215,0),MATCH(BF$48,SAM!$B$7:$HA$7,0)),0) -> 0 | BG84: =_xlfn.IFNA(INDEX(SAM!$B$8:$HA$215,MATCH($BC84,SAM!$A$8:$A$215,0),MATCH(BG$48,SAM!$B$7:$HA$7,0)),0) -> 0 | BH84: =_xlfn.IFNA(INDEX(SAM!$B$8:$HA$215,MATCH($BC84,SAM!$A$8:$A$215,0),MATCH(BH$48,SAM!$B$7:$HA$7,0)),0) -> 0 | BI84: =_xlfn.IFNA(INDEX(SAM!$B$8:$HA$215,MATCH($BC84,SAM!$A$8:$A$215,0),MATCH(BI$48,SAM!$B$7:$HA$7,0)),0) -> 0 | BJ84: =_xlfn.IFNA(INDEX(SAM!$B$8:$HA$215,MATCH($BC84,SAM!$A$8:$A$215,0),MATCH(BJ$48,SAM!$B$7:$HA$7,0)),0) -> 0 | BK84: =_xlfn.IFNA(INDEX(SAM!$B$8:$HA$215,MATCH($BC84,SAM!$A$8:$A$215,0),MATCH(BK$48,SAM!$B$7:$HA$7,0)),0) -> 0 | ... BR84: =_xlfn.IFNA(INDEX(SAM!$B$8:$HA$215,MATCH($BC84,SAM!$A$8:$A$215,0),MATCH(BR$48,SAM!$B$7:$HA$7,0)),0) -> 0 | BT84: =AL84 -> cmach | BU84: =SUM(BD84:BR84,AM84:BA84) -> 78.283889 | BW84: ctran | BX84: =100*VLOOKUP(BW84,$BT$49:$BU$94,2,FALSE)/$BU$95 -> 2.5300364
A85: =HLOOKUP(B85,$B$6:$BR$9,4,FALSE) -> manufacturing | B85: oman | C85: =IFERROR(100*U85/U$95,"") -> 0.030750131 | D85: =IFERROR(100*V85/V$95,"") -> 0.041284401 | E85: =IFERROR(100*W85/W$95,"") -> 0.06127146 | F85: =IFERROR(100*X85/X$95,"") -> 0.11700935 | G85: =IFERROR(100*Y85/Y$95,"") -> 0.21688792 | H85: =IFERROR(100*Z85/Z$95,"") -> 0.026878029 | I85: =IFERROR(100*AA85/AA$95,"") -> 0.10806858 | J85: =IFERROR(100*AB85/AB$95,"") -> 0.047965625 | ... R85: =IFERROR(100*AJ85/AJ$95,"") -> 0.19855359 | T85: =B85 -> oman | U85: =IFERROR(AM85+BD85,"") -> 0.080696178 | V85: =IFERROR(AN85+BE85,"") -> 0.15433482 | W85: =IFERROR(AO85+BF85,"") -> 0.35715228 | X85: =IFERROR(AP85+BG85,"") -> 0.93448944 | Y85: =IFERROR(AQ85+BH85,"") -> 3.1009563 | Z85: =IFERROR(AR85+BI85,"") -> 0.0046446596 | AA85: =IFERROR(AS85+BJ85,"") -> 0.024103754 | AB85: =IFERROR(AT85+BK85,"") -> 0.013179633 | ... AI85: =IFERROR(BA85+BR85,"") -> 6.3984279 | AJ85: =SUM(U85:AI85) -> 12.969027 | AL85: ="c"&T85 -> coman | AM85: =_xlfn.IFNA(INDEX(SAM!$B$8:$HA$215,MATCH($AL85,SAM!$A$8:$A$215,0),MATCH(AM$48,SAM!$B$7:$HA$7,0)),0) -> 0.080696178 | AN85: =_xlfn.IFNA(INDEX(SAM!$B$8:$HA$215,MATCH($AL85,SAM!$A$8:$A$215,0),MATCH(AN$48,SAM!$B$7:$HA$7,0)),0) -> 0.15433482 | AO85: =_xlfn.IFNA(INDEX(SAM!$B$8:$HA$215,MATCH($AL85,SAM!$A$8:$A$215,0),MATCH(AO$48,SAM!$B$7:$HA$7,0)),0) -> 0.35715228 | AP85: =_xlfn.IFNA(INDEX(SAM!$B$8:$HA$215,MATCH($AL85,SAM!$A$8:$A$215,0),MATCH(AP$48,SAM!$B$7:$HA$7,0)),0) -> 0.93448944 | AQ85: =_xlfn.IFNA(INDEX(SAM!$B$8:$HA$215,MATCH($AL85,SAM!$A$8:$A$215,0),MATCH(AQ$48,SAM!$B$7:$HA$7,0)),0) -> 3.1009563 | AR85: =_xlfn.IFNA(INDEX(SAM!$B$8:$HA$215,MATCH($AL85,SAM!$A$8:$A$215,0),MATCH(AR$48,SAM!$B$7:$HA$7,0)),0) -> 0.0046446596 | AS85: =_xlfn.IFNA(INDEX(SAM!$B$8:$HA$215,MATCH($AL85,SAM!$A$8:$A$215,0),MATCH(AS$48,SAM!$B$7:$HA$7,0)),0) -> 0.024103754 | AT85: =_xlfn.IFNA(INDEX(SAM!$B$8:$HA$215,MATCH($AL85,SAM!$A$8:$A$215,0),MATCH(AT$48,SAM!$B$7:$HA$7,0)),0) -> 0.013179633 | ... BA85: =_xlfn.IFNA(INDEX(SAM!$B$8:$HA$215,MATCH($AL85,SAM!$A$8:$A$215,0),MATCH(BA$48,SAM!$B$7:$HA$7,0)),0) -> 6.3984279 | BC85: ="a"&T85 -> aoman | BD85: =_xlfn.IFNA(INDEX(SAM!$B$8:$HA$215,MATCH($BC85,SAM!$A$8:$A$215,0),MATCH(BD$48,SAM!$B$7:$HA$7,0)),0) -> 0 | BE85: =_xlfn.IFNA(INDEX(SAM!$B$8:$HA$215,MATCH($BC85,SAM!$A$8:$A$215,0),MATCH(BE$48,SAM!$B$7:$HA$7,0)),0) -> 0 | BF85: =_xlfn.IFNA(INDEX(SAM!$B$8:$HA$215,MATCH($BC85,SAM!$A$8:$A$215,0),MATCH(BF$48,SAM!$B$7:$HA$7,0)),0) -> 0 | BG85: =_xlfn.IFNA(INDEX(SAM!$B$8:$HA$215,MATCH($BC85,SAM!$A$8:$A$215,0),MATCH(BG$48,SAM!$B$7:$HA$7,0)),0) -> 0 | BH85: =_xlfn.IFNA(INDEX(SAM!$B$8:$HA$215,MATCH($BC85,SAM!$A$8:$A$215,0),MATCH(BH$48,SAM!$B$7:$HA$7,0)),0) -> 0 | BI85: =_xlfn.IFNA(INDEX(SAM!$B$8:$HA$215,MATCH($BC85,SAM!$A$8:$A$215,0),MATCH(BI$48,SAM!$B$7:$HA$7,0)),0) -> 0 | BJ85: =_xlfn.IFNA(INDEX(SAM!$B$8:$HA$215,MATCH($BC85,SAM!$A$8:$A$215,0),MATCH(BJ$48,SAM!$B$7:$HA$7,0)),0) -> 0 | BK85: =_xlfn.IFNA(INDEX(SAM!$B$8:$HA$215,MATCH($BC85,SAM!$A$8:$A$215,0),MATCH(BK$48,SAM!$B$7:$HA$7,0)),0) -> 0 | ... BR85: =_xlfn.IFNA(INDEX(SAM!$B$8:$HA$215,MATCH($BC85,SAM!$A$8:$A$215,0),MATCH(BR$48,SAM!$B$7:$HA$7,0)),0) -> 0 | BT85: =AL85 -> coman | BU85: =SUM(BD85:BR85,AM85:BA85) -> 12.969027 | BW85: chotl | BX85: =100*VLOOKUP(BW85,$BT$49:$BU$94,2,FALSE)/$BU$95 -> 0.52849459
A86: =HLOOKUP(B86,$B$6:$BR$9,4,FALSE) -> contruction | B86: cons | C86: =IFERROR(100*U86/U$95,"") -> 0 | D86: =IFERROR(100*V86/V$95,"") -> 0 | E86: =IFERROR(100*W86/W$95,"") -> 0 | F86: =IFERROR(100*X86/X$95,"") -> 0 | G86: =IFERROR(100*Y86/Y$95,"") -> 0 | H86: =IFERROR(100*Z86/Z$95,"") -> 0 | I86: =IFERROR(100*AA86/AA$95,"") -> 0 | J86: =IFERROR(100*AB86/AB$95,"") -> 0 | ... R86: =IFERROR(100*AJ86/AJ$95,"") -> 0 | T86: =B86 -> cons | U86: =IFERROR(AM86+BD86,"") -> 0 | V86: =IFERROR(AN86+BE86,"") -> 0 | W86: =IFERROR(AO86+BF86,"") -> 0 | X86: =IFERROR(AP86+BG86,"") -> 0 | Y86: =IFERROR(AQ86+BH86,"") -> 0 | Z86: =IFERROR(AR86+BI86,"") -> 0 | AA86: =IFERROR(AS86+BJ86,"") -> 0 | AB86: =IFERROR(AT86+BK86,"") -> 0 | ... AI86: =IFERROR(BA86+BR86,"") -> 0 | AJ86: =SUM(U86:AI86) -> 0 | AL86: ="c"&T86 -> ccons | AM86: =_xlfn.IFNA(INDEX(SAM!$B$8:$HA$215,MATCH($AL86,SAM!$A$8:$A$215,0),MATCH(AM$48,SAM!$B$7:$HA$7,0)),0) -> 0 | AN86: =_xlfn.IFNA(INDEX(SAM!$B$8:$HA$215,MATCH($AL86,SAM!$A$8:$A$215,0),MATCH(AN$48,SAM!$B$7:$HA$7,0)),0) -> 0 | AO86: =_xlfn.IFNA(INDEX(SAM!$B$8:$HA$215,MATCH($AL86,SAM!$A$8:$A$215,0),MATCH(AO$48,SAM!$B$7:$HA$7,0)),0) -> 0 | AP86: =_xlfn.IFNA(INDEX(SAM!$B$8:$HA$215,MATCH($AL86,SAM!$A$8:$A$215,0),MATCH(AP$48,SAM!$B$7:$HA$7,0)),0) -> 0 | AQ86: =_xlfn.IFNA(INDEX(SAM!$B$8:$HA$215,MATCH($AL86,SAM!$A$8:$A$215,0),MATCH(AQ$48,SAM!$B$7:$HA$7,0)),0) -> 0 | AR86: =_xlfn.IFNA(INDEX(SAM!$B$8:$HA$215,MATCH($AL86,SAM!$A$8:$A$215,0),MATCH(AR$48,SAM!$B$7:$HA$7,0)),0) -> 0 | AS86: =_xlfn.IFNA(INDEX(SAM!$B$8:$HA$215,MATCH($AL86,SAM!$A$8:$A$215,0),MATCH(AS$48,SAM!$B$7:$HA$7,0)),0) -> 0 | AT86: =_xlfn.IFNA(INDEX(SAM!$B$8:$HA$215,MATCH($AL86,SAM!$A$8:$A$215,0),MATCH(AT$48,SAM!$B$7:$HA$7,0)),0) -> 0 | ... BA86: =_xlfn.IFNA(INDEX(SAM!$B$8:$HA$215,MATCH($AL86,SAM!$A$8:$A$215,0),MATCH(BA$48,SAM!$B$7:$HA$7,0)),0) -> 0 | BC86: ="a"&T86 -> acons | BD86: =_xlfn.IFNA(INDEX(SAM!$B$8:$HA$215,MATCH($BC86,SAM!$A$8:$A$215,0),MATCH(BD$48,SAM!$B$7:$HA$7,0)),0) -> 0 | BE86: =_xlfn.IFNA(INDEX(SAM!$B$8:$HA$215,MATCH($BC86,SAM!$A$8:$A$215,0),MATCH(BE$48,SAM!$B$7:$HA$7,0)),0) -> 0 | BF86: =_xlfn.IFNA(INDEX(SAM!$B$8:$HA$215,MATCH($BC86,SAM!$A$8:$A$215,0),MATCH(BF$48,SAM!$B$7:$HA$7,0)),0) -> 0 | BG86: =_xlfn.IFNA(INDEX(SAM!$B$8:$HA$215,MATCH($BC86,SAM!$A$8:$A$215,0),MATCH(BG$48,SAM!$B$7:$HA$7,0)),0) -> 0 | BH86: =_xlfn.IFNA(INDEX(SAM!$B$8:$HA$215,MATCH($BC86,SAM!$A$8:$A$215,0),MATCH(BH$48,SAM!$B$7:$HA$7,0)),0) -> 0 | BI86: =_xlfn.IFNA(INDEX(SAM!$B$8:$HA$215,MATCH($BC86,SAM!$A$8:$A$215,0),MATCH(BI$48,SAM!$B$7:$HA$7,0)),0) -> 0 | BJ86: =_xlfn.IFNA(INDEX(SAM!$B$8:$HA$215,MATCH($BC86,SAM!$A$8:$A$215,0),MATCH(BJ$48,SAM!$B$7:$HA$7,0)),0) -> 0 | BK86: =_xlfn.IFNA(INDEX(SAM!$B$8:$HA$215,MATCH($BC86,SAM!$A$8:$A$215,0),MATCH(BK$48,SAM!$B$7:$HA$7,0)),0) -> 0 | ... BR86: =_xlfn.IFNA(INDEX(SAM!$B$8:$HA$215,MATCH($BC86,SAM!$A$8:$A$215,0),MATCH(BR$48,SAM!$B$7:$HA$7,0)),0) -> 0 | BT86: =AL86 -> ccons | BU86: =SUM(BD86:BR86,AM86:BA86) -> 0 | BW86: crest | BX86: =100*VLOOKUP(BW86,$BT$49:$BU$94,2,FALSE)/$BU$95 -> 1.3527404
